Workbook

Sheet Instructions & overview
C5: Bank Diagnostic
C6: INVEST: The Process & Toolkit for Unleashing SME Banking
C10: Last modified: Septmber 23rd, 2025 | E10: Contact details for further inquiries:
E11: karen.rodriguez@dalberg.com
E12: kusi.hornberger@dalberg.com
C14: OVERVIEW
C16: The Bank Diagnostic is an Excel-based template to help funders and banks identify capability gaps to be filled to effectively deliver SME banking. It offers a menu of options to inform technical assistance efforts or internal initiatives aimed at strengthening a bank’s SME banking capabilities.
C18: Focus audience:
C19: USE CASE
C21: The tool allows banks to self-assess and allows TA funders to identify their partner bank's existing capabilities and gaps in terms of SME banking across six assessment areas: 1) strategy, 2) talent and organizational structure, 3) competitive positioning, 4) operational processes, 5) products and value proposition, and 6) digital readiness. It helps inform strategic pathways and prioritize relevant TA opportunities to strengthen SME finance delivery. The Bank Diagnostic serves as a practical starting point for banks to understand their current capabilities relative to the best-in-class models for SME banking in order to enter the market or scale their existing business.
C23: OBJECTIVES
C25: 1. Assess banks'city and internal readiness to deliver SME banking using 30+ indicators focused on core institutional capabilities, including digital readiness. 2. Identify capacity-building opportunities to strengthen SME finance and accelerate digital transformation.
C27: GUIDANCE
C29: This file consists of seven tabs, including this one. Below is a high-level description of each tab, along with specific instructions on how users can interact with them to complete the bank diagnostic successfully.
C31: Tab Name | D31: Description | E31: Instructions
C33: Financial performance | D33: This tab presents a dashboard of key financial performance indicators that can be filled out for banks with an existing SME banking business. It offers a visual overview of performance in the SME segment. Filling out this tab is optional, as it depends on the availability of information. | E33: Complete the financial performance dashboard by collecting or requesting the necessary data to populate each indicator, including metrics related to portfolio size and growth, portfolio health, customer loyalty, SME revenue contribution, profitability, and productivity. The dashboard is designed to be flexible; users are encouraged to edit or add indicators as needed to suit the specific context or analytical goals. Please note that this dashboard should be adjusted to reflect relevant indicators based on banks availability of data and / or priorities of user
C34: Bank diagnostic | D34: This tab presents the Bank Diagnostic Framework, outlining key assessment areas and indicators, along with space for stakeholders to assign scores and provide rationale for each. It also includes guidance on how to automate and customize the tool to reflect users' varying priorities (e.g., by adding or removing indicators). Specific questions on digital readiness are included in a distinct format. | E34: Edit the following two cells across assessment areas and indicators: '1. Score: To input scores per category on a High/Medium/Low or Yes/No scale 2. Rationale: To provide a justification or explanation for the selected score
C35: Examples | D35: These tabs include examples of how to score banks across assessment areas and indicators. They provide illustrative scores and rationales based solely on secondary data. As such, the examples are for demonstration purposes only and are intended to support stakeholders in conducting their own bank diagnostics. The information presented is not fully accurate and should not be used as a definitive reference. | E35: Use these examples as guidance for scoring and what type of rationale to include across assessment areas.
C36: Methodology | D36: This tab provides an overview of the methodology used to obtain the bank diagnostic results, including the scoring logic and the roadmaps for mitigating the identified gaps. | E36: Review the scoring guidance and focus area considerations. Add or remove categories as needed to align with your organization’s priorities.
C37: Results | D37: This tab provides an overview of the bank diagnostic results, highlighting the maturity level of each assessment area, including digital readiness. It also outlines suggested pathways to address the identified gaps. | E37: Consider the most pressing gaps and review the suggested strategies for strengthening SME banking. Engage relevant decision-making teams to help guide future analysis and interventions.
C39: USING THIS TOOL EFFECTIVELY
C41: SMEs are defined here as firms with 10–250 employees and revenues of USD 100K–15M. While definitions vary by market, this standard is used for consistency, while most tools also apply to informal or smaller enterprises.
C43: This tool is designed to be geography-agnostic and applicable across all banks and TA funders. It is intended as a flexible resource that can be adapted and customized to fit each organization's specific needs, goals, and contextual realities. The tool serves as a starting point that can be built upon and tailored as needed. Users are encouraged to treat this as a living tool, one that can be updated over time to reflect emerging learnings and strategic shifts. For more information, reference the tool's user guide.
C45: The Bank Diagnostic is a core component of INVEST: The Process & Toolkit for Unleashing SME Banking, a public resource that helps banks and TA funders strengthen SME banking operations. It was developed through a highly consultative process and draws on learnings from experienced ecosystem experts. The Bank Diagnostic is closely linked to other tools from the toolkit, especially in terms of strategic and TA recommendations across focus areas to address identified capability gaps.
D46: Move to the next sheet to begin assessing the SME readiness of your organization or partner bank!

Sheet Financial performance
D3: Bank's Overall SME Financial Performance
D4: •Before initiating the bank diagnostic, please gather or request the necessary data to populate the following key indicators. These will provide a comprehensive overview of the bank’s financial performance. If this information is not available, leave the tab empty. •In addition to the metrics listed, please include any other relevant indicators that may enhance the analysis, such as operational efficiency, net interest margins, profit per SME officer, or others that reflect segment-level financial performance.
C18: Year | D18: SME portfolio size (USD million) | E18: SME share | J18: Year | K18: SME revenue (USD million) | L18: Overall revenue (USD million) | Q18: Year | R18: SME CIR | S18: Overall CIR
C19: 2020 | D19: 5 | E19: 0.05 | J19: 2020 | K19: 130 | L19: 720 | Q19: 2020 | R19: 0.68 | S19: 0.54
C20: 2021 | D20: 5.5 | E20: 0.07 | J20: 2021 | K20: 145 | L20: 760 | Q20: 2021 | R20: 0.65 | S20: 0.54
C21: 2022 | D21: 5.7 | E21: 0.07 | J21: 2022 | K21: 160 | L21: 820 | Q21: 2022 | R21: 0.65 | S21: 0.53
C22: 2023 | D22: 7 | E22: 0.1 | J22: 2023 | K22: 170 | L22: 850 | Q22: 2023 | R22: 0.62 | S22: 0.54
C23: 2024 | D23: 7.5 | E23: 0.12 | J23: 2024 | K23: 210 | L23: 980 | Q23: 2024 | R23: 0.59 | S23: 0.48
J24: Average | K24: =AVERAGE(K19:K23) -> 163 | L24: =AVERAGE(L19:L23) -> 826
C47: Year | D47: SME NPS | E47: Overall NPS | J47: Year | K47: SMEs NPL | L47: Overall NPL | Q47: Year | R47: Loans per officer SME segment | S47: Overall loans per officer
C48: 2020 | D48: 3 | E48: 45 | J48: 2020 | K48: 0.08 | L48: 0.03 | Q48: 2020 | R48: 90 | S48: 150
C49: 2021 | D49: 5 | E49: 45 | J49: 2021 | K49: 0.06 | L49: 0.03 | Q49: 2021 | R49: 90 | S49: 150
C50: 2022 | D50: 15 | E50: 46 | J50: 2022 | K50: 0.04 | L50: 0.025 | Q50: 2022 | R50: 95 | S50: 150
C51: 2023 | D51: 35 | E51: 48 | J51: 2023 | K51: 0.04 | L51: 0.025 | Q51: 2023 | R51: 102 | S51: 150
C52: 2024 | D52: 30 | E52: 50 | J52: 2024 | K52: 0.025 | L52: 0.02 | Q52: 2024 | R52: 115 | S52: 150

Sheet Bank diagnostic
A1: Let
D4: Bank diagnostic
D5: • In this tab, you can complete the Bank diagnostic for your bank or a partner bank. • Start by entering information about the specific bank you are assessing, including its name, country of operation, and type. For "Bank type," tiers are typically defined by the size of the bank’s assets: Tier 1 banks usually hold assets of around $100 billion or more, Tier 2 banks hold between $1 billion and $100 billion, and Tier 3 banks have assets of $1 billion or less. These ranges may vary by country and should be adjusted to local market conditions where appropriate. • Please enter scores for each of the five assessment areas in column E, and provide a brief justification for each score in column F. • The questions specifically focused on digital capabilities can be found within the different assessment areas with the following format: • Completing the assessment effectively requires access to primary information. To this end, it is recommended to conduct interviews with multiple bank staff, as indicated in column I. Suggested interview questions are listed in column D to support this process and are also compiled in a standalone Interview Guide that accompanies this tool. • Automation and customization guidelines can be found in columns K and L.
D9: Bank profile | H9: Overall standing
D10: Name: | F10: Bank X | H10: {=_xlfn.IFS(H11<Methodology!G30,"Low maturity",H11<Methodology!G29,"Mid maturity",H11>=Methodology!G29,"High maturity")} -> #VALUE!
D11: Country of operation: | H11: {=_xlfn.LET(_xlpm.scores, _xlfn._xlws.FILTER(F19:F105, F19:F105<>""),SUMPRODUCT((_xlpm.scores="High")*Methodology!F15+(_xlpm.scores="Medium")*Methodology!F16+((_xlpm.scores="Low") + (_xlpm.scores="No data"))*Methodology!F17+(_xlpm.scores="Yes")*Methodology!I15+(_xlpm.scores="No")*Methodology!I16))} -> 128
D12: Bank type:
D16: Criteria | E16: Interview questions and guide | F16: Score | G16: Rationale | H16: Scoring guidance | I16: Direction | J16: Assessment tips | K16: Type of source | L16: Notes on customization | M16: Automation guidelines
D17: 1. Strategy
C18: # | D18: Overall strategy
C19: 1.1 | D19: 1.1 SME banking is a top priority for the bank | E19: Is SME banking among the bank's top strategic priorities for the next 2–3 years? How would it rank compared to other key priorities? | F19: Medium | H19: High: SME banking is explicitly named as one of the bank’s top 3 short-term strategic priorities Medium: SME banking is listed among the top 4–10 strategic priorities Low: SME banking is not clearly reflected among the bank's top strategic priorities or is absent from current strategy documentation | I19: Positive, given banks that consider SME programs a high priority are likely committed to their execution | J19: Interview at least two bank staff, including a senior leader (e.g., COO, CEO, or CSO), to ensure a well-rounded perspective | K19: Primary | M19: If recording is allowed, use ChatGPT or a similar AI tool to analyze the transcripts of interviews and identify key takeaways related to the bank's SME strategy. Prompt example: “Analyze these transcripts to extract insights to answer the following questions related to the bank’s SME strategy. If information is missing or unclear in the transcripts, search external public sources (e.g., annual reports, investor presentations, strategy briefs) to complement your responses. For each question: i) Summarize the relevant insight based on the transcript, ii) Complement information from public documents if helpful, iii) Include one short quote (from either the transcript or a public source) as supporting evidence Questions to answer: 1.1 Is SME banking a top strategic priority for the bank? 1.2 Does the SME portfolio represent a significant share of the bank’s overall business? 1.3 Are SME goals clearly defined, time-bound, and reflected across departments? 1.4 Are SME strategies and outcomes reviewed regularly by senior leadership? 1.5 Are SME strategies supported by structured, multi-year investment plans? 1.6 Is the SME strategy embedded across departments and delivery channels (e.g., credit, ops, digital)? 1.7 Are SME impact goals (e.g., inclusion, gender, climate) defined, tracked, and reviewed? 1.8 Has the bank successfully delivered SME-related change initiatives in the past 3–5 years (e.g., product rollout, migration, segment launches)?" Note: Any AI-generated findings should be reviewed and validated by the user to ensure accuracy and contextual relevance.
C20: 1.2 | D20: 1.2 The targeted or current SME portfolio represents a significant share of the bank’s overall business | E20: What is the current share of SME lending in the bank's total business? What share is the bank targeting over the next few years? | F20: High | H20: High: SMEs make up ≥20% of the bank’s current or targeted lending Medium: SMEs represent 10–19% of the bank’s lending Low: SMEs represent less than 10% of the bank’s lending | I20: Positive, as a high SME share of the loan book signals that SMEs are a core commercial focus, likely supported by resource allocation | J20: Interview at least two bank staff, including a senior leader (e.g., COO, CEO, or CSO), to ensure a well-rounded perspective | K20: Primary
C21: 1.3 | D21: SME strategy
C22: 1.3 | D22: 1.3 SME goals are clearly defined and time-bound | E22: Has the bank defined an SME segment with specific goals? If so, what are their time horizons, and how frequently are they tracked? | F22: High | H22: High: The bank has defined SME as a distinct segment with specific and measurable goals with 3–5 year timelines, tied to planning cycles Medium: SME goals exist but are not concrete, time-bound, or lack consistent tracking and updating Low: SME-related goals are vague or aspirational, with no actionable framework | I22: Positive, as clear, time-bound SME goals that are shared across teams suggest strategic cohesion and prioritization | J22: Interview the SME Business Lead (or related positions) or a senior leader (e.g., CSO) to validate Complement with secondary information, such as annual reports and investor relations presentations | K22: Both
C23: 1.4 | D23: 1.4 SME strategy and outcomes are periodically reviewed by senior leadership | E23: Do leadership members oversee SME banking operations? If so, who? How frequently does this person review progress on the SME strategy? | F23: Low | H23: High: SME operations and outcomes are closely monitored by at least one senior executive who is accountable for executing and reviewing the overall strategy on a quarterly basis Medium: SME operations are monitored but not reviewed as frequently by senior leadership (e.g., only annually) Low: No structured oversight or accountability is limited to middle management staff | I23: Positive, as periodic strategy reviews by senior leadership ensure accountability and course correction aligned with executive decision cycles | J23: Interview a senior leader (e.g., CSO or CEO) to validate | K23: Primary | L23: Adjust to reflect the organization’s governance structure and team composition, while ensuring appropriate leadership oversight
C24: 1.5 | D24: 1.5 SME strategy is supported by structured, multi-year investment plans | E24: Does the bank have defined investment plans to deliver on its SME strategy? If so, what are the execution timelines, and what resources have been allocated to support it? | F24: High | H24: High: The bank has defined both medium-term (1-3 year horizon) and long-term (4-6 year horizon) investment plans and allocated sufficient resources in alignment with SME goals Medium: There is an investment plan, but resource allocation or execution timelines are not as clearly defined (e.g., very long term) Low: There are no investment plans or if present these lack clear resource allocation and timelines for execution | I24: Positive, since the presence of both medium- and long-term investment plans reflects a credible roadmap and strong institutional commitment | J24: Interview a senior leader (e.g., CSO or CEO) and the SME Business Lead (or related positions) to validate Complement with internal budget documents or similar resources | K24: Primary | L24: It's common for small banks to receive a medium or low score, as they may not have the resources to develop multi-year investment plans
C25: 1.6 | D25: 1.6 SME strategy is embedded across departments and delivery channels | E25: Is the SME strategy reflected in the work of core teams (e.g., credit, risk, operations)? Are these teams held accountable for delivering on SME-related priorities? | F25: High | H25: High: The bank has a SME strategy that is known and reflected across core departments (e.g., credit, ops, risk, digital) and delivery teams (e.g., branches, agents, RMs). SME objectives and priorities are understood at the field level and included in branch plans Medium: SME priorities are partially reflected in support departments but weakly cascaded to delivery channels; some staff are aware, but ownership is uneven Low: There is not an SME strategy in place or there is little awareness or alignment on the SME strategy | I25: Positive, as a broad-based understanding of SME priorities across functions improves consistency in service delivery | J25: Interview the SME Business Lead (or related positions) to validate | K25: Primary | L25: Include specific core departments or teams
C26: 1.7 | D26: 1.7 SME impact goals have defined metrics and are consistently tracked | E26: Are there defined inclusion or impact goals for SME banking? If so, how frequently are these monitored? | F26: Low | H26: High: Inclusion KPIs (e.g., % loans to women-led or climate-aligned SMEs) are defined, tracked, and reviewed at least annually Medium: Inclusion KPIs are defined but not tracked periodically or at the SME level Low: Inclusion KPIs are not defined or tracked throughout the organization | I26: Positive, as the regular tracking of SME impact metrics demonstrates a commitment to measuring outcomes beyond disbursements and aligned with financial inclusion | J26: Interview the SME Business Lead (or related positions) to validate Complement with secondary information, such as annual reports and investor relations presentations | K26: Both | L26: Tailor to align with specific impact goals of interest (e.g., rural development, gender inclusion, job creation)
C27: 1.8 | D27: 1.8 Proven track record delivering strategic change initiatives (e.g., product rollout, digital migration, segment launch) | E27: Has the bank implemented any major strategic or operational initiatives in the past 3–5 years (e.g., new business segment, digital transformation, or product launch)? If so, what were the outcomes and how effectively were these initiatives delivered? | F27: High | H27: High: The bank has successfully implemented at least two strategic or operational initiatives in the past 3–5 years, with clear delivery outcomes and cross-functional coordination Medium: Some change initiatives were implemented but with delays, limited scale, or unclear outcomes Low: Limited or no record of executing structured change beyond business-as-usual operations | I27: Positive, since the successful delivery of change initiatives reflects strong execution, learning, and adaptation capacity, which can be leveraged to drive future SME initiatives | J27: Interview a senior leader (e.g., CSO, COO, or CEO) to validate | K27: Primary | L27: Include mainly if the bank has limited SME experience to validate its change management capacity
D28: 2. Talent and organizational structure
C29: 2.1 | D29: 2.1 Dedicated SME unit with defined roles and execution responsibility | E29: Does the bank have a dedicated SME unit with defined roles and responsibilities? If so, how many staff members are exclusively focused on SME-related activities? | F29: Low | H29: High: The bank has a full-time SME unit of at least 3–5 staff with defined roles and responsibilities across core departments (e.g., sales, credit, and product). The team has decision-making authority Medium: The bank has 1-2 designated staff members, but SME is one of many responsibilities or roles that they hold in the bank Low: No SME-specific staff or execution roles exist | I29: Positive, as the presence of a full-time, multi-functional SME team with clear responsibilities and decision-making authority indicates strong internal ownership and coordination capacity | J29: Interview a senior leader (e.g., CSO or CEO) or the SME Business Lead (or related positions) to validate Complement with secondary information, such as LinkedIn profiles and team composition on the bank's website | K29: Both | L29: Adjust the size of the SME team based on the overall staff capacity and scale of the organization | M29: If recording is allowed, use ChatGPT or a similar AI tool to analyze the transcripts of interviews and identify key takeaways related to the bank's SME talent and organizational structure. Prompt example: “Analyze these transcripts to extract insights to answer the following questions related to the bank’s SME team structure and collaboration. If information is missing or unclear in the transcripts, search external public sources (e.g., annual reports, org charts, bank websites) to complement your responses. For each question: i) Summarize the relevant insight based on the transcript; ii) Complement with public information if helpful, and iii) Include one short quote (from either the transcript or a public source) as supporting evidence. Questions to answer: 2.1 Does the bank have a dedicated SME unit with clear roles and execution responsibility? 2.2 Are SME performance targets and incentives defined across departments? 2.3 Are relevant trainings for SME banking provided to relevant staff?" Note: Any AI-generated findings should be reviewed and validated by the user to ensure accuracy and contextual relevance.
C30: 2.2 | D30: 2.2 SME staff have performance targets and incentives | E30: Do staff involved in SME banking have performance targets or incentives specifically tied to SME results? If so, which roles have KPIs? How are these encouraging performance? | F30: High | H30: High: SME KPIs (e.g., loan disbursement, NPLs, turnaround time, cross-sell) are embedded in the SME unit's performance evaluations, and incentives reward SME results Medium: SME KPIs exist but only for front-line or business development staff, or incentives are not sufficiently encouraging performance Low: There are no clearly defined SME KPIs or incentives | I30: Positive, as embedding SME performance metrics in team performance can reinforces strategic prioritization | J30: Interview the SME Business Lead (or related positions) to validate | K30: Primary
C31: 2.4 | D31: 2.3 Relevant trainings for SME banking are provided for relevant staff | E31: Does the bank offer SME-specific training for staff? If so, which staff members receive this training, and how frequently is it delivered? | F31: High | H31: High: Staff related to SME operations or strategy receive the pertinent training and have ongoing upskilling opportunities to properly execute their roles in the SME context Medium: SME specific training is not sufficiently provided, or is only provided to some staff Low: No SME-specific training or technical capacity-building is available | I31: Positive, since widespread SME-specific training ensures that staff are equipped with the knowledge and tools needed to serve the SME segment effectively | J31: Interview the SME Business Lead (or related positions) to validate | K31: Primary
D32: 3. Competitive positioning
C33: 3.1 | D33: 3.1 SME strategy is informed by market research and benchmarking | E33: Has the bank conducted any market research or competitive benchmarking focused on SME segments? If so, when was it done? How has it influenced SME strategy or product development? | F33: High | H33: High: The bank conducts market or client research (e.g., SME segmentation studies, behavioral data, competitor market share analysis) on at least a yearly basis, and findings have influenced strategy, product design, or delivery priorities Medium: Some SME-related research exists (e.g., old market studies or internal data analysis), but is not consistently updated or has limited influence on decision-making Low: No SME-specific research has been conducted, or insights are not used to shape strategy or service design | I33: Positive, as the use of structured SME research and competitor analysis ensures better-tailored products and services and overall positioning | J33: Interview the SME Business Lead (or related positions) to validate | K33: Primary | M33: If recording is allowed, use ChatGPT or a similar AI tool to analyze the transcripts of interviews and identify key takeaways related to the bank’s competitive SME positioning. Prompt example: “Analyze these transcripts to extract insights to answer the following questions related to SME market strategy and differentiation. If transcript information is missing or unclear, search public sources (e.g., bank websites, strategy decks, press releases) to strengthen responses. For each question: i) Summarize relevant insight from the transcript; ii) Complement with public material if available, and iii) Include a short quote from the transcript or source. Questions to answer: 3.1 Is SME strategy informed by market research and benchmarking? 3.2 Does the bank actively target SME segments with untapped market opportunity? 3.3 Is the SME value proposition well-recognized across the market? 3.4 Does the bank use data analytics to shape SME product delivery and innovation?" Note: Any AI-generated findings should be reviewed and validated by the user to ensure accuracy and contextual relevance.
C34: 3.2 | D34: 3.2 The bank actively identifies and targets SME segments with an uncaptured market potential | E34: Does the bank target specific SME segments? If so, how were these segments selected? Was the untapped market potential a factor in their selection? | F34: Low | H34: High: The bank deliberately targets SME segments that are underserved and show clear market potential, meaning limited competition from other banks and unmet demand Medium: The bank segments and targets SMEs, but selection is not clearly based on an untapped opportunity Low: The bank serves SMEs broadly without segment-specific targeting or consideration of competitive saturation | I34: Positive, because proactive targeting of high-potential SME segments improves the bank’s ability to differentiate in competitive markets | J34: Interview the SME Business Lead (or related positions) to validate | K34: Primary
C35: 3.3 | D35: 3.3 SME competitive positioning is well-recognized across the market | E35: Does the bank have a defined SME brand or value proposition? If so, how is it marketed and communicated to the public? | F35: High | H35: High: The bank has a distinct SME brand or value proposition that is consistently communicated across channels (e.g., website, marketing, physical branches) and recognized by clients or stakeholders Medium: The bank offers SME services and may reference SMEs in its materials, but lacks a clear value proposition or consistent branding that differentiates it from competitors Low: SME offerings are not visibly positioned or promoted. There is no SME-specific branding, value proposition, or messaging | I35: Positive, as a distinct and consistently communicated SME brand or value proposition enhances market visibility and reinforces the bank’s reputation as a serious SME player | J35: Interview a senior leader (e.g., CSO or CEO) or the SME Business Lead (or related positions) to validate Complement with secondary information, such as press coverage, award recognitions, and social media campaigns | K35: Secondary
C36: 3.4 | D36: 3.4 [Digital] The value proposition of SME banking is enhanced by data analytics and digital innovation | E36: Does the bank use market research or customer insights to guide SME banking priorities? How often is this done, and how consistently is it applied? | F36: Medium | H36: High: The SME value proposition is regularly enhanced through the use of data analytics or digital innovation (e.g., automated onboarding, digital credit scoring). These tools are actively used to shape SME product development or service delivery Medium: Some SME initiatives are informed by data or enhanced through digital strategies, but this is applied inconsistently or on a limited basis Low: SME offerings are rarely or never shaped by data analytics or digital tools | I36: Positive, as basing initiatives on market analyses ensures relevance, enhances SME uptake, and supports value-driven innovation | J36: Interview a senior leader (e.g., CIO or CTO) as well as key staff responsible for SME digital banking (e.g., Head of SME Banking or similar roles) | K36: Primary
D37: 4. Operational processes
C38: 4.1 | D38: 4.1 SME credit processes are flexible and adapted to typical access-to-finance constraints and priorities of SMEs | E38: Does the bank use credit processes specifically tailored to SME clients? If so, what are those processes? How institutionalized are these? | F38: Medium | H38: High: Credit assessment processes are meaningfully adapted to SME realities (e.g., cash-flow-based analysis, flexible collateral, data-driven models) and are consistently applied by staff handling SME lending Medium: Some SME-appropriate credit practices exist but are applied inconsistently or are not institutionalized Low: SME credit follows standard corporate models with no tailored features | I38: Positive, because when the bank’s credit processes are meaningfully tailored to SME realities, financial products can be offered more safely and inclusively to a broader SME customer base | J38: Interview the SME Business Lead (or related positions) or other internal experts (e.g., Head of Credit or Head of Risk) to validate | K38: Primary | M38: If recording is allowed, use ChatGPT or a similar AI tool to analyze the transcripts of interviews and identify key takeaways related to SME operational processes. Prompt example: “Analyze these transcripts to extract insights to answer the following questions about SME process design and execution. Where transcripts are incomplete, search public materials (e.g., product brochures, operations manuals, public client journeys) to fill gaps. For each question: i) Summarize the key insight from the transcript; ii) Complement with public information as needed, and iii) Include a short quote (from either source) to support your answer. Questions to answer: 4.1 Are SME credit processes flexible and adapted to client realities? 4.2 Does segmentation drive product and service tailoring for SMEs? 4.3 Do relationship managers deliver tailored engagement to SMEs? 4.4 Is broader client data analyzed to identify unserved SME clients and cross-sell opportunities and support credit assessments? 4.5 Is SME performance tracked through internal systems and routine reporting? 4.6 Are the key bank systems integrated and work smoothly to support SME operations? 4.7 Does the bank have a clear change management framework to ensure reliable SME operations? 4.8 How long does the bank usually take to launch a new SME digital feature? 4.9 Are SME digital services compliant with data privacy regulations?" Note: Any AI-generated findings should be reviewed and validated by the user to ensure accuracy and contextual relevance.
C39: 4.2 | D39: 4.2 Segmentation drives the design and tailoring of products and services | E39: Has the bank defined SME segments (e.g., by size, sector, lifecycle)? If so, how are those used to tailor products and services? | F39: High | H39: High: SME segments are well-defined (e.g., by size, lifecycle, sector) and actively shape product or service design (e.g., pricing, bundling, distribution). Segmentation is regularly reviewed and updated Medium: Key SME segments are identified but used only superficially in some aspects of product and service design Low: There is no clear SME segmentation, or segmentation exists but has no influence on product or service decisions | I39: Positive, as the use of clearly defined SME segments to shape product, pricing, and delivery strategies enables more relevant and effective offerings across client types | J39: Interview the SME Business Lead (or related positions) or other internal experts (e.g., Product Manager) to validate | K39: Primary
C40: 4.3 | D40: 4.3 Relationship managers deliver tailored engagement to SMEs | E40: Does the bank assign relationship managers or officers to SME clients? What does their engagement consist of? | F40: Medium | H40: High: Relationship managers or account officers are assigned to SME clients with defined portfolios and use structured engagement tools (e.g., CRM systems) Medium: There are SME focused staff who engage clients, but there are no consistent or standardized engagement practices Low: There is no relationship management model for SMEs, or interactions are reactive or handled by generalist staff | I40: Positive, since assigning relationship managers with dedicated SME portfolios ensures more consistent and targeted support that helps deepen long-term client relationships | J40: Interview the SME Business Lead (or related positions) or other internal experts (e.g., Lead Engagement Manager) to validate | K40: Primary
D41: 4.4 The bank analyzes broad client data to identify SME owners within other customer segments for cross-selling SME products and assessing creditworthiness | E41: Does the bank analyze broader customer data to identify existing clients from other segments (e.g., retail, corporate) who are SME owners or managers? If so, how is this data used to cross-sell SME banking products and assess creditworthiness? | F41: Medium | H41: High: The bank systematically analyzes broad client data (e.g., transaction history, product usage, private financial profiles) to proactively identify SME owners or managers among clients in other segments (e.g., retail, corporate) and consistently uses these insights to cross-sell SME banking products and support credit assessments Medium: The bank occasionally or partially uses broad client data to identify SME owners in other segments, but this is not systematic, and the insights not commonly used to support cross-selling or credit evaluation Low: The bank does not analyze or use client data to expand its SME portfolio | I41: Positive, since proactively analyzing broad client data enables banks to identify untapped SME opportunities within their existing customer base, improve cross-selling of SME products, and strengthen credit risk assessments | J41: Interview the SME Business Lead (or related positions) to validate
C42: 4.4 | D42: 4.5 SME banking is integrated into internal systems and performance tracked through routine reporting | E42: Is SME performance tracked in the bank's reporting systems? How frequently is it reviewed? | F42: High | H42: High: SME portfolio performance (e.g., loan volume, NPLs, product use, client growth, default risk, officer productivity) is integrated into the bank’s reporting systems and reviewed at least quarterly Medium: SME data is tracked in core reporting systems but not disaggregated, periodically updated, or reviewed Low: SME is not embedded into reporting systems, or there is no regular SME performance tracking | I42: Positive, because integrating SME performance metrics into core systems and reviewing them regularly enables continuous improvement and supports more responsive management of the segment | J42: Interview a senior leader (e.g., COO) or the SME Business Lead (or related positions) to validate | K42: Primary
C43: 4.5 | D43: 4.6 [Digital] Key data systems (CRM, loan origination system, API) are fully integrated to enable seamless information flow across departments and branches | E43: Are the bank’s key systems integrated and function smoothly to support SME digital operations? If so, are any manual steps or interventions still required? | F43: High | H43: High: All critical systems that support SME banking, like customer records, loan approvals, and payments, are fully integrated and work smoothly together across departments and branches Medium: Some systems are connected, but others (like credit or customer information) still require manual steps or data transfers Low: Most systems are separate, requiring staff to manually move information between them, which slows down processes and increases the risk of errors | I43: Positive, since integrated systems streamline workflows, reduce duplication, and improve the delivery of SME digital services. | J43: Interview a senior leader (e.g., CIO or CTO) as well as key staff responsible for SME digital banking (e.g., Head of SME Banking or similar roles) | K43: Primary
C44: 4.6 | D44: 4.7 [Digital] The SME banking unit has a change management framework in place that enables rapid implementation of digital, data, and AI solutions internally and for clients | E44: Does the bank have a clear change management framework or approach to ensure reliable SME digital operations? If so, what procedures are in place for implementing updates or upgrades? | F44: High | H44: High: The bank follows clear procedures for keeping SME digital services running, including service-level commitments, tools for tracking and fixing issues, and structured rollout plans for changes and updates Medium: Some practices are in place (like issue tracking or support teams), but there's no single, consistent approach Low: Support for SME digital services is mostly informal. Issues are handled on an ad hoc basis | I44: Positive, because structured change management frameworks minimize service downtime and maintain trust during system upgrades. | J44: Interview a senior leader (e.g., CIO or CTO) as well as key staff responsible for SME digital banking (e.g., Head of SME Banking or similar roles) | K44: Primary
C45: 4.7 | D45: 4.8 [Digital] New SME digital features are typically launched quickly | E45: How long does it typically take to launch a new SME digital feature from ideation to release? | F45: Low | H45: High: Most SME digital features go from concept to release in under 12 weeks, supported by short development cycles and fast approvals Medium: The typical time to launch is 3–6 months, with some internal delays or dependencies Low: Launching a new SME digital feature takes 6+ months, or timelines are unpredictable | I45: Positive, because frequent release of new digital features reflects a responsive, customer-centric innovation cycle. | J45: Interview a senior leader (e.g., CIO or CTO) as well as key staff responsible for SME digital banking (e.g., Head of SME Banking or similar roles) | K45: Primary
C46: 4.8 | D46: 4.9 [Digital] SME digital services are compliant with data privacy regulations (e.g., consent capture, data usage visibility, storage security) | E46: Are SME digital services compliant with data privacy regulations (e.g., consent capture, data usage visibility, storage security)? | F46: Yes | H46: Yes: SME digital services have consent flows, visible data use terms, and storage aligned to national/global privacy standards No: No evidence of privacy protections or regulatory alignment | I46: Positive, because compliance with privacy and security regulations is essential to maintain trust and meet legal standards. | J46: Interview a senior leader (e.g., CIO or CTO) as well as key staff responsible for SME digital banking (e.g., Head of SME Banking or similar roles) | K46: Primary
D47: 5. Products and value proposition
D48: SME offerings
C49: 5.1 | D49: 5.1 Financial product offering is aligned and responsive to SME lifecycle stages | E49: Does the bank offer financial products specifically designed for SMEs? If so, how are they tailored to different SME lifecycle stages? What SME needs do these products address for each stage? | F49: Medium | H49: High: The bank has identified key SME financial needs (e.g., working capital, equipment purchase, trade liquidity) and offers dedicated products that directly address these needs across all major SME lifecycle stages (e.g., startup, growth, maturity) Medium: The bank offers a broad range of standard SME products (e.g., overdrafts, term loans) and partially addresses some lifecycle needs, but products are not explicitly differentiated across lifecycle stages Low: The SME product offering is standardized and mostly limited to basic loan structures | I49: Positive, as offering SME-specific financial products tailored to lifecycle needs can help meet evolving SME demands, increase product uptake, and deepen client relationships over time | J49: Interview the SME Business Lead (or related positions) to validate Complement with secondary information, such as public product offerings | K49: Both | M49: If recording is allowed, use ChatGPT or a similar AI tool to analyze the transcripts of interviews and identify key takeaways related to SME product design and financial outcomes. Prompt example: “Analyze these transcripts to extract insights to answer the following questions about SME offerings and financial performance. If data is missing in the transcript, search public sources (e.g., product catalogs, annual reports, press releases) to complement your answers. For each question: i) Summarize the insight from the transcript; ii) Use public information to fill gaps if needed; and iii) Include a short quote from the transcript or source. Questions to answer: 5.1 Is the financial product offering responsive to the key SME lifecycle stages (e.g., startup, growth, maturity)? 5.2 Are there unique and differentiated products for key customer groups (e.g., women, agribusinesses, young entrepreneurs)? 5.3 Are non-financial services available and tailored to SME needs? 5.4 Does the bank offer multiple digital non-financial services for SMEs? 5.5 What feedback do SMEs provide on the SME-facing platform? 5.6 Can SMEs perform core banking tasks easily through the bank's digital channels? 5.7 Has the SME loan portfolio shown consistent growth? 5.8 Is the SME NPL rate within acceptable thresholds? 5.9 Are SME portfolios financially sustainable or profitable? 5.10 Do SME clients use multiple financial products?" Note: Any AI-generated findings should be reviewed and validated by the user to ensure accuracy and contextual relevance.
D50: 5.2 SME offerings include dedicated products for specific segments or client groups | E50: Does the bank offer SME products tailored to specific sub-segments or sectors (e.g., women-led businesses, agribusinesses, exporters, family-owned SMEs)? How do these differentiate from SME standardized products? | F50: Medium | H50: High: The bank offers fully developed product offerings targeting relevant SME sub-segments (e.g., women entrepreneurs, agribusinesses, exporters, family businesses) Medium: The bank has some products tailored to SME segments, but mostly offers standardized products with slight adjustments Low: The bank treats SMEs as a uniform group with no differentiation or sector-specific offerings | I50: Positive, as offering SME products tailored to specific sub-segments or sectors enhances competitive differentiation and can improve customer acquisition and loyalty | J50: Interview the SME Business Lead (or related positions) to validate Complement with secondary information, such as public product offerings | K50: Both
C51: 5.2 | D51: 5.3 Non-financial services are available and tailored to SME needs | E51: Does the bank offer non-financial services for SMEs? If so, what types of services are provided (e.g., training, advisory, networking opportunities) and what needs are they responding to? | F51: High | H51: High: The bank offers structured, SME-tailored non-financial services (e.g., training, mentorship, business advisory), targeted by segment or business need, and often bundled with financial products Medium: Some non-financial services are offered (e.g., financial literacy), but they are generic, lightly delivered, or not tailored to SME segments Low: There are no structured non-financial services offered to SMEs | I51: Positive, because structured, segment-tailored non-financial services (e.g., training, mentorship, advisory) enhance SME financial performance and reinforce the bank’s role as a trusted partner | J51: Interview the SME Business Lead (or related positions) to validate Complement with secondary information, such as public product offerings | K51: Both
D52: 5.4 [Digital] SME customers can perform core banking tasks (e.g., payments, balance checks, transfers) through the bank’s digital channels | E52: Can SME customers perform core banking tasks (e.g., payments, checking balances, transfers) through the bank’s digital channels? If so, are these services available on both mobile and web platforms? | F52: High | H52: High: A full range of SME financial services, including payments, transfers, account management, and business-specific tools, are accessible and fully functional through mobile and web platforms Medium: Some services are digitally available, but others are incomplete or require offline support Low: Key services are unavailable digitally or frequently fail | I52: Positive, since digital enablement of core tasks supports SME autonomy, improves efficiency, and promotes customer loyalty. | J52: Interview a senior leader (e.g., CIO or CTO) as well as key staff responsible for SME digital banking (e.g., Head of SME Banking or similar roles) | K52: Primary
C53: 5.3 | D53: 5.5 [Digital] Multiple digital non-financial services (e.g., cashflow management tools, invoicing, financial planning dashboards) are offered to SMEs | E53: Does the bank offer digital non-financial services (e.g., cashflow management tools, invoicing tools, financial planning tools) to SMEs? If so, which non-financial services are available? | F53: Medium | H53: High: The bank offers multiple integrated non-financial tools via its SME platform or client interface (e.g., invoice generation, expense tracking, cash flow dashboards, and business analytics) Medium: Some basic, digital non-financial services are offered (e.g., invoice templates or simple calculators) Low: No digital non-financial services are available | I53: Positive, because offering digital non-financial tools supports broader SME needs and boosts their performance, enhancing loyalty and value delivery. | J53: Interview a senior leader (e.g., CIO or CTO) as well as key staff responsible for SME digital banking (e.g., Head of SME Banking or similar roles) | K53: Primary
C54: 5.4 | D54: 5.6 [Digital] SME-facing digital channels are easy to use, accessible, and reliable across web and mobile | E54: What feedback do SMEs provide on digital channels' speed, ease of use, and accessibility across web and mobile? How frequently do they submit complaints? | F54: High | H54: High: SME customers consistently report high satisfaction with the usability, speed, and accessibility of the bank's digital channels. These are intuitive, mobile-friendly, and usable by customers with varying levels of digital fluency Medium: SME users report a generally functional experience, but with occasional complaints about usability, navigation, or mobile optimization Low: SME feedback highlights frequent frustration with the digital channels' interface, speed, or mobile performance | I54: Positive, since an intuitive and reliable digital interface enhances customer satisfaction and encourages consistent usage. | J54: Interview a senior leader (e.g., CIO or CTO) as well as key staff responsible for SME digital banking (e.g., Head of SME Banking or similar roles) | K54: Primary
D55: Financial performance
C56: 5.6 | D56: 5.7 SME loan portfolio shows consistent growth | E56: Does the bank track SME loan portfolio data? If so, how has the portfolio performed over the past three years in terms of volume and number of clients? | F56: Medium | H56: High: SME loan portfolio has grown annually over the past three years Medium: Portfolio has grown, but inconsistently, over the past 3 years (ups and downs but net positive) Low: Flat or declining SME portfolio over the past three years | I56: Positive, as sustained SME portfolio growth over multiple years indicates strong market demand, effective outreach, and a likely alignment between product design and SME needs | J56: Interview the SME Business Lead (or related positions) or other internal experts (e.g., Head of Credit) to validate | K56: Primary | L56: Adjust time frames to match preferences or definitions of portfolio performance
C57: 5.7 | D57: 5.8 SME NPL rate is within acceptable thresholds | E57: What is the non-performing loan rate for the SME portfolio? How does it compare to the NPL of the overall loan book? | F57: High | H57: High: SME NPLs are <5% and stable or improving Medium: SME NPLs are 5–12% Low: SME NPLs are >12% or worsening over time | I57: Positive, because maintaining low and stable SME NPLs suggests strong risk management practices and signals that credit offerings are well-calibrated to borrower capacity | J57: Interview the SME Business Lead (or related positions) or other internal experts (e.g., Head of Credit or Head of Risk) to validate | K57: Primary | L57: Adjust the NPL ranges to match the averages of the region of interest
C58: 5.8 | D58: 5.9 SME clients use multiple financial products, reflecting strong uptake | E58: Does the bank track the average number of financial products acquired by SME clients? If so, what is the current average? What types of non-credit products are commonly used by SMEs (e.g., payments, savings, insurance, FX)? | F58: Low | H58: High: A majority of SME clients use multiple products beyond credit (e.g., deposits, payments, insurance), with strong uptake of complementary services and clear efforts to deepen client relationships Medium: Most SME clients use more than one product (typically credit plus one), but product bundling is not proactively offered or acquired Low: Most SME clients rely on a single product (typically credit), with minimal use of additional services | I58: Positive, as high product uptake across SME clients reflects deeper relationships, improved client retention, and more diversified revenue streams for the bank | J58: Interview the SME Business Lead (or related positions) to validate | K58: Primary
C59: 5.9 | D59: 5.10 SME portfolios are financially sustainable or profitable | E59: Does the bank track the profitability or sustainability of its SME portfolio? What do those indicators show? | F59: High | H59: High: The SME portfolio is profitable or contributes positively to the bank’s bottom line, based on internal costing or segment financials Medium: Portfolio is near breakeven or shows improving contribution over time Low: The SME portfolio is consistently generating losses, with negative contribution to profitability or requiring significant subsidy | I59: Positive, since SME portfolio profitability shows that the segment contributes to the bank’s financial performance and supports long-term viability | J59: Interview a senior leader (e.g., CFO or COO) and the SME Business Lead (or related positions) to validate | K59: Primary

Sheet Example 1
D4: Bank diagnostic
D5: •This sheet showcases a real-world example of the bank diagnostic in practice and provides guidance on scoring the various assessment areas and indicators. •Please note that this example is for illustrative purposes only. The scoring and rationale are based on secondary data and would likely differ significantly if complemented with primary data.
D9: Bank profile | G9: Overall standing
D10: Name: | E10: Family Bank | G10: {=_xlfn.IFS(G11<Methodology!G30,"Low maturity",G11<Methodology!G29,"Mid maturity",G11>=Methodology!G29,"High maturity")} -> #VALUE!
D11: Country of operation: | E11: Kenya | G11: {=_xlfn.LET(_xlpm.scores, _xlfn._xlws.FILTER(E19:E105, E19:E105<>""),SUMPRODUCT((_xlpm.scores="High")*Methodology!F15+(_xlpm.scores="Medium")*Methodology!F16+((_xlpm.scores="Low") + (_xlpm.scores="No data"))*Methodology!F17+(_xlpm.scores="Yes")*Methodology!I15+(_xlpm.scores="No")*Methodology!I16))} -> 102
D12: Bank type: | E12: Tier 2
D16: Criteria | E16: Score | F16: Rationale | G16: Scoring guidance | H16: Direction | I16: Assessment tips | J16: Type of source
D17: 1. Strategy
C18: # | D18: Overall strategy
C19: 1.1 | D19: 1.1 SME banking is a top priority for the bank | E19: No data | F19: This information needs to be validated with the bank's senior leadership. | G19: High: SME banking is explicitly named as one of the bank’s top 3 short-term strategic priorities Medium: SME banking is listed among the top 4–10 strategic priorities Low: SME banking is not clearly reflected among the bank's top strategic priorities or is absent from current strategy documentation | H19: Positive, given banks that consider SME programs a high priority are likely committed to their execution | I19: Interview at least two bank staff, including a senior leader (e.g., COO, CEO, or CSO), to ensure a well-rounded perspective | J19: Primary
C20: 1.2 | D20: 1.2 The targeted or current SME portfolio represents a significant share of the bank’s overall business | E20: No data | F20: This information needs to be validated with the bank's senior leadership. | G20: High: SMEs make up ≥20% of the bank’s current or targeted lending Medium: SMEs represent 10–19% of the bank’s lending Low: SMEs represent less than 10% of the bank’s lending | H20: Positive, as a high SME share of the loan book signals that SMEs are a core commercial focus, likely supported by resource allocation | I20: Interview at least two bank staff, including a senior leader (e.g., COO, CEO, or CSO), to ensure a well-rounded perspective | J20: Primary
C21: 1.3 | D21: SME strategy
C22: 1.3 | D22: 1.3 SME goals are clearly defined and time-bound | E22: High | F22: Family Bank has defined SME goals (e.g., portfolio growth, gender inclusion, and agribusiness results), but these do not have publicly available explicit KPIs and are not time-bound. | G22: High: The bank has defined SME as a distinct segment with specific and measurable goals with 3–5 year timelines, tied to planning cycles Medium: SME goals exist but are not concrete, time-bound, or lack consistent tracking and updating Low: SME-related goals are vague or aspirational, with no actionable framework | H22: Positive, as clear, time-bound SME goals that are shared across teams suggest strategic cohesion and prioritization | I22: Interview the SME Business Lead (or related positions) or a senior leader (e.g., CSO) to validate Complement with secondary information, such as annual reports and investor relations presentations | J22: Both
C23: 1.4 | D23: 1.4 SME strategy and outcomes are periodically reviewed by senior leadership | E23: Medium | F23: SME banking is overseen directly by the Board, and I assume leadership members are in charge of supervision and execution of SME strategy (this is not publicly available). | G23: High: SME operations and outcomes are closely monitored by at least one senior executive who is accountable for executing and reviewing the overall strategy on a quarterly basis Medium: SME operations are monitored but not reviewed as frequently by senior leadership (e.g., only annually) Low: No structured oversight or accountability is limited to middle management staff | H23: Positive, as periodic strategy reviews by senior leadership ensure accountability and course correction aligned with executive decision cycles | I23: Interview a senior leader (e.g., CSO or CEO) to validate | J23: Primary
C24: 1.5 | D24: 1.5 SME strategy is supported by structured, multi-year investment plans | E24: Medium | F24: The growth of Family Bank's SME segment is presented as a key priority by Family Bank's leadership. Additionally, the bank has raised significant resources from corporate bonds and DFIs (ADB) to boost SME lending. However, there are no publicly available investment plans for the medium and long term. | G24: High: The bank has defined both medium-term (1-3 year horizon) and long-term (4-6 year horizon) investment plans and allocated sufficient resources in alignment with SME goals Medium: There is an investment plan, but resource allocation or execution timelines are not as clearly defined (e.g., very long term) Low: There are no investment plans or if present these lack clear resource allocation and timelines for execution | H24: Positive, since the presence of both medium- and long-term investment plans reflects a credible roadmap and strong institutional commitment | I24: Interview a senior leader (e.g., CSO or CEO) and the SME Business Lead (or related positions) to validate Complement with internal budget documents or similar resources | J24: Primary
C25: 1.6 | D25: 1.6 SME strategy is embedded across departments and delivery channels | E25: Medium | F25: SME banking is proven to be a key pillar in Family Bank's overall operations and focus, as showcased in its annual integrated reports. This cascades into its core departments, including risk, compliance, information, and finance. | G25: High: The bank has a SME strategy that is known and reflected across core departments (e.g., credit, ops, risk, digital) and delivery teams (e.g., branches, agents, RMs). SME objectives and priorities are understood at the field level and included in branch plans Medium: SME priorities are partially reflected in support departments but weakly cascaded to delivery channels; some staff are aware, but ownership is uneven Low: There is not an SME strategy in place or there is little awareness or alignment on the SME strategy | H25: Positive, as a broad-based understanding of SME priorities across functions improves consistency in service delivery | I25: Interview the SME Business Lead (or related positions) to validate | J25: Primary
C26: 1.7 | D26: 1.7 SME impact goals have defined metrics and are consistently tracked | E26: High | F26: Family Bank focuses on women and climate-centered metrics and tracks and reports on them annually. These are overseen directly by the Board and are reviewed annually. | G26: High: Inclusion KPIs (e.g., % loans to women-led or climate-aligned SMEs) are defined, tracked, and reviewed at least annually Medium: Inclusion KPIs are defined but not tracked periodically or at the SME level Low: Inclusion KPIs are not defined or tracked throughout the organization | H26: Positive, as the regular tracking of SME impact metrics demonstrates a commitment to measuring outcomes beyond disbursements and aligned with financial inclusion | I26: Interview the SME Business Lead (or related positions) to validate Complement with secondary information, such as annual reports and investor relations presentations | J26: Both
C27: 1.8 | D27: 1.8 Proven track record delivering strategic change initiatives (e.g., product rollout, digital migration, segment launch) | E27: High | F27: Family Bank has a proven track record of delivering strategic change initiatives, including the digital transformation of the bank with solutions such as PesaPap mobile app. | G27: High: The bank has successfully implemented at least two strategic or operational initiatives in the past 3–5 years, with clear delivery outcomes and cross-functional coordination Medium: Some change initiatives were implemented but with delays, limited scale, or unclear outcomes Low: Limited or no record of executing structured change beyond business-as-usual operations | H27: Positive, since the successful delivery of change initiatives reflects strong execution, learning, and adaptation capacity, which can be leveraged to drive future SME initiatives | I27: Interview a senior leader (e.g., CSO, COO, or CEO) to validate | J27: Primary
D28: 2. Talent and organizational structure
C29: 2.1 | D29: 2.1 Dedicated SME unit with defined roles and execution responsibility | E29: High | F29: There are multiple staff members focused solely on SME across departments, including retail banking, credit & risk management, trade finance, and others. | G29: High: The bank has a full-time SME unit of at least 3–5 staff with defined roles and responsibilities across core departments (e.g., sales, credit, and product). The team has decision-making authority Medium: The bank has 1-2 designated staff members, but SME is one of many responsibilities or roles that they hold in the bank Low: No SME-specific staff or execution roles exist | H29: Positive, as the presence of a full-time, multi-functional SME team with clear responsibilities and decision-making authority indicates strong internal ownership and coordination capacity | I29: Interview a senior leader (e.g., CSO or CEO) or the SME Business Lead (or related positions) to validate Complement with secondary information, such as LinkedIn profiles and team composition on the bank's website | J29: Both
C30: 2.2 | D30: 2.2 SME staff have performance targets and incentives | E30: No data | F30: Primary information is needed to answer this question. | G30: High: SME KPIs (e.g., loan disbursement, NPLs, turnaround time, cross-sell) are embedded in the SME unit's performance evaluations, and incentives reward SME results Medium: SME KPIs exist but only for front-line or business development staff, or incentives are not sufficiently encouraging performance Low: There are no clearly defined SME KPIs or incentives | H30: Positive, as embedding SME performance metrics in team performance can reinforce strategic prioritization | I30: Interview the SME Business Lead (or related positions) to validate | J30: Primary
C31: 2.4 | D31: 2.3 Relevant trainings for SME banking are provided for relevant staff | E31: Medium | F31: Family Bank has invested in SME-related capacity building for its staff across core departments (including credit, business development, and relationship management). However, it has done this through standalone efforts instead of ongoing opportunities. | G31: High: Staff related to SME operations or strategy receive the pertinent training and have ongoing upskilling opportunities to properly execute their roles in the SME context Medium: SME specific training is not sufficiently provided, or is only provided to some staff Low: No SME-specific training or technical capacity-building is available | H31: Positive, since widespread SME-specific training ensures that staff are equipped with the knowledge and tools needed to serve the SME segment effectively | I31: Interview the SME Business Lead (or related positions) to validate | J31: Primary
D32: 3. Competitive positioning
C33: 3.1 | D33: 3.1 SME strategy is informed by market research and benchmarking | E33: High | F33: While specific market research initiatives are not detailed, the bank's targeted programs for women and youth entrepreneurs suggest a data-driven approach to identifying and serving SME segments. These are presented on annual reports. | G33: High: The bank conducts market or client research (e.g., SME segmentation studies, behavioral data, competitor market share analysis) on at least a yearly basis, and findings have influenced strategy, product design, or delivery priorities Medium: Some SME-related research exists (e.g., old market studies or internal data analysis), but is not consistently updated or has limited influence on decision-making Low: No SME-specific research has been conducted, or insights are not used to shape strategy or service design | H33: Positive, as the use of structured SME research and competitor analysis ensures better-tailored products and services and overall positioning | I33: Interview the SME Business Lead (or related positions) to validate | J33: Primary
C34: 3.2 | D34: 3.2 The bank actively identifies and targets SME segments with an uncaptured market potential | E34: High | F34: SMEs form 80% of Family Bank's customer base. It targets Agribusinesses, women-owned enterprises, and youth businesses by recognizing their unique needs in its product and service offerings. It tracks segment-specific data in its annual reports. | G34: High: The bank deliberately targets SME segments that are underserved and show clear market potential, meaning limited competition from other banks and unmet demand Medium: The bank segments and targets SMEs, but selection is not clearly based on an untapped opportunity Low: The bank serves SMEs broadly without segment-specific targeting or consideration of competitive saturation | H34: Positive, because proactive targeting of high-potential SME segments improves the bank’s ability to differentiate in competitive markets | I34: Interview the SME Business Lead (or related positions) to validate | J34: Primary
C35: 3.3 | D35: 3.3 SME competitive positioning is well-recognized across the market | E35: High | F35: Family Bank positions itself as an SME-focused institution across its public communications and strategy documents. It has been awarded Best SME Bank in Kenya and has extensive reach to SMEs through its multiple branches (95) and rural presence. | G35: High: The bank has a distinct SME brand or value proposition that is consistently communicated across channels (e.g., website, marketing, physical branches) and recognized by clients or stakeholders Medium: The bank offers SME services and may reference SMEs in its materials, but lacks a clear value proposition or consistent branding that differentiates it from competitors Low: SME offerings are not visibly positioned or promoted. There is no SME-specific branding, value proposition, or messaging | H35: Positive, as a distinct and consistently communicated SME brand or value proposition enhances market visibility and reinforces the bank’s reputation as a serious SME player | I35: Interview a senior leader (e.g., CSO or CEO) or the SME Business Lead (or related positions) to validate Complement with secondary information, such as press coverage, award recognitions, and social media campaigns | J35: Secondary
C36: 3.4 | D36: 3.4 [Digital] The value proposition of SME banking is enhanced by data analytics and digital innovation | E36: No data | F36: Primary information is needed to answer this question. | G36: High: The SME value proposition is regularly enhanced through the use of data analytics or digital innovation (e.g., automated onboarding, digital credit scoring). These tools are actively used to shape SME product development or service delivery Medium: Some SME initiatives are informed by data or enhanced through digital strategies, but this is applied inconsistently or on a limited basis Low: SME offerings are rarely or never shaped by data analytics or digital tools | H36: Positive, as basing initiatives on market analyses ensures relevance, enhances SME uptake, and supports value-driven innovation. | I36: Interview a senior leader (e.g., CIO or CTO) as well as key staff responsible for SME digital banking (e.g., Head of SME Banking or similar roles) | J36: Primary
D37: 4. Operational processes
C38: 4.1 | D38: 4.1 SME credit processes are flexible and adapted to typical access-to-finance constraints and priorities of SMEs | E38: High | F38: Family Bank has tailored processes that recognize SME possibilities. For example, it uses cash-flow-based credit assessment models backed with insurance to lend to smallholder farmers. It also offers flexible collateral requirements to accommodate SME needs. | G38: High: Credit assessment processes are meaningfully adapted to SME realities (e.g., cash-flow-based analysis, flexible collateral, data-driven models) and are consistently applied by staff handling SME lending Medium: Some SME-appropriate credit practices exist but are applied inconsistently or are not institutionalized Low: SME credit follows standard corporate models with no tailored features | H38: Positive, because when the bank’s credit processes are meaningfully tailored to SME realities, financial products can be offered more safely and inclusively to a broader SME customer base | I38: Interview the SME Business Lead (or related positions) or other internal experts (e.g., Head of Credit or Head of Risk) to validate | J38: Primary
C39: 4.2 | D39: 4.2 Segmentation drives the design and tailoring of products and services | E39: High | F39: Family Bank focuses on specific SME segments, including agribusiness, women, and even Chinese-owned SMEs. Limited information on how frequently these segments are updated. | G39: High: SME segments are well-defined (e.g., by size, lifecycle, sector) and actively shape product or service design (e.g., pricing, bundling, distribution). Segmentation is regularly reviewed and updated Medium: Key SME segments are identified but used only superficially in some aspects of product and service design Low: There is no clear SME segmentation, or segmentation exists but has no influence on product or service decisions | H39: Positive, as the use of clearly defined SME segments to shape product, pricing, and delivery strategies enables more relevant and effective offerings across client types | I39: Interview the SME Business Lead (or related positions) or other internal experts (e.g., Product Manager) to validate | J39: Primary
C40: 4.3 | D40: 4.3 Relationship managers deliver tailored engagement to SMEs | E40: High | F40: Family Bank uses a relationship management model that offers end-to-end support. Relationship managers are usually assigned to specific SME segments or sectors. The bank implements CRM practices to enhance service quality and customer relations. | G40: High: Relationship managers or account officers are assigned to SME clients with defined portfolios and use structured engagement tools (e.g., CRM systems) Medium: There are SME focused staff who engage clients, but there are no consistent or standardized engagement practices Low: There is no relationship management model for SMEs, or interactions are reactive or handled by generalist staff | H40: Positive, since assigning relationship managers with dedicated SME portfolios ensures more consistent and targeted support that helps deepen long-term client relationships | I40: Interview the SME Business Lead (or related positions) or other internal experts (e.g., Lead Engagement Manager) to validate | J40: Primary
D41: 4.4 The bank analyzes broad client data to identify SME owners within other customer segments for cross-selling SME products and assessing creditworthiness | E41: No data | F41: Primary information is needed to answer this question. | G41: High: The bank systematically analyzes broad client data (e.g., transaction history, product usage, private financial profiles) to proactively identify SME owners or managers among clients in other segments (e.g., retail, corporate) and consistently uses these insights to cross-sell SME banking products and support credit assessments Medium: The bank occasionally or partially uses broad client data to identify SME owners in other segments, but this is not systematic, and the insights not commonly used to support cross-selling or credit evaluation Low: The bank does not analyze or use client data to expand its SME portfolio | H41: Positive, since proactively analyzing broad client data enables banks to identify untapped SME opportunities within their existing customer base, improve cross-selling of SME products, and strengthen credit risk assessments | I41: Interview the SME Business Lead (or related positions) to validate
C42: 4.4 | D42: 4.5 SME banking is integrated into internal systems and performance tracked through routine reporting | E42: High | F42: No information has been publicly disclosed, but from the Bank's reporting and tracking, SME portfolio performance seems to be monitored regularly and used to inform decision-making. | G42: High: SME portfolio performance (e.g., loan volume, NPLs, product use, client growth, default risk, officer productivity) is integrated into the bank’s reporting systems and reviewed at least quarterly Medium: SME data is tracked in core reporting systems but not disaggregated, periodically updated, or reviewed Low: SME is not embedded into reporting systems, or there is no regular SME performance tracking | H42: Positive, because integrating SME performance metrics into core systems and reviewing them regularly enables continuous improvement and supports more responsive management of the segment | I42: Interview a senior leader (e.g., COO) or the SME Business Lead (or related positions) to validate | J42: Primary
C43: 4.5 | D43: 4.6 [Digital] Key data systems (CRM, loan origination system, API) are fully integrated to enable seamless information flow across departments and branches | E43: No data | F43: Primary information is needed to answer this question. | G43: High: All critical systems that support SME banking, like customer records, loan approvals, and payments, are fully integrated and work smoothly together across departments and branches Medium: Some systems are connected, but others (like credit or customer information) still require manual steps or data transfers Low: Most systems are separate, requiring staff to manually move information between them, which slows down processes and increases the risk of errors | H43: Positive, since integrated systems streamline workflows, reduce duplication, and improve the delivery of SME digital services. | I43: Interview a senior leader (e.g., CIO or CTO) as well as key staff responsible for SME digital banking (e.g., Head of SME Banking or similar roles) | J43: Primary
C44: 4.6 | D44: 4.7 [Digital] The SME banking unit has a change management framework in place that enables rapid implementation of digital, data, and AI solutions internally and for clients | E44: No data | F44: Primary information is needed to answer this question. | G44: High: The bank follows clear procedures for keeping SME digital services running, including service-level commitments, tools for tracking and fixing issues, and structured rollout plans for changes and updates Medium: Some practices are in place (like issue tracking or support teams), but there's no single, consistent approach Low: Support for SME digital services is mostly informal. Issues are handled on an ad hoc basis | H44: Positive, because structured change management frameworks minimize service downtime and maintain trust during system upgrades. | I44: Interview a senior leader (e.g., CIO or CTO) as well as key staff responsible for SME digital banking (e.g., Head of SME Banking or similar roles) | J44: Primary
C45: 4.7 | D45: 4.8 [Digital] New SME digital features are typically launched quickly | E45: No data | F45: Primary information is needed to answer this question. | G45: High: Most SME digital features go from concept to release in under 12 weeks, supported by short development cycles and fast approvals Medium: The typical time to launch is 3–6 months, with some internal delays or dependencies Low: Launching a new SME digital feature takes 6+ months, or timelines are unpredictable | H45: Positive, because frequent release of new digital features reflects a responsive, customer-centric innovation cycle. | I45: Interview a senior leader (e.g., CIO or CTO) as well as key staff responsible for SME digital banking (e.g., Head of SME Banking or similar roles) | J45: Primary
C46: 4.8 | D46: 4.9 [Digital] SME digital services are compliant with data privacy regulations (e.g., consent capture, data usage visibility, storage security) | E46: No data | F46: Primary information is needed to answer this question. | G46: Yes: SME digital services have consent flows, visible data use terms, and storage aligned to national/global privacy standards No: No evidence of privacy protections or regulatory alignment | H46: Positive, because compliance with privacy and security regulations is essential to maintain trust and meet legal standards. | I46: Interview a senior leader (e.g., CIO or CTO) as well as key staff responsible for SME digital banking (e.g., Head of SME Banking or similar roles) | J46: Primary
D47: 5. Products and value proposition
D48: SME offerings
C49: 5.1 | D49: 5.1 Financial product offering is aligned and responsive to SME lifecycle stages | E49: Medium | F49: Family Bank offers products that are responsive to key SME lifecycle stages, including solutions tailored for businesses in nascent stages (e.g., Boost Loans) as well as those in more mature stages (e.g., Structured Trade Finance). | G49: High: The bank has identified key SME financial needs (e.g., working capital, equipment purchase, trade liquidity) and offers dedicated products that directly address these needs across all major SME lifecycle stages (e.g., startup, growth, maturity) Medium: The bank offers a broad range of standard SME products (e.g., overdrafts, term loans) and partially addresses some lifecycle needs, but products are not explicitly differentiated across lifecycle stages Low: The SME product offering is standardized and mostly limited to basic loan structures | H49: Positive, as offering SME-specific financial products tailored to lifecycle needs can help meet evolving SME demands, increase product uptake, and deepen client relationships over time | I49: Interview the SME Business Lead (or related positions) to validate Complement with secondary information, such as public product offerings | J49: Both
D50: 5.2 SME offerings include dedicated products for specific segments or client groups | E50: High | F50: Family Bank has a range of financial offerings that reflect and respond to MSME needs, including Agri-Business Loans, Trade Finance, and micro-loans, among others. The Bank has innovative products adapted to business needs, such as sector-specific loans. | G50: High: The bank offers fully developed product offerings targeting relevant SME sub-segments (e.g., women entrepreneurs, agribusinesses, exporters, family businesses) Medium: The bank has some products tailored to SME segments, but mostly offers standardized products with slight adjustments Low: The bank treats SMEs as a uniform group with no differentiation or sector-specific offerings | H50: Positive, as offering SME products tailored to specific sub-segments or sectors enhances competitive differentiation and can improve customer acquisition and loyalty | I50: Interview the SME Business Lead (or related positions) to validate Complement with secondary information, such as public product offerings | J50: Both
C51: 5.2 | D51: 5.3 Non-financial services are available and tailored to SME needs | E51: Medium | F51: Family Bank offers multiple non-financial services, including education, networking, and mobile banking support. However, these services are mainly directed to women, which limit their scope and reach among SME costumbers. | G51: High: The bank offers structured, SME-tailored non-financial services (e.g., training, mentorship, business advisory), targeted by segment or business need, and often bundled with financial products Medium: Some non-financial services are offered (e.g., financial literacy), but they are generic, lightly delivered, or not tailored to SME segments Low: There are no structured non-financial services offered to SMEs | H51: Positive, because structured, segment-tailored non-financial services (e.g., training, mentorship, advisory) enhance SME financial performance and reinforce the bank’s role as a trusted partner | I51: Interview the SME Business Lead (or related positions) to validate Complement with secondary information, such as public product offerings | J51: Both
D52: 5.4 [Digital] SME customers can perform core banking tasks (e.g., payments, balance checks, transfers) through the bank’s digital channels | E52: No data | F52: Primary information is needed to answer this question. | G52: High: A full range of SME financial services, including payments, transfers, account management, and business-specific tools, are accessible and fully functional through mobile and web platforms Medium: Some services are digitally available, but others are incomplete or require offline support Low: Key services are unavailable digitally or frequently fail | H52: Positive, since digital enablement of core tasks supports SME autonomy, improves efficiency, and promotes customer loyalty. | I52: Interview a senior leader (e.g., CIO or CTO) as well as key staff responsible for SME digital banking (e.g., Head of SME Banking or similar roles) | J52: Primary
C53: 5.3 | D53: 5.5 [Digital] Multiple digital non-financial services (e.g., cashflow management tools, invoicing, financial planning dashboards) are offered to SMEs | E53: No data | F53: Primary information is needed to answer this question. | G53: High: The bank offers multiple integrated non-financial tools via its SME platform or client interface (e.g., invoice generation, expense tracking, cash flow dashboards, and business analytics) Medium: Some basic, digital non-financial services are offered (e.g., invoice templates or simple calculators) Low: No digital non-financial services are available | H53: Positive, because offering digital non-financial tools supports broader SME needs and boosts their performance, enhancing loyalty and value delivery. | I53: Interview a senior leader (e.g., CIO or CTO) as well as key staff responsible for SME digital banking (e.g., Head of SME Banking or similar roles) | J53: Primary
C54: 5.4 | D54: 5.6 [Digital] SME-facing digital channels are easy to use, accessible, and reliable across web and mobile | E54: No data | F54: Primary information is needed to answer this question. | G54: High: SME customers consistently report high satisfaction with the usability, speed, and accessibility of the bank's digital channels. These are intuitive, mobile-friendly, and usable by customers with varying levels of digital fluency Medium: SME users report a generally functional experience, but with occasional complaints about usability, navigation, or mobile optimization Low: SME feedback highlights frequent frustration with the digital channels' interface, speed, or mobile performance | H54: Positive, since an intuitive and reliable digital interface enhances customer satisfaction and encourages consistent usage. | I54: Interview a senior leader (e.g., CIO or CTO) as well as key staff responsible for SME digital banking (e.g., Head of SME Banking or similar roles) | J54: Primary
D55: Financial performance
C56: 5.6 | D56: 5.7 SME loan portfolio shows consistent growth | E56: High | F56: Family Bank's SME portfolio has grown steadily in the last three years, reporting a 7% growth in the last year. | G56: High: SME loan portfolio has grown annually over the past three years Medium: Portfolio has grown, but inconsistently, over the past 3 years (ups and downs but net positive) Low: Flat or declining SME portfolio over the past three years | H56: Positive, as sustained SME portfolio growth over multiple years indicates strong market demand, effective outreach, and a likely alignment between product design and SME needs | I56: Interview the SME Business Lead (or related positions) or other internal experts (e.g., Head of Credit) to validate | J56: Primary
C57: 5.7 | D57: 5.8 SME NPL rate is within acceptable thresholds | E57: No data | F57: No information publicly available- | G57: High: SME NPLs are <5% and stable or improving Medium: SME NPLs are 5–12% Low: SME NPLs are >12% or worsening over time | H57: Positive, because maintaining low and stable SME NPLs suggests strong risk management practices and signals that credit offerings are well-calibrated to borrower capacity | I57: Interview the SME Business Lead (or related positions) or other internal experts (e.g., Head of Credit or Head of Risk) to validate | J57: Primary
C58: 5.8 | D58: 5.9 SME clients use multiple financial products, reflecting strong uptake | E58: No data | F58: Limited information on client cross-sell (no public data or indicators). | G58: High: A majority of SME clients use multiple products beyond credit (e.g., deposits, payments, insurance), with strong uptake of complementary services and clear efforts to deepen client relationships Medium: Most SME clients use more than one product (typically credit plus one), but product bundling is not proactively offered or acquired Low: Most SME clients rely on a single product (typically credit), with minimal use of additional services | H58: Positive, as high product uptake across SME clients reflects deeper relationships, improved client retention, and more diversified revenue streams for the bank | I58: Interview the SME Business Lead (or related positions) to validate | J58: Primary
C59: 5.9 | D59: 5.10 SME portfolios are financially sustainable or profitable | E59: High | F59: Family Bank's SME portfolio seems profitable as evidenced by rising interest income in 2023 and awards in SME excellence. | G59: High: The SME portfolio is profitable or contributes positively to the bank’s bottom line, based on internal costing or segment financials Medium: Portfolio is near breakeven or shows improving contribution over time Low: The SME portfolio is consistently generating losses, with negative contribution to profitability or requiring significant subsidy | H59: Positive, since SME portfolio profitability shows that the segment contributes to the bank’s financial performance and supports long-term viability | I59: Interview a senior leader (e.g., CFO or COO) and the SME Business Lead (or related positions) to validate | J59: Primary

Sheet Example 2
D4: Bank diagnostic
D5: •This sheet showcases a real-world example of the bank diagnostic in practice and provides guidance on scoring the various assessment areas and indicators. •Please note that this example is for illustrative purposes only. The scoring and rationale are based on secondary data and would likely differ significantly if complemented with primary data.
D9: Bank profile | G9: Overall standing
D10: Name: | E10: Banco Finandina | G10: {=_xlfn.IFS(G11<Methodology!G30,"Low maturity",G11<Methodology!G29,"Mid maturity",G11>=Methodology!G29,"High maturity")} -> #VALUE!
D11: Country of operation: | E11: Colombia | G11: {=_xlfn.LET(_xlpm.scores, _xlfn._xlws.FILTER(E19:E105, E19:E105<>""),SUMPRODUCT((_xlpm.scores="High")*Methodology!F15+(_xlpm.scores="Medium")*Methodology!F16+((_xlpm.scores="Low") + (_xlpm.scores="No data"))*Methodology!F17+(_xlpm.scores="Yes")*Methodology!I15+(_xlpm.scores="No")*Methodology!I16))} -> 60
D12: Bank type: | E12: Tier 2
D16: Criteria | E16: Score | F16: Rationale | G16: Scoring guidance | H16: Direction | I16: Assessment tips | J16: Type of source
D17: 1. Strategy
C18: # | D18: Overall strategy
C19: 1.1 | D19: 1.1 SME banking is a top priority for the bank | E19: No data | F19: This information needs to be validated with the bank's senior leadership. | G19: High: SME banking is explicitly named as one of the bank’s top 3 short-term strategic priorities Medium: SME banking is listed among the top 4–10 strategic priorities Low: SME banking is not clearly reflected among the bank's top strategic priorities or is absent from current strategy documentation | H19: Positive, given banks that consider SME programs a high priority are likely committed to their execution | I19: Interview at least two bank staff, including a senior leader (e.g., COO, CEO, or CSO), to ensure a well-rounded perspective | J19: Primary
C20: 1.2 | D20: 1.2 The targeted or current SME portfolio represents a significant share of the bank’s overall business | E20: No data | F20: This information needs to be validated with the bank's senior leadership. | G20: High: SMEs make up ≥20% of the bank’s current or targeted lending Medium: SMEs represent 10–19% of the bank’s lending Low: SMEs represent less than 10% of the bank’s lending | H20: Positive, as a high SME share of the loan book signals that SMEs are a core commercial focus, likely supported by resource allocation | I20: Interview at least two bank staff, including a senior leader (e.g., COO, CEO, or CSO), to ensure a well-rounded perspective | J20: Primary
C21: 1.3 | D21: SME strategy
C22: 1.3 | D22: 1.3 SME goals are clearly defined and time-bound | E22: Low | F22: Fincandina has no published specific SME targets or segment-specific indicators. Its published reports do not prioritize SME portfolios or targets. | G22: High: The bank has defined SME as a distinct segment with specific and measurable goals with 3–5 year timelines, tied to planning cycles Medium: SME goals exist but are not concrete, time-bound, or lack consistent tracking and updating Low: SME-related goals are vague or aspirational, with no actionable framework | H22: Positive, as clear, time-bound SME goals that are shared across teams suggest strategic cohesion and prioritization | I22: Interview the SME Business Lead (or related positions) or a senior leader (e.g., CSO) to validate Complement with secondary information, such as annual reports and investor relations presentations | J22: Both
C23: 1.4 | D23: 1.4 SME strategy and outcomes are periodically reviewed by senior leadership | E23: No data | F23: There is no public evidence that Finandina’s leadership formally reviews SME strategy or performance; reports focus on financial and digital outcomes without SME-specific discussion. | G23: High: SME operations and outcomes are closely monitored by at least one senior executive who is accountable for executing and reviewing the overall strategy on a quarterly basis Medium: SME operations are monitored but not reviewed as frequently by senior leadership (e.g., only annually) Low: No structured oversight or accountability is limited to middle management staff | H23: Positive, as periodic strategy reviews by senior leadership ensure accountability and course correction aligned with executive decision cycles | I23: Interview a senior leader (e.g., CSO or CEO) to validate | J23: Primary
C24: 1.5 | D24: 1.5 SME strategy is supported by structured, multi-year investment plans | E24: Low | F24: Finandina has invested over USD 10 million in digital transformation, indirectly benefiting SMEs, but it has not allocated funding to a dedicated, multi-year SME strategy. | G24: High: The bank has defined both medium-term (1-3 year horizon) and long-term (4-6 year horizon) investment plans and allocated sufficient resources in alignment with SME goals Medium: There is an investment plan, but resource allocation or execution timelines are not as clearly defined (e.g., very long term) Low: There are no investment plans or if present these lack clear resource allocation and timelines for execution | H24: Positive, since the presence of both medium- and long-term investment plans reflects a credible roadmap and strong institutional commitment | I24: Interview a senior leader (e.g., CSO or CEO) and the SME Business Lead (or related positions) to validate Complement with internal budget documents or similar resources | J24: Primary
C25: 1.6 | D25: 1.6 SME strategy is embedded across departments and delivery channels | E25: Medium | F25: Banco Finandina appears to have an implicit SME banking strategy, offering products and services under its "Business" portfolio and assigning oversight to cross-functional committees. However, SME banking does not appear to be strategic priority across the organization. | G25: High: The bank has a SME strategy that is known and reflected across core departments (e.g., credit, ops, risk, digital) and delivery teams (e.g., branches, agents, RMs). SME objectives and priorities are understood at the field level and included in branch plans Medium: SME priorities are partially reflected in support departments but weakly cascaded to delivery channels; some staff are aware, but ownership is uneven Low: There is not an SME strategy in place or there is little awareness or alignment on the SME strategy | H25: Positive, as a broad-based understanding of SME priorities across functions improves consistency in service delivery | I25: Interview the SME Business Lead (or related positions) to validate | J25: Primary
C26: 1.7 | D26: 1.7 SME impact goals have defined metrics and are consistently tracked | E26: Medium | F26: Finandina has set measurable impact goals for relevant development areas, such as green transportation. However, green projects are not tailored to SME needs and don't have time-bound KPIs, but more generalized goals. | G26: High: Inclusion KPIs (e.g., % loans to women-led or climate-aligned SMEs) are defined, tracked, and reviewed at least annually Medium: Inclusion KPIs are defined but not tracked periodically or at the SME level Low: Inclusion KPIs are not defined or tracked throughout the organization | H26: Positive, as the regular tracking of SME impact metrics demonstrates a commitment to measuring outcomes beyond disbursements and aligned with financial inclusion | I26: Interview the SME Business Lead (or related positions) to validate Complement with secondary information, such as annual reports and investor relations presentations | J26: Both
C27: 1.8 | D27: 1.8 Proven track record delivering strategic change initiatives (e.g., product rollout, digital migration, segment launch) | E27: High | F27: Finandina has effectively executed strategic initiatives, including the launch of Colombia’s first fully digital credit card, digital savings accounts, and a broader transformation into a 100% digital bank. | G27: High: The bank has successfully implemented at least two strategic or operational initiatives in the past 3–5 years, with clear delivery outcomes and cross-functional coordination Medium: Some change initiatives were implemented but with delays, limited scale, or unclear outcomes Low: Limited or no record of executing structured change beyond business-as-usual operations | H27: Positive, since the successful delivery of change initiatives reflects strong execution, learning, and adaptation capacity, which can be leveraged to drive future SME initiatives | I27: Interview a senior leader (e.g., CSO, COO, or CEO) to validate | J27: Primary
D28: 2. Talent and organizational structure
C29: 2.1 | D29: 2.1 Dedicated SME unit with defined roles and execution responsibility | E29: Medium | F29: Finandina appears to have a dedicated focus on business clients within its organization but not an explicit SME banking segment. It has limited staff with core SME responsibilities. | G29: High: The bank has a full-time SME unit of at least 3–5 staff with defined roles and responsibilities across core departments (e.g., sales, credit, and product). The team has decision-making authority Medium: The bank has 1-2 designated staff members, but SME is one of many responsibilities or roles that they hold in the bank Low: No SME-specific staff or execution roles exist | H29: Positive, as the presence of a full-time, multi-functional SME team with clear responsibilities and decision-making authority indicates strong internal ownership and coordination capacity | I29: Interview a senior leader (e.g., CSO or CEO) or the SME Business Lead (or related positions) to validate Complement with secondary information, such as LinkedIn profiles and team composition on the bank's website | J29: Both
C30: 2.2 | D30: 2.2 SME staff have performance targets and incentives | E30: No data | F30: Primary information is needed to answer this question. | G30: High: SME KPIs (e.g., loan disbursement, NPLs, turnaround time, cross-sell) are embedded in the SME unit's performance evaluations, and incentives reward SME results Medium: SME KPIs exist but only for front-line or business development staff, or incentives are not sufficiently encouraging performance Low: There are no clearly defined SME KPIs or incentives | H30: Positive, as embedding SME performance metrics in team performance can reinforces strategic prioritization | I30: Interview the SME Business Lead (or related positions) to validate | J30: Primary
C31: 2.4 | D31: 2.3 Relevant trainings for SME banking are provided for relevant staff | E31: Medium | F31: Finandina emphasizes staff training and development in general – for instance, in 2021 it provided over 2,600 hours of training and numerous educational scholarships to employees. However, there are no mentions of trainings tailored to the SME context. | G31: High: Staff related to SME operations or strategy receive the pertinent training and have ongoing upskilling opportunities to properly execute their roles in the SME context Medium: SME specific training is not sufficiently provided, or is only provided to some staff Low: No SME-specific training or technical capacity-building is available | H31: Positive, since widespread SME-specific training ensures that staff are equipped with the knowledge and tools needed to serve the SME segment effectively | I31: Interview the SME Business Lead (or related positions) to validate | J31: Primary
D32: 3. Competitive positioning
C33: 3.1 | D33: 3.1 SME strategy is informed by market research and benchmarking | E33: Medium | F33: Finandina’s SME offerings respond to specific segment needs, using market insights to design offerings like factoring and targeting underserved groups through its sustainable bond. However, there is no evidence of benchmarking or market positioning. | G33: High: The bank conducts market or client research (e.g., SME segmentation studies, behavioral data, competitor market share analysis) on at least a yearly basis, and findings have influenced strategy, product design, or delivery priorities Medium: Some SME-related research exists (e.g., old market studies or internal data analysis), but is not consistently updated or has limited influence on decision-making Low: No SME-specific research has been conducted, or insights are not used to shape strategy or service design | H33: Positive, as the use of structured SME research and competitor analysis ensures better-tailored products and services and overall positioning | I33: Interview the SME Business Lead (or related positions) to validate | J33: Primary
C34: 3.2 | D34: 3.2 The bank actively identifies and targets SME segments with an uncaptured market potential | E34: High | F34: The bank explicitly targets underserved SMEs, channeling credit to women-led and vulnerable-region businesses, and supporting informal entrepreneurs through digital access and microloans. | G34: High: The bank deliberately targets SME segments that are underserved and show clear market potential, meaning limited competition from other banks and unmet demand Medium: The bank segments and targets SMEs, but selection is not clearly based on an untapped opportunity Low: The bank serves SMEs broadly without segment-specific targeting or consideration of competitive saturation | H34: Positive, because proactive targeting of high-potential SME segments improves the bank’s ability to differentiate in competitive markets | I34: Interview the SME Business Lead (or related positions) to validate | J34: Primary
C35: 3.3 | D35: 3.3 SME competitive positioning is well-recognized across the market | E35: Low | F35: Finandina is not publicly recognized as a leading SME bank in Colombia. Its reputation has been built more on digital banking innovation. | G35: High: The bank has a distinct SME brand or value proposition that is consistently communicated across channels (e.g., website, marketing, physical branches) and recognized by clients or stakeholders Medium: The bank offers SME services and may reference SMEs in its materials, but lacks a clear value proposition or consistent branding that differentiates it from competitors Low: SME offerings are not visibly positioned or promoted. There is no SME-specific branding, value proposition, or messaging | H35: Positive, as a distinct and consistently communicated SME brand or value proposition enhances market visibility and reinforces the bank’s reputation as a serious SME player | I35: Interview a senior leader (e.g., CSO or CEO) or the SME Business Lead (or related positions) to validate Complement with secondary information, such as press coverage, award recognitions, and social media campaigns | J35: Secondary
C36: 3.4 | D36: 3.4 [Digital] The value proposition of SME banking is enhanced by data analytics and digital innovation | E36: No data | F36: Primary information is needed to answer this question. | G36: High: The SME value proposition is regularly enhanced through the use of data analytics or digital innovation (e.g., automated onboarding, digital credit scoring). These tools are actively used to shape SME product development or service delivery Medium: Some SME initiatives are informed by data or enhanced through digital strategies, but this is applied inconsistently or on a limited basis Low: SME offerings are rarely or never shaped by data analytics or digital tools | H36: Positive, as basing initiatives on market analyses ensures relevance, enhances SME uptake, and supports value-driven innovation. | I36: Interview a senior leader (e.g., CIO or CTO) as well as key staff responsible for SME digital banking (e.g., Head of SME Banking or similar roles) | J36: Primary
D37: 4. Operational processes
C38: 4.1 | D38: 4.1 SME credit processes are flexible and adapted to typical access-to-finance constraints and priorities of SMEs | E38: No data | F38: Little public information exists about Finandina’s specific credit model for SMEs. The bank’s risk management statements acknowledge SMEs as part of a diversified portfolio, but they do not describe using specialized credit methodologies. | G38: High: Credit assessment processes are meaningfully adapted to SME realities (e.g., cash-flow-based analysis, flexible collateral, data-driven models) and are consistently applied by staff handling SME lending Medium: Some SME-appropriate credit practices exist but are applied inconsistently or are not institutionalized Low: SME credit follows standard corporate models with no tailored features | H38: Positive, because when the bank’s credit processes are meaningfully tailored to SME realities, financial products can be offered more safely and inclusively to a broader SME customer base | I38: Interview the SME Business Lead (or related positions) or other internal experts (e.g., Head of Credit or Head of Risk) to validate | J38: Primary
C39: 4.2 | D39: 4.2 Segmentation drives the design and tailoring of products and services | E39: Medium | F39: Finandina broadly identifies SME segments, such as women-led enterprises and SMEs located in vulnerable locations. The bank also recognizes the key segments in which SMEs operate (E.g., services, commerce, and retail). However, there is no evidence that products and services are tailored according to these segments. | G39: High: SME segments are well-defined (e.g., by size, lifecycle, sector) and actively shape product or service design (e.g., pricing, bundling, distribution). Segmentation is regularly reviewed and updated Medium: Key SME segments are identified but used only superficially in some aspects of product and service design Low: There is no clear SME segmentation, or segmentation exists but has no influence on product or service decisions | H39: Positive, as the use of clearly defined SME segments to shape product, pricing, and delivery strategies enables more relevant and effective offerings across client types | I39: Interview the SME Business Lead (or related positions) or other internal experts (e.g., Product Manager) to validate | J39: Primary
C40: 4.3 | D40: 4.3 Relationship managers deliver tailored engagement to SMEs | E40: Low | F40: Finandina’s predominantly digital banking model means traditional relationship manager practices are less emphasized. In fact, the bank highlights a self-service digital model. | G40: High: Relationship managers or account officers are assigned to SME clients with defined portfolios and use structured engagement tools (e.g., CRM systems) Medium: There are SME focused staff who engage clients, but there are no consistent or standardized engagement practices Low: There is no relationship management model for SMEs, or interactions are reactive or handled by generalist staff | H40: Positive, since assigning relationship managers with dedicated SME portfolios ensures more consistent and targeted support that helps deepen long-term client relationships | I40: Interview the SME Business Lead (or related positions) or other internal experts (e.g., Lead Engagement Manager) to validate | J40: Primary
D41: 4.4 The bank analyzes broad client data to identify SME owners within other customer segments for cross-selling SME products and assessing creditworthiness | E41: No data | F41: Primary information is needed to answer this question. | G41: High: The bank systematically analyzes broad client data (e.g., transaction history, product usage, private financial profiles) to proactively identify SME owners or managers among clients in other segments (e.g., retail, corporate) and consistently uses these insights to cross-sell SME banking products and support credit assessments Medium: The bank occasionally or partially uses broad client data to identify SME owners in other segments, but this is not systematic, and the insights not commonly used to support cross-selling or credit evaluation Low: The bank does not analyze or use client data to expand its SME portfolio | H41: Positive, since proactively analyzing broad client data enables banks to identify untapped SME opportunities within their existing customer base, improve cross-selling of SME products, and strengthen credit risk assessments | I41: Interview the SME Business Lead (or related positions) to validate
C42: 4.4 | D42: 4.5 SME banking is integrated into internal systems and performance tracked through routine reporting | E42: Medium | F42: Finandina undoubtedly monitors its loan portfolio through internal systems, but it does not publicly share specific data for SME segments. The bank’s reporting to regulators and investors segments loans broadly. | G42: High: SME portfolio performance (e.g., loan volume, NPLs, product use, client growth, default risk, officer productivity) is integrated into the bank’s reporting systems and reviewed at least quarterly Medium: SME data is tracked in core reporting systems but not disaggregated, periodically updated, or reviewed Low: SME is not embedded into reporting systems, or there is no regular SME performance tracking | H42: Positive, because integrating SME performance metrics into core systems and reviewing them regularly enables continuous improvement and supports more responsive management of the segment | I42: Interview a senior leader (e.g., COO) or the SME Business Lead (or related positions) to validate | J42: Primary
C43: 4.5 | D43: 4.6 [Digital] Key data systems (CRM, loan origination system, API) are fully integrated to enable seamless information flow across departments and branches | E43: No data | F43: Primary information is needed to answer this question. | G43: High: All critical systems that support SME banking, like customer records, loan approvals, and payments, are fully integrated and work smoothly together across departments and branches Medium: Some systems are connected, but others (like credit or customer information) still require manual steps or data transfers Low: Most systems are separate, requiring staff to manually move information between them, which slows down processes and increases the risk of errors | H43: Positive, since integrated systems streamline workflows, reduce duplication, and improve the delivery of SME digital services. | I43: Interview a senior leader (e.g., CIO or CTO) as well as key staff responsible for SME digital banking (e.g., Head of SME Banking or similar roles) | J43: Primary
C44: 4.6 | D44: 4.7 [Digital] The SME banking unit has a change management framework in place that enables rapid implementation of digital, data, and AI solutions internally and for clients | E44: No data | F44: Primary information is needed to answer this question. | G44: High: The bank follows clear procedures for keeping SME digital services running, including service-level commitments, tools for tracking and fixing issues, and structured rollout plans for changes and updates Medium: Some practices are in place (like issue tracking or support teams), but there's no single, consistent approach Low: Support for SME digital services is mostly informal. Issues are handled on an ad hoc basis | H44: Positive, because structured change management frameworks minimize service downtime and maintain trust during system upgrades. | I44: Interview a senior leader (e.g., CIO or CTO) as well as key staff responsible for SME digital banking (e.g., Head of SME Banking or similar roles) | J44: Primary
C45: 4.7 | D45: 4.8 [Digital] New SME digital features are typically launched quickly | E45: No data | F45: Primary information is needed to answer this question. | G45: High: Most SME digital features go from concept to release in under 12 weeks, supported by short development cycles and fast approvals Medium: The typical time to launch is 3–6 months, with some internal delays or dependencies Low: Launching a new SME digital feature takes 6+ months, or timelines are unpredictable | H45: Positive, because frequent release of new digital features reflects a responsive, customer-centric innovation cycle. | I45: Interview a senior leader (e.g., CIO or CTO) as well as key staff responsible for SME digital banking (e.g., Head of SME Banking or similar roles) | J45: Primary
C46: 4.8 | D46: 4.9 [Digital] SME digital services are compliant with data privacy regulations (e.g., consent capture, data usage visibility, storage security) | E46: No data | F46: Primary information is needed to answer this question. | G46: Yes: SME digital services have consent flows, visible data use terms, and storage aligned to national/global privacy standards No: No evidence of privacy protections or regulatory alignment | H46: Positive, because compliance with privacy and security regulations is essential to maintain trust and meet legal standards. | I46: Interview a senior leader (e.g., CIO or CTO) as well as key staff responsible for SME digital banking (e.g., Head of SME Banking or similar roles) | J46: Primary
D47: 5. Products and value proposition
D48: SME offerings
C49: 5.1 | D49: 5.1 Financial product offering is aligned and responsive to SME lifecycle stages | E49: Medium | F49: Finandina’s business product suite responds to SME needs, offering tools like the Cuenta de Ahorro Empresarial for liquidity management and factoring to address working capital gaps. However, the number of products directed or tailored to SMEs specifically is limited. | G49: High: The bank has identified key SME financial needs (e.g., working capital, equipment purchase, trade liquidity) and offers dedicated products that directly address these needs across all major SME lifecycle stages (e.g., startup, growth, maturity) Medium: The bank offers a broad range of standard SME products (e.g., overdrafts, term loans) and partially addresses some lifecycle needs, but products are not explicitly differentiated across lifecycle stages Low: The SME product offering is standardized and mostly limited to basic loan structures | H49: Positive, as offering SME-specific financial products tailored to lifecycle needs can help meet evolving SME demands, increase product uptake, and deepen client relationships over time | I49: Interview the SME Business Lead (or related positions) to validate Complement with secondary information, such as public product offerings | J49: Both
D50: 5.2 SME offerings include dedicated products for specific segments or client groups | E50: Low | F50: Finandina does not publicly offer SME products for specific segments or client groups. | G50: High: The bank offers fully developed product offerings targeting relevant SME sub-segments (e.g., women entrepreneurs, agribusinesses, exporters, family businesses) Medium: The bank has some products tailored to SME segments, but mostly offers standardized products with slight adjustments Low: The bank treats SMEs as a uniform group with no differentiation or sector-specific offerings | H50: Positive, as offering SME products tailored to specific sub-segments or sectors enhances competitive differentiation and can improve customer acquisition and loyalty | I50: Interview the SME Business Lead (or related positions) to validate Complement with secondary information, such as public product offerings | J50: Both
C51: 5.2 | D51: 5.3 Non-financial services are available and tailored to SME needs | E51: Medium | F51: Finandina offers minimal non-financial SME support beyond blog content and educational articles; no structured advisory or training programs are publicly available. | G51: High: The bank offers structured, SME-tailored non-financial services (e.g., training, mentorship, business advisory), targeted by segment or business need, and often bundled with financial products Medium: Some non-financial services are offered (e.g., financial literacy), but they are generic, lightly delivered, or not tailored to SME segments Low: There are no structured non-financial services offered to SMEs | H51: Positive, because structured, segment-tailored non-financial services (e.g., training, mentorship, advisory) enhance SME financial performance and reinforce the bank’s role as a trusted partner | I51: Interview the SME Business Lead (or related positions) to validate Complement with secondary information, such as public product offerings | J51: Both
D52: 5.4 [Digital] SME customers can perform core banking tasks (e.g., payments, balance checks, transfers) through the bank’s digital channels | E52: No data | F52: Primary information is needed to answer this question. | G52: High: A full range of SME financial services, including payments, transfers, account management, and business-specific tools, are accessible and fully functional through mobile and web platforms Medium: Some services are digitally available, but others are incomplete or require offline support Low: Key services are unavailable digitally or frequently fail | H52: Positive, since digital enablement of core tasks supports SME autonomy, improves efficiency, and promotes customer loyalty. | I52: Interview a senior leader (e.g., CIO or CTO) as well as key staff responsible for SME digital banking (e.g., Head of SME Banking or similar roles) | J52: Primary
C53: 5.3 | D53: 5.5 [Digital] Multiple digital non-financial services (e.g., cashflow management tools, invoicing, financial planning dashboards) are offered to SMEs | E53: No data | F53: Primary information is needed to answer this question. | G53: High: The bank offers multiple integrated non-financial tools via its SME platform or client interface (e.g., invoice generation, expense tracking, cash flow dashboards, and business analytics) Medium: Some basic, digital non-financial services are offered (e.g., invoice templates or simple calculators) Low: No digital non-financial services are available | H53: Positive, because offering digital non-financial tools supports broader SME needs and boosts their performance, enhancing loyalty and value delivery. | I53: Interview a senior leader (e.g., CIO or CTO) as well as key staff responsible for SME digital banking (e.g., Head of SME Banking or similar roles) | J53: Primary
C54: 5.4 | D54: 5.6 [Digital] SME-facing digital channels are easy to use, accessible, and reliable across web and mobile | E54: No data | F54: Primary information is needed to answer this question. | G54: High: SME customers consistently report high satisfaction with the usability, speed, and accessibility of the bank's digital channels. These are intuitive, mobile-friendly, and usable by customers with varying levels of digital fluency Medium: SME users report a generally functional experience, but with occasional complaints about usability, navigation, or mobile optimization Low: SME feedback highlights frequent frustration with the digital channels' interface, speed, or mobile performance | H54: Positive, since an intuitive and reliable digital interface enhances customer satisfaction and encourages consistent usage. | I54: Interview a senior leader (e.g., CIO or CTO) as well as key staff responsible for SME digital banking (e.g., Head of SME Banking or similar roles) | J54: Primary
D55: Financial performance
C56: 5.6 | D56: 5.7 SME loan portfolio shows consistent growth | E56: No data | F56: Primary information is needed to answer this question. | G56: High: SME loan portfolio has grown annually over the past three years Medium: Portfolio has grown, but inconsistently, over the past 3 years (ups and downs but net positive) Low: Flat or declining SME portfolio over the past three years | H56: Positive, as sustained SME portfolio growth over multiple years indicates strong market demand, effective outreach, and a likely alignment between product design and SME needs | I56: Interview the SME Business Lead (or related positions) or other internal experts (e.g., Head of Credit) to validate | J56: Primary
C57: 5.7 | D57: 5.8 SME NPL rate is within acceptable thresholds | E57: No data | F57: Primary information is needed to answer this question. | G57: High: SME NPLs are <5% and stable or improving Medium: SME NPLs are 5–12% Low: SME NPLs are >12% or worsening over time | H57: Positive, because maintaining low and stable SME NPLs suggests strong risk management practices and signals that credit offerings are well-calibrated to borrower capacity | I57: Interview the SME Business Lead (or related positions) or other internal experts (e.g., Head of Credit or Head of Risk) to validate | J57: Primary
C58: 5.8 | D58: 5.9 SME clients use multiple financial products, reflecting strong uptake | E58: No data | F58: Primary information is needed to answer this question. | G58: High: A majority of SME clients use multiple products beyond credit (e.g., deposits, payments, insurance), with strong uptake of complementary services and clear efforts to deepen client relationships Medium: Most SME clients use more than one product (typically credit plus one), but product bundling is not proactively offered or acquired Low: Most SME clients rely on a single product (typically credit), with minimal use of additional services | H58: Positive, as high product uptake across SME clients reflects deeper relationships, improved client retention, and more diversified revenue streams for the bank | I58: Interview the SME Business Lead (or related positions) to validate | J58: Primary
C59: 5.9 | D59: 5.10 SME portfolios are financially sustainable or profitable | E59: No data | F59: Primary information is needed to answer this question. | G59: High: The SME portfolio is profitable or contributes positively to the bank’s bottom line, based on internal costing or segment financials Medium: Portfolio is near breakeven or shows improving contribution over time Low: The SME portfolio is consistently generating losses, with negative contribution to profitability or requiring significant subsidy | H59: Positive, since SME portfolio profitability shows that the segment contributes to the bank’s financial performance and supports long-term viability | I59: Interview a senior leader (e.g., CFO or COO) and the SME Business Lead (or related positions) to validate | J59: Primary

Sheet Methodology
E4: Methodology
E5: •This sheet outlines the scoring logic and key inputs that underpin the results of the SME bank diagnostic tool. •It defines scoring ratings, how overall scores are calculated, and the input for the gap analysis and strategic recommendations. The suggested paths to level up and focus areas are intended to be initial guidance to be taken for discussion; they are not prescriptive or seek to represent final solutions. •The framework is designed to be adaptable: you are encouraged to tailor scoring or recommendations to align with your organization's priorities and context.
E10: Overall bank diagnostic
E12: 1. Scoring guidance
E14: Label | F14: Numeric Score | H14: Label | I14: Numeric Score
E15: High | F15: 5 | H15: Yes | I15: 5
E16: Medium | F16: 3 | H16: No | I16: 0
E17: Low | F17: 1 | H17: No data | I17: 1
E19: Category | F19: Number of questions | G19: Low | H19: Medium | I19: High
E20: ='Bank diagnostic'!D17 -> 1. Strategy | F20: {=_xlfn.LET(_xlpm.range, 'Bank diagnostic'!D:D,_xlpm.startRow, MATCH(E20, _xlpm.range, 0) + 1,_xlpm.endRow, MATCH(E21, _xlpm.range, 0) - 1,_xlpm.section, INDEX(_xlpm.range, _xlpm.startRow):INDEX(_xlpm.range, _xlpm.endRow),_xlpm.indicators, _xlfn._xlws.FILTER(_xlpm.section, ISNUMBER(--LEFT(_xlpm.section,3)) * ISNUMBER(VALUE(MID(_xlpm.section,3,1))) * ISERROR(SEARCH("[Digital]", _xlpm.section))),ROWS(_xlpm.indicators))} -> #VALUE! | G20: =F20*$F$17 -> #VALUE! | H20: =F20*$F$16 -> #VALUE! | I20: =$F$15*F20 -> #VALUE!
E21: ='Bank diagnostic'!D28 -> 2. Talent and organizational structure | F21: {=_xlfn.LET(_xlpm.range, 'Bank diagnostic'!D:D,_xlpm.startRow, MATCH(E21, _xlpm.range, 0) + 1,_xlpm.endRow, MATCH(E22, _xlpm.range, 0) - 1,_xlpm.section, INDEX(_xlpm.range, _xlpm.startRow):INDEX(_xlpm.range, _xlpm.endRow),_xlpm.indicators, _xlfn._xlws.FILTER(_xlpm.section, ISNUMBER(--LEFT(_xlpm.section,3)) * ISNUMBER(VALUE(MID(_xlpm.section,3,1))) * ISERROR(SEARCH("[Digital]", _xlpm.section))),ROWS(_xlpm.indicators))} -> #VALUE! | G21: =F21*$F$17 -> #VALUE! | H21: =F21*$F$16 -> #VALUE! | I21: =$F$15*F21 -> #VALUE!
E22: ='Bank diagnostic'!D32 -> 3. Competitive positioning | F22: {=_xlfn.LET(_xlpm.range, 'Bank diagnostic'!D:D,_xlpm.startRow, MATCH(E22, _xlpm.range, 0) + 1,_xlpm.endRow, MATCH(E23, _xlpm.range, 0) - 1,_xlpm.section, INDEX(_xlpm.range, _xlpm.startRow):INDEX(_xlpm.range, _xlpm.endRow),_xlpm.indicators, _xlfn._xlws.FILTER(_xlpm.section, ISNUMBER(--LEFT(_xlpm.section,3)) * ISNUMBER(VALUE(MID(_xlpm.section,3,1))) * ISERROR(SEARCH("[Digital]", _xlpm.section))),ROWS(_xlpm.indicators))} -> #VALUE! | G22: =F22*$F$17 -> #VALUE! | H22: =F22*$F$16 -> #VALUE! | I22: =$F$15*F22 -> #VALUE!
E23: ='Bank diagnostic'!D37 -> 4. Operational processes | F23: {=_xlfn.LET(_xlpm.range, 'Bank diagnostic'!D:D,_xlpm.startRow, MATCH(E23, _xlpm.range, 0) + 1,_xlpm.endRow, MATCH(E24, _xlpm.range, 0) - 1,_xlpm.section, INDEX(_xlpm.range, _xlpm.startRow):INDEX(_xlpm.range, _xlpm.endRow),_xlpm.indicators, _xlfn._xlws.FILTER(_xlpm.section, ISNUMBER(--LEFT(_xlpm.section,3)) * ISNUMBER(VALUE(MID(_xlpm.section,3,1))) * ISERROR(SEARCH("[Digital]", _xlpm.section))),ROWS(_xlpm.indicators))} -> #VALUE! | G23: =F23*$F$17 -> #VALUE! | H23: =F23*$F$16 -> #VALUE! | I23: =$F$15*F23 -> #VALUE!
E24: ='Bank diagnostic'!D47 -> 5. Products and value proposition | F24: {=_xlfn.LET( _xlpm.range, 'Bank diagnostic'!D:D, _xlpm.startRow, MATCH(E24, _xlpm.range, 0) + 1, _xlpm.endRow, IFERROR(MATCH(E25, _xlpm.range, 0) - 1, LOOKUP(2, 1/(_xlpm.range<>""), ROW(_xlpm.range))), _xlpm.section, INDEX(_xlpm.range, _xlpm.startRow):INDEX(_xlpm.range, _xlpm.endRow), _xlpm.indicators, _xlfn._xlws.FILTER(_xlpm.section, ISNUMBER(--LEFT(_xlpm.section,3)) * ISNUMBER(VALUE(MID(_xlpm.section,3,1))) * ISERROR(SEARCH("[Digital]", _xlpm.section))), ROWS(_xlpm.indicators) )} -> #VALUE! | G24: =F24*$F$17 -> #VALUE! | H24: =F24*$F$16 -> #VALUE! | I24: =$F$15*F24 -> #VALUE!
E25: 6. Digital | F25: =COUNTIF('Bank diagnostic'!D:D, "*[Digital]*") -> 8 | G25: =F25*$F$17 -> 8 | H25: =F25*$F$16 -> 24 | I25: =$F$15*F25 -> 40
E26: Total | F26: =SUM(F20:F25) -> #VALUE! | G26: =SUM(G20:G25) -> #VALUE! | H26: =SUM(H20:H25) -> #VALUE! | I26: =SUM(I20:I25) -> #VALUE!
E28: SME banking maturity | F28: % of total (max) | G28: Min | H28: Max
E29: High maturity | F29: 0.8 | G29: =H29*F29 -> #VALUE! | H29: =I26 -> #VALUE!
E30: Mid maturity | F30: 0.6 | G30: =H29*F30 -> #VALUE! | H30: =G29-1 -> #VALUE!
E31: Low maturity | F31: >60% | G31: =G26 -> #VALUE! | H31: =G30-1 -> #VALUE!
E34: 2. Input for gap analysis and strategic recommendations
E36: Gap (low) | F36: Path to level-up | G36: Propsoed focus areas | H36: Gap (medium) | I36: Path to level-up | J36: Proposed focus areas
D37: # | E37: ='Bank diagnostic'!D17 -> 1. Strategy
D38: =VALUE(LEFT('Bank diagnostic'!D19,FIND(" ",'Bank diagnostic'!D19)-1)) -> 1.1 | E38: {=IFERROR(_xlfn.TEXTAFTER(INDEX('Bank diagnostic'!H:H, MATCH(TRUE, ISNUMBER(SEARCH(D38, 'Bank diagnostic'!D:D)), 0)),"Low:"), "Not Found")} -> SME banking is not clearly reflected among the bank's top strategic priorities or is absent from current strategy documentation | F38: Engage senior-leadership to clarify the relevance of SME banking as a strategic priority | G38: Provide a clear business case for the specific opportunity and an overview of the market enablers and market opportunity. Use the Business Case Tool to help build internal alignment and quantify the opportunity | H38: {=IFERROR(_xlfn.TEXTBEFORE(_xlfn.TEXTAFTER(INDEX('Bank diagnostic'!H:H, MATCH(TRUE, ISNUMBER(SEARCH(D38, 'Bank diagnostic'!D:D)), 0)),"Medium: "),"Low:"),"Not Found")} -> SME banking is listed among the top 4–10 strategic priorities | I38: Engage senior-leadership to clarify the relevance of SME banking as a strategic priority | J38: Provide a clear business case for the specific opportunity and an overview of the market enablers and market opportunity
D39: =VALUE(LEFT('Bank diagnostic'!D20,FIND(" ",'Bank diagnostic'!D20)-1)) -> 1.2 | E39: {=IFERROR(_xlfn.TEXTAFTER(INDEX('Bank diagnostic'!H:H, MATCH(TRUE, ISNUMBER(SEARCH(D39, 'Bank diagnostic'!D:D)), 0)),"Low:"), "Not Found")} -> SMEs represent less than 10% of the bank’s lending | F39: Further understand constraints to increase lending which could be driven by lack of SME reach, lack or inadequate product offering (financial and non-financial), unqualified staff,or unclear value proposition, among others | G39: Carry out an in depth assessment of the SME banking business performance to identify constraints and refine the strategy | H39: {=IFERROR(_xlfn.TEXTBEFORE(_xlfn.TEXTAFTER(INDEX('Bank diagnostic'!H:H, MATCH(TRUE, ISNUMBER(SEARCH(D39, 'Bank diagnostic'!D:D)), 0)),"Medium: "),"Low:"),"Not Found")} -> SMEs represent 10–19% of the bank’s lending | I39: Actively identify growth opportunities by conducting market assessments, market sizing, competitive analysis, and enterprise needs assessments | J39: Inform a growth strategy and roadmap to target increased penetration of the SME market
E40: SME strategy
D41: =VALUE(LEFT('Bank diagnostic'!D22,FIND(" ",'Bank diagnostic'!D22)-1)) -> 1.3 | E41: {=IFERROR(_xlfn.TEXTAFTER(INDEX('Bank diagnostic'!H:H, MATCH(TRUE, ISNUMBER(SEARCH(D41, 'Bank diagnostic'!D:D)), 0)),"Low:"), "Not Found")} -> SME-related goals are vague or aspirational, with no actionable framework | F41: Develop SME goals that are SMART (specific, measurable, achievable, relevant, and time-bound), and link them to the bank’s strategic plans | G41: Run goal-setting workshops with department heads to define 3–5 year SME targets and roadmaps with clear timelines, budget, and reporting frequency | H41: {=IFERROR(_xlfn.TEXTBEFORE(_xlfn.TEXTAFTER(INDEX('Bank diagnostic'!H:H, MATCH(TRUE, ISNUMBER(SEARCH(D41, 'Bank diagnostic'!D:D)), 0)),"Medium: "),"Low:"),"Not Found")} -> SME goals exist but are not concrete, time-bound, or lack consistent tracking and updating | I41: Revisit SME goals and identify if they need adjustment to align with SMART criteria and if a performance management system is required | J41: Build SME KPI dashboards and set quarterly review checkpoints with senior leadership. Use the Bank Dashboard Tool as a starting point | L41: High: The bank has defined, specific, and measurable SME goals with 3–5 year timelines, tied to planning cycles
D42: =VALUE(LEFT('Bank diagnostic'!D23,FIND(" ",'Bank diagnostic'!D23)-1)) -> 1.4 | E42: {=IFERROR(_xlfn.TEXTAFTER(INDEX('Bank diagnostic'!H:H, MATCH(TRUE, ISNUMBER(SEARCH(D42, 'Bank diagnostic'!D:D)), 0)),"Low:"), "Not Found")} -> No structured oversight or accountability is limited to middle management staff | F42: Appoint senior leaders to oversee SME strategy execution and integrate accountability into management routines | G42: Designate at least one senior staff member with formal oversight of SME strategy and performance; define a simple accountability mechanism with quarterly reporting or dashboard updates | H42: {=IFERROR(_xlfn.TEXTBEFORE(_xlfn.TEXTAFTER(INDEX('Bank diagnostic'!H:H, MATCH(TRUE, ISNUMBER(SEARCH(D42, 'Bank diagnostic'!D:D)), 0)),"Medium: "),"Low:"),"Not Found")} -> SME operations are monitored but not reviewed as frequently by senior leadership (e.g., only annually) | I42: Increase the frequency and depth of SME performance oversight by senior leadership | J42: Add SME progress as a standing agenda item in management committee meetings and rotate SME department updates quarterly | L42: High: SME operations and outcomes are closely monitored by at least one senior executive who is accountable for executing and reviewing the overall strategy on a quarterly basis
D43: =VALUE(LEFT('Bank diagnostic'!D24,FIND(" ",'Bank diagnostic'!D24)-1)) -> 1.5 | E43: {=IFERROR(_xlfn.TEXTAFTER(INDEX('Bank diagnostic'!H:H, MATCH(TRUE, ISNUMBER(SEARCH(D43, 'Bank diagnostic'!D:D)), 0)),"Low:"), "Not Found")} -> There are no investment plans or if present these lack clear resource allocation and timelines for execution | F43: Define SME investment needs and prioritize initiatives with structured budget planning and ownership | G43: Draft an SME investment roadmap with short- and medium-term priorities, budget lines, and department leads | H43: {=IFERROR(_xlfn.TEXTBEFORE(_xlfn.TEXTAFTER(INDEX('Bank diagnostic'!H:H, MATCH(TRUE, ISNUMBER(SEARCH(D43, 'Bank diagnostic'!D:D)), 0)),"Medium: "),"Low:"),"Not Found")} -> There is an investment plan, but resource allocation or execution timelines are not as clearly defined (e.g., very long term) | I43: Strengthen investment plans with specific timelines and SME-aligned resourcing | J43: Revise existing plans to include 1–3 and 4–6 year SME milestones tied to tracked spending commitments | L43: High: The bank has defined both medium-term (1-3 year horizon) and long-term (4-6 year horizon) investment plans and allocated sufficient resources in alignment with SME goals
D44: =VALUE(LEFT('Bank diagnostic'!D25,FIND(" ",'Bank diagnostic'!D25)-1)) -> 1.6 | E44: {=IFERROR(_xlfn.TEXTAFTER(INDEX('Bank diagnostic'!H:H, MATCH(TRUE, ISNUMBER(SEARCH(D44, 'Bank diagnostic'!D:D)), 0)),"Low:"), "Not Found")} -> There is not an SME strategy in place or there is little awareness or alignment on the SME strategy | F44: Develop a clear SME strategy aligned with the bank’s capacities, mission, and competitive positioning | G44: Launch a rapid strategy design sprint with leadership and department heads to co-create SME priorities, and formalize them in an internal strategy brief | H44: {=IFERROR(_xlfn.TEXTBEFORE(_xlfn.TEXTAFTER(INDEX('Bank diagnostic'!H:H, MATCH(TRUE, ISNUMBER(SEARCH(D44, 'Bank diagnostic'!D:D)), 0)),"Medium: "),"Low:"),"Not Found")} -> SME priorities are partially reflected in support departments but weakly cascaded to delivery channels; some staff are aware, but ownership is uneven | I44: Align SME priorities with core departmental functions, responsibilities, and accountability structures | J44: Revisit the SME strategy to ensure it is specific, actionable, and aligned with frontline realities; then cascade it through departmental working sessions and internal presentations to position its value-add
D45: =VALUE(LEFT('Bank diagnostic'!D26,FIND(" ",'Bank diagnostic'!D26)-1)) -> 1.7 | E45: {=IFERROR(_xlfn.TEXTAFTER(INDEX('Bank diagnostic'!H:H, MATCH(TRUE, ISNUMBER(SEARCH(D45, 'Bank diagnostic'!D:D)), 0)),"Low:"), "Not Found")} -> Inclusion KPIs are not defined or tracked throughout the organization | F45: Define SME inclusion priorities (e.g., women-led, youth, rural) and introduce basic KPIs | G45: Hold workshops on KPI definition for inclusion priorities and integrate tracking through dashboards or monitoring tools | H45: {=IFERROR(_xlfn.TEXTBEFORE(_xlfn.TEXTAFTER(INDEX('Bank diagnostic'!H:H, MATCH(TRUE, ISNUMBER(SEARCH(D45, 'Bank diagnostic'!D:D)), 0)),"Medium: "),"Low:"),"Not Found")} -> Inclusion KPIs are defined but not tracked periodically or at the SME level | I45: Institutionalize regular reviews of inclusion KPIs and link them with SME performance reviews | J45: Embed inclusion KPI tracking in annual SME strategy reviews and require departments to report on target achievement | L45: High: Inclusion KPIs (e.g., % loans to women-led or climate-aligned SMEs) are defined, tracked, and reviewed at least annually
D46: =VALUE(LEFT('Bank diagnostic'!D27,FIND(" ",'Bank diagnostic'!D27)-1)) -> 1.8 | E46: {=IFERROR(_xlfn.TEXTAFTER(INDEX('Bank diagnostic'!H:H, MATCH(TRUE, ISNUMBER(SEARCH(D46, 'Bank diagnostic'!D:D)), 0)),"Low:"), "Not Found")} -> Limited or no record of executing structured change beyond business-as-usual operations | F46: Start tracking key change initiatives (e.g., digital transformation, new products, segment pivots) and capture institutional learnings through structured reviews | G46: Establish basic change management capabilities related to MEL, knowledge management, and ongoing training or upskilling opportunities in areas where transformation is desired | H46: {=IFERROR(_xlfn.TEXTBEFORE(_xlfn.TEXTAFTER(INDEX('Bank diagnostic'!H:H, MATCH(TRUE, ISNUMBER(SEARCH(D46, 'Bank diagnostic'!D:D)), 0)),"Medium: "),"Low:"),"Not Found")} -> Some change initiatives were implemented but with delays, limited scale, or unclear outcomes | I46: Consistently track and reflect on change initiatives to identify capacity gaps and improve implementation | J46: Introduce a standard post-initiative review tool or structured reflection workshop to extract lessons and define next steps for effective change management | L46: High: The bank has successfully implemented at least two strategic or operational initiatives in the past 3–5 years, with clear delivery outcomes and cross-functional coordination
E47: ='Bank diagnostic'!D28 -> 2. Talent and organizational structure
D48: =VALUE(LEFT('Bank diagnostic'!D29,FIND(" ",'Bank diagnostic'!D29)-1)) -> 2.1 | E48: {=IFERROR(_xlfn.TEXTAFTER(INDEX('Bank diagnostic'!H:H, MATCH(TRUE, ISNUMBER(SEARCH(D48, 'Bank diagnostic'!D:D)), 0)),"Low:"), "Not Found")} -> No SME-specific staff or execution roles exist | F48: Assign formal SME responsibilities to teams and specific individuals aligned with SME strategy and delivery needs | G48: Designate SME focal points in core departments (e.g., credit, product, ops), with SME duties reflected in job descriptions and performance expectations | H48: {=IFERROR(_xlfn.TEXTBEFORE(_xlfn.TEXTAFTER(INDEX('Bank diagnostic'!H:H, MATCH(TRUE, ISNUMBER(SEARCH(D48, 'Bank diagnostic'!D:D)), 0)),"Medium: "),"Low:"),"Not Found")} -> The bank has 1-2 designated staff members, but SME is one of many responsibilities or roles that they hold in the bank | I48: Define a focused SME unit with dedicated SME roles and ensure senior-level buy-in | J48: Allocate SME delivery time explicitly in job responsibilities and assign SME-linked performance objectives where relevant | L48: High: The bank has a full-time SME team of at least 3–5 staff with defined roles and responsibilities across core departments (e.g., sales, credit, and product). The team has decision-making authority
D49: =VALUE(LEFT('Bank diagnostic'!D30,FIND(" ",'Bank diagnostic'!D30)-1)) -> 2.2 | E49: {=IFERROR(_xlfn.TEXTAFTER(INDEX('Bank diagnostic'!H:H, MATCH(TRUE, ISNUMBER(SEARCH(D49, 'Bank diagnostic'!D:D)), 0)),"Low:"), "Not Found")} -> There are no clearly defined SME KPIs or incentives | F49: Define SME performance metrics and link them to internal review cycles | G49: Hold cross-functional design sessions to define SME KPIs and embed them into performance tracking systems. Use the e Bank Dashboard Tool as a starting point | H49: {=IFERROR(_xlfn.TEXTBEFORE(_xlfn.TEXTAFTER(INDEX('Bank diagnostic'!H:H, MATCH(TRUE, ISNUMBER(SEARCH(D49, 'Bank diagnostic'!D:D)), 0)),"Medium: "),"Low:"),"Not Found")} -> SME KPIs exist but only for front-line or business development staff, or incentives are not sufficiently encouraging performance | I49: Link SME KPIs to team-level performance and track them consistently | J49: Integrate SME KPIs into dashboards and automate performance tracking. Include them in quarterly department reviews tied to incentive mechanisms. Use the Bank Dashboard Tool as a starting point | L49: High: All core departments (e.g., credit, risk, operations, digital) have defined SME tasks and collaborate effectively
D50: =VALUE(LEFT('Bank diagnostic'!D31,FIND(" ",'Bank diagnostic'!D31)-1)) -> 2.3 | E50: {=IFERROR(_xlfn.TEXTAFTER(INDEX('Bank diagnostic'!H:H, MATCH(TRUE, ISNUMBER(SEARCH(D50, 'Bank diagnostic'!D:D)), 0)),"Low:"), "Not Found")} -> No SME-specific training or technical capacity-building is available | F50: Introduce foundational training to build SME knowledge and awareness among relevant teams | G50: Roll out a mandatory SME fundamentals module for new and existing staff, co-developed with SME business leads | H50: {=IFERROR(_xlfn.TEXTBEFORE(_xlfn.TEXTAFTER(INDEX('Bank diagnostic'!H:H, MATCH(TRUE, ISNUMBER(SEARCH(D50, 'Bank diagnostic'!D:D)), 0)),"Medium: "),"Low:"),"Not Found")} -> SME specific training is not sufficiently provided, or is only provided to some staff | I50: Standardize SME training and integrate it into formal staff development plans | J50: Integrate SME training into role-based learning pathways and track participation via internal learning platforms. Reinforce content through refresher sessions | L50: High: Staff across departments receive the pertinent training and have ongoing upskilling opportunities to properly execute their roles in the SME context
E51: ='Bank diagnostic'!D32 -> 3. Competitive positioning
D52: =VALUE(LEFT('Bank diagnostic'!D33,FIND(" ",'Bank diagnostic'!D33)-1)) -> 3.1 | E52: {=IFERROR(_xlfn.TEXTAFTER(INDEX('Bank diagnostic'!H:H, MATCH(TRUE, ISNUMBER(SEARCH(D52, 'Bank diagnostic'!D:D)), 0)),"Low:"), "Not Found")} -> No SME-specific research has been conducted, or insights are not used to shape strategy or service design | F52: Conduct SME-specific client research and apply findings to strategy or product design | G52: Run a rapid SME client survey and present findings in a management learning session to inform strategy or product priorities. Use the Market Assessment and Market Sizing Tools as a starting point | H52: {=IFERROR(_xlfn.TEXTBEFORE(_xlfn.TEXTAFTER(INDEX('Bank diagnostic'!H:H, MATCH(TRUE, ISNUMBER(SEARCH(D52, 'Bank diagnostic'!D:D)), 0)),"Medium: "),"Low:"),"Not Found")} -> Some SME-related research exists (e.g., old market studies or internal data analysis), but is not consistently updated or has limited influence on decision-making | I52: Institutionalize research processes and ensure insights inform decision making processes | J52: Develop a rolling SME insights calendar (e.g., annual segmentation refresh, feedback loops) and link insights to product design, marketing, and strategy reviews. Use the market Market Assessment and Market Sizing Tools as a starting point | L52: High: The bank conducts market or client research (e.g., SME segmentation studies, behavioral data, competitor benchmarking) on at least a yearly basis, and findings have influenced strategy, product design, or delivery priorities
D53: =VALUE(LEFT('Bank diagnostic'!D34,FIND(" ",'Bank diagnostic'!D34)-1)) -> 3.2 | E53: {=IFERROR(_xlfn.TEXTAFTER(INDEX('Bank diagnostic'!H:H, MATCH(TRUE, ISNUMBER(SEARCH(D53, 'Bank diagnostic'!D:D)), 0)),"Low:"), "Not Found")} -> The bank serves SMEs broadly without segment-specific targeting or consideration of competitive saturation | F53: Launch targeted outreach and begin collecting demographic and segment data | G53: Launch targeted outreach campaigns for underserved SME segments (e.g., women-led, rural SMEs) and add demographic fields to client onboarding forms or CRM | H53: {=IFERROR(_xlfn.TEXTBEFORE(_xlfn.TEXTAFTER(INDEX('Bank diagnostic'!H:H, MATCH(TRUE, ISNUMBER(SEARCH(D53, 'Bank diagnostic'!D:D)), 0)),"Medium: "),"Low:"),"Not Found")} -> The bank segments and targets SMEs, but selection is not clearly based on an untapped opportunity | I53: Embed systematic tracking of segment-specific client data to identify scale opportunities and improvement opportunities | J53: Integrate segment-disaggregated SME data (e.g., gender, location, business size) into CRM and monitor engagement by segment for targeted follow-up | L53: High: The bank has an active outreach to underserved segments and uses a systematic approach to client engagement, including tracking segment specific data
D54: =VALUE(LEFT('Bank diagnostic'!D35,FIND(" ",'Bank diagnostic'!D35)-1)) -> 3.3 | E54: {=IFERROR(_xlfn.TEXTAFTER(INDEX('Bank diagnostic'!H:H, MATCH(TRUE, ISNUMBER(SEARCH(D54, 'Bank diagnostic'!D:D)), 0)),"Low:"), "Not Found")} -> SME offerings are not visibly positioned or promoted. There is no SME-specific branding, value proposition, or messaging | F54: Develop and communicate a basic SME value proposition across key channels | G54: Draft a distinct SME value proposition and update website, brochures, and in-branch materials to consistently highlight SME relevance. Use the Impact Case as a starting point | H54: {=IFERROR(_xlfn.TEXTBEFORE(_xlfn.TEXTAFTER(INDEX('Bank diagnostic'!H:H, MATCH(TRUE, ISNUMBER(SEARCH(D54, 'Bank diagnostic'!D:D)), 0)),"Medium: "),"Low:"),"Not Found")} -> The bank offers SME services and may reference SMEs in its materials, but lacks a clear value proposition or consistent branding that differentiates it from competitors | I54: Strengthen SME branding and align messaging across all customer touchpoints | J54: Create SME branding guidelines and align messaging across physical branches, digital channels, and sales scripts. Use the Impact Case as a starting point | L54: High: The bank has a distinct SME brand or value proposition that is consistently communicated across channels (e.g., website, marketing, physical branches) and recognized by clients or stakeholders
D55: =VALUE(LEFT('Bank diagnostic'!D36,FIND(" ",'Bank diagnostic'!D36)-1)) -> 3.4 | E55: {=IFERROR(_xlfn.TEXTAFTER(INDEX('Bank diagnostic'!H:H, MATCH(TRUE, ISNUMBER(SEARCH(D55, 'Bank diagnostic'!D:D)), 0)),"Low:"), "Not Found")} -> SME offerings are rarely or never shaped by data analytics or digital tools | F55: Launch basic user research (e.g., SME interviews, field visits) to uncover SME needs, pain points, and innovation opportunities | G55: Pair internal data (e.g., channel usage, declined loan applications) with 5–10 client interviews to quickly surface frictions that can be addressed through innovations or enhancements | H55: {=IFERROR(_xlfn.TEXTBEFORE(_xlfn.TEXTAFTER(INDEX('Bank diagnostic'!H:H, MATCH(TRUE, ISNUMBER(SEARCH(D55, 'Bank diagnostic'!D:D)), 0)),"Medium: "),"Low:"),"Not Found")} -> Some SME initiatives are informed by data or enhanced through digital strategies, but this is applied inconsistently or on a limited basis | I55: Institutionalize data analytics as a core component of product planning and use insights to guide feature development | J55: Build a recurring SME insights cycle by combining annual data analytics insights with quarterly product pulse checks, and integrate findings into product roadmap reviews and decision-making
E56: ='Bank diagnostic'!D37 -> 4. Operational processes
D57: =VALUE(LEFT('Bank diagnostic'!D38,FIND(" ",'Bank diagnostic'!D38)-1)) -> 4.1 | E57: {=IFERROR(_xlfn.TEXTAFTER(INDEX('Bank diagnostic'!H:H, MATCH(TRUE, ISNUMBER(SEARCH(D57, 'Bank diagnostic'!D:D)), 0)),"Low:"), "Not Found")} -> SME credit follows standard corporate models with no tailored features | F57: Introduce basic adaptations to credit processes that reflect SME-specific needs | G57: Develop SME-specific credit guidelines (e.g., flexible collateral, cashflow-based assessment) and train credit officers on when/how to apply them | H57: {=IFERROR(_xlfn.TEXTBEFORE(_xlfn.TEXTAFTER(INDEX('Bank diagnostic'!H:H, MATCH(TRUE, ISNUMBER(SEARCH(D57, 'Bank diagnostic'!D:D)), 0)),"Medium: "),"Low:"),"Not Found")} -> Some SME-appropriate credit practices exist but are applied inconsistently or are not institutionalized | I57: Standardize and embed SME-appropriate credit practices into core lending policies | J57: Update credit policy manuals to reflect SME-specific practices and train credit staff to apply them consistently | L57: High: Credit assessment processes are meaningfully adapted to SME realities (e.g., cash-flow-based analysis, flexible collateral, short documentation paths) and are consistently applied by staff handling SME lending
D58: =VALUE(LEFT('Bank diagnostic'!D39,FIND(" ",'Bank diagnostic'!D39)-1)) -> 4.2 | E58: {=IFERROR(_xlfn.TEXTAFTER(INDEX('Bank diagnostic'!H:H, MATCH(TRUE, ISNUMBER(SEARCH(D58, 'Bank diagnostic'!D:D)), 0)),"Low:"), "Not Found")} -> There is no clear SME segmentation, or segmentation exists but has no influence on product or service decisions | F58: Define core SME segments and use them to shape product development | G58: Segment SMEs using simple dimensions (e.g., size, age, sector) and map needs per segment to inform product and pricing design. Use the Segmentation Tool as a starting point | H58: {=IFERROR(_xlfn.TEXTBEFORE(_xlfn.TEXTAFTER(INDEX('Bank diagnostic'!H:H, MATCH(TRUE, ISNUMBER(SEARCH(D58, 'Bank diagnostic'!D:D)), 0)),"Medium: "),"Low:"),"Not Found")} -> Key SME segments are identified but used only superficially in some aspects of product and service design | I58: Operationalize segmentation to guide differentiated offerings and delivery models | J58: Use SME segment data to redesign key offerings and adjust distribution or communication strategies accordingly. Use the Segmentation Tool as a starting point | L58: High: SME segments are well-defined (e.g., by size, lifecycle, sector) and actively shape product or service design (e.g., pricing, bundling, distribution). Segmentation is regularly reviewed and updated
D59: =VALUE(LEFT('Bank diagnostic'!D40,FIND(" ",'Bank diagnostic'!D40)-1)) -> 4.3 | E59: {=IFERROR(_xlfn.TEXTAFTER(INDEX('Bank diagnostic'!H:H, MATCH(TRUE, ISNUMBER(SEARCH(D59, 'Bank diagnostic'!D:D)), 0)),"Low:"), "Not Found")} -> There is no relationship management model for SMEs, or interactions are reactive or handled by generalist staff | F59: Assign SME relationship ownership and introduce structured engagement | G59: Assign relationship managers to SME portfolios and introduce engagement tools like client plans, visit trackers, or basic CRM usage | H59: {=IFERROR(_xlfn.TEXTBEFORE(_xlfn.TEXTAFTER(INDEX('Bank diagnostic'!H:H, MATCH(TRUE, ISNUMBER(SEARCH(D59, 'Bank diagnostic'!D:D)), 0)),"Medium: "),"Low:"),"Not Found")} -> There are SME focused staff who engage clients, but there are no consistent or standardized engagement practices | I59: Standardize SME relationship management processes | J59: Develop an SME client management playbook with engagement cadence, documentation templates, and feedback loops | L59: High: Relationship managers or account officers are assigned to SME clients with defined portfolios and use structured engagement tools (e.g., CRM systems)
D60: =VALUE(LEFT('Bank diagnostic'!D41,FIND(" ",'Bank diagnostic'!D41)-1)) -> 4.4 | E60: {=IFERROR(_xlfn.TEXTAFTER(INDEX('Bank diagnostic'!H:H, MATCH(TRUE, ISNUMBER(SEARCH(D60, 'Bank diagnostic'!D:D)), 0)),"Low:"), "Not Found")} -> The bank does not analyze or use client data to expand its SME portfolio | F60: Coordinate with other key bank departments (e.g., retail, corporate) to access relevant client data that can help identify potential SME owners | G60: Incorporate broad client data into SME data practices and systems to analyze cross-sell opportunities and support credit assessment processes | H60: {=IFERROR(_xlfn.TEXTBEFORE(_xlfn.TEXTAFTER(INDEX('Bank diagnostic'!H:H, MATCH(TRUE, ISNUMBER(SEARCH(D60, 'Bank diagnostic'!D:D)), 0)),"Medium: "),"Low:"),"Not Found")} -> The bank occasionally or partially uses broad client data to identify SME owners in other segments, but this is not systematic, and the insights not commonly used to support cross-selling or credit evaluation | I60: Institutionalize client data analysis as a key process within the SME unit to support the expansion of the SME portfolio | J60: Systematize the analysis of broad client data for SME cross-sell by deploying automated algorithms to detect SME ownership across all client segments and embedding formal internal process guidelines
D61: =VALUE(LEFT('Bank diagnostic'!D42,FIND(" ",'Bank diagnostic'!D42)-1)) -> 4.5 | E61: {=IFERROR(_xlfn.TEXTAFTER(INDEX('Bank diagnostic'!H:H, MATCH(TRUE, ISNUMBER(SEARCH(D61, 'Bank diagnostic'!D:D)), 0)),"Low:"), "Not Found")} -> SME is not embedded into reporting systems, or there is no regular SME performance tracking | F61: Start tracking SME portfolio performance using basic indicators | G61: Add SME-specific filters (e.g., loan volume, client count) into existing dashboards and assign ownership for quarterly reporting. Use the Bank Dashboards Tool as a starting point | H61: {=IFERROR(_xlfn.TEXTBEFORE(_xlfn.TEXTAFTER(INDEX('Bank diagnostic'!H:H, MATCH(TRUE, ISNUMBER(SEARCH(D61, 'Bank diagnostic'!D:D)), 0)),"Medium: "),"Low:"),"Not Found")} -> SME data is tracked in core reporting systems but not disaggregated, periodically updated, or reviewed | I61: Improve granularity and cadence of SME performance tracking | J61: Set up automated reports with disaggregated SME indicators and integrate insights into quarterly organizational reviews | L61: High: SME portfolio performance (e.g., loan volume, NPLs, product use, client growth) is integrated into the bank’s reporting systems and reviewed at least quarterly
D62: =VALUE(LEFT('Bank diagnostic'!D43,FIND(" ",'Bank diagnostic'!D43)-1)) -> 4.6 | E62: {=IFERROR(_xlfn.TEXTAFTER(INDEX('Bank diagnostic'!H:H, MATCH(TRUE, ISNUMBER(SEARCH(D62, 'Bank diagnostic'!D:D)), 0)),"Low:"), "Not Found")} -> Most systems are separate, requiring staff to manually move information between them, which slows down processes and increases the risk of errors | F62: Map core SME-related systems and pinpoint where manual steps or weak connections slow down digital workflows | G62: Facilitate an IT-SME business workshop to identify system handoffs that cause the most friction (e.g., onboarding, loan origination), and prioritize them for early-stage integration pilots | H62: {=IFERROR(_xlfn.TEXTBEFORE(_xlfn.TEXTAFTER(INDEX('Bank diagnostic'!H:H, MATCH(TRUE, ISNUMBER(SEARCH(D62, 'Bank diagnostic'!D:D)), 0)),"Medium: "),"Low:"),"Not Found")} -> Some systems are connected, but others (like credit or customer information) still require manual steps or data transfers | I62: Develop a phased integration roadmap to connect remaining fragmented systems, starting with those most critical to SME banking | J62: Use APIs or middleware to connect high-priority systems and align this workstream with broader IT architecture upgrades
D63: =VALUE(LEFT('Bank diagnostic'!D44,FIND(" ",'Bank diagnostic'!D44)-1)) -> 4.7 | E63: {=IFERROR(_xlfn.TEXTAFTER(INDEX('Bank diagnostic'!H:H, MATCH(TRUE, ISNUMBER(SEARCH(D63, 'Bank diagnostic'!D:D)), 0)),"Low:"), "Not Found")} -> Support for SME digital services is mostly informal. Issues are handled on an ad hoc basis | F63: Surface common service breakdowns affecting SME users and designate initial owners responsible for resolving them | G63: Launch a shared SME issue log, assign interim coordinators, and review trends monthly to track resolution speed | H63: {=IFERROR(_xlfn.TEXTBEFORE(_xlfn.TEXTAFTER(INDEX('Bank diagnostic'!H:H, MATCH(TRUE, ISNUMBER(SEARCH(D63, 'Bank diagnostic'!D:D)), 0)),"Medium: "),"Low:"),"Not Found")} -> Some practices are in place (like issue tracking or support teams), but there's no single, consistent approach | I63: Establish a structured digital support model with defined roles, escalation paths, and performance targets | J63: Codify service processes in a playbook, set service-level objectives, and digitize support flows
D64: =VALUE(LEFT('Bank diagnostic'!D45,FIND(" ",'Bank diagnostic'!D45)-1)) -> 4.8 | E64: {=IFERROR(_xlfn.TEXTAFTER(INDEX('Bank diagnostic'!H:H, MATCH(TRUE, ISNUMBER(SEARCH(D64, 'Bank diagnostic'!D:D)), 0)),"Low:"), "Not Found")} -> Launching a new SME digital feature takes 6+ months, or timelines are unpredictable | F64: Analyze past SME digital initiatives to uncover process delays (e.g., internal reviews, testing) and define what “fast-track” could look like | G64: Map and streamline the delivery workflow by identifying handoff delays (e.g., approvals, vendor onboarding) and introducing simplified fast tracks | H64: {=IFERROR(_xlfn.TEXTBEFORE(_xlfn.TEXTAFTER(INDEX('Bank diagnostic'!H:H, MATCH(TRUE, ISNUMBER(SEARCH(D64, 'Bank diagnostic'!D:D)), 0)),"Medium: "),"Low:"),"Not Found")} -> The typical time to launch is 3–6 months, with some internal delays or dependencies | I64: Align SME digital stakeholders around a shared delivery cadence by connecting sprint planning, testing, and approvals | J64: Create a shared release calendar and automate testing and deployment stages to shorten cycle times and improve coordination
D65: =VALUE(LEFT('Bank diagnostic'!D46,FIND(" ",'Bank diagnostic'!D46)-1)) -> 4.9 | E65: {=IFERROR(_xlfn.TEXTAFTER(INDEX('Bank diagnostic'!H:H, MATCH(TRUE, ISNUMBER(SEARCH(D65, 'Bank diagnostic'!D:D)), 0)),"No:"), "Not Found")} -> No evidence of privacy protections or regulatory alignment | F65: Benchmark existing SME data practices against local data protection laws and baseline requirements | G65: Implement SME-specific consent management tools and provide clear digital privacy settings in self-service interfaces
E66: ='Bank diagnostic'!D47 -> 5. Products and value proposition
E67: ='Bank diagnostic'!D48 -> SME offerings
D68: =VALUE(LEFT('Bank diagnostic'!D49,FIND(" ",'Bank diagnostic'!D49)-1)) -> 5.1 | E68: {=IFERROR(_xlfn.TEXTAFTER(INDEX('Bank diagnostic'!H:H, MATCH(TRUE, ISNUMBER(SEARCH(D68, 'Bank diagnostic'!D:D)), 0)),"Low:"), "Not Found")} -> The SME product offering is standardized and mostly limited to basic loan structures | F68: Expand the SME product suite to include non-credit financial services | G68: Map common SME financial needs (e.g., payments, savings, insurance) across lifecycle stages, then introduce at least one new non-loan product | H68: {=IFERROR(_xlfn.TEXTBEFORE(_xlfn.TEXTAFTER(INDEX('Bank diagnostic'!H:H, MATCH(TRUE, ISNUMBER(SEARCH(D68, 'Bank diagnostic'!D:D)), 0)),"Medium: "),"Low:"),"Not Found")} -> The bank offers a broad range of standard SME products (e.g., overdrafts, term loans) and partially addresses some lifecycle needs, but products are not explicitly differentiated across lifecycle stages | I68: Use client feedback and usage data to refine and tailor offerings according to key lifecycle stages (e.g., startup, growth, maturity) | J68: Collect maturity-level SME usage data and validate product design through client workshops to refine features, pricing, and bundling | L68: High: The bank has identified the most pressing SME financing needs (e.g., working capital gaps, equipment purchase, trade liquidity) and offers dedicated products that directly address these. It has products targeting specific SME segments (e.g., women, agribusinesses, green finance, etc.).
D69: =VALUE(LEFT('Bank diagnostic'!D50,FIND(" ",'Bank diagnostic'!D50)-1)) -> 5.2 | E69: {=IFERROR(_xlfn.TEXTAFTER(INDEX('Bank diagnostic'!H:H, MATCH(TRUE, ISNUMBER(SEARCH(D69, 'Bank diagnostic'!D:D)), 0)),"Low:"), "Not Found")} -> The bank treats SMEs as a uniform group with no differentiation or sector-specific offerings | F69: Identify the most relevant client groups and product needs to start tailoring SME offering accordingly | G69: Collect data to identify relevant SME client groups (e.g., women, agribusinesses, young entrepreneurs) and pilot low-risk tailored products for at least one of these | H69: {=IFERROR(_xlfn.TEXTBEFORE(_xlfn.TEXTAFTER(INDEX('Bank diagnostic'!H:H, MATCH(TRUE, ISNUMBER(SEARCH(D69, 'Bank diagnostic'!D:D)), 0)),"Medium: "),"Low:"),"Not Found")} -> The bank has some products tailored to SME segments, but mostly offers standardized products with slight adjustments | I69: Systematically track portfolio performance, product uptake, and repayment behaviors by sub-segment (e.g., women-led SMEs, agribusinesses) | J69: Use data analytics to proactively offer tailored product and services based on transaction patterns, industry cycles, or client behavior within sub-segments
D70: =VALUE(LEFT('Bank diagnostic'!D51,FIND(" ",'Bank diagnostic'!D51)-1)) -> 5.3 | E70: {=IFERROR(_xlfn.TEXTAFTER(INDEX('Bank diagnostic'!H:H, MATCH(TRUE, ISNUMBER(SEARCH(D70, 'Bank diagnostic'!D:D)), 0)),"Low:"), "Not Found")} -> There are no structured non-financial services offered to SMEs | F70: Launch foundational non-financial services to build SME capacity | G70: Start with a low-cost, high-impact support offer, such as monthly group webinars, to introduce value-added engagement to SME clients | H70: {=IFERROR(_xlfn.TEXTBEFORE(_xlfn.TEXTAFTER(INDEX('Bank diagnostic'!H:H, MATCH(TRUE, ISNUMBER(SEARCH(D70, 'Bank diagnostic'!D:D)), 0)),"Medium: "),"Low:"),"Not Found")} -> Some non-financial services are offered (e.g., financial literacy), but they are generic, lightly delivered, or not tailored to SME segments | I70: Make non-financial services more targeted and integrated into client engagement | J70: Develop tiered non-financial offerings (e.g., growth clinics, peer networking events, sector-specific toolkits) and promote them actively for higher engagement | L70: High: The bank offers structured, SME-tailored non-financial services (e.g., training, mentorship, business advisory), targeted by segment or business need, and often bundled with financial products
D71: =VALUE(LEFT('Bank diagnostic'!D52,FIND(" ",'Bank diagnostic'!D52)-1)) -> 5.4 | E71: {=IFERROR(_xlfn.TEXTAFTER(INDEX('Bank diagnostic'!H:H, MATCH(TRUE, ISNUMBER(SEARCH(D71, 'Bank diagnostic'!D:D)), 0)),"Low:"), "Not Found")} -> Key services are unavailable digitally or frequently fail | F71: Inventory SME-relevant digital services (e.g., payments, transfers, account management) and identify where service delivery is incomplete, inconsistent, or fails | G71: Prioritize fixes for high-impact gaps (e.g., failed transfers, blocked transactions), and ensure core services meet uptime thresholds | H71: {=IFERROR(_xlfn.TEXTBEFORE(_xlfn.TEXTAFTER(INDEX('Bank diagnostic'!H:H, MATCH(TRUE, ISNUMBER(SEARCH(D71, 'Bank diagnostic'!D:D)), 0)),"Medium: "),"Low:"),"Not Found")} -> Some services are digitally available, but others are incomplete or require offline support | I71: Compare functionality and reliability of SME services across digital channels to ensure consistency and eliminate dependency on in-person channels | J71: Upgrade underperforming SME services (e.g., transfers, payments) to match performance of core retail features, ensuring 24/7 availability across mobile and web
D72: =VALUE(LEFT('Bank diagnostic'!D53,FIND(" ",'Bank diagnostic'!D53)-1)) -> 5.5 | E72: {=IFERROR(_xlfn.TEXTAFTER(INDEX('Bank diagnostic'!H:H, MATCH(TRUE, ISNUMBER(SEARCH(D72, 'Bank diagnostic'!D:D)), 0)),"Low:"), "Not Found")} -> No digital non-financial services are available | F72: Identify the non-financial services that can be offered digitally to respond to SME pain points or challenges | G72: Introduce SME-facing tools such as digital recordkeeping templates, business advisory, or tax calculators through the mobile app or web portal | H72: {=IFERROR(_xlfn.TEXTBEFORE(_xlfn.TEXTAFTER(INDEX('Bank diagnostic'!H:H, MATCH(TRUE, ISNUMBER(SEARCH(D72, 'Bank diagnostic'!D:D)), 0)),"Medium: "),"Low:"),"Not Found")} -> Some basic, digital non-financial services are offered (e.g., invoice templates or simple calculators) | I72: Create a digital plan for the bank's non-financial offering to respond to all of the most pressing SME needs (e.g., business growth, compliance) and focus on increasing digital engagement. | J72: Offer access to SME-relevant tools like business health dashboards, e-commerce onboarding kits, or connections to accounting services
D73: =VALUE(LEFT('Bank diagnostic'!D54,FIND(" ",'Bank diagnostic'!D54)-1)) -> 5.6 | E73: {=IFERROR(_xlfn.TEXTAFTER(INDEX('Bank diagnostic'!H:H, MATCH(TRUE, ISNUMBER(SEARCH(D73, 'Bank diagnostic'!D:D)), 0)),"Low:"), "Not Found")} -> SME feedback highlights frequent frustration with the digital channels' interface, speed, or mobile performance | F73: Collect and categorize user complaints related to digital experience (e.g., navigation, load times) and use frontline staff and usage data as inputs | G73: Run a usability audit on mobile and web platforms, and prioritize quick wins (e.g., loading speed, menu clarity) for iterative rollout | H73: {=IFERROR(_xlfn.TEXTBEFORE(_xlfn.TEXTAFTER(INDEX('Bank diagnostic'!H:H, MATCH(TRUE, ISNUMBER(SEARCH(D73, 'Bank diagnostic'!D:D)), 0)),"Medium: "),"Low:"),"Not Found")} -> SME users report a generally functional experience, but with occasional complaints about usability, navigation, or mobile optimization | I73: Use structured user testing with SME clients to validate interface improvements and ensure platforms meet diverse usability needs | J73: Integrate usability testing into the design cycle and link findings to the digital product backlog
E74: ='Bank diagnostic'!D55 -> Financial performance
D75: =VALUE(LEFT('Bank diagnostic'!D56,FIND(" ",'Bank diagnostic'!D56)-1)) -> 5.7 | E75: {=IFERROR(_xlfn.TEXTAFTER(INDEX('Bank diagnostic'!H:H, MATCH(TRUE, ISNUMBER(SEARCH(D75, 'Bank diagnostic'!D:D)), 0)),"Low:"), "Not Found")} -> Flat or declining SME portfolio over the past three years | F75: Stabilize and restart portfolio growth through targeted strategies | G75: Analyze SME drop-off trends and adjust product, marketing, or risk approaches to unlock growth | H75: {=IFERROR(_xlfn.TEXTBEFORE(_xlfn.TEXTAFTER(INDEX('Bank diagnostic'!H:H, MATCH(TRUE, ISNUMBER(SEARCH(D75, 'Bank diagnostic'!D:D)), 0)),"Medium: "),"Low:"),"Not Found")} -> Portfolio has grown, but inconsistently, over the past 3 years (ups and downs but net positive) | I75: Sustain growth through targeted acquisition and channel discipline | J75: Set quarterly SME growth targets by segment and run targeted campaigns linked to those segments’ preferred products or channels | L75: High: SME loan portfolio has grown annually over the past three years
D76: =VALUE(LEFT('Bank diagnostic'!D57,FIND(" ",'Bank diagnostic'!D57)-1)) -> 5.8 | E76: {=IFERROR(_xlfn.TEXTAFTER(INDEX('Bank diagnostic'!H:H, MATCH(TRUE, ISNUMBER(SEARCH(D76, 'Bank diagnostic'!D:D)), 0)),"Low:"), "Not Found")} -> SME NPLs are >12% or worsening over time | F76: Reduce risk exposure and improve early warning capability | G76: Launch a risk deep-dive to diagnose drivers and develop early warning signals for high-risk clients. Start with the Credit Riks Management Tool | H76: {=IFERROR(_xlfn.TEXTBEFORE(_xlfn.TEXTAFTER(INDEX('Bank diagnostic'!H:H, MATCH(TRUE, ISNUMBER(SEARCH(D76, 'Bank diagnostic'!D:D)), 0)),"Medium: "),"Low:"),"Not Found")} -> SME NPLs are 5–12% | I76: Improve loan performance through portfolio segmentation and pre-default action | J76: Segment SME NPLs by cause (e.g., documentation gaps, repayment capacity) and design differentiated resolution strategies for each group. Start with the Credit Riks Management Tool | L76: High: SME NPLs are <5% and stable or improving
D77: =VALUE(LEFT('Bank diagnostic'!D58,FIND(" ",'Bank diagnostic'!D58)-1)) -> 5.9 | E77: {=IFERROR(_xlfn.TEXTAFTER(INDEX('Bank diagnostic'!H:H, MATCH(TRUE, ISNUMBER(SEARCH(D77, 'Bank diagnostic'!D:D)), 0)),"Low:"), "Not Found")} -> Most SME clients rely on a single product (typically credit), with minimal use of additional services | F77: Deepen SME client relationships by driving structured uptake of product bundles | G77: Conduct client-level wallet share analysis and launch targeted cross-sell campaigns for priority products | H77: {=IFERROR(_xlfn.TEXTBEFORE(_xlfn.TEXTAFTER(INDEX('Bank diagnostic'!H:H, MATCH(TRUE, ISNUMBER(SEARCH(D77, 'Bank diagnostic'!D:D)), 0)),"Medium: "),"Low:"),"Not Found")} -> Most SME clients use more than one product (typically credit plus one), but product bundling is not proactively offered or acquired | I77: Institutionalize product bundling and link it to the client lifecycle and segmentation strategy | J77: Define relevant SME product bundles according to SME client behaviours and needs and train frontline staff to offer them as default options during sales and renewals | L77: High: A majority of SME clients use multiple products beyond credit (e.g., deposits, payments, insurance), with strong uptake of complementary services and clear efforts to deepen client relationships
D78: =VALUE(LEFT('Bank diagnostic'!D59,FIND(" ",'Bank diagnostic'!D59)-1)) -> 5.1 | E78: {=IFERROR(_xlfn.TEXTAFTER(INDEX('Bank diagnostic'!H:H, MATCH(TRUE, ISNUMBER(SEARCH(D78, 'Bank diagnostic'!D:D)), 0)),"Low:"), "Not Found")} -> The SME product offering is standardized and mostly limited to basic loan structures | F78: Understand and address the root causes of underperformance in the SME portfolio | G78: Conduct a profitability analysis at the product and segment level to identify causes and adjust pricing or delivery models based on results | H78: {=IFERROR(_xlfn.TEXTBEFORE(_xlfn.TEXTAFTER(INDEX('Bank diagnostic'!H:H, MATCH(TRUE, ISNUMBER(SEARCH(D78, 'Bank diagnostic'!D:D)), 0)),"Medium: "),"Low:"),"Not Found")} -> The bank offers a broad range of standard SME products (e.g., overdrafts, term loans) and partially addresses some lifecycle needs, but products are not explicitly differentiated across lifecycle stages | I78: Improve SME contribution by optimizing revenue mix and cost structures | J78: Use segment-level financial data to refine acquisition strategies and prioritize operational improvements in low-yield or high-cost areas of SME delivery | L78: High: The SME portfolio is profitable or contributes positively to the bank’s bottom line, based on internal costing or segment financials

Sheet Results
C6: Bank SME banking maturity
C11: Bank name: | D11: ='Bank diagnostic'!F10 -> Bank X
C12: Overall score: | D12: =_xlfn.CONCAT(TEXT('Bank diagnostic'!H11,"0")," / ",Methodology!I26) -> #VALUE!
C13: Overall standing: | D13: ='Bank diagnostic'!H10 -> #VALUE!
C14: High maturity areas (inc. digital) | D14: =COUNTIF(J20:J25, "High maturity") & " / 6 areas ranked as high maturity" -> 1 / 6 areas ranked as high maturity
C15: Refer to the methodology tab to understand the scoring criteria
C17: Overview of the bank diagnostic | N17: Gap analysis and recommended focus areas
F19: Assessment area | G19: Score | H19: Max | J19: Rating | N19: Area | O19: Key gaps | P19: Path to level up | Q19: Proposed focus areas
F20: ='Bank diagnostic'!D17 -> 1. Strategy | G20: {=_xlfn.LET(_xlpm.range, 'Bank diagnostic'!D:D,_xlpm.values, 'Bank diagnostic'!F:F,_xlpm.startLabel, F20,_xlpm.nextLabel, F21,_xlpm.startRow, MATCH(_xlpm.startLabel, _xlpm.range, 0) + 1,_xlpm.endRow, IFERROR(MATCH(_xlpm.nextLabel, _xlpm.range, 0) - 1, LOOKUP(2,1/(_xlpm.range<>""), ROW(_xlpm.range))),_xlpm.indicatorRange, INDEX(_xlpm.range, _xlpm.startRow):INDEX(_xlpm.range, _xlpm.endRow),_xlpm.scores, INDEX(_xlpm.values, _xlpm.startRow):INDEX(_xlpm.values, _xlpm.endRow),_xlpm.filterMask, ISERROR(SEARCH("[Digital]", _xlpm.indicatorRange)),_xlpm.filteredScores, _xlfn._xlws.FILTER(_xlpm.scores, _xlpm.filterMask),SUMPRODUCT((_xlpm.filteredScores="High")*Methodology!$F$15+(_xlpm.filteredScores="Medium")*Methodology!$F$16+((_xlpm.filteredScores="Low")+(_xlpm.filteredScores="No data"))*Methodology!$F$17+(_xlpm.filteredScores="Yes")*Methodology!$I$15+(_xlpm.filteredScores="No")*Methodology!$I$16))} -> 30 | H20: =G20/Methodology!I20 -> #VALUE! | I20: 1 | J20: {=_xlfn.IFS(G20<=(Methodology!I20*Methodology!$F$30),"Low maturity", G20<(Methodology!I20*Methodology!$F$29),"Mid maturity",G20>=(Methodology!I20*Methodology!$F$29),"High maturity")} -> #VALUE! | N20: ='Bank diagnostic'!D17 -> 1. Strategy | O20: ="• " & IFERROR(_xlfn.TEXTJOIN(CHAR(10) & "• ", TRUE, IF('Bank diagnostic'!F19="Low", Methodology!E38, IF('Bank diagnostic'!F19="Medium", Methodology!H38, "")), IF('Bank diagnostic'!F20="Low", Methodology!E39, IF('Bank diagnostic'!F20="Medium", Methodology!H39, "")), IF('Bank diagnostic'!F22="Low", Methodology!E41, IF('Bank diagnostic'!F22="Medium", Methodology!H41, "")), IF('Bank diagnostic'!F23="Low", Methodology!E42, IF('Bank diagnostic'!F23="Medium", Methodology!H42, "")), IF('Bank diagnostic'!F24="Low", Methodology!E43, IF('Bank diagnostic'!F24="Medium", Methodology!H43, "")), IF('Bank diagnostic'!F25="Low", Methodology!E44, IF('Bank diagnostic'!F25="Medium", Methodology!H44, "")), IF('Bank diagnostic'!F26="Low", Methodology!E45, IF('Bank diagnostic'!F26="Medium", Methodology!H45, "")), IF('Bank diagnostic'!F27="Low", Methodology!E46, IF('Bank diagnostic'!F27="Medium", Methodology!H46, "")) ), "") -> • SME banking is listed among the top 4–10 strategic priorities • No structured oversight or accountability is limited to middle management staff • Inclusion KPIs are not defined or tracked throughout the organization | P20: ="• " & IFERROR(_xlfn.TEXTJOIN(CHAR(10) & "• ", TRUE, IF('Bank diagnostic'!F19="Low", Methodology!F38, IF('Bank diagnostic'!F19="Medium", Methodology!I38, "")), IF('Bank diagnostic'!F20="Low", Methodology!F39, IF('Bank diagnostic'!F20="Medium", Methodology!I39, "")), IF('Bank diagnostic'!F22="Low", Methodology!F41, IF('Bank diagnostic'!F22="Medium", Methodology!I41, "")), IF('Bank diagnostic'!F23="Low", Methodology!F42, IF('Bank diagnostic'!F23="Medium", Methodology!I42, "")), IF('Bank diagnostic'!F24="Low", Methodology!F43, IF('Bank diagnostic'!F24="Medium", Methodology!I43, "")), IF('Bank diagnostic'!F25="Low", Methodology!F44, IF('Bank diagnostic'!F25="Medium", Methodology!I44, "")), IF('Bank diagnostic'!F26="Low", Methodology!F45, IF('Bank diagnostic'!F26="Medium", Methodology!I45, "")), IF('Bank diagnostic'!F27="Low", Methodology!F46, IF('Bank diagnostic'!F27="Medium", Methodology!I46, "")) ), "") -> • Engage senior-leadership to clarify the relevance of SME banking as a strategic priority • Appoint senior leaders to oversee SME strategy execution and integrate accountability into management routines • Define SME inclusion priorities (e.g., women-led, youth, rural) and introduce basic KPIs | Q20: ="• " & IFERROR(_xlfn.TEXTJOIN(CHAR(10) & "• ", TRUE, IF('Bank diagnostic'!F19="Low", Methodology!G38, IF('Bank diagnostic'!F19="Medium", Methodology!J38, "")), IF('Bank diagnostic'!F20="Low", Methodology!G39, IF('Bank diagnostic'!F20="Medium", Methodology!J39, "")), IF('Bank diagnostic'!F22="Low", Methodology!G41, IF('Bank diagnostic'!F22="Medium", Methodology!J41, "")), IF('Bank diagnostic'!F23="Low", Methodology!G42, IF('Bank diagnostic'!F23="Medium", Methodology!J42, "")), IF('Bank diagnostic'!F24="Low", Methodology!G43, IF('Bank diagnostic'!F24="Medium", Methodology!J43, "")), IF('Bank diagnostic'!F25="Low", Methodology!G44, IF('Bank diagnostic'!F25="Medium", Methodology!J44, "")), IF('Bank diagnostic'!F26="Low", Methodology!G45, IF('Bank diagnostic'!F26="Medium", Methodology!J45, "")), IF('Bank diagnostic'!F27="Low", Methodology!G46, IF('Bank diagnostic'!F27="Medium", Methodology!J46, "")) ), "") -> • Provide a clear business case for the specific opportunity and an overview of the market enablers and market opportunity • Designate at least one senior staff member with formal oversight of SME strategy and performance; define a simple accountability mechanism with quarterly reporting or dashboard updates • Hold workshops on KPI definition for inclusion priorities and integrate tracking through dashboards or monitoring tools
F21: ='Bank diagnostic'!D28 -> 2. Talent and organizational structure | G21: {=_xlfn.LET(_xlpm.range, 'Bank diagnostic'!D:D,_xlpm.values, 'Bank diagnostic'!F:F,_xlpm.startLabel, F21,_xlpm.nextLabel, F22,_xlpm.startRow, MATCH(_xlpm.startLabel, _xlpm.range, 0) + 1,_xlpm.endRow, IFERROR(MATCH(_xlpm.nextLabel, _xlpm.range, 0) - 1, LOOKUP(2,1/(_xlpm.range<>""), ROW(_xlpm.range))),_xlpm.indicatorRange, INDEX(_xlpm.range, _xlpm.startRow):INDEX(_xlpm.range, _xlpm.endRow),_xlpm.scores, INDEX(_xlpm.values, _xlpm.startRow):INDEX(_xlpm.values, _xlpm.endRow),_xlpm.filterMask, ISERROR(SEARCH("[Digital]", _xlpm.indicatorRange)),_xlpm.filteredScores, _xlfn._xlws.FILTER(_xlpm.scores, _xlpm.filterMask),SUMPRODUCT((_xlpm.filteredScores="High")*Methodology!$F$15+(_xlpm.filteredScores="Medium")*Methodology!$F$16+((_xlpm.filteredScores="Low")+(_xlpm.filteredScores="No data"))*Methodology!$F$17+(_xlpm.filteredScores="Yes")*Methodology!$I$15+(_xlpm.filteredScores="No")*Methodology!$I$16))} -> 11 | H21: =G21/Methodology!I21 -> #VALUE! | I21: 1 | J21: {=_xlfn.IFS(G21<=(Methodology!I21*Methodology!$F$30),"Low maturity", G21<(Methodology!I21*Methodology!$F$29),"Mid maturity",G21>=(Methodology!I21*Methodology!$F$29),"High maturity")} -> #VALUE! | N21: ='Bank diagnostic'!D28 -> 2. Talent and organizational structure | O21: {="• " & IFERROR(_xlfn.TEXTJOIN(CHAR(10) & "• ", TRUE, IF('Bank diagnostic'!F28:F31="Low", Methodology!E47:E50, IF('Bank diagnostic'!F28:F31="Medium", Methodology!H47:H50, "")) ), "")} -> • No SME-specific staff or execution roles exist | P21: {="• " & IFERROR(_xlfn.TEXTJOIN(CHAR(10) & "• ", TRUE, IF('Bank diagnostic'!F28:F31="Low", Methodology!F47:F50, IF('Bank diagnostic'!F28:F31="Medium", Methodology!I47:I50, "")) ), "")} -> • Assign formal SME responsibilities to teams and specific individuals aligned with SME strategy and delivery needs | Q21: {="• " & IFERROR(_xlfn.TEXTJOIN(CHAR(10) & "• ", TRUE, IF('Bank diagnostic'!F28:F31="Low", Methodology!G47:G50, IF('Bank diagnostic'!F28:F31="Medium", Methodology!J47:J50, "")) ), "")} -> • Designate SME focal points in core departments (e.g., credit, product, ops), with SME duties reflected in job descriptions and performance expectations
F22: ='Bank diagnostic'!D32 -> 3. Competitive positioning | G22: {=_xlfn.LET(_xlpm.range, 'Bank diagnostic'!D:D,_xlpm.values, 'Bank diagnostic'!F:F,_xlpm.startLabel, F22,_xlpm.nextLabel, F23,_xlpm.startRow, MATCH(_xlpm.startLabel, _xlpm.range, 0) + 1,_xlpm.endRow, IFERROR(MATCH(_xlpm.nextLabel, _xlpm.range, 0) - 1, LOOKUP(2,1/(_xlpm.range<>""), ROW(_xlpm.range))),_xlpm.indicatorRange, INDEX(_xlpm.range, _xlpm.startRow):INDEX(_xlpm.range, _xlpm.endRow),_xlpm.scores, INDEX(_xlpm.values, _xlpm.startRow):INDEX(_xlpm.values, _xlpm.endRow),_xlpm.filterMask, ISERROR(SEARCH("[Digital]", _xlpm.indicatorRange)),_xlpm.filteredScores, _xlfn._xlws.FILTER(_xlpm.scores, _xlpm.filterMask),SUMPRODUCT((_xlpm.filteredScores="High")*Methodology!$F$15+(_xlpm.filteredScores="Medium")*Methodology!$F$16+((_xlpm.filteredScores="Low")+(_xlpm.filteredScores="No data"))*Methodology!$F$17+(_xlpm.filteredScores="Yes")*Methodology!$I$15+(_xlpm.filteredScores="No")*Methodology!$I$16))} -> 11 | H22: =G22/Methodology!I22 -> #VALUE! | I22: 1 | J22: {=_xlfn.IFS(G22<=(Methodology!I22*Methodology!$F$30),"Low maturity", G22<(Methodology!I22*Methodology!$F$29),"Mid maturity",G22>=(Methodology!I22*Methodology!$F$29),"High maturity")} -> #VALUE! | N22: ='Bank diagnostic'!D32 -> 3. Competitive positioning | O22: {="• " & IFERROR(_xlfn.TEXTJOIN(CHAR(10) & "• ", TRUE, IF('Bank diagnostic'!F33:F35="Low", Methodology!E52:E54, IF('Bank diagnostic'!F33:F35="Medium", Methodology!H52:H54, "")) ), "")} -> • The bank serves SMEs broadly without segment-specific targeting or consideration of competitive saturation | P22: {="• " & IFERROR(_xlfn.TEXTJOIN(CHAR(10) & "• ", TRUE, IF('Bank diagnostic'!F33:F35="Low", Methodology!F52:F54, IF('Bank diagnostic'!F33:F35="Medium", Methodology!I52:I54, "")) ), "")} -> • Launch targeted outreach and begin collecting demographic and segment data | Q22: {="• " & IFERROR(_xlfn.TEXTJOIN(CHAR(10) & "• ", TRUE, IF('Bank diagnostic'!F33:F35="Low", Methodology!G52:G54, IF('Bank diagnostic'!F33:F35="Medium", Methodology!J52:J54, "")) ), "")} -> • Launch targeted outreach campaigns for underserved SME segments (e.g., women-led, rural SMEs) and add demographic fields to client onboarding forms or CRM
F23: ='Bank diagnostic'!D37 -> 4. Operational processes | G23: {=_xlfn.LET(_xlpm.range, 'Bank diagnostic'!D:D,_xlpm.values, 'Bank diagnostic'!F:F,_xlpm.startLabel, F23,_xlpm.nextLabel, F24,_xlpm.startRow, MATCH(_xlpm.startLabel, _xlpm.range, 0) + 1,_xlpm.endRow, IFERROR(MATCH(_xlpm.nextLabel, _xlpm.range, 0) - 1, LOOKUP(2,1/(_xlpm.range<>""), ROW(_xlpm.range))),_xlpm.indicatorRange, INDEX(_xlpm.range, _xlpm.startRow):INDEX(_xlpm.range, _xlpm.endRow),_xlpm.scores, INDEX(_xlpm.values, _xlpm.startRow):INDEX(_xlpm.values, _xlpm.endRow),_xlpm.filterMask, ISERROR(SEARCH("[Digital]", _xlpm.indicatorRange)),_xlpm.filteredScores, _xlfn._xlws.FILTER(_xlpm.scores, _xlpm.filterMask),SUMPRODUCT((_xlpm.filteredScores="High")*Methodology!$F$15+(_xlpm.filteredScores="Medium")*Methodology!$F$16+((_xlpm.filteredScores="Low")+(_xlpm.filteredScores="No data"))*Methodology!$F$17+(_xlpm.filteredScores="Yes")*Methodology!$I$15+(_xlpm.filteredScores="No")*Methodology!$I$16))} -> 19 | H23: =G23/Methodology!I23 -> #VALUE! | I23: 1 | J23: {=_xlfn.IFS(G23<=(Methodology!I23*Methodology!$F$30),"Low maturity", G23<(Methodology!I23*Methodology!$F$29),"Mid maturity",G23>=(Methodology!I23*Methodology!$F$29),"High maturity")} -> #VALUE! | N23: ='Bank diagnostic'!D37 -> 4. Operational processes | O23: {="• " & IFERROR(_xlfn.TEXTJOIN(CHAR(10) & "• ", TRUE, IF('Bank diagnostic'!F38:F42="Low", Methodology!E57:E61, IF('Bank diagnostic'!F38:F42="Medium", Methodology!H57:H61, "")) ), "")} -> • Some SME-appropriate credit practices exist but are applied inconsistently or are not institutionalized • There are SME focused staff who engage clients, but there are no consistent or standardized engagement practices • The bank occasionally or partially uses broad client data to identify SME owners in other segments, but this is not systematic, and the insights not commonly used to support cross-selling or credit evaluation | P23: {="• " & IFERROR(_xlfn.TEXTJOIN(CHAR(10) & "• ", TRUE, IF('Bank diagnostic'!F38:F42="Low", Methodology!F57:F61, IF('Bank diagnostic'!F38:F42="Medium", Methodology!I57:I61, "")) ), "")} -> • Standardize and embed SME-appropriate credit practices into core lending policies • Standardize SME relationship management processes • Institutionalize client data analysis as a key process within the SME unit to support the expansion of the SME portfolio | Q23: {="• " & IFERROR(_xlfn.TEXTJOIN(CHAR(10) & "• ", TRUE, IF('Bank diagnostic'!F38:F42="Low", Methodology!G57:G61, IF('Bank diagnostic'!F38:F42="Medium", Methodology!J57:J61, "")) ), "")} -> • Update credit policy manuals to reflect SME-specific practices and train credit staff to apply them consistently • Develop an SME client management playbook with engagement cadence, documentation templates, and feedback loops • Systematize the analysis of broad client data for SME cross-sell by deploying automated algorithms to detect SME ownership across all client segments and embedding formal internal process guidelines
F24: ='Bank diagnostic'!D47 -> 5. Products and value proposition | G24: {=_xlfn.LET(_xlpm.range, 'Bank diagnostic'!D:D,_xlpm.values, 'Bank diagnostic'!F:F,_xlpm.startLabel, F24,_xlpm.nextLabel, F25,_xlpm.startRow, MATCH(_xlpm.startLabel, _xlpm.range, 0) + 1,_xlpm.endRow, IFERROR(MATCH(_xlpm.nextLabel, _xlpm.range, 0) - 1, LOOKUP(2,1/(_xlpm.range<>""), ROW(_xlpm.range))), _xlpm.indicatorRange, INDEX(_xlpm.range, _xlpm.startRow):INDEX(_xlpm.range, _xlpm.endRow),_xlpm.scores, INDEX(_xlpm.values, _xlpm.startRow):INDEX(_xlpm.values, _xlpm.endRow),_xlpm.filterMask, ISERROR(SEARCH("[Digital]", _xlpm.indicatorRange)),_xlpm.filteredScores, _xlfn._xlws.FILTER(_xlpm.scores, _xlpm.filterMask),SUMPRODUCT((_xlpm.filteredScores="High")*Methodology!$F$15 +(_xlpm.filteredScores="Medium")*Methodology!$F$16 +((_xlpm.filteredScores="Low")+(_xlpm.filteredScores="No data"))*Methodology!$F$17 +(_xlpm.filteredScores="Yes")*Methodology!$I$15 +(_xlpm.filteredScores="No")*Methodology!$I$16))} -> 25 | H24: =G24/Methodology!I24 -> #VALUE! | I24: 1 | J24: {=_xlfn.IFS(G24<=(Methodology!I24*Methodology!$F$30),"Low maturity", G24<(Methodology!I24*Methodology!$F$29),"Mid maturity",G24>=(Methodology!I24*Methodology!$F$29),"High maturity")} -> #VALUE! | N24: ='Bank diagnostic'!D47 -> 5. Products and value proposition | O24: {="• " & IFERROR(_xlfn.TEXTJOIN(CHAR(10) & "• ", TRUE, IF('Bank diagnostic'!F49:F51="Low", Methodology!E68:E70, IF('Bank diagnostic'!F49:F51="Medium", Methodology!H68:H70, "")), IF('Bank diagnostic'!F56:F59="Low", Methodology!E75:E78, IF('Bank diagnostic'!F56:F59="Medium", Methodology!H75:H78, "")) ), "")} -> • The bank offers a broad range of standard SME products (e.g., overdrafts, term loans) and partially addresses some lifecycle needs, but products are not explicitly differentiated across lifecycle stages • The bank has some products tailored to SME segments, but mostly offers standardized products with slight adjustments • Portfolio has grown, but inconsistently, over the past 3 years (ups and downs but net positive) • Most SME clients rely on a single product (typically credit), with minimal use of additional services | P24: {="• " & IFERROR(_xlfn.TEXTJOIN(CHAR(10) & "• ", TRUE, IF('Bank diagnostic'!F49:F51="Low", Methodology!F68:F70, IF('Bank diagnostic'!F49:F51="Medium", Methodology!I68:I70, "")), IF('Bank diagnostic'!F56:F59="Low", Methodology!F75:F78, IF('Bank diagnostic'!F56:F59="Medium", Methodology!I75:I78, "")) ), "")} -> • Use client feedback and usage data to refine and tailor offerings according to key lifecycle stages (e.g., startup, growth, maturity) • Systematically track portfolio performance, product uptake, and repayment behaviors by sub-segment (e.g., women-led SMEs, agribusinesses) • Sustain growth through targeted acquisition and channel discipline • Deepen SME client relationships by driving structured uptake of product bundles | Q24: {="• " & IFERROR(_xlfn.TEXTJOIN(CHAR(10) & "• ", TRUE, IF('Bank diagnostic'!F49:F51="Low", Methodology!G68:G70, IF('Bank diagnostic'!F49:F51="Medium", Methodology!J68:J70, "")), IF('Bank diagnostic'!F56:F59="Low", Methodology!G75:G78, IF('Bank diagnostic'!F56:F59="Medium", Methodology!J75:J78, "")) ), "")} -> • Collect maturity-level SME usage data and validate product design through client workshops to refine features, pricing, and bundling • Use data analytics to proactively offer tailored product and services based on transaction patterns, industry cycles, or client behavior within sub-segments • Set quarterly SME growth targets by segment and run targeted campaigns linked to those segments’ preferred products or channels • Conduct client-level wallet share analysis and launch targeted cross-sell campaigns for priority products
F25: 6. Digital | G25: {=_xlfn.LET( _xlpm.indicators, 'Bank diagnostic'!D:D, _xlpm.values, 'Bank diagnostic'!F:F, _xlpm.isDigital, ISNUMBER(SEARCH("[Digital]", _xlpm.indicators)), _xlpm.digitalScores, _xlfn._xlws.FILTER(_xlpm.values, _xlpm.isDigital), SUMPRODUCT( (_xlpm.digitalScores="High")*Methodology!$F$15 + (_xlpm.digitalScores="Medium")*Methodology!$F$16 + ((_xlpm.digitalScores="Low")+(_xlpm.digitalScores="No data"))*Methodology!$F$17 + (_xlpm.digitalScores="Yes")*Methodology!$I$15 + (_xlpm.digitalScores="No")*Methodology!$I$16 ) )} -> 32 | H25: =G25/Methodology!I25 -> 0.8 | I25: 1 | J25: {=_xlfn.IFS(G25<=(Methodology!I25*Methodology!$F$30),"Low maturity", G25<(Methodology!I25*Methodology!$F$29),"Mid maturity",G25>=(Methodology!I25*Methodology!$F$29),"High maturity")} -> High maturity | N25: 6. Digital | O25: ="• " & IFERROR(_xlfn.TEXTJOIN(CHAR(10) & "• ", TRUE, IF('Bank diagnostic'!F36="Low", Methodology!E55, IF('Bank diagnostic'!F36="Medium", Methodology!H55, "")), IF('Bank diagnostic'!F43="Low", Methodology!E62, IF('Bank diagnostic'!F43="Medium", Methodology!H62, "")), IF('Bank diagnostic'!F44="Low", Methodology!E63, IF('Bank diagnostic'!F44="Medium", Methodology!H63, "")), IF('Bank diagnostic'!F45="Low", Methodology!E64, IF('Bank diagnostic'!F45="Medium", Methodology!H64, "")), IF('Bank diagnostic'!F46="Low", Methodology!E65, IF('Bank diagnostic'!F46="Medium", Methodology!H65, "")), IF('Bank diagnostic'!F53="Low", Methodology!E72, IF('Bank diagnostic'!F53="Medium", Methodology!H72, "")), IF('Bank diagnostic'!F54="Low", Methodology!E73, IF('Bank diagnostic'!F54="Medium", Methodology!H73, "")), IF('Bank diagnostic'!#REF!="Low", Methodology!#REF!, IF('Bank diagnostic'!#REF!="Medium", Methodology!#REF!, "")) ), "") -> • | P25: ="• " & IFERROR(_xlfn.TEXTJOIN(CHAR(10) & "• ", TRUE, IF('Bank diagnostic'!F36="Low", Methodology!F55, IF('Bank diagnostic'!F36="Medium", Methodology!I55, "")), IF('Bank diagnostic'!F43="Low", Methodology!F62, IF('Bank diagnostic'!F43="Medium", Methodology!I62, "")), IF('Bank diagnostic'!F44="Low", Methodology!F63, IF('Bank diagnostic'!F44="Medium", Methodology!I63, "")), IF('Bank diagnostic'!F45="Low", Methodology!F64, IF('Bank diagnostic'!F45="Medium", Methodology!I64, "")), IF('Bank diagnostic'!F46="Low", Methodology!F65, IF('Bank diagnostic'!F46="Medium", Methodology!I65, "")), IF('Bank diagnostic'!F53="Low", Methodology!F72, IF('Bank diagnostic'!F53="Medium", Methodology!I72, "")), IF('Bank diagnostic'!F54="Low", Methodology!F73, IF('Bank diagnostic'!F54="Medium", Methodology!I73, "")), IF('Bank diagnostic'!#REF!="Low", Methodology!#REF!, IF('Bank diagnostic'!#REF!="Medium", Methodology!#REF!, "")) ), "") -> • | Q25: ="• " & IFERROR(_xlfn.TEXTJOIN(CHAR(10) & "• ", TRUE, IF('Bank diagnostic'!F36="Low", Methodology!G55, IF('Bank diagnostic'!F36="Medium", Methodology!J55, "")), IF('Bank diagnostic'!F43="Low", Methodology!G62, IF('Bank diagnostic'!F43="Medium", Methodology!J62, "")), IF('Bank diagnostic'!F44="Low", Methodology!G63, IF('Bank diagnostic'!F44="Medium", Methodology!J63, "")), IF('Bank diagnostic'!F45="Low", Methodology!G64, IF('Bank diagnostic'!F45="Medium", Methodology!J64, "")), IF('Bank diagnostic'!F46="Low", Methodology!G65, IF('Bank diagnostic'!F46="Medium", Methodology!J65, "")), IF('Bank diagnostic'!F53="Low", Methodology!G72, IF('Bank diagnostic'!F53="Medium", Methodology!J72, "")), IF('Bank diagnostic'!F54="Low", Methodology!G73, IF('Bank diagnostic'!F54="Medium", Methodology!J73, "")), IF('Bank diagnostic'!#REF!="Low", Methodology!#REF!, IF('Bank diagnostic'!#REF!="Medium", Methodology!#REF!, "")) ), "") -> •
F26: Criteria met | G26: 0

Sheet Peer benchmark
C3: ='Bank diagnostic'!F10 -> Bank X | D3: ='Example 1'!E10 -> Family Bank | E3: ='Example 2'!E10 -> Banco Finandina
B4: Overall score: | C4: =Results!D12 -> #VALUE!
B5: Overall standing: | C5: =Results!D13 -> #VALUE! | D5: ='Example 1'!G10 -> #VALUE! | E5: ='Example 2'!G10 -> #VALUE!
B6: High maturity areas (inc. digital) | C6: =Results!D14 -> 1 / 6 areas ranked as high maturity
B7: Rating by area
B8: Assessment area
B9: =Results!F20 -> 1. Strategy | C9: =Results!J20 -> #VALUE!
B10: =Results!F21 -> 2. Talent and organizational structure | C10: =Results!J21 -> #VALUE!
B11: =Results!F22 -> 3. Competitive positioning | C11: =Results!J22 -> #VALUE!
B12: =Results!F23 -> 4. Operational processes | C12: =Results!J23 -> #VALUE!
B13: =Results!F24 -> 5. Products and value proposition | C13: =Results!J24 -> #VALUE!
B14: =Results!F25 -> 6. Digital | C14: =Results!J25 -> High maturity

Sheet References
C2: Countries
C3: Afghanistan
C4: Albania
C5: Algeria
C6: Andorra
C7: Angola
C8: Anguilla
C9: Antigua and Barbuda
C10: Argentina
C11: Armenia
C12: Aruba
C13: Ascension
... C221: Zimbabwe
