Workbook
Name Choice: '[1]Lists (2)'!$B$5:$B$7
Name CodeCountries: [2]Lists!$C$212:$C$242
Name CodeCountries: [1]Lists!$C$212:$C$242
Name country: '[3]Pull-down menus'!$C$38:$C$236
Name Input: [2]Lists!$C$6:$C$7
Name Input: [1]Lists!$C$6:$C$7
Name Type: [2]Lists!$C$247:$C$248
Name Type: [1]Lists!$C$247:$C$248
Name YesNo: [2]Lists!$C$252:$C$253
Name YesNo: [1]Lists!$C$252:$C$253

Sheet Instructions & Overview
I5: Business Case Tool
I6: INVEST: The Process & Toolkit for Unleashing SME Banking
D11: Last modified: June XX, 2025
D13: OVERVIEW
D15: The Business Case Tool is an Excel-based diagnostic designed to help commercial banks estimate the return they could expect on their SME banking expansion. It ties in with the market sizing tool, a data-driven summary of over 160 markets, and combines the specific cost and revenue drivers of the institution to evaluate the upfront costs, overall returns, break even points and cash flow over a 7-year horizon. The tool relies on assessments made by the user in order to best align with the prevaling market conditions, various strategy options and the policies pursued by the institution for which the user is making their assessment.
D18: Focus audience:
D19: USE CASE
D21: The tool allows users to formulate a goal and a combination of strategies for achieving it, and assess: 1) Total investment requirements, 2) Total returns, 3) Profit and cash flows, and 4) Operational indicators. It supports confident strategy formulation and prioritization by estimating the outcomes each approach would deliver over the medium-term. Please note that despite the 7-year horizon, the model calculates the figures in current real terms, since the financial institutions it is being used for could adopt different policies to control for macroeconomic factors such as inflation and wage growth and are the best suited to foresee how these factors might influence their local economy in the medium term.
D25: OBJECTIVES
D27: 1. Provide a quick and intuitive assessment of the revenue potential of an expansion into the SME segment. 2. Enable users to assess the feasibility of their objectives and adjust them to target the optimal outcome. 3. Support evidence-based decision-making for SME banking expansion in their market.
D31: GUIDANCE
D33: This file consists of seven tabs, including this one. Below is a high-level description of each tab, along with specific instructions on how users can interact with them to leverage the tool succesfully.
D36: Tab Name | F36: Description | AK36: Instructions | AM36: Instructions
D38: Assumptions | F38: This tab allows the user to set their targets and insert the conditions under which they would operate in order to achieve those targets and to set alternative values to run a sensitivity analysis on the factors laid out in the model. | AM38: Insert the conditions under which you want to model the scenario.
D40: Outputs overview | F40: This tab highlights the most important outcomes determining the feasibility of the expansion and provides a visual representation of the progression of the project. | AM40: Review key outputs for your primary scenario.
D42: Sensitivity analysis | F42: This tab follows the layout of the "Outputs overview" but highlights the differences in the outcomes resulting from the sensitivity analysis. | AM42: Review differences in key outputs between your primary and comparison scenarios.
D44: Key financial and ops fig.s LCY | F44: This sheet gives detailed figures on the financial outcomes and operating parameters of the project on a quarterly and annual level over a 7-year horizon. | AM44: -
D46: Alt. scenario LCY | F46: This sheet gives the same figures as the previous sheet for the alternative scenario that the sensitivity analysis is based on. | AM46: -
D48: Key financial and ops fig.s COM | F48: Since it is common practice, especially in smaller markets where the local currency is weak or unstable, to assess major projects in a foreign currency, like reserve currencies, this sheet provides an overview of the same numbers as the previous sheet presented in a second currency of the user's choosing. | AM48: -
D50: Alt. scenario COM | F50: This sheet gives the same figures as the previous sheet for the alternative scenario that the sensitivity analysis is based on. | AM50: -
D52: All scenarios | F52: This sheet consolidates the figures from the previous four sheets and provides a side by side comparison. | AM52: If you would like to view the individual scenarios in a single sheet, go straight to this sheet.
D54: Baseline Headcount Estimate | F54: This tab contains an extract from the related Market Sizing Tool to enable this tool to estimate the project's market share and feasibility of the user's targets within the wider context of the selected market. | AM54: -
D56: Lists | F56: Location of Pull-Down lists used in this model | AM56: -
D59: USING THIS TOOL EFFECTIVELY
D61: This tool is designed for a wide range of users—including TA funders, commercial banks, and ecosystem enablers—who want to assess the feasibility and the expected returns of a push for expansion in the SME sector using various combinations of strategies.
D64: The tool provides a strong foundation for project assessment. Users can set their targets, align parameters with the existing conditions under which they operate or the conditions they strive for, the tool provides an assessment of the bank's readiness and opportunity for SME banking.
D68: LINKS TO USER GUIDE AND VIDEO TUTORIAL
K69: Move to the next sheet to begin screening potential partner banks and identifying the most suitable candidates!
D71: User Guide: | E71: [insert link]
D73: Video tutorial: | E73: [insert link]

Sheet Assumptions
C2: Business Case Tool
C3: Please only fill in the orange cells in columns D and G. If your selections render any other fields unnecessary, they will automatically be blacked out.
B5: Please select your country | D5: Albania | E5: Please select the country for which you want to use the tool from the drop-down menu
C6: Local currency | D6: ALL | E6: Please enter the local currency of the country for which you want to use the tool. Please note that all inputs should be done in the local currency.
C7: Rounding (local currency) | D7: no rounding | E7: Please select if you want the results displayed in full amounts, thousands, millions or billions of local currency
C8: Comparison currency | D8: USD | E8: If you want to see the results modelled in a second currency, please insert that currency here. Please note that the compariosn currency is for illustrative purposes only. Inputs in the model should be done in local currency.
C9: Rounding (comparison currency) | D9: no rounding | E9: Please select if you want the results displayed in full amounts, thousands, millions or billions of comparison currency
C10: Exchange rate | D10: 0.012 | E10: Please insert the exchange rate between the two currencies (in a format of one unit of local currency to one unit in comparison currency)
B11: Target share of market captured by sector | F11: Captured share of overall market | G11: Values for sensitivity analysis Overwrite cells where you want to compare with different values from column D
C12: - medium | D12: 200 | E12: Please insert the target number of clients in this sector you would like to achieve | F12: =IFERROR(Assumptions!D12/(_xlfn.XLOOKUP(Assumptions!$D$5, 'Baseline Headcount Estimates'!$B$13:$B$180, 'Baseline Headcount Estimates'!$R$13:$R$180, "")*1000), "N/A") -> 0.070294779 | G12: =D12 -> 200 | H12: =IFERROR(Assumptions!G12/(_xlfn.XLOOKUP(Assumptions!$D$5, 'Baseline Headcount Estimates'!$B$13:$B$180, 'Baseline Headcount Estimates'!$R$13:$R$180, "")*1000), "N/A") -> 0.070294779 | I12: =IF(F12>1,"TARGET EXCEEDS TOTAL MARKET","") | J12: =IF(H12>1,"TARGET EXCEEDS TOTAL MARKET","")
C13: - small | D13: 1000 | E13: Please insert the target number of clients in this sector you would like to achieve | F13: =IFERROR(Assumptions!D13/(_xlfn.XLOOKUP(Assumptions!$D$5, 'Baseline Headcount Estimates'!$B$13:$B$180, 'Baseline Headcount Estimates'!$Q$13:$Q$180, "")*1000), "N/A") -> 0.12018056 | G13: =D13 -> 1000 | H13: =IFERROR(Assumptions!G13/(_xlfn.XLOOKUP(Assumptions!$D$5, 'Baseline Headcount Estimates'!$B$13:$B$180, 'Baseline Headcount Estimates'!$Q$13:$Q$180, "")*1000), "N/A") -> 0.12018056 | I13: =IF(F13>1,"TARGET EXCEEDS TOTAL MARKET","") | J13: =IF(H13>1,"TARGET EXCEEDS TOTAL MARKET","")
C14: - very small | D14: 5000 | E14: Please insert the target number of clients in this sector you would like to achieve | F14: =IFERROR(Assumptions!D14/(_xlfn.XLOOKUP(Assumptions!$D$5, 'Baseline Headcount Estimates'!$B$13:$B$180, 'Baseline Headcount Estimates'!$P$13:$P$180, "")*1000), "N/A") -> 0.19759702 | G14: =D14 -> 5000 | H14: =IFERROR(Assumptions!G14/(_xlfn.XLOOKUP(Assumptions!$D$5, 'Baseline Headcount Estimates'!$B$13:$B$180, 'Baseline Headcount Estimates'!$P$13:$P$180, "")*1000), "N/A") -> 0.19759702 | I14: =IF(F14>1,"TARGET EXCEEDS TOTAL MARKET","") | J14: =IF(H14>1,"TARGET EXCEEDS TOTAL MARKET","")
C15: - self-employed and micro | D15: 40000 | E15: Please insert the target number of clients in this sector you would like to achieve | F15: =IFERROR(Assumptions!D15/(_xlfn.XLOOKUP(Assumptions!$D$5, 'Baseline Headcount Estimates'!$B$13:$B$180, 'Baseline Headcount Estimates'!$O$13:$O$180, "")*1000), "N/A") -> 0.19002391 | G15: =D15 -> 40000 | H15: =IFERROR(Assumptions!G15/(_xlfn.XLOOKUP(Assumptions!$D$5, 'Baseline Headcount Estimates'!$B$13:$B$180, 'Baseline Headcount Estimates'!$O$13:$O$180, "")*1000), "N/A") -> 0.19002391 | I15: =IF(F15>1,"TARGET EXCEEDS TOTAL MARKET","") | J15: =IF(H15>1,"TARGET EXCEEDS TOTAL MARKET","")
C16: Target timeline for acquisition of new clients | D16: 5 | E16: Please insert the time (in years, between 1 and 5) in which you would like to achieve the targets set out above | G16: =D16 -> 5
C17: Share of electronic banking | D17: 0.5 | E17: Please insert the share of your clients that do their banking primarily online | G17: =D17 -> 0.5
B18: Interest rates and fees
C19: Interest rate on business loans | D19: 0.05 | E19: Please insert the average interest rate on business loans that your institution charges clients | G19: =D19 -> 0.05
C20: Interest rate on mortgages | D20: 0.035 | E20: Please insert the average interest rate on mortgage-backed home loans that your institution charges clients | G20: =D20 -> 0.035
C21: Interest rate on autoloans | D21: 0.08 | E21: Please insert the average interest rate on autoloans that your institution charges clients | G21: =D21 -> 0.08
C22: Interest rate on deposits | D22: 0.015 | E22: Please insert the average interest rate on savings and long-term deposits that your institution pays clients | G22: =D22 -> 0.015
C23: Refinancing rate | D23: 0.02 | E23: Please insert the average refinancing rate of the local financial market | G23: =D23 -> 0.02
C24: Account maintenance fee | D24: 0 | E24: Please insert average account maintenance fee as % of average account balance. If no such fee is charged, insert 0 | G24: =D24 -> 0
C25: Interest rate on checking accounts | D25: 0.005 | E25: Please insert the average interest rate paid to clients for balances in their checking accounts. If no such interest rate is paid, insert 0 | G25: =D25 -> 0.005
C26: Transaction fees (intrabank) | D26: 0.002 | E26: Please insert the transaction fees (as % of the transaction amount) charged to clients for transactions made to other acounts in your institution for a payment order submitted in person in a bank branch | G26: =D26 -> 0.002
C27: Transaction fees e-banking (intrabank) | D27: =D26/2 -> 0.001 | E27: Please insert the transaction fees (as % of the transaction amount) charged to clients for transactions made to other acounts in your institution for a payment order submitted through electronic banking | G27: =D27 -> 0.001
C28: Transaction fees (interbank) | D28: 0.005 | E28: Please insert the transaction fees (as % of the transaction amount) charged to clients for transactions made to acounts in another financial institution less fees payable to intermediaries and receiving institution for a payment order submitted in person in a bank branch | G28: =D28 -> 0.005
C29: Transaction fees e-banking (interbank) | D29: =D28/2 -> 0.0025 | E29: Please insert the transaction fees (as % of the transaction amount) charged to clients for transactions made to acounts in another financial institution less fees payable to intermediaries and receiving institution for a payment order submitted through electronic banking | G29: =D29 -> 0.0025
C30: Transaction fees (international) | D30: 0.01 | E30: Please insert the transaction fees (as % of the transaction amount) charged to clients for international transactions less fees payable to intermediaries and receiving institution for a payment order submitted in person in a bank branch | G30: =D30 -> 0.01
C31: Transaction fees e-banking (international) | D31: =D30/2 -> 0.005 | E31: Please insert the transaction fees (as % of the transaction amount) charged to clients for international transactions less fees payable to intermediaries and receiving institution for a payment order submitted through electronic banking | G31: =D31 -> 0.005
C32: Loan processing fee | D32: 0.01 | E32: Please insert the fee (as % of loan amount) charged for processing loans | G32: =D32 -> 0.01
B33: Services | F33: In comparison currency (if applicable)
C34: NPL | D34: 0.01 | E34: Please insert the proportion of loans written down annually as non-performing | G34: =D34 -> 0.01
C35: Reserve requirement | D35: 0.1 | E35: Please insert the minimum reserve rate mandated by the central bank | G35: =D35 -> 0.1
C36: Interest earned on minimum reserves | D36: 0.01 | E36: If the central bank pays any interest on the reserves, please insert the interest rate here. Otherwise, insert 0 | G36: =D36 -> 0.01
C37: Average business loan volume for medium enterprises | D37: 100000000 | E37: Please insert the average loan volume outstanding for a company in this sector with your institution | F37: =D37*$D$10 -> 1200000 | G37: =D37 -> 100000000 | H37: =G37*$D$10 -> 1200000
C38: Average business loan volume for small enterprises | D38: 10000000 | E38: Please insert the average loan volume outstanding for a company in this sector with your institution | F38: =D38*$D$10 -> 120000 | G38: =D38 -> 10000000 | H38: =G38*$D$10 -> 120000
C39: Average business loan volume for very small enterprises | D39: 2500000 | E39: Please insert the average loan volume outstanding for a company in this sector with your institution | F39: =D39*$D$10 -> 30000 | G39: =D39 -> 2500000 | H39: =G39*$D$10 -> 30000
C40: Average business loan volume for micro enterprises and self employed entrepreneurs | D40: 500000 | E40: Please insert the average loan volume outstanding for a company in this sector with your institution | F40: =D40*$D$10 -> 6000 | G40: =D40 -> 500000 | H40: =G40*$D$10 -> 6000
C41: Average business loan uptake for medium enterprises | D41: 0.4 | E41: Please insert the proportion of companies in this sector that have loans outstanding with your institution | G41: =D41 -> 0.4
C42: Average business loan uptake for small enterprises | D42: 0.4 | E42: Please insert the proportion of companies in this sector that have loans outstanding with your institution | G42: =D42 -> 0.4
C43: Average business loan uptake for very small enterprises | D43: 0.4 | E43: Please insert the proportion of companies in this sector that have loans outstanding with your institution | G43: =D43 -> 0.4
C44: Average business loan uptake for micro enterprises and self employed entrepreneurs | D44: 0.4 | E44: Please insert the proportion of companies in this sector that have loans outstanding with your institution | G44: =D44 -> 0.4
C45: Average home loan volume | D45: 5000000 | E45: Please insert the average home loan volume with your institution | F45: =D45*$D$10 -> 60000 | G45: =D45 -> 5000000 | H45: =G45*$D$10 -> 60000
C46: Average home loan uptake | D46: 0.1 | E46: Please insert the proportion of clients which have outstanding home loans with your institution | G46: =D46 -> 0.1
C47: Average auto loan volume | D47: 1000000 | E47: Please insert the average auto loan volume with your institution | F47: =D47*$D$10 -> 12000 | G47: =D47 -> 1000000 | H47: =G47*$D$10 -> 12000
C48: Average auto loan uptake | D48: 0.05 | E48: Please insert the proportion of clients which have outstanding auto loans with your institution | G48: =D48 -> 0.05
C49: Average savings deposit amount | D49: 250000 | E49: Please insert the average balance of a long-term or savings deposit with your institution | F49: =D49*$D$10 -> 3000 | G49: =D49 -> 250000 | H49: =G49*$D$10 -> 3000
C50: Average savings uptake | D50: 0.2 | E50: Please insert the proportion of clients which have outstanding savings loans with your institution | G50: =D50 -> 0.2
C51: Average checking account balance | D51: 50000 | E51: Please insert the average balance of a checking account with your institution | F51: =D51*$D$10 -> 600 | G51: =D51 -> 50000 | H51: =G51*$D$10 -> 600
C52: Average intrabank transactions (monthly) | D52: 100000 | E52: Please insert the average volume of intrabank transactions an enterprise makes through your institution | F52: =D52*$D$10 -> 1200 | G52: =D52 -> 100000 | H52: =G52*$D$10 -> 1200
C53: Average interbank transactions (monthly) | D53: 100000 | E53: Please insert the average volume of interbank transactions an enterprise makes through your institution | F53: =D53*$D$10 -> 1200 | G53: =D53 -> 100000 | H53: =G53*$D$10 -> 1200
C54: Average international transactions (monthly) | D54: 100000 | E54: Please insert the average volume of international transactions an enterprise makes through your institution | F54: =D54*$D$10 -> 1200 | G54: =D54 -> 100000 | H54: =G54*$D$10 -> 1200
C55: Average insurance premium (yearly) | D55: 100000 | E55: Please insert the average insurance premium amount underwritten by your institution | F55: =D55*$D$10 -> 1200 | G55: =D55 -> 100000 | H55: =G55*$D$10 -> 1200
C56: Average insurance uptake | D56: 0.1 | E56: Please insert the proportion of clients which get insurance through your institution | G56: =D56 -> 0.1
C57: Income from providing non-financial services | D57: 10000000 | E57: If your institution plans on providing non-financial services such as newsletters, workshops, webinars, CSR initiatives, networking events and such, insert the total income expected to be derived from these activities. If no such services are planned, insert 0. | F57: =D57*$D$10 -> 120000 | G57: =D57 -> 10000000 | H57: =G57*$D$10 -> 120000
C58: Cost for providing non-financial services | D58: 25000000 | E58: If your institution plans on providing non-financial services such as newsletters, workshops, webinars, CSR initiatives, networking events and such, insert the total cost to organize these activities (note, some of these services may be conducted at a loss in order to raise the profile of the institution, so the costs can exceed the incomes stated above). If no such services are planned, insert 0. | F58: =D58*$D$10 -> 300000 | G58: =D58 -> 25000000 | H58: =G58*$D$10 -> 300000
C59: Number of non-financial services clients annually | D59: 1000 | E59: If your institution plans on providing non-financial services such as newsletters, workshops, webinars, CSR initiatives, networking events and such to participants who are not existing clients, insert the total number of participants who are not existing clients in these activities. If no such activities are planned, insert 0. | G59: =D59 -> 1000
C60: Expected conversion of NFS clients to financial services clients | D60: 0.05 | E60: If your institution plans on providing non-financial services such as newsletters, workshops, webinars, CSR initiatives, networking events and such to participants who are not existing clients insert the proportion of those expected to convert to clients | G60: 0.05
B62: CIT rate | D62: 0.1 | E62: Please insert the applicable corporate income tax rate in your jurisdiction | G62: =D62 -> 0.1
B63: Employee effectiveness
C64: Average clients served by in clerk in person | D64: 200 | E64: Please insert the average number of clients a bank clerk can service in a branch | G64: =D64 -> 200
C65: Average clients served by support online | D65: 500 | E65: Please insert the average number of clients a back office employee can service for online support | G65: =D65 -> 500
C66: Average loans processed by loan officer | D66: 50 | E66: Please insert the average number of loan applications a loan officer can process | G66: =D66 -> 50
C67: Average clients supervised by manager | D67: 1000 | E67: Please insert the average number of clients for which a branch manager can be responsible | G67: =D67 -> 1000
B68: Employee compensation | F68: In comparison currency (if applicable)
C69: Average annual compensation and costs clerk | D69: 1500000 | E69: Please insert the average compensation and additional training, development and retention costs for the position | F69: =D69*$D$10 -> 18000 | G69: =D69 -> 1500000 | H69: =G69*$D$10 -> 18000
C70: Average annual compensation and costs support | D70: 2000000 | E70: Please insert the average compensation and additional training, development and retention costs for the position | F70: =D70*$D$10 -> 24000 | G70: =D70 -> 2000000 | H70: =G70*$D$10 -> 24000
C71: Average annual compensation and costs loan officer | D71: 2000000 | E71: Please insert the average compensation and additional training, development and retention costs for the position | F71: =D71*$D$10 -> 24000 | G71: =D71 -> 2000000 | H71: =G71*$D$10 -> 24000
C72: Average annual compensation and costs manager | D72: 4000000 | E72: Please insert the average compensation and additional training, development and retention costs for the position | F72: =D72*$D$10 -> 48000 | G72: =D72 -> 4000000 | H72: =G72*$D$10 -> 48000
B73: Infrastructure and operating costs | F73: In comparison currency (if applicable)
C74: Average number of clients serviced by one branch | D74: 1000 | E74: Please insert the number of MSME clients that one branch could effectively service | G74: =D74 -> 1000
C75: Average number of clients serviced by one service agent outlet | D75: 100 | E75: If your institution uses third-party service agents to provide a portion of the services on behalf of the bank, please insert the number of MSME clients that one agent outlet could effectively service | G75: =D75 -> 100
C76: Share of transactions conducted through service agents | D76: 0.5 | E76: If your institution uses third-party service agents to provide a portion of the services on behalf of the bank, please insert the percentage of transactions that are carried out through them | G76: =D76 -> 0.5
C77: Average monthly commisions paid to service agents | D77: 100000 | E77: If your institution uses third-party service agents to provide a portion of the services on behalf of the bank, please insert the average commissions paid monthly to one such service agent | G77: =D77 -> 100000
C78: Annual cost for renting and maintaing one branch | D78: 5000000 | E78: Please insert the cost of premises for one branch, including rent, maintenance, cleaning, security | F78: =D78*$D$10 -> 60000 | G78: =D78 -> 5000000 | H78: =G78*$D$10 -> 60000
C79: Value of equipment installed in one branch | D79: 10000000 | E79: Please insert the value of the equipment required for the general functioning of the branch (common area furniture, server, survailance etc.) | F79: =D79*$D$10 -> 120000 | G79: =D79 -> 10000000 | H79: =G79*$D$10 -> 120000
C80: Value of equipment for individual use of employees | D80: 150000 | E80: Please insert the value of one fully equipped workspace (desk, chair, computer and all accompanying accessories) | F80: =D80*$D$10 -> 1800 | G80: =D80 -> 150000 | H80: =G80*$D$10 -> 1800
C81: Value of IT infrastructure | D81: 250000000 | E81: Please insert the value of the IT infrastructure (servers and propriatery software) required to service the target additional business | F81: =D81*$D$10 -> 3000000 | G81: =D81 -> 250000000 | H81: =G81*$D$10 -> 3000000
C82: IT maintenance | D82: 50000000 | E82: Please insert the annual cost for maintenance of IT equipment | F82: =D82*$D$10 -> 600000 | G82: =D82 -> 50000000 | H82: =G82*$D$10 -> 600000
C83: Average cost of office supplies for one branch | D83: 500000 | E83: Please insert the annual cost of office supplies used by one branch | F83: =D83*$D$10 -> 6000 | G83: =D83 -> 500000 | H83: =G83*$D$10 -> 6000
B84: Client acquisiton and retention | F84: In comparison currency (if applicable)
C85: Attrition rate | D85: 0.025 | E85: Please insert the proportion of clients that stop doing business with your institution every year | G85: =D85 -> 0.025
C86: Advertising and marketing expenditure | D86: 50000 | E86: Please insert the average marketing spend required for the acquisiton of one client | F86: =D86*$D$10 -> 600 | G86: =D86 -> 50000 | H86: =G86*$D$10 -> 600
C87: Projected organic growth | D87: 0.03 | E87: Please insert the expected client acquisiton through recommendations from other clients and word-of-month | G87: =D87 -> 0.03
C88: Target share of clients acquired through commission-based agents | D88: 0.1 | E88: If your institution plans on engaging commissions based agents for client acquisition or a bonus system for acquired clients from in-house staff, please insert the share of clients you target acquiring through this channel | G88: =D88 -> 0.1
C89: Average agent commision for acquired client | D89: 20000 | E89: If your institution plans on engaging commissions based agents for client acquisition or a bonus system for acquired clients from in-house staff, please insert the average commission paid to the agent | F89: =D89*$D$10 -> 240 | G89: =D89 -> 20000 | H89: =G89*$D$10 -> 240

Sheet Outputs overview 
C2: Business Case Tool
C3: =IF(Assumptions!D7<>Lists!B2,CONCATENATE("Outputs overview- ",Assumptions!D7," of ",Assumptions!D6),CONCATENATE("Outputs overview- in ",Assumptions!D6)) -> Outputs overview- in ALL
C5: =CONCATENATE("TOTAL INVESTMENT (",Assumptions!D6,")") -> TOTAL INVESTMENT (ALL) | D5: =-('Key financial and ops fig.s LCY'!H58+'Key financial and ops fig.s LCY'!M58+'Key financial and ops fig.s LCY'!R58+'Key financial and ops fig.s LCY'!W58+'Key financial and ops fig.s LCY'!AG58+'Key financial and ops fig.s LCY'!AL58) -> 433850000
C6: =CONCATENATE("TOTAL INVESTMENT (",Assumptions!D8,")") -> TOTAL INVESTMENT (USD) | D6: =D5*Assumptions!D10 -> 5206200
C7: =CONCATENATE("TOTAL NET INCOME (",Assumptions!D6,") OVER 7-YEAR PERIOD") -> TOTAL NET INCOME (ALL) OVER 7-YEAR PERIOD | D7: ='Key financial and ops fig.s LCY'!AL49 -> 7.322392e+09
C8: =CONCATENATE("TOTAL NET INCOME (",Assumptions!D8,") OVER 7-YEAR PERIOD") -> TOTAL NET INCOME (USD) OVER 7-YEAR PERIOD | D8: =D7*Assumptions!D10 -> 87868704
C9: ABSOLUTE ROI | D9: =D7/D5 -> 16.877704
C10: ANNUALIZED ROI | D10: =D9/7 -> 2.4111006
C12: BREAK EVEN | D12: {=INDEX('Key financial and ops fig.s LCY'!D5:AL5, MATCH(TRUE, 'Key financial and ops fig.s LCY'!D49:AL49>0, 0))} -> Y2
C13: FIRST PROFITABLE QUARTER | D13: {=INDEX('Key financial and ops fig.s LCY'!D5:AL5, MATCH(TRUE, 'Key financial and ops fig.s LCY'!D45:AL45>0, 0))} -> Q3 Y1
C14: REPAYMENT OF INVESTMENT | D14: {=INDEX('Key financial and ops fig.s LCY'!D5:AL5, MATCH(TRUE, 'Key financial and ops fig.s LCY'!D61:AL61>0, 0))} -> Q2 Y3

Sheet Sensitivity analysis
C2: Business Case Tool
C3: =IF(Assumptions!D7<>Lists!B2,CONCATENATE("Outputs overview- ",Assumptions!D7," of ",Assumptions!D6),CONCATENATE("Outputs overview- in ",Assumptions!D6)) -> Outputs overview- in ALL
D4: Base scenario | E4: Alternative scenario | F4: Difference
C5: =CONCATENATE("TOTAL INVESTMENT (",Assumptions!D6,")") -> TOTAL INVESTMENT (ALL) | D5: =-('Key financial and ops fig.s LCY'!H58+'Key financial and ops fig.s LCY'!M58+'Key financial and ops fig.s LCY'!R58+'Key financial and ops fig.s LCY'!W58+'Key financial and ops fig.s LCY'!AG58+'Key financial and ops fig.s LCY'!AL58) -> 433850000 | E5: =-('Alt. scenario LCY'!H58+'Alt. scenario LCY'!M58+'Alt. scenario LCY'!R58+'Alt. scenario LCY'!W58+'Alt. scenario LCY'!AG58+'Alt. scenario LCY'!AL58) -> 433850000 | F5: =E5-D5 -> 0
C6: =CONCATENATE("TOTAL INVESTMENT (",Assumptions!D8,")") -> TOTAL INVESTMENT (USD) | D6: =D5*Assumptions!D10 -> 5206200 | E6: =E5*Assumptions!D10 -> 5206200 | F6: =E6-D6 -> 0
C7: =CONCATENATE("TOTAL NET INCOME (",Assumptions!D6,") OVER 7-YEAR PERIOD") -> TOTAL NET INCOME (ALL) OVER 7-YEAR PERIOD | D7: ='Key financial and ops fig.s LCY'!AL49 -> 7.322392e+09 | E7: ='Alt. scenario LCY'!AL49 -> 7.322392e+09 | F7: =E7-D7 -> 0
C8: =CONCATENATE("TOTAL NET INCOME (",Assumptions!D8,") OVER 7-YEAR PERIOD") -> TOTAL NET INCOME (USD) OVER 7-YEAR PERIOD | D8: =D7*Assumptions!D10 -> 87868704 | E8: =E7*Assumptions!D10 -> 87868704 | F8: =E8-D8 -> 0
C9: ABSOLUTE ROI | D9: =D7/D5 -> 16.877704 | E9: =E7/E5 -> 16.877704 | F9: =E9-D9 -> 0
C10: ANNUALIZED ROI | D10: =D9/7 -> 2.4111006 | E10: =E9/7 -> 2.4111006 | F10: =E10-D10 -> 0
C12: BREAK EVEN | D12: {=INDEX('Key financial and ops fig.s LCY'!D5:AL5, MATCH(TRUE, 'Key financial and ops fig.s LCY'!D49:AL49>0, 0))} -> Y2 | E12: {=INDEX('Alt. scenario LCY'!D5:AL5, MATCH(TRUE, 'Alt. scenario LCY'!D49:AL49>0, 0))} -> Y2 | F12: =IF(E12<>D12,"DIFFERENT PERIOD","")
C13: FIRST PROFITABLE QUARTER | D13: {=INDEX('Key financial and ops fig.s LCY'!D5:AL5, MATCH(TRUE, 'Key financial and ops fig.s LCY'!D45:AL45>0, 0))} -> Q3 Y1 | E13: {=INDEX('Alt. scenario LCY'!D5:AL5, MATCH(TRUE, 'Alt. scenario LCY'!D45:AL45>0, 0))} -> Q3 Y1 | F13: =IF(E13<>D13,"DIFFERENT PERIOD","")
C14: REPAYMENT OF INVESTMENT | D14: {=INDEX('Key financial and ops fig.s LCY'!D5:AL5, MATCH(TRUE, 'Key financial and ops fig.s LCY'!D61:AL61>0, 0))} -> Q2 Y3 | E14: {=INDEX('Alt. scenario LCY'!D5:AL5, MATCH(TRUE, 'Alt. scenario LCY'!D61:AL61>0, 0))} -> Q2 Y3 | F14: =IF(E14<>D14,"DIFFERENT PERIOD","")
K83: .

Sheet Key financial and ops fig.s LCY
C2: Business Case Tool
C3: =IF(Assumptions!D7<>Lists!B2,CONCATENATE("Modelled outputs- ",Assumptions!D7," of ",Assumptions!D6),CONCATENATE("Modelled outputs- in ",Assumptions!D6)) -> Modelled outputs- in ALL
A5: INCOME STATEMENT | D5: Q1 Y1 | E5: Q2 Y1 | F5: Q3 Y1 | G5: Q4 Y1 | H5: Y1 | I5: Q1 Y2 | J5: Q2 Y2 | K5: Q3 Y2 | L5: Q4 Y2 | M5: Y2 | N5: Q1 Y3 | O5: Q2 Y3 | P5: Q3 Y3 | Q5: Q4 Y3 | R5: Y3 | S5: Q1 Y4 | T5: Q2 Y4 | U5: Q3 Y4 | V5: Q4 Y4 | W5: Y4 | X5: Q1 Y5 | Y5: Q2 Y5 | Z5: Q3 Y5 | AA5: Q4 Y5 | AB5: Y5 | AC5: Q1 Y6 | AD5: Q2 Y6 | AE5: Q3 Y6 | AF5: Q4 Y6 | AG5: Y6 | AH5: Q1 Y7 | AI5: Q2 Y7 | AJ5: Q3 Y7 | AK5: Q4 Y7 | AL5: Y7
C6: Net interest income on business loans | D6: =D76*(Assumptions!$D$19-Assumptions!$D$23)/4 -> 9316406.2 | E6: =E76*(Assumptions!$D$19-Assumptions!$D$23)/4 -> 18515625 | F6: =F76*(Assumptions!$D$19-Assumptions!$D$23)/4 -> 27597656 | G6: =G76*(Assumptions!$D$19-Assumptions!$D$23)/4 -> 36562500 | H6: =SUM(D6:G6) -> 91992188 | I6: =I76*(Assumptions!$D$19-Assumptions!$D$23)/4 -> 45410156 | J6: =J76*(Assumptions!$D$19-Assumptions!$D$23)/4 -> 54140625 | K6: =K76*(Assumptions!$D$19-Assumptions!$D$23)/4 -> 62753906 | L6: =L76*(Assumptions!$D$19-Assumptions!$D$23)/4 -> 71250000 | M6: =SUM(I6:L6) -> 2.3355469e+08 | N6: =N76*(Assumptions!$D$19-Assumptions!$D$23)/4 -> 79628906 | O6: =O76*(Assumptions!$D$19-Assumptions!$D$23)/4 -> 87890625 | P6: =P76*(Assumptions!$D$19-Assumptions!$D$23)/4 -> 96035156 | Q6: =Q76*(Assumptions!$D$19-Assumptions!$D$23)/4 -> 1.040625e+08 | R6: =SUM(N6:Q6) -> 3.6761719e+08 | S6: =S76*(Assumptions!$D$19-Assumptions!$D$23)/4 -> 1.1197266e+08 | T6: =T76*(Assumptions!$D$19-Assumptions!$D$23)/4 -> 1.1976563e+08 | U6: =U76*(Assumptions!$D$19-Assumptions!$D$23)/4 -> 1.2744141e+08 | V6: =V76*(Assumptions!$D$19-Assumptions!$D$23)/4 -> 135000000 | W6: =SUM(S6:V6) -> 4.9417969e+08 | X6: =X76*(Assumptions!$D$19-Assumptions!$D$23)/4 -> 1.4244141e+08 | Y6: =Y76*(Assumptions!$D$19-Assumptions!$D$23)/4 -> 149765625 | Z6: =Z76*(Assumptions!$D$19-Assumptions!$D$23)/4 -> 1.5697266e+08 | AA6: =AA76*(Assumptions!$D$19-Assumptions!$D$23)/4 -> 164062500 | AB6: =SUM(X6:AA6) -> 6.1324219e+08 | AC6: =AC76*(Assumptions!$D$19-Assumptions!$D$23)/4 -> 162890625 | AD6: =AD76*(Assumptions!$D$19-Assumptions!$D$23)/4 -> 161718750 | AE6: =AE76*(Assumptions!$D$19-Assumptions!$D$23)/4 -> 160546875 | AF6: =AF76*(Assumptions!$D$19-Assumptions!$D$23)/4 -> 159375000 | AG6: =SUM(AC6:AF6) -> 644531250 | AH6: =AH76*(Assumptions!$D$19-Assumptions!$D$23)/4 -> 158203125 | AI6: =AI76*(Assumptions!$D$19-Assumptions!$D$23)/4 -> 157031250 | AJ6: =AJ76*(Assumptions!$D$19-Assumptions!$D$23)/4 -> 155859375 | AK6: =AK76*(Assumptions!$D$19-Assumptions!$D$23)/4 -> 154687500 | AL6: =SUM(AH6:AK6) -> 625781250
C7: Net interest income on mortgages | D7: =D77*(Assumptions!$D$20-Assumptions!$D$23)/4 -> 4304179.7 | E7: =E77*(Assumptions!$D$20-Assumptions!$D$23)/4 -> 8554218.8 | F7: =F77*(Assumptions!$D$20-Assumptions!$D$23)/4 -> 12750117 | G7: =G77*(Assumptions!$D$20-Assumptions!$D$23)/4 -> 16891875 | H7: =SUM(D7:G7) -> 42500391 | I7: =I77*(Assumptions!$D$20-Assumptions!$D$23)/4 -> 20979492 | J7: =J77*(Assumptions!$D$20-Assumptions!$D$23)/4 -> 25012969 | K7: =K77*(Assumptions!$D$20-Assumptions!$D$23)/4 -> 28992305 | L7: =L77*(Assumptions!$D$20-Assumptions!$D$23)/4 -> 32917500 | M7: =SUM(I7:L7) -> 1.0790227e+08 | N7: =N77*(Assumptions!$D$20-Assumptions!$D$23)/4 -> 36788555 | O7: =O77*(Assumptions!$D$20-Assumptions!$D$23)/4 -> 40605469 | P7: =P77*(Assumptions!$D$20-Assumptions!$D$23)/4 -> 44368242 | Q7: =Q77*(Assumptions!$D$20-Assumptions!$D$23)/4 -> 48076875 | R7: =SUM(N7:Q7) -> 1.6983914e+08 | S7: =S77*(Assumptions!$D$20-Assumptions!$D$23)/4 -> 51731367 | T7: =T77*(Assumptions!$D$20-Assumptions!$D$23)/4 -> 55331719 | U7: =U77*(Assumptions!$D$20-Assumptions!$D$23)/4 -> 58877930 | V7: =V77*(Assumptions!$D$20-Assumptions!$D$23)/4 -> 62370000 | W7: =SUM(S7:V7) -> 2.2831102e+08 | X7: =X77*(Assumptions!$D$20-Assumptions!$D$23)/4 -> 65807930 | Y7: =Y77*(Assumptions!$D$20-Assumptions!$D$23)/4 -> 69191719 | Z7: =Z77*(Assumptions!$D$20-Assumptions!$D$23)/4 -> 72521367 | AA7: =AA77*(Assumptions!$D$20-Assumptions!$D$23)/4 -> 75796875 | AB7: =SUM(X7:AA7) -> 2.8331789e+08 | AC7: =AC77*(Assumptions!$D$20-Assumptions!$D$23)/4 -> 75255469 | AD7: =AD77*(Assumptions!$D$20-Assumptions!$D$23)/4 -> 74714063 | AE7: =AE77*(Assumptions!$D$20-Assumptions!$D$23)/4 -> 74172656 | AF7: =AF77*(Assumptions!$D$20-Assumptions!$D$23)/4 -> 73631250 | AG7: =SUM(AC7:AF7) -> 2.9777344e+08 | AH7: =AH77*(Assumptions!$D$20-Assumptions!$D$23)/4 -> 73089844 | AI7: =AI77*(Assumptions!$D$20-Assumptions!$D$23)/4 -> 72548438 | AJ7: =AJ77*(Assumptions!$D$20-Assumptions!$D$23)/4 -> 72007031 | AK7: =AK77*(Assumptions!$D$20-Assumptions!$D$23)/4 -> 71465625 | AL7: =SUM(AH7:AK7) -> 2.8911094e+08
C8: Net interest income on auto loans and leasing | D8: =D78*(Assumptions!$D$21-Assumptions!$D$23)/4 -> 1721671.9 | E8: =E78*(Assumptions!$D$21-Assumptions!$D$23)/4 -> 3421687.5 | F8: =F78*(Assumptions!$D$21-Assumptions!$D$23)/4 -> 5100046.9 | G8: =G78*(Assumptions!$D$21-Assumptions!$D$23)/4 -> 6756750 | H8: =SUM(D8:G8) -> 17000156 | I8: =I78*(Assumptions!$D$21-Assumptions!$D$23)/4 -> 8391796.9 | J8: =J78*(Assumptions!$D$21-Assumptions!$D$23)/4 -> 10005188 | K8: =K78*(Assumptions!$D$21-Assumptions!$D$23)/4 -> 11596922 | L8: =L78*(Assumptions!$D$21-Assumptions!$D$23)/4 -> 13167000 | M8: =SUM(I8:L8) -> 43160906 | N8: =N78*(Assumptions!$D$21-Assumptions!$D$23)/4 -> 14715422 | O8: =O78*(Assumptions!$D$21-Assumptions!$D$23)/4 -> 16242188 | P8: =P78*(Assumptions!$D$21-Assumptions!$D$23)/4 -> 17747297 | Q8: =Q78*(Assumptions!$D$21-Assumptions!$D$23)/4 -> 19230750 | R8: =SUM(N8:Q8) -> 67935656 | S8: =S78*(Assumptions!$D$21-Assumptions!$D$23)/4 -> 20692547 | T8: =T78*(Assumptions!$D$21-Assumptions!$D$23)/4 -> 22132688 | U8: =U78*(Assumptions!$D$21-Assumptions!$D$23)/4 -> 23551172 | V8: =V78*(Assumptions!$D$21-Assumptions!$D$23)/4 -> 24948000 | W8: =SUM(S8:V8) -> 91324406 | X8: =X78*(Assumptions!$D$21-Assumptions!$D$23)/4 -> 26323172 | Y8: =Y78*(Assumptions!$D$21-Assumptions!$D$23)/4 -> 27676688 | Z8: =Z78*(Assumptions!$D$21-Assumptions!$D$23)/4 -> 29008547 | AA8: =AA78*(Assumptions!$D$21-Assumptions!$D$23)/4 -> 30318750 | AB8: =SUM(X8:AA8) -> 1.1332716e+08 | AC8: =AC78*(Assumptions!$D$21-Assumptions!$D$23)/4 -> 30102188 | AD8: =AD78*(Assumptions!$D$21-Assumptions!$D$23)/4 -> 29885625 | AE8: =AE78*(Assumptions!$D$21-Assumptions!$D$23)/4 -> 29669062 | AF8: =AF78*(Assumptions!$D$21-Assumptions!$D$23)/4 -> 29452500 | AG8: =SUM(AC8:AF8) -> 119109375 | AH8: =AH78*(Assumptions!$D$21-Assumptions!$D$23)/4 -> 29235938 | AI8: =AI78*(Assumptions!$D$21-Assumptions!$D$23)/4 -> 29019375 | AJ8: =AJ78*(Assumptions!$D$21-Assumptions!$D$23)/4 -> 28802812 | AK8: =AK78*(Assumptions!$D$21-Assumptions!$D$23)/4 -> 28586250 | AL8: =SUM(AH8:AK8) -> 115644375
C9: Net interest income on deposits | D9: =D79*(Assumptions!$D$23-Assumptions!$D$22)/4 -> 143472.66 | E9: =E79*(Assumptions!$D$23-Assumptions!$D$22)/4 -> 285140.63 | F9: =F79*(Assumptions!$D$23-Assumptions!$D$22)/4 -> 425003.91 | G9: =G79*(Assumptions!$D$23-Assumptions!$D$22)/4 -> 563062.5 | H9: =SUM(D9:G9) -> 1416679.7 | I9: =I79*(Assumptions!$D$23-Assumptions!$D$22)/4 -> 699316.41 | J9: =J79*(Assumptions!$D$23-Assumptions!$D$22)/4 -> 833765.63 | K9: =K79*(Assumptions!$D$23-Assumptions!$D$22)/4 -> 966410.16 | L9: =L79*(Assumptions!$D$23-Assumptions!$D$22)/4 -> 1097250 | M9: =SUM(I9:L9) -> 3596742.2 | N9: =N79*(Assumptions!$D$23-Assumptions!$D$22)/4 -> 1226285.2 | O9: =O79*(Assumptions!$D$23-Assumptions!$D$22)/4 -> 1353515.6 | P9: =P79*(Assumptions!$D$23-Assumptions!$D$22)/4 -> 1478941.4 | Q9: =Q79*(Assumptions!$D$23-Assumptions!$D$22)/4 -> 1602562.5 | R9: =SUM(N9:Q9) -> 5661304.7 | S9: =S79*(Assumptions!$D$23-Assumptions!$D$22)/4 -> 1724378.9 | T9: =T79*(Assumptions!$D$23-Assumptions!$D$22)/4 -> 1844390.6 | U9: =U79*(Assumptions!$D$23-Assumptions!$D$22)/4 -> 1962597.7 | V9: =V79*(Assumptions!$D$23-Assumptions!$D$22)/4 -> 2079000 | W9: =SUM(S9:V9) -> 7610367.2 | X9: =X79*(Assumptions!$D$23-Assumptions!$D$22)/4 -> 2193597.7 | Y9: =Y79*(Assumptions!$D$23-Assumptions!$D$22)/4 -> 2306390.6 | Z9: =Z79*(Assumptions!$D$23-Assumptions!$D$22)/4 -> 2417378.9 | AA9: =AA79*(Assumptions!$D$23-Assumptions!$D$22)/4 -> 2526562.5 | AB9: =SUM(X9:AA9) -> 9443929.7 | AC9: =AC79*(Assumptions!$D$23-Assumptions!$D$22)/4 -> 2508515.6 | AD9: =AD79*(Assumptions!$D$23-Assumptions!$D$22)/4 -> 2490468.8 | AE9: =AE79*(Assumptions!$D$23-Assumptions!$D$22)/4 -> 2472421.9 | AF9: =AF79*(Assumptions!$D$23-Assumptions!$D$22)/4 -> 2454375 | AG9: =SUM(AC9:AF9) -> 9925781.3 | AH9: =AH79*(Assumptions!$D$23-Assumptions!$D$22)/4 -> 2436328.1 | AI9: =AI79*(Assumptions!$D$23-Assumptions!$D$22)/4 -> 2418281.3 | AJ9: =AJ79*(Assumptions!$D$23-Assumptions!$D$22)/4 -> 2400234.4 | AK9: =AK79*(Assumptions!$D$23-Assumptions!$D$22)/4 -> 2382187.5 | AL9: =SUM(AH9:AK9) -> 9637031.3
C10: Net interest income on checking account balances | D10: =D80*(Assumptions!$D$23-Assumptions!$D$25)/4 -> 430417.97 | E10: =E80*(Assumptions!$D$23-Assumptions!$D$25)/4 -> 855421.88 | F10: =F80*(Assumptions!$D$23-Assumptions!$D$25)/4 -> 1275011.7 | G10: =G80*(Assumptions!$D$23-Assumptions!$D$25)/4 -> 1689187.5 | H10: =SUM(D10:G10) -> 4250039.1 | I10: =I80*(Assumptions!$D$23-Assumptions!$D$25)/4 -> 2097949.2 | J10: =J80*(Assumptions!$D$23-Assumptions!$D$25)/4 -> 2501296.9 | K10: =K80*(Assumptions!$D$23-Assumptions!$D$25)/4 -> 2899230.5 | L10: =L80*(Assumptions!$D$23-Assumptions!$D$25)/4 -> 3291750 | M10: =SUM(I10:L10) -> 10790227 | N10: =N80*(Assumptions!$D$23-Assumptions!$D$25)/4 -> 3678855.5 | O10: =O80*(Assumptions!$D$23-Assumptions!$D$25)/4 -> 4060546.9 | P10: =P80*(Assumptions!$D$23-Assumptions!$D$25)/4 -> 4436824.2 | Q10: =Q80*(Assumptions!$D$23-Assumptions!$D$25)/4 -> 4807687.5 | R10: =SUM(N10:Q10) -> 16983914 | S10: =S80*(Assumptions!$D$23-Assumptions!$D$25)/4 -> 5173136.7 | T10: =T80*(Assumptions!$D$23-Assumptions!$D$25)/4 -> 5533171.9 | U10: =U80*(Assumptions!$D$23-Assumptions!$D$25)/4 -> 5887793 | V10: =V80*(Assumptions!$D$23-Assumptions!$D$25)/4 -> 6237000 | W10: =SUM(S10:V10) -> 22831102 | X10: =X80*(Assumptions!$D$23-Assumptions!$D$25)/4 -> 6580793 | Y10: =Y80*(Assumptions!$D$23-Assumptions!$D$25)/4 -> 6919171.9 | Z10: =Z80*(Assumptions!$D$23-Assumptions!$D$25)/4 -> 7252136.7 | AA10: =AA80*(Assumptions!$D$23-Assumptions!$D$25)/4 -> 7579687.5 | AB10: =SUM(X10:AA10) -> 28331789 | AC10: =AC80*(Assumptions!$D$23-Assumptions!$D$25)/4 -> 7525546.9 | AD10: =AD80*(Assumptions!$D$23-Assumptions!$D$25)/4 -> 7471406.2 | AE10: =AE80*(Assumptions!$D$23-Assumptions!$D$25)/4 -> 7417265.6 | AF10: =AF80*(Assumptions!$D$23-Assumptions!$D$25)/4 -> 7363125 | AG10: =SUM(AC10:AF10) -> 29777344 | AH10: =AH80*(Assumptions!$D$23-Assumptions!$D$25)/4 -> 7308984.4 | AI10: =AI80*(Assumptions!$D$23-Assumptions!$D$25)/4 -> 7254843.8 | AJ10: =AJ80*(Assumptions!$D$23-Assumptions!$D$25)/4 -> 7200703.1 | AK10: =AK80*(Assumptions!$D$23-Assumptions!$D$25)/4 -> 7146562.5 | AL10: =SUM(AH10:AK10) -> 28911094
B11: Net interest income | D11: =SUM(D6:D10) -> 15916148 | E11: =SUM(E6:E10) -> 31632094 | F11: =SUM(F6:F10) -> 47147836 | G11: =SUM(G6:G10) -> 62463375 | H11: =SUM(D11:G11) -> 1.5715945e+08 | I11: =SUM(I6:I10) -> 77578711 | J11: =SUM(J6:J10) -> 92493844 | K11: =SUM(K6:K10) -> 1.0720877e+08 | L11: =SUM(L6:L10) -> 121723500 | M11: =SUM(I11:L11) -> 3.9900483e+08 | N11: =SUM(N6:N10) -> 1.3603802e+08 | O11: =SUM(O6:O10) -> 1.5015234e+08 | P11: =SUM(P6:P10) -> 1.6406646e+08 | Q11: =SUM(Q6:Q10) -> 1.7778038e+08 | R11: =SUM(N11:Q11) -> 6.280372e+08 | S11: =SUM(S6:S10) -> 1.9129409e+08 | T11: =SUM(T6:T10) -> 2.0460759e+08 | U11: =SUM(U6:U10) -> 2.177209e+08 | V11: =SUM(V6:V10) -> 230634000 | W11: =SUM(S11:V11) -> 8.4425658e+08 | X11: =SUM(X6:X10) -> 2.433469e+08 | Y11: =SUM(Y6:Y10) -> 2.5585959e+08 | Z11: =SUM(Z6:Z10) -> 2.6817209e+08 | AA11: =SUM(AA6:AA10) -> 280284375 | AB11: =SUM(X11:AA11) -> 1.047663e+09 | AC11: =SUM(AC6:AC10) -> 2.7828234e+08 | AD11: =SUM(AD6:AD10) -> 2.7628031e+08 | AE11: =SUM(AE6:AE10) -> 2.7427828e+08 | AF11: =SUM(AF6:AF10) -> 272276250 | AG11: =SUM(AC11:AF11) -> 1.1011172e+09 | AH11: =SUM(AH6:AH10) -> 2.7027422e+08 | AI11: =SUM(AI6:AI10) -> 2.6827219e+08 | AJ11: =SUM(AJ6:AJ10) -> 2.6627016e+08 | AK11: =SUM(AK6:AK10) -> 264268125 | AL11: =SUM(AH11:AK11) -> 1.0690847e+09
A12: NET INTEREST INCOME | D12: =D11 -> 15916148 | E12: =E11 -> 31632094 | F12: =F11 -> 47147836 | G12: =G11 -> 62463375 | H12: =SUM(D12:G12) -> 1.5715945e+08 | I12: =I11 -> 77578711 | J12: =J11 -> 92493844 | K12: =K11 -> 1.0720877e+08 | L12: =L11 -> 121723500 | M12: =SUM(I12:L12) -> 3.9900483e+08 | N12: =N11 -> 1.3603802e+08 | O12: =O11 -> 1.5015234e+08 | P12: =P11 -> 1.6406646e+08 | Q12: =Q11 -> 1.7778038e+08 | R12: =SUM(N12:Q12) -> 6.280372e+08 | S12: =S11 -> 1.9129409e+08 | T12: =T11 -> 2.0460759e+08 | U12: =U11 -> 2.177209e+08 | V12: =V11 -> 230634000 | W12: =SUM(S12:V12) -> 8.4425658e+08 | X12: =X11 -> 2.433469e+08 | Y12: =Y11 -> 2.5585959e+08 | Z12: =Z11 -> 2.6817209e+08 | AA12: =AA11 -> 280284375 | AB12: =SUM(X12:AA12) -> 1.047663e+09 | AC12: =AC11 -> 2.7828234e+08 | AD12: =AD11 -> 2.7628031e+08 | AE12: =AE11 -> 2.7427828e+08 | AF12: =AF11 -> 272276250 | AG12: =SUM(AC12:AF12) -> 1.1011172e+09 | AH12: =AH11 -> 2.7027422e+08 | AI12: =AI11 -> 2.6827219e+08 | AJ12: =AJ11 -> 2.6627016e+08 | AK12: =AK11 -> 264268125 | AL12: =SUM(AH12:AK12) -> 1.0690847e+09
C13: Net intrabank transaction fees income | D13: =(D81*(1-Assumptions!$D$17)*Assumptions!$D$26+D81*(Assumptions!$D$17)*Assumptions!$D$27) -> 1033003.1 | E13: =(E81*(1-Assumptions!$D$17)*Assumptions!$D$26+E81*(Assumptions!$D$17)*Assumptions!$D$27) -> 2053012.5 | F13: =(F81*(1-Assumptions!$D$17)*Assumptions!$D$26+F81*(Assumptions!$D$17)*Assumptions!$D$27) -> 3060028.1 | G13: =(G81*(1-Assumptions!$D$17)*Assumptions!$D$26+G81*(Assumptions!$D$17)*Assumptions!$D$27) -> 4054050 | H13: =SUM(D13:G13) -> 10200094 | I13: =(I81*(1-Assumptions!$D$17)*Assumptions!$D$26+I81*(Assumptions!$D$17)*Assumptions!$D$27) -> 5035078.1 | J13: =(J81*(1-Assumptions!$D$17)*Assumptions!$D$26+J81*(Assumptions!$D$17)*Assumptions!$D$27) -> 6003112.5 | K13: =(K81*(1-Assumptions!$D$17)*Assumptions!$D$26+K81*(Assumptions!$D$17)*Assumptions!$D$27) -> 6958153.1 | L13: =(L81*(1-Assumptions!$D$17)*Assumptions!$D$26+L81*(Assumptions!$D$17)*Assumptions!$D$27) -> 7900200 | M13: =SUM(I13:L13) -> 25896544 | N13: =(N81*(1-Assumptions!$D$17)*Assumptions!$D$26+N81*(Assumptions!$D$17)*Assumptions!$D$27) -> 8829253.1 | O13: =(O81*(1-Assumptions!$D$17)*Assumptions!$D$26+O81*(Assumptions!$D$17)*Assumptions!$D$27) -> 9745312.5 | P13: =(P81*(1-Assumptions!$D$17)*Assumptions!$D$26+P81*(Assumptions!$D$17)*Assumptions!$D$27) -> 10648378 | Q13: =(Q81*(1-Assumptions!$D$17)*Assumptions!$D$26+Q81*(Assumptions!$D$17)*Assumptions!$D$27) -> 11538450 | R13: =SUM(N13:Q13) -> 40761394 | S13: =(S81*(1-Assumptions!$D$17)*Assumptions!$D$26+S81*(Assumptions!$D$17)*Assumptions!$D$27) -> 12415528 | T13: =(T81*(1-Assumptions!$D$17)*Assumptions!$D$26+T81*(Assumptions!$D$17)*Assumptions!$D$27) -> 13279612 | U13: =(U81*(1-Assumptions!$D$17)*Assumptions!$D$26+U81*(Assumptions!$D$17)*Assumptions!$D$27) -> 14130703 | V13: =(V81*(1-Assumptions!$D$17)*Assumptions!$D$26+V81*(Assumptions!$D$17)*Assumptions!$D$27) -> 14968800 | W13: =SUM(S13:V13) -> 54794644 | X13: =(X81*(1-Assumptions!$D$17)*Assumptions!$D$26+X81*(Assumptions!$D$17)*Assumptions!$D$27) -> 15793903 | Y13: =(Y81*(1-Assumptions!$D$17)*Assumptions!$D$26+Y81*(Assumptions!$D$17)*Assumptions!$D$27) -> 16606012 | Z13: =(Z81*(1-Assumptions!$D$17)*Assumptions!$D$26+Z81*(Assumptions!$D$17)*Assumptions!$D$27) -> 17405128 | AA13: =(AA81*(1-Assumptions!$D$17)*Assumptions!$D$26+AA81*(Assumptions!$D$17)*Assumptions!$D$27) -> 18191250 | AB13: =SUM(X13:AA13) -> 67996294 | AC13: =(AC81*(1-Assumptions!$D$17)*Assumptions!$D$26+AC81*(Assumptions!$D$17)*Assumptions!$D$27) -> 18061312 | AD13: =(AD81*(1-Assumptions!$D$17)*Assumptions!$D$26+AD81*(Assumptions!$D$17)*Assumptions!$D$27) -> 17931375 | AE13: =(AE81*(1-Assumptions!$D$17)*Assumptions!$D$26+AE81*(Assumptions!$D$17)*Assumptions!$D$27) -> 17801438 | AF13: =(AF81*(1-Assumptions!$D$17)*Assumptions!$D$26+AF81*(Assumptions!$D$17)*Assumptions!$D$27) -> 17671500 | AG13: =SUM(AC13:AF13) -> 71465625 | AH13: =(AH81*(1-Assumptions!$D$17)*Assumptions!$D$26+AH81*(Assumptions!$D$17)*Assumptions!$D$27) -> 17541562 | AI13: =(AI81*(1-Assumptions!$D$17)*Assumptions!$D$26+AI81*(Assumptions!$D$17)*Assumptions!$D$27) -> 17411625 | AJ13: =(AJ81*(1-Assumptions!$D$17)*Assumptions!$D$26+AJ81*(Assumptions!$D$17)*Assumptions!$D$27) -> 17281688 | AK13: =(AK81*(1-Assumptions!$D$17)*Assumptions!$D$26+AK81*(Assumptions!$D$17)*Assumptions!$D$27) -> 17151750 | AL13: =SUM(AH13:AK13) -> 69386625
C14: Net interbank transaction fees income | D14: =(D82*(1-Assumptions!$D$17)*Assumptions!$D$28+D82*(Assumptions!$D$17)*Assumptions!$D$29) -> 2582507.8 | E14: =(E82*(1-Assumptions!$D$17)*Assumptions!$D$28+E82*(Assumptions!$D$17)*Assumptions!$D$29) -> 5132531.2 | F14: =(F82*(1-Assumptions!$D$17)*Assumptions!$D$28+F82*(Assumptions!$D$17)*Assumptions!$D$29) -> 7650070.3 | G14: =(G82*(1-Assumptions!$D$17)*Assumptions!$D$28+G82*(Assumptions!$D$17)*Assumptions!$D$29) -> 10135125 | H14: =SUM(D14:G14) -> 25500234 | I14: =(I82*(1-Assumptions!$D$17)*Assumptions!$D$28+I82*(Assumptions!$D$17)*Assumptions!$D$29) -> 12587695 | J14: =(J82*(1-Assumptions!$D$17)*Assumptions!$D$28+J82*(Assumptions!$D$17)*Assumptions!$D$29) -> 15007781 | K14: =(K82*(1-Assumptions!$D$17)*Assumptions!$D$28+K82*(Assumptions!$D$17)*Assumptions!$D$29) -> 17395383 | L14: =(L82*(1-Assumptions!$D$17)*Assumptions!$D$28+L82*(Assumptions!$D$17)*Assumptions!$D$29) -> 19750500 | M14: =SUM(I14:L14) -> 64741359 | N14: =(N82*(1-Assumptions!$D$17)*Assumptions!$D$28+N82*(Assumptions!$D$17)*Assumptions!$D$29) -> 22073133 | O14: =(O82*(1-Assumptions!$D$17)*Assumptions!$D$28+O82*(Assumptions!$D$17)*Assumptions!$D$29) -> 24363281 | P14: =(P82*(1-Assumptions!$D$17)*Assumptions!$D$28+P82*(Assumptions!$D$17)*Assumptions!$D$29) -> 26620945 | Q14: =(Q82*(1-Assumptions!$D$17)*Assumptions!$D$28+Q82*(Assumptions!$D$17)*Assumptions!$D$29) -> 28846125 | R14: =SUM(N14:Q14) -> 1.0190348e+08 | S14: =(S82*(1-Assumptions!$D$17)*Assumptions!$D$28+S82*(Assumptions!$D$17)*Assumptions!$D$29) -> 31038820 | T14: =(T82*(1-Assumptions!$D$17)*Assumptions!$D$28+T82*(Assumptions!$D$17)*Assumptions!$D$29) -> 33199031 | U14: =(U82*(1-Assumptions!$D$17)*Assumptions!$D$28+U82*(Assumptions!$D$17)*Assumptions!$D$29) -> 35326758 | V14: =(V82*(1-Assumptions!$D$17)*Assumptions!$D$28+V82*(Assumptions!$D$17)*Assumptions!$D$29) -> 37422000 | W14: =SUM(S14:V14) -> 1.3698661e+08 | X14: =(X82*(1-Assumptions!$D$17)*Assumptions!$D$28+X82*(Assumptions!$D$17)*Assumptions!$D$29) -> 39484758 | Y14: =(Y82*(1-Assumptions!$D$17)*Assumptions!$D$28+Y82*(Assumptions!$D$17)*Assumptions!$D$29) -> 41515031 | Z14: =(Z82*(1-Assumptions!$D$17)*Assumptions!$D$28+Z82*(Assumptions!$D$17)*Assumptions!$D$29) -> 43512820 | AA14: =(AA82*(1-Assumptions!$D$17)*Assumptions!$D$28+AA82*(Assumptions!$D$17)*Assumptions!$D$29) -> 45478125 | AB14: =SUM(X14:AA14) -> 1.6999073e+08 | AC14: =(AC82*(1-Assumptions!$D$17)*Assumptions!$D$28+AC82*(Assumptions!$D$17)*Assumptions!$D$29) -> 45153281 | AD14: =(AD82*(1-Assumptions!$D$17)*Assumptions!$D$28+AD82*(Assumptions!$D$17)*Assumptions!$D$29) -> 44828438 | AE14: =(AE82*(1-Assumptions!$D$17)*Assumptions!$D$28+AE82*(Assumptions!$D$17)*Assumptions!$D$29) -> 44503594 | AF14: =(AF82*(1-Assumptions!$D$17)*Assumptions!$D$28+AF82*(Assumptions!$D$17)*Assumptions!$D$29) -> 44178750 | AG14: =SUM(AC14:AF14) -> 1.7866406e+08 | AH14: =(AH82*(1-Assumptions!$D$17)*Assumptions!$D$28+AH82*(Assumptions!$D$17)*Assumptions!$D$29) -> 43853906 | AI14: =(AI82*(1-Assumptions!$D$17)*Assumptions!$D$28+AI82*(Assumptions!$D$17)*Assumptions!$D$29) -> 43529062 | AJ14: =(AJ82*(1-Assumptions!$D$17)*Assumptions!$D$28+AJ82*(Assumptions!$D$17)*Assumptions!$D$29) -> 43204219 | AK14: =(AK82*(1-Assumptions!$D$17)*Assumptions!$D$28+AK82*(Assumptions!$D$17)*Assumptions!$D$29) -> 42879375 | AL14: =SUM(AH14:AK14) -> 1.7346656e+08
C15: Net international transaction fees income | D15: =(D82*(1-Assumptions!$D$17)*Assumptions!$D$30+D82*(Assumptions!$D$17)*Assumptions!$D$31) -> 5165015.6 | E15: =(E82*(1-Assumptions!$D$17)*Assumptions!$D$30+E82*(Assumptions!$D$17)*Assumptions!$D$31) -> 10265062 | F15: =(F82*(1-Assumptions!$D$17)*Assumptions!$D$30+F82*(Assumptions!$D$17)*Assumptions!$D$31) -> 15300141 | G15: =(G82*(1-Assumptions!$D$17)*Assumptions!$D$30+G82*(Assumptions!$D$17)*Assumptions!$D$31) -> 20270250 | H15: =SUM(D15:G15) -> 51000469 | I15: =(I82*(1-Assumptions!$D$17)*Assumptions!$D$30+I82*(Assumptions!$D$17)*Assumptions!$D$31) -> 25175391 | J15: =(J82*(1-Assumptions!$D$17)*Assumptions!$D$30+J82*(Assumptions!$D$17)*Assumptions!$D$31) -> 30015562 | K15: =(K82*(1-Assumptions!$D$17)*Assumptions!$D$30+K82*(Assumptions!$D$17)*Assumptions!$D$31) -> 34790766 | L15: =(L82*(1-Assumptions!$D$17)*Assumptions!$D$30+L82*(Assumptions!$D$17)*Assumptions!$D$31) -> 39501000 | M15: =SUM(I15:L15) -> 1.2948272e+08 | N15: =(N82*(1-Assumptions!$D$17)*Assumptions!$D$30+N82*(Assumptions!$D$17)*Assumptions!$D$31) -> 44146266 | O15: =(O82*(1-Assumptions!$D$17)*Assumptions!$D$30+O82*(Assumptions!$D$17)*Assumptions!$D$31) -> 48726562 | P15: =(P82*(1-Assumptions!$D$17)*Assumptions!$D$30+P82*(Assumptions!$D$17)*Assumptions!$D$31) -> 53241891 | Q15: =(Q82*(1-Assumptions!$D$17)*Assumptions!$D$30+Q82*(Assumptions!$D$17)*Assumptions!$D$31) -> 57692250 | R15: =SUM(N15:Q15) -> 2.0380697e+08 | S15: =(S82*(1-Assumptions!$D$17)*Assumptions!$D$30+S82*(Assumptions!$D$17)*Assumptions!$D$31) -> 62077641 | T15: =(T82*(1-Assumptions!$D$17)*Assumptions!$D$30+T82*(Assumptions!$D$17)*Assumptions!$D$31) -> 66398062 | U15: =(U82*(1-Assumptions!$D$17)*Assumptions!$D$30+U82*(Assumptions!$D$17)*Assumptions!$D$31) -> 70653516 | V15: =(V82*(1-Assumptions!$D$17)*Assumptions!$D$30+V82*(Assumptions!$D$17)*Assumptions!$D$31) -> 74844000 | W15: =SUM(S15:V15) -> 2.7397322e+08 | X15: =(X82*(1-Assumptions!$D$17)*Assumptions!$D$30+X82*(Assumptions!$D$17)*Assumptions!$D$31) -> 78969516 | Y15: =(Y82*(1-Assumptions!$D$17)*Assumptions!$D$30+Y82*(Assumptions!$D$17)*Assumptions!$D$31) -> 83030062 | Z15: =(Z82*(1-Assumptions!$D$17)*Assumptions!$D$30+Z82*(Assumptions!$D$17)*Assumptions!$D$31) -> 87025641 | AA15: =(AA82*(1-Assumptions!$D$17)*Assumptions!$D$30+AA82*(Assumptions!$D$17)*Assumptions!$D$31) -> 90956250 | AB15: =SUM(X15:AA15) -> 3.3998147e+08 | AC15: =(AC82*(1-Assumptions!$D$17)*Assumptions!$D$30+AC82*(Assumptions!$D$17)*Assumptions!$D$31) -> 90306562 | AD15: =(AD82*(1-Assumptions!$D$17)*Assumptions!$D$30+AD82*(Assumptions!$D$17)*Assumptions!$D$31) -> 89656875 | AE15: =(AE82*(1-Assumptions!$D$17)*Assumptions!$D$30+AE82*(Assumptions!$D$17)*Assumptions!$D$31) -> 89007188 | AF15: =(AF82*(1-Assumptions!$D$17)*Assumptions!$D$30+AF82*(Assumptions!$D$17)*Assumptions!$D$31) -> 88357500 | AG15: =SUM(AC15:AF15) -> 357328125 | AH15: =(AH82*(1-Assumptions!$D$17)*Assumptions!$D$30+AH82*(Assumptions!$D$17)*Assumptions!$D$31) -> 87707812 | AI15: =(AI82*(1-Assumptions!$D$17)*Assumptions!$D$30+AI82*(Assumptions!$D$17)*Assumptions!$D$31) -> 87058125 | AJ15: =(AJ82*(1-Assumptions!$D$17)*Assumptions!$D$30+AJ82*(Assumptions!$D$17)*Assumptions!$D$31) -> 86408438 | AK15: =(AK82*(1-Assumptions!$D$17)*Assumptions!$D$30+AK82*(Assumptions!$D$17)*Assumptions!$D$31) -> 85758750 | AL15: =SUM(AH15:AK15) -> 346933125
C16: Loan processing fees income | D16: =(D76+D77+D78)*Assumptions!$D$32 -> 25047469 | E16: =(E76+E77+E78-D76-D77-D78)*Assumptions!$D$34 -> 24732406 | F16: =(F76+F77+F78-E76-E77-E78)*Assumptions!$D$34 -> 24417344 | G16: =(G76+G77+G78-F76-F77-F78)*Assumptions!$D$34 -> 24102281 | H16: =SUM(D16:G16) -> 98299500 | I16: =(I76+I77+I78-H76-H77-H78)*Assumptions!$D$34 -> 23787219 | J16: =(J76+J77+J78-I76-I77-I78)*Assumptions!$D$34 -> 23472156 | K16: =(K76+K77+K78-J76-J77-J78)*Assumptions!$D$34 -> 23157094 | L16: =(L76+L77+L78-K76-K77-K78)*Assumptions!$D$34 -> 22842031 | M16: =SUM(I16:L16) -> 93258500 | N16: =(N76+N77+N78-M76-M77-M78)*Assumptions!$D$34 -> 22526969 | O16: =(O76+O77+O78-N76-N77-N78)*Assumptions!$D$34 -> 22211906 | P16: =(P76+P77+P78-O76-O77-O78)*Assumptions!$D$34 -> 21896844 | Q16: =(Q76+Q77+Q78-P76-P77-P78)*Assumptions!$D$34 -> 21581781 | R16: =SUM(N16:Q16) -> 88217500 | S16: =(S76+S77+S78-R76-R77-R78)*Assumptions!$D$34 -> 21266719 | T16: =(T76+T77+T78-S76-S77-S78)*Assumptions!$D$34 -> 20951656 | U16: =(U76+U77+U78-T76-T77-T78)*Assumptions!$D$34 -> 20636594 | V16: =(V76+V77+V78-U76-U77-U78)*Assumptions!$D$34 -> 20321531 | W16: =SUM(S16:V16) -> 83176500 | X16: =(X76+X77+X78-W76-W77-W78)*Assumptions!$D$34 -> 20006469 | Y16: =(Y76+Y77+Y78-X76-X77-X78)*Assumptions!$D$34 -> 19691406 | Z16: =(Z76+Z77+Z78-Y76-Y77-Y78)*Assumptions!$D$34 -> 19376344 | AA16: =(AA76+AA77+AA78-Z76-Z77-Z78)*Assumptions!$D$34 -> 19061281 | AB16: =SUM(X16:AA16) -> 78135500 | AC16: =(AC76+AC77+AC78-AB76-AB77-AB78)*Assumptions!$D$34 -> -3150625 | AD16: =(AD76+AD77+AD78-AC76-AC77-AC78)*Assumptions!$D$34 -> -3150625 | AE16: =(AE76+AE77+AE78-AD76-AD77-AD78)*Assumptions!$D$34 -> -3150625 | AF16: =(AF76+AF77+AF78-AE76-AE77-AE78)*Assumptions!$D$34 -> -3150625 | AG16: =SUM(AC16:AF16) -> -12602500 | AH16: =(AH76+AH77+AH78-AG76-AG77-AG78)*Assumptions!$D$34 -> -3150625 | AI16: =(AI76+AI77+AI78-AH76-AH77-AH78)*Assumptions!$D$34 -> -3150625 | AJ16: =(AJ76+AJ77+AJ78-AI76-AI77-AI78)*Assumptions!$D$34 -> -3150625 | AK16: =(AK76+AK77+AK78-AJ76-AJ77-AJ78)*Assumptions!$D$34 -> -3150625 | AL16: =SUM(AH16:AK16) -> -12602500
B17: Fee income | D17: =SUM(D13:D16) -> 33827995 | E17: =SUM(E13:E16) -> 42183012 | F17: =SUM(F13:F16) -> 50427583 | G17: =SUM(G13:G16) -> 58561706 | H17: =SUM(D17:G17) -> 1.850003e+08 | I17: =SUM(I13:I16) -> 66585383 | J17: =SUM(J13:J16) -> 74498612 | K17: =SUM(K13:K16) -> 82301395 | L17: =SUM(L13:L16) -> 89993731 | M17: =SUM(I17:L17) -> 3.1337912e+08 | N17: =SUM(N13:N16) -> 97575620 | O17: =SUM(O13:O16) -> 1.0504706e+08 | P17: =SUM(P13:P16) -> 1.1240806e+08 | Q17: =SUM(Q13:Q16) -> 1.1965861e+08 | R17: =SUM(N17:Q17) -> 4.3468935e+08 | S17: =SUM(S13:S16) -> 1.2679871e+08 | T17: =SUM(T13:T16) -> 1.3382836e+08 | U17: =SUM(U13:U16) -> 1.4074757e+08 | V17: =SUM(V13:V16) -> 1.4755633e+08 | W17: =SUM(S17:V17) -> 5.4893097e+08 | X17: =SUM(X13:X16) -> 1.5425465e+08 | Y17: =SUM(Y13:Y16) -> 1.6084251e+08 | Z17: =SUM(Z13:Z16) -> 1.6731993e+08 | AA17: =SUM(AA13:AA16) -> 1.7368691e+08 | AB17: =SUM(X17:AA17) -> 6.56104e+08 | AC17: =SUM(AC13:AC16) -> 1.5037053e+08 | AD17: =SUM(AD13:AD16) -> 1.4926606e+08 | AE17: =SUM(AE13:AE16) -> 1.4816159e+08 | AF17: =SUM(AF13:AF16) -> 147057125 | AG17: =SUM(AC17:AF17) -> 5.9485531e+08 | AH17: =SUM(AH13:AH16) -> 1.4595266e+08 | AI17: =SUM(AI13:AI16) -> 1.4484819e+08 | AJ17: =SUM(AJ13:AJ16) -> 1.4374372e+08 | AK17: =SUM(AK13:AK16) -> 142639250 | AL17: =SUM(AH17:AK17) -> 5.7718381e+08
A18: NET FEE INCOME | D18: =D17 -> 33827995 | E18: =E17 -> 42183012 | F18: =F17 -> 50427583 | G18: =G17 -> 58561706 | H18: =SUM(D18:G18) -> 1.850003e+08 | I18: =I17 -> 66585383 | J18: =J17 -> 74498612 | K18: =K17 -> 82301395 | L18: =L17 -> 89993731 | M18: =SUM(I18:L18) -> 3.1337912e+08 | N18: =N17 -> 97575620 | O18: =O17 -> 1.0504706e+08 | P18: =P17 -> 1.1240806e+08 | Q18: =Q17 -> 1.1965861e+08 | R18: =SUM(N18:Q18) -> 4.3468935e+08 | S18: =S17 -> 1.2679871e+08 | T18: =T17 -> 1.3382836e+08 | U18: =U17 -> 1.4074757e+08 | V18: =V17 -> 1.4755633e+08 | W18: =SUM(S18:V18) -> 5.4893097e+08 | X18: =X17 -> 1.5425465e+08 | Y18: =Y17 -> 1.6084251e+08 | Z18: =Z17 -> 1.6731993e+08 | AA18: =AA17 -> 1.7368691e+08 | AB18: =SUM(X18:AA18) -> 6.56104e+08 | AC18: =AC17 -> 1.5037053e+08 | AD18: =AD17 -> 1.4926606e+08 | AE18: =AE17 -> 1.4816159e+08 | AF18: =AF17 -> 147057125 | AG18: =SUM(AC18:AF18) -> 5.9485531e+08 | AH18: =AH17 -> 1.4595266e+08 | AI18: =AI17 -> 1.4484819e+08 | AJ18: =AJ17 -> 1.4374372e+08 | AK18: =AK17 -> 142639250 | AL18: =SUM(AH18:AK18) -> 5.7718381e+08
C19: Insurance premium income | D19: =SUM(D72:D75)*Assumptions!$D$55*Assumptions!$D$56/4/VLOOKUP(Assumptions!$D$7, Lists!$B$7:$C$10, 2, FALSE) -> 5738906.2 | E19: =SUM(E72:E75)*Assumptions!$D$55*Assumptions!$D$56/4/VLOOKUP(Assumptions!$D$7, Lists!$B$7:$C$10, 2, FALSE) -> 11405625 | F19: =SUM(F72:F75)*Assumptions!$D$55*Assumptions!$D$56/4/VLOOKUP(Assumptions!$D$7, Lists!$B$7:$C$10, 2, FALSE) -> 17000156 | G19: =SUM(G72:G75)*Assumptions!$D$55*Assumptions!$D$56/4/VLOOKUP(Assumptions!$D$7, Lists!$B$7:$C$10, 2, FALSE) -> 22522500 | H19: =SUM(D19:G19) -> 56667188 | I19: =SUM(I72:I75)*Assumptions!$D$55*Assumptions!$D$56/4/VLOOKUP(Assumptions!$D$7, Lists!$B$7:$C$10, 2, FALSE) -> 27972656 | J19: =SUM(J72:J75)*Assumptions!$D$55*Assumptions!$D$56/4/VLOOKUP(Assumptions!$D$7, Lists!$B$7:$C$10, 2, FALSE) -> 33350625 | K19: =SUM(K72:K75)*Assumptions!$D$55*Assumptions!$D$56/4/VLOOKUP(Assumptions!$D$7, Lists!$B$7:$C$10, 2, FALSE) -> 38656406 | L19: =SUM(L72:L75)*Assumptions!$D$55*Assumptions!$D$56/4/VLOOKUP(Assumptions!$D$7, Lists!$B$7:$C$10, 2, FALSE) -> 43890000 | M19: =SUM(I19:L19) -> 1.4386969e+08 | N19: =SUM(N72:N75)*Assumptions!$D$55*Assumptions!$D$56/4/VLOOKUP(Assumptions!$D$7, Lists!$B$7:$C$10, 2, FALSE) -> 49051406 | O19: =SUM(O72:O75)*Assumptions!$D$55*Assumptions!$D$56/4/VLOOKUP(Assumptions!$D$7, Lists!$B$7:$C$10, 2, FALSE) -> 54140625 | P19: =SUM(P72:P75)*Assumptions!$D$55*Assumptions!$D$56/4/VLOOKUP(Assumptions!$D$7, Lists!$B$7:$C$10, 2, FALSE) -> 59157656 | Q19: =SUM(Q72:Q75)*Assumptions!$D$55*Assumptions!$D$56/4/VLOOKUP(Assumptions!$D$7, Lists!$B$7:$C$10, 2, FALSE) -> 64102500 | R19: =SUM(N19:Q19) -> 2.2645219e+08 | S19: =SUM(S72:S75)*Assumptions!$D$55*Assumptions!$D$56/4/VLOOKUP(Assumptions!$D$7, Lists!$B$7:$C$10, 2, FALSE) -> 68975156 | T19: =SUM(T72:T75)*Assumptions!$D$55*Assumptions!$D$56/4/VLOOKUP(Assumptions!$D$7, Lists!$B$7:$C$10, 2, FALSE) -> 73775625 | U19: =SUM(U72:U75)*Assumptions!$D$55*Assumptions!$D$56/4/VLOOKUP(Assumptions!$D$7, Lists!$B$7:$C$10, 2, FALSE) -> 78503906 | V19: =SUM(V72:V75)*Assumptions!$D$55*Assumptions!$D$56/4/VLOOKUP(Assumptions!$D$7, Lists!$B$7:$C$10, 2, FALSE) -> 83160000 | W19: =SUM(S19:V19) -> 3.0441469e+08 | X19: =SUM(X72:X75)*Assumptions!$D$55*Assumptions!$D$56/4/VLOOKUP(Assumptions!$D$7, Lists!$B$7:$C$10, 2, FALSE) -> 87743906 | Y19: =SUM(Y72:Y75)*Assumptions!$D$55*Assumptions!$D$56/4/VLOOKUP(Assumptions!$D$7, Lists!$B$7:$C$10, 2, FALSE) -> 92255625 | Z19: =SUM(Z72:Z75)*Assumptions!$D$55*Assumptions!$D$56/4/VLOOKUP(Assumptions!$D$7, Lists!$B$7:$C$10, 2, FALSE) -> 96695156 | AA19: =SUM(AA72:AA75)*Assumptions!$D$55*Assumptions!$D$56/4/VLOOKUP(Assumptions!$D$7, Lists!$B$7:$C$10, 2, FALSE) -> 101062500 | AB19: =SUM(X19:AA19) -> 3.7775719e+08 | AC19: =SUM(AC72:AC75)*Assumptions!$D$55*Assumptions!$D$56/4/VLOOKUP(Assumptions!$D$7, Lists!$B$7:$C$10, 2, FALSE) -> 100340625 | AD19: =SUM(AD72:AD75)*Assumptions!$D$55*Assumptions!$D$56/4/VLOOKUP(Assumptions!$D$7, Lists!$B$7:$C$10, 2, FALSE) -> 99618750 | AE19: =SUM(AE72:AE75)*Assumptions!$D$55*Assumptions!$D$56/4/VLOOKUP(Assumptions!$D$7, Lists!$B$7:$C$10, 2, FALSE) -> 98896875 | AF19: =SUM(AF72:AF75)*Assumptions!$D$55*Assumptions!$D$56/4/VLOOKUP(Assumptions!$D$7, Lists!$B$7:$C$10, 2, FALSE) -> 98175000 | AG19: =SUM(AC19:AF19) -> 397031250 | AH19: =SUM(AH72:AH75)*Assumptions!$D$55*Assumptions!$D$56/4/VLOOKUP(Assumptions!$D$7, Lists!$B$7:$C$10, 2, FALSE) -> 97453125 | AI19: =SUM(AI72:AI75)*Assumptions!$D$55*Assumptions!$D$56/4/VLOOKUP(Assumptions!$D$7, Lists!$B$7:$C$10, 2, FALSE) -> 96731250 | AJ19: =SUM(AJ72:AJ75)*Assumptions!$D$55*Assumptions!$D$56/4/VLOOKUP(Assumptions!$D$7, Lists!$B$7:$C$10, 2, FALSE) -> 96009375 | AK19: =SUM(AK72:AK75)*Assumptions!$D$55*Assumptions!$D$56/4/VLOOKUP(Assumptions!$D$7, Lists!$B$7:$C$10, 2, FALSE) -> 95287500 | AL19: =SUM(AH19:AK19) -> 385481250
C20: Non-financial services (NFS) income | D20: =Assumptions!$D$57/4/VLOOKUP(Assumptions!$D$7, Lists!$B$7:$C$10, 2, FALSE) -> 2500000 | E20: =Assumptions!$D$57/4/VLOOKUP(Assumptions!$D$7, Lists!$B$7:$C$10, 2, FALSE) -> 2500000 | F20: =Assumptions!$D$57/4/VLOOKUP(Assumptions!$D$7, Lists!$B$7:$C$10, 2, FALSE) -> 2500000 | G20: =Assumptions!$D$57/4/VLOOKUP(Assumptions!$D$7, Lists!$B$7:$C$10, 2, FALSE) -> 2500000 | H20: =SUM(D20:G20) -> 10000000 | I20: =Assumptions!$D$57/4/VLOOKUP(Assumptions!$D$7, Lists!$B$7:$C$10, 2, FALSE) -> 2500000 | J20: =Assumptions!$D$57/4/VLOOKUP(Assumptions!$D$7, Lists!$B$7:$C$10, 2, FALSE) -> 2500000 | K20: =Assumptions!$D$57/4/VLOOKUP(Assumptions!$D$7, Lists!$B$7:$C$10, 2, FALSE) -> 2500000 | L20: =Assumptions!$D$57/4/VLOOKUP(Assumptions!$D$7, Lists!$B$7:$C$10, 2, FALSE) -> 2500000 | M20: =SUM(I20:L20) -> 10000000 | N20: =Assumptions!$D$57/4/VLOOKUP(Assumptions!$D$7, Lists!$B$7:$C$10, 2, FALSE) -> 2500000 | O20: =Assumptions!$D$57/4/VLOOKUP(Assumptions!$D$7, Lists!$B$7:$C$10, 2, FALSE) -> 2500000 | P20: =Assumptions!$D$57/4/VLOOKUP(Assumptions!$D$7, Lists!$B$7:$C$10, 2, FALSE) -> 2500000 | Q20: =Assumptions!$D$57/4/VLOOKUP(Assumptions!$D$7, Lists!$B$7:$C$10, 2, FALSE) -> 2500000 | R20: =SUM(N20:Q20) -> 10000000 | S20: =Assumptions!$D$57/4/VLOOKUP(Assumptions!$D$7, Lists!$B$7:$C$10, 2, FALSE) -> 2500000 | T20: =Assumptions!$D$57/4/VLOOKUP(Assumptions!$D$7, Lists!$B$7:$C$10, 2, FALSE) -> 2500000 | U20: =Assumptions!$D$57/4/VLOOKUP(Assumptions!$D$7, Lists!$B$7:$C$10, 2, FALSE) -> 2500000 | V20: =Assumptions!$D$57/4/VLOOKUP(Assumptions!$D$7, Lists!$B$7:$C$10, 2, FALSE) -> 2500000 | W20: =SUM(S20:V20) -> 10000000 | X20: =Assumptions!$D$57/4/VLOOKUP(Assumptions!$D$7, Lists!$B$7:$C$10, 2, FALSE) -> 2500000 | Y20: =Assumptions!$D$57/4/VLOOKUP(Assumptions!$D$7, Lists!$B$7:$C$10, 2, FALSE) -> 2500000 | Z20: =Assumptions!$D$57/4/VLOOKUP(Assumptions!$D$7, Lists!$B$7:$C$10, 2, FALSE) -> 2500000 | AA20: =Assumptions!$D$57/4/VLOOKUP(Assumptions!$D$7, Lists!$B$7:$C$10, 2, FALSE) -> 2500000 | AB20: =SUM(X20:AA20) -> 10000000 | AC20: =Assumptions!$D$57/4/VLOOKUP(Assumptions!$D$7, Lists!$B$7:$C$10, 2, FALSE) -> 2500000 | AD20: =Assumptions!$D$57/4/VLOOKUP(Assumptions!$D$7, Lists!$B$7:$C$10, 2, FALSE) -> 2500000 | AE20: =Assumptions!$D$57/4/VLOOKUP(Assumptions!$D$7, Lists!$B$7:$C$10, 2, FALSE) -> 2500000 | AF20: =Assumptions!$D$57/4/VLOOKUP(Assumptions!$D$7, Lists!$B$7:$C$10, 2, FALSE) -> 2500000 | AG20: =SUM(AC20:AF20) -> 10000000 | AH20: =Assumptions!$D$57/4/VLOOKUP(Assumptions!$D$7, Lists!$B$7:$C$10, 2, FALSE) -> 2500000 | AI20: =Assumptions!$D$57/4/VLOOKUP(Assumptions!$D$7, Lists!$B$7:$C$10, 2, FALSE) -> 2500000 | AJ20: =Assumptions!$D$57/4/VLOOKUP(Assumptions!$D$7, Lists!$B$7:$C$10, 2, FALSE) -> 2500000 | AK20: =Assumptions!$D$57/4/VLOOKUP(Assumptions!$D$7, Lists!$B$7:$C$10, 2, FALSE) -> 2500000 | AL20: =SUM(AH20:AK20) -> 10000000
C21: Non-financial services (NFS) costs | D21: =-Assumptions!$D$58/4/VLOOKUP(Assumptions!$D$7, Lists!$B$7:$C$10, 2, FALSE) -> -6250000 | E21: =-Assumptions!$D$58/4/VLOOKUP(Assumptions!$D$7, Lists!$B$7:$C$10, 2, FALSE) -> -6250000 | F21: =-Assumptions!$D$58/4/VLOOKUP(Assumptions!$D$7, Lists!$B$7:$C$10, 2, FALSE) -> -6250000 | G21: =-Assumptions!$D$58/4/VLOOKUP(Assumptions!$D$7, Lists!$B$7:$C$10, 2, FALSE) -> -6250000 | H21: =SUM(D21:G21) -> -25000000 | I21: =-Assumptions!$D$58/4/VLOOKUP(Assumptions!$D$7, Lists!$B$7:$C$10, 2, FALSE) -> -6250000 | J21: =-Assumptions!$D$58/4/VLOOKUP(Assumptions!$D$7, Lists!$B$7:$C$10, 2, FALSE) -> -6250000 | K21: =-Assumptions!$D$58/4/VLOOKUP(Assumptions!$D$7, Lists!$B$7:$C$10, 2, FALSE) -> -6250000 | L21: =-Assumptions!$D$58/4/VLOOKUP(Assumptions!$D$7, Lists!$B$7:$C$10, 2, FALSE) -> -6250000 | M21: =SUM(I21:L21) -> -25000000 | N21: =-Assumptions!$D$58/4/VLOOKUP(Assumptions!$D$7, Lists!$B$7:$C$10, 2, FALSE) -> -6250000 | O21: =-Assumptions!$D$58/4/VLOOKUP(Assumptions!$D$7, Lists!$B$7:$C$10, 2, FALSE) -> -6250000 | P21: =-Assumptions!$D$58/4/VLOOKUP(Assumptions!$D$7, Lists!$B$7:$C$10, 2, FALSE) -> -6250000 | Q21: =-Assumptions!$D$58/4/VLOOKUP(Assumptions!$D$7, Lists!$B$7:$C$10, 2, FALSE) -> -6250000 | R21: =SUM(N21:Q21) -> -25000000 | S21: =-Assumptions!$D$58/4/VLOOKUP(Assumptions!$D$7, Lists!$B$7:$C$10, 2, FALSE) -> -6250000 | T21: =-Assumptions!$D$58/4/VLOOKUP(Assumptions!$D$7, Lists!$B$7:$C$10, 2, FALSE) -> -6250000 | U21: =-Assumptions!$D$58/4/VLOOKUP(Assumptions!$D$7, Lists!$B$7:$C$10, 2, FALSE) -> -6250000 | V21: =-Assumptions!$D$58/4/VLOOKUP(Assumptions!$D$7, Lists!$B$7:$C$10, 2, FALSE) -> -6250000 | W21: =SUM(S21:V21) -> -25000000 | X21: =-Assumptions!$D$58/4/VLOOKUP(Assumptions!$D$7, Lists!$B$7:$C$10, 2, FALSE) -> -6250000 | Y21: =-Assumptions!$D$58/4/VLOOKUP(Assumptions!$D$7, Lists!$B$7:$C$10, 2, FALSE) -> -6250000 | Z21: =-Assumptions!$D$58/4/VLOOKUP(Assumptions!$D$7, Lists!$B$7:$C$10, 2, FALSE) -> -6250000 | AA21: =-Assumptions!$D$58/4/VLOOKUP(Assumptions!$D$7, Lists!$B$7:$C$10, 2, FALSE) -> -6250000 | AB21: =SUM(X21:AA21) -> -25000000 | AC21: =-Assumptions!$D$58/4/VLOOKUP(Assumptions!$D$7, Lists!$B$7:$C$10, 2, FALSE) -> -6250000 | AD21: =-Assumptions!$D$58/4/VLOOKUP(Assumptions!$D$7, Lists!$B$7:$C$10, 2, FALSE) -> -6250000 | AE21: =-Assumptions!$D$58/4/VLOOKUP(Assumptions!$D$7, Lists!$B$7:$C$10, 2, FALSE) -> -6250000 | AF21: =-Assumptions!$D$58/4/VLOOKUP(Assumptions!$D$7, Lists!$B$7:$C$10, 2, FALSE) -> -6250000 | AG21: =SUM(AC21:AF21) -> -25000000 | AH21: =-Assumptions!$D$58/4/VLOOKUP(Assumptions!$D$7, Lists!$B$7:$C$10, 2, FALSE) -> -6250000 | AI21: =-Assumptions!$D$58/4/VLOOKUP(Assumptions!$D$7, Lists!$B$7:$C$10, 2, FALSE) -> -6250000 | AJ21: =-Assumptions!$D$58/4/VLOOKUP(Assumptions!$D$7, Lists!$B$7:$C$10, 2, FALSE) -> -6250000 | AK21: =-Assumptions!$D$58/4/VLOOKUP(Assumptions!$D$7, Lists!$B$7:$C$10, 2, FALSE) -> -6250000 | AL21: =SUM(AH21:AK21) -> -25000000
C22: Net income from non-financial services | D22: =D20+D21 -> -3750000 | E22: =E20+E21 -> -3750000 | F22: =F20+F21 -> -3750000 | G22: =G20+G21 -> -3750000 | H22: =SUM(D22:G22) -> -15000000 | I22: =I20+I21 -> -3750000 | J22: =J20+J21 -> -3750000 | K22: =K20+K21 -> -3750000 | L22: =L20+L21 -> -3750000 | M22: =SUM(I22:L22) -> -15000000 | N22: =N20+N21 -> -3750000 | O22: =O20+O21 -> -3750000 | P22: =P20+P21 -> -3750000 | Q22: =Q20+Q21 -> -3750000 | R22: =SUM(N22:Q22) -> -15000000 | S22: =S20+S21 -> -3750000 | T22: =T20+T21 -> -3750000 | U22: =U20+U21 -> -3750000 | V22: =V20+V21 -> -3750000 | W22: =SUM(S22:V22) -> -15000000 | X22: =X20+X21 -> -3750000 | Y22: =Y20+Y21 -> -3750000 | Z22: =Z20+Z21 -> -3750000 | AA22: =AA20+AA21 -> -3750000 | AB22: =SUM(X22:AA22) -> -15000000 | AC22: =AC20+AC21 -> -3750000 | AD22: =AD20+AD21 -> -3750000 | AE22: =AE20+AE21 -> -3750000 | AF22: =AF20+AF21 -> -3750000 | AG22: =SUM(AC22:AF22) -> -15000000 | AH22: =AH20+AH21 -> -3750000 | AI22: =AI20+AI21 -> -3750000 | AJ22: =AJ20+AJ21 -> -3750000 | AK22: =AK20+AK21 -> -3750000 | AL22: =SUM(AH22:AK22) -> -15000000
B23: Non-banking income | D23: =D19+D22 -> 1988906.2 | E23: =E19+E22 -> 7655625 | F23: =F19+F22 -> 13250156 | G23: =G19+G22 -> 18772500 | H23: =SUM(D23:G23) -> 41667188 | I23: =I19+I22 -> 24222656 | J23: =J19+J22 -> 29600625 | K23: =K19+K22 -> 34906406 | L23: =L19+L22 -> 40140000 | M23: =SUM(I23:L23) -> 1.2886969e+08 | N23: =N19+N22 -> 45301406 | O23: =O19+O22 -> 50390625 | P23: =P19+P22 -> 55407656 | Q23: =Q19+Q22 -> 60352500 | R23: =SUM(N23:Q23) -> 2.1145219e+08 | S23: =S19+S22 -> 65225156 | T23: =T19+T22 -> 70025625 | U23: =U19+U22 -> 74753906 | V23: =V19+V22 -> 79410000 | W23: =SUM(S23:V23) -> 2.8941469e+08 | X23: =X19+X22 -> 83993906 | Y23: =Y19+Y22 -> 88505625 | Z23: =Z19+Z22 -> 92945156 | AA23: =AA19+AA22 -> 97312500 | AB23: =SUM(X23:AA23) -> 3.6275719e+08 | AC23: =AC19+AC22 -> 96590625 | AD23: =AD19+AD22 -> 95868750 | AE23: =AE19+AE22 -> 95146875 | AF23: =AF19+AF22 -> 94425000 | AG23: =SUM(AC23:AF23) -> 382031250 | AH23: =AH19+AH22 -> 93703125 | AI23: =AI19+AI22 -> 92981250 | AJ23: =AJ19+AJ22 -> 92259375 | AK23: =AK19+AK22 -> 91537500 | AL23: =SUM(AH23:AK23) -> 370481250
A24: NON-BANKING INCOME | D24: =D23 -> 1988906.2 | E24: =E23 -> 7655625 | F24: =F23 -> 13250156 | G24: =G23 -> 18772500 | H24: =SUM(D24:G24) -> 41667188 | I24: =I23 -> 24222656 | J24: =J23 -> 29600625 | K24: =K23 -> 34906406 | L24: =L23 -> 40140000 | M24: =SUM(I24:L24) -> 1.2886969e+08 | N24: =N23 -> 45301406 | O24: =O23 -> 50390625 | P24: =P23 -> 55407656 | Q24: =Q23 -> 60352500 | R24: =SUM(N24:Q24) -> 2.1145219e+08 | S24: =S23 -> 65225156 | T24: =T23 -> 70025625 | U24: =U23 -> 74753906 | V24: =V23 -> 79410000 | W24: =SUM(S24:V24) -> 2.8941469e+08 | X24: =X23 -> 83993906 | Y24: =Y23 -> 88505625 | Z24: =Z23 -> 92945156 | AA24: =AA23 -> 97312500 | AB24: =SUM(X24:AA24) -> 3.6275719e+08 | AC24: =AC23 -> 96590625 | AD24: =AD23 -> 95868750 | AE24: =AE23 -> 95146875 | AF24: =AF23 -> 94425000 | AG24: =SUM(AC24:AF24) -> 382031250 | AH24: =AH23 -> 93703125 | AI24: =AI23 -> 92981250 | AJ24: =AJ23 -> 92259375 | AK24: =AK23 -> 91537500 | AL24: =SUM(AH24:AK24) -> 370481250
A25: TOTAL INCOME BEFORE CREDIT IMPAIRMENT CHARGE | D25: =D24+D18+D12 -> 51733050 | E25: =E24+E18+E12 -> 81470731 | F25: =F24+F18+F12 -> 110825575 | G25: =G24+G18+G12 -> 1.3979758e+08 | H25: =SUM(D25:G25) -> 3.8382694e+08 | I25: =I24+I18+I12 -> 168386750 | J25: =J24+J18+J12 -> 1.9659308e+08 | K25: =K24+K18+K12 -> 224416575 | L25: =L24+L18+L12 -> 2.5185723e+08 | M25: =SUM(I25:L25) -> 8.4125364e+08 | N25: =N24+N18+N12 -> 278915050 | O25: =O24+O18+O12 -> 3.0559003e+08 | P25: =P24+P18+P12 -> 331882175 | Q25: =Q24+Q18+Q12 -> 3.5779148e+08 | R25: =SUM(N25:Q25) -> 1.2741787e+09 | S25: =S24+S18+S12 -> 383317950 | T25: =T24+T18+T12 -> 4.0846158e+08 | U25: =U24+U18+U12 -> 433222375 | V25: =V24+V18+V12 -> 4.5760033e+08 | W25: =SUM(S25:V25) -> 1.6826022e+09 | X25: =X24+X18+X12 -> 481595450 | Y25: =Y24+Y18+Y12 -> 5.0520773e+08 | Z25: =Z24+Z18+Z12 -> 528437175 | AA25: =AA24+AA18+AA12 -> 5.5128378e+08 | AB25: =SUM(X25:AA25) -> 2.0665241e+09 | AC25: =AC24+AC18+AC12 -> 525243500 | AD25: =AD24+AD18+AD12 -> 521415125 | AE25: =AE24+AE18+AE12 -> 517586750 | AF25: =AF24+AF18+AF12 -> 513758375 | AG25: =SUM(AC25:AF25) -> 2078003750 | AH25: =AH24+AH18+AH12 -> 509930000 | AI25: =AI24+AI18+AI12 -> 506101625 | AJ25: =AJ24+AJ18+AJ12 -> 502273250 | AK25: =AK24+AK18+AK12 -> 498444875 | AL25: =SUM(AH25:AK25) -> 2016749750
C26: Charges for credit losses | D26: =(D76+D77+D78)*-Assumptions!$D$34/4 -> -6261867.2 | E26: =(E76+E77+E78)*-Assumptions!$D$34/4 -> -12444969 | F26: =(F76+F77+F78)*-Assumptions!$D$34/4 -> -18549305 | G26: =(G76+G77+G78)*-Assumptions!$D$34/4 -> -24574875 | H26: =SUM(D26:G26) -> -61831016 | I26: =(I76+I77+I78)*-Assumptions!$D$34/4 -> -30521680 | J26: =(J76+J77+J78)*-Assumptions!$D$34/4 -> -36389719 | K26: =(K76+K77+K78)*-Assumptions!$D$34/4 -> -42178992 | L26: =(L76+L77+L78)*-Assumptions!$D$34/4 -> -47889500 | M26: =SUM(I26:L26) -> -1.5697989e+08 | N26: =(N76+N77+N78)*-Assumptions!$D$34/4 -> -53521242 | O26: =(O76+O77+O78)*-Assumptions!$D$34/4 -> -59074219 | P26: =(P76+P77+P78)*-Assumptions!$D$34/4 -> -64548430 | Q26: =(Q76+Q77+Q78)*-Assumptions!$D$34/4 -> -69943875 | R26: =SUM(N26:Q26) -> -2.4708777e+08 | S26: =(S76+S77+S78)*-Assumptions!$D$34/4 -> -75260555 | T26: =(T76+T77+T78)*-Assumptions!$D$34/4 -> -80498469 | U26: =(U76+U77+U78)*-Assumptions!$D$34/4 -> -85657617 | V26: =(V76+V77+V78)*-Assumptions!$D$34/4 -> -90738000 | W26: =SUM(S26:V26) -> -3.3215464e+08 | X26: =(X76+X77+X78)*-Assumptions!$D$34/4 -> -95739617 | Y26: =(Y76+Y77+Y78)*-Assumptions!$D$34/4 -> -1.0066247e+08 | Z26: =(Z76+Z77+Z78)*-Assumptions!$D$34/4 -> -1.0550655e+08 | AA26: =(AA76+AA77+AA78)*-Assumptions!$D$34/4 -> -110271875 | AB26: =SUM(X26:AA26) -> -4.1218052e+08 | AC26: =(AC76+AC77+AC78)*-Assumptions!$D$34/4 -> -1.0948422e+08 | AD26: =(AD76+AD77+AD78)*-Assumptions!$D$34/4 -> -1.0869656e+08 | AE26: =(AE76+AE77+AE78)*-Assumptions!$D$34/4 -> -1.0790891e+08 | AF26: =(AF76+AF77+AF78)*-Assumptions!$D$34/4 -> -107121250 | AG26: =SUM(AC26:AF26) -> -4.3321094e+08 | AH26: =(AH76+AH77+AH78)*-Assumptions!$D$34/4 -> -1.0633359e+08 | AI26: =(AI76+AI77+AI78)*-Assumptions!$D$34/4 -> -1.0554594e+08 | AJ26: =(AJ76+AJ77+AJ78)*-Assumptions!$D$34/4 -> -1.0475828e+08 | AK26: =(AK76+AK77+AK78)*-Assumptions!$D$34/4 -> -103970625 | AL26: =SUM(AH26:AK26) -> -4.2060844e+08
B27: Charges for credit losses | D27: =D26 -> -6261867.2 | E27: =E26 -> -12444969 | F27: =F26 -> -18549305 | G27: =G26 -> -24574875 | H27: =SUM(D27:G27) -> -61831016 | I27: =I26 -> -30521680 | J27: =J26 -> -36389719 | K27: =K26 -> -42178992 | L27: =L26 -> -47889500 | M27: =SUM(I27:L27) -> -1.5697989e+08 | N27: =N26 -> -53521242 | O27: =O26 -> -59074219 | P27: =P26 -> -64548430 | Q27: =Q26 -> -69943875 | R27: =SUM(N27:Q27) -> -2.4708777e+08 | S27: =S26 -> -75260555 | T27: =T26 -> -80498469 | U27: =U26 -> -85657617 | V27: =V26 -> -90738000 | W27: =SUM(S27:V27) -> -3.3215464e+08 | X27: =X26 -> -95739617 | Y27: =Y26 -> -1.0066247e+08 | Z27: =Z26 -> -1.0550655e+08 | AA27: =AA26 -> -110271875 | AB27: =SUM(X27:AA27) -> -4.1218052e+08 | AC27: =AC26 -> -1.0948422e+08 | AD27: =AD26 -> -1.0869656e+08 | AE27: =AE26 -> -1.0790891e+08 | AF27: =AF26 -> -107121250 | AG27: =SUM(AC27:AF27) -> -4.3321094e+08 | AH27: =AH26 -> -1.0633359e+08 | AI27: =AI26 -> -1.0554594e+08 | AJ27: =AJ26 -> -1.0475828e+08 | AK27: =AK26 -> -103970625 | AL27: =SUM(AH27:AK27) -> -4.2060844e+08
A28: TOTAL INCOME AFTER CREDIT IMPAIRMENT CHARGE | D28: =D25-D27 -> 57994917 | E28: =E25-E27 -> 93915700 | F28: =F25-F27 -> 1.2937488e+08 | G28: =G25-G27 -> 1.6437246e+08 | H28: =SUM(D28:G28) -> 4.4565795e+08 | I28: =I25-I27 -> 1.9890843e+08 | J28: =J25-J27 -> 232982800 | K28: =K25-K27 -> 2.6659557e+08 | L28: =L25-L27 -> 2.9974673e+08 | M28: =SUM(I28:L28) -> 9.9823353e+08 | N28: =N25-N27 -> 3.3243629e+08 | O28: =O25-O27 -> 364664250 | P28: =P25-P27 -> 3.964306e+08 | Q28: =Q25-Q27 -> 4.2773536e+08 | R28: =SUM(N28:Q28) -> 1.5212665e+09 | S28: =S25-S27 -> 4.585785e+08 | T28: =T25-T27 -> 488960050 | U28: =U25-U27 -> 5.1887999e+08 | V28: =V25-V27 -> 5.4833833e+08 | W28: =SUM(S28:V28) -> 2.0147569e+09 | X28: =X25-X27 -> 5.7733507e+08 | Y28: =Y25-Y27 -> 605870200 | Z28: =Z25-Z27 -> 6.3394373e+08 | AA28: =AA25-AA27 -> 6.6155566e+08 | AB28: =SUM(X28:AA28) -> 2.4787047e+09 | AC28: =AC25-AC27 -> 6.3472772e+08 | AD28: =AD25-AD27 -> 6.3011169e+08 | AE28: =AE25-AE27 -> 6.2549566e+08 | AF28: =AF25-AF27 -> 620879625 | AG28: =SUM(AC28:AF28) -> 2.5112147e+09 | AH28: =AH25-AH27 -> 6.1626359e+08 | AI28: =AI25-AI27 -> 6.1164756e+08 | AJ28: =AJ25-AJ27 -> 6.0703153e+08 | AK28: =AK25-AK27 -> 602415500 | AL28: =SUM(AH28:AK28) -> 2.4373582e+09
C29: Employee compensation (clerks) | D29: =D87*-Assumptions!$D$69/4/VLOOKUP(Assumptions!$D$7, Lists!$B$7:$C$10, 2, FALSE) -> -2250000 | E29: =E87*-Assumptions!$D$69/4/VLOOKUP(Assumptions!$D$7, Lists!$B$7:$C$10, 2, FALSE) -> -4500000 | F29: =F87*-Assumptions!$D$69/4/VLOOKUP(Assumptions!$D$7, Lists!$B$7:$C$10, 2, FALSE) -> -6750000 | G29: =G87*-Assumptions!$D$69/4/VLOOKUP(Assumptions!$D$7, Lists!$B$7:$C$10, 2, FALSE) -> -8625000 | H29: =SUM(D29:G29) -> -22125000 | I29: =I87*-Assumptions!$D$69/4/VLOOKUP(Assumptions!$D$7, Lists!$B$7:$C$10, 2, FALSE) -> -10500000 | J29: =J87*-Assumptions!$D$69/4/VLOOKUP(Assumptions!$D$7, Lists!$B$7:$C$10, 2, FALSE) -> -12750000 | K29: =K87*-Assumptions!$D$69/4/VLOOKUP(Assumptions!$D$7, Lists!$B$7:$C$10, 2, FALSE) -> -14625000 | L29: =L87*-Assumptions!$D$69/4/VLOOKUP(Assumptions!$D$7, Lists!$B$7:$C$10, 2, FALSE) -> -16500000 | M29: =SUM(I29:L29) -> -54375000 | N29: =N87*-Assumptions!$D$69/4/VLOOKUP(Assumptions!$D$7, Lists!$B$7:$C$10, 2, FALSE) -> -18750000 | O29: =O87*-Assumptions!$D$69/4/VLOOKUP(Assumptions!$D$7, Lists!$B$7:$C$10, 2, FALSE) -> -20625000 | P29: =P87*-Assumptions!$D$69/4/VLOOKUP(Assumptions!$D$7, Lists!$B$7:$C$10, 2, FALSE) -> -22500000 | Q29: =Q87*-Assumptions!$D$69/4/VLOOKUP(Assumptions!$D$7, Lists!$B$7:$C$10, 2, FALSE) -> -24375000 | R29: =SUM(N29:Q29) -> -86250000 | S29: =S87*-Assumptions!$D$69/4/VLOOKUP(Assumptions!$D$7, Lists!$B$7:$C$10, 2, FALSE) -> -25875000 | T29: =T87*-Assumptions!$D$69/4/VLOOKUP(Assumptions!$D$7, Lists!$B$7:$C$10, 2, FALSE) -> -27750000 | U29: =U87*-Assumptions!$D$69/4/VLOOKUP(Assumptions!$D$7, Lists!$B$7:$C$10, 2, FALSE) -> -29625000 | V29: =V87*-Assumptions!$D$69/4/VLOOKUP(Assumptions!$D$7, Lists!$B$7:$C$10, 2, FALSE) -> -31500000 | W29: =SUM(S29:V29) -> -114750000 | X29: =X87*-Assumptions!$D$69/4/VLOOKUP(Assumptions!$D$7, Lists!$B$7:$C$10, 2, FALSE) -> -33000000 | Y29: =Y87*-Assumptions!$D$69/4/VLOOKUP(Assumptions!$D$7, Lists!$B$7:$C$10, 2, FALSE) -> -34875000 | Z29: =Z87*-Assumptions!$D$69/4/VLOOKUP(Assumptions!$D$7, Lists!$B$7:$C$10, 2, FALSE) -> -36375000 | AA29: =AA87*-Assumptions!$D$69/4/VLOOKUP(Assumptions!$D$7, Lists!$B$7:$C$10, 2, FALSE) -> -38250000 | AB29: =SUM(X29:AA29) -> -142500000 | AC29: =AC87*-Assumptions!$D$69/4/VLOOKUP(Assumptions!$D$7, Lists!$B$7:$C$10, 2, FALSE) -> -37875000 | AD29: =AD87*-Assumptions!$D$69/4/VLOOKUP(Assumptions!$D$7, Lists!$B$7:$C$10, 2, FALSE) -> -37500000 | AE29: =AE87*-Assumptions!$D$69/4/VLOOKUP(Assumptions!$D$7, Lists!$B$7:$C$10, 2, FALSE) -> -37125000 | AF29: =AF87*-Assumptions!$D$69/4/VLOOKUP(Assumptions!$D$7, Lists!$B$7:$C$10, 2, FALSE) -> -37125000 | AG29: =SUM(AC29:AF29) -> -149625000 | AH29: =AH87*-Assumptions!$D$69/4/VLOOKUP(Assumptions!$D$7, Lists!$B$7:$C$10, 2, FALSE) -> -36750000 | AI29: =AI87*-Assumptions!$D$69/4/VLOOKUP(Assumptions!$D$7, Lists!$B$7:$C$10, 2, FALSE) -> -36375000 | AJ29: =AJ87*-Assumptions!$D$69/4/VLOOKUP(Assumptions!$D$7, Lists!$B$7:$C$10, 2, FALSE) -> -36375000 | AK29: =AK87*-Assumptions!$D$69/4/VLOOKUP(Assumptions!$D$7, Lists!$B$7:$C$10, 2, FALSE) -> -36000000 | AL29: =SUM(AH29:AK29) -> -145500000
C30: Employee compensation (IT and support) | D30: =D88*-Assumptions!$D$70/4/VLOOKUP(Assumptions!$D$7, Lists!$B$7:$C$10, 2, FALSE) -> -1500000 | E30: =E88*-Assumptions!$D$70/4/VLOOKUP(Assumptions!$D$7, Lists!$B$7:$C$10, 2, FALSE) -> -2500000 | F30: =F88*-Assumptions!$D$70/4/VLOOKUP(Assumptions!$D$7, Lists!$B$7:$C$10, 2, FALSE) -> -3500000 | G30: =G88*-Assumptions!$D$70/4/VLOOKUP(Assumptions!$D$7, Lists!$B$7:$C$10, 2, FALSE) -> -5000000 | H30: =SUM(D30:G30) -> -12500000 | I30: =I88*-Assumptions!$D$70/4/VLOOKUP(Assumptions!$D$7, Lists!$B$7:$C$10, 2, FALSE) -> -6000000 | J30: =J88*-Assumptions!$D$70/4/VLOOKUP(Assumptions!$D$7, Lists!$B$7:$C$10, 2, FALSE) -> -7000000 | K30: =K88*-Assumptions!$D$70/4/VLOOKUP(Assumptions!$D$7, Lists!$B$7:$C$10, 2, FALSE) -> -8000000 | L30: =L88*-Assumptions!$D$70/4/VLOOKUP(Assumptions!$D$7, Lists!$B$7:$C$10, 2, FALSE) -> -9000000 | M30: =SUM(I30:L30) -> -30000000 | N30: =N88*-Assumptions!$D$70/4/VLOOKUP(Assumptions!$D$7, Lists!$B$7:$C$10, 2, FALSE) -> -10000000 | O30: =O88*-Assumptions!$D$70/4/VLOOKUP(Assumptions!$D$7, Lists!$B$7:$C$10, 2, FALSE) -> -11000000 | P30: =P88*-Assumptions!$D$70/4/VLOOKUP(Assumptions!$D$7, Lists!$B$7:$C$10, 2, FALSE) -> -12000000 | Q30: =Q88*-Assumptions!$D$70/4/VLOOKUP(Assumptions!$D$7, Lists!$B$7:$C$10, 2, FALSE) -> -13000000 | R30: =SUM(N30:Q30) -> -46000000 | S30: =S88*-Assumptions!$D$70/4/VLOOKUP(Assumptions!$D$7, Lists!$B$7:$C$10, 2, FALSE) -> -14000000 | T30: =T88*-Assumptions!$D$70/4/VLOOKUP(Assumptions!$D$7, Lists!$B$7:$C$10, 2, FALSE) -> -15000000 | U30: =U88*-Assumptions!$D$70/4/VLOOKUP(Assumptions!$D$7, Lists!$B$7:$C$10, 2, FALSE) -> -16000000 | V30: =V88*-Assumptions!$D$70/4/VLOOKUP(Assumptions!$D$7, Lists!$B$7:$C$10, 2, FALSE) -> -17000000 | W30: =SUM(S30:V30) -> -62000000 | X30: =X88*-Assumptions!$D$70/4/VLOOKUP(Assumptions!$D$7, Lists!$B$7:$C$10, 2, FALSE) -> -18000000 | Y30: =Y88*-Assumptions!$D$70/4/VLOOKUP(Assumptions!$D$7, Lists!$B$7:$C$10, 2, FALSE) -> -18500000 | Z30: =Z88*-Assumptions!$D$70/4/VLOOKUP(Assumptions!$D$7, Lists!$B$7:$C$10, 2, FALSE) -> -19500000 | AA30: =AA88*-Assumptions!$D$70/4/VLOOKUP(Assumptions!$D$7, Lists!$B$7:$C$10, 2, FALSE) -> -20500000 | AB30: =SUM(X30:AA30) -> -76500000 | AC30: =AC88*-Assumptions!$D$70/4/VLOOKUP(Assumptions!$D$7, Lists!$B$7:$C$10, 2, FALSE) -> -20500000 | AD30: =AD88*-Assumptions!$D$70/4/VLOOKUP(Assumptions!$D$7, Lists!$B$7:$C$10, 2, FALSE) -> -20000000 | AE30: =AE88*-Assumptions!$D$70/4/VLOOKUP(Assumptions!$D$7, Lists!$B$7:$C$10, 2, FALSE) -> -20000000 | AF30: =AF88*-Assumptions!$D$70/4/VLOOKUP(Assumptions!$D$7, Lists!$B$7:$C$10, 2, FALSE) -> -20000000 | AG30: =SUM(AC30:AF30) -> -80500000 | AH30: =AH88*-Assumptions!$D$70/4/VLOOKUP(Assumptions!$D$7, Lists!$B$7:$C$10, 2, FALSE) -> -19500000 | AI30: =AI88*-Assumptions!$D$70/4/VLOOKUP(Assumptions!$D$7, Lists!$B$7:$C$10, 2, FALSE) -> -19500000 | AJ30: =AJ88*-Assumptions!$D$70/4/VLOOKUP(Assumptions!$D$7, Lists!$B$7:$C$10, 2, FALSE) -> -19500000 | AK30: =AK88*-Assumptions!$D$70/4/VLOOKUP(Assumptions!$D$7, Lists!$B$7:$C$10, 2, FALSE) -> -19500000 | AL30: =SUM(AH30:AK30) -> -78000000
C31: Employee compensation (loan officers) | D31: =D89*-Assumptions!$D$71/4/VLOOKUP(Assumptions!$D$7, Lists!$B$7:$C$10, 2, FALSE) -> -1000000 | E31: =E89*-Assumptions!$D$71/4/VLOOKUP(Assumptions!$D$7, Lists!$B$7:$C$10, 2, FALSE) -> -1500000 | F31: =F89*-Assumptions!$D$71/4/VLOOKUP(Assumptions!$D$7, Lists!$B$7:$C$10, 2, FALSE) -> -2000000 | G31: =G89*-Assumptions!$D$71/4/VLOOKUP(Assumptions!$D$7, Lists!$B$7:$C$10, 2, FALSE) -> -2500000 | H31: =SUM(D31:G31) -> -7000000 | I31: =I89*-Assumptions!$D$71/4/VLOOKUP(Assumptions!$D$7, Lists!$B$7:$C$10, 2, FALSE) -> -3500000 | J31: =J89*-Assumptions!$D$71/4/VLOOKUP(Assumptions!$D$7, Lists!$B$7:$C$10, 2, FALSE) -> -4000000 | K31: =K89*-Assumptions!$D$71/4/VLOOKUP(Assumptions!$D$7, Lists!$B$7:$C$10, 2, FALSE) -> -4500000 | L31: =L89*-Assumptions!$D$71/4/VLOOKUP(Assumptions!$D$7, Lists!$B$7:$C$10, 2, FALSE) -> -5000000 | M31: =SUM(I31:L31) -> -17000000 | N31: =N89*-Assumptions!$D$71/4/VLOOKUP(Assumptions!$D$7, Lists!$B$7:$C$10, 2, FALSE) -> -5500000 | O31: =O89*-Assumptions!$D$71/4/VLOOKUP(Assumptions!$D$7, Lists!$B$7:$C$10, 2, FALSE) -> -6000000 | P31: =P89*-Assumptions!$D$71/4/VLOOKUP(Assumptions!$D$7, Lists!$B$7:$C$10, 2, FALSE) -> -7000000 | Q31: =Q89*-Assumptions!$D$71/4/VLOOKUP(Assumptions!$D$7, Lists!$B$7:$C$10, 2, FALSE) -> -7500000 | R31: =SUM(N31:Q31) -> -26000000 | S31: =S89*-Assumptions!$D$71/4/VLOOKUP(Assumptions!$D$7, Lists!$B$7:$C$10, 2, FALSE) -> -8000000 | T31: =T89*-Assumptions!$D$71/4/VLOOKUP(Assumptions!$D$7, Lists!$B$7:$C$10, 2, FALSE) -> -8500000 | U31: =U89*-Assumptions!$D$71/4/VLOOKUP(Assumptions!$D$7, Lists!$B$7:$C$10, 2, FALSE) -> -9000000 | V31: =V89*-Assumptions!$D$71/4/VLOOKUP(Assumptions!$D$7, Lists!$B$7:$C$10, 2, FALSE) -> -9500000 | W31: =SUM(S31:V31) -> -35000000 | X31: =X89*-Assumptions!$D$71/4/VLOOKUP(Assumptions!$D$7, Lists!$B$7:$C$10, 2, FALSE) -> -10000000 | Y31: =Y89*-Assumptions!$D$71/4/VLOOKUP(Assumptions!$D$7, Lists!$B$7:$C$10, 2, FALSE) -> -10500000 | Z31: =Z89*-Assumptions!$D$71/4/VLOOKUP(Assumptions!$D$7, Lists!$B$7:$C$10, 2, FALSE) -> -11000000 | AA31: =AA89*-Assumptions!$D$71/4/VLOOKUP(Assumptions!$D$7, Lists!$B$7:$C$10, 2, FALSE) -> -11500000 | AB31: =SUM(X31:AA31) -> -43000000 | AC31: =AC89*-Assumptions!$D$71/4/VLOOKUP(Assumptions!$D$7, Lists!$B$7:$C$10, 2, FALSE) -> -11500000 | AD31: =AD89*-Assumptions!$D$71/4/VLOOKUP(Assumptions!$D$7, Lists!$B$7:$C$10, 2, FALSE) -> -11000000 | AE31: =AE89*-Assumptions!$D$71/4/VLOOKUP(Assumptions!$D$7, Lists!$B$7:$C$10, 2, FALSE) -> -11000000 | AF31: =AF89*-Assumptions!$D$71/4/VLOOKUP(Assumptions!$D$7, Lists!$B$7:$C$10, 2, FALSE) -> -11000000 | AG31: =SUM(AC31:AF31) -> -44500000 | AH31: =AH89*-Assumptions!$D$71/4/VLOOKUP(Assumptions!$D$7, Lists!$B$7:$C$10, 2, FALSE) -> -11000000 | AI31: =AI89*-Assumptions!$D$71/4/VLOOKUP(Assumptions!$D$7, Lists!$B$7:$C$10, 2, FALSE) -> -11000000 | AJ31: =AJ89*-Assumptions!$D$71/4/VLOOKUP(Assumptions!$D$7, Lists!$B$7:$C$10, 2, FALSE) -> -11000000 | AK31: =AK89*-Assumptions!$D$71/4/VLOOKUP(Assumptions!$D$7, Lists!$B$7:$C$10, 2, FALSE) -> -10500000 | AL31: =SUM(AH31:AK31) -> -43500000
C32: Employee compensation (management) | D32: =D90*-Assumptions!$D$72/4/VLOOKUP(Assumptions!$D$7, Lists!$B$7:$C$10, 2, FALSE) -> -3000000 | E32: =E90*-Assumptions!$D$72/4/VLOOKUP(Assumptions!$D$7, Lists!$B$7:$C$10, 2, FALSE) -> -5000000 | F32: =F90*-Assumptions!$D$72/4/VLOOKUP(Assumptions!$D$7, Lists!$B$7:$C$10, 2, FALSE) -> -7000000 | G32: =G90*-Assumptions!$D$72/4/VLOOKUP(Assumptions!$D$7, Lists!$B$7:$C$10, 2, FALSE) -> -10000000 | H32: =SUM(D32:G32) -> -25000000 | I32: =I90*-Assumptions!$D$72/4/VLOOKUP(Assumptions!$D$7, Lists!$B$7:$C$10, 2, FALSE) -> -12000000 | J32: =J90*-Assumptions!$D$72/4/VLOOKUP(Assumptions!$D$7, Lists!$B$7:$C$10, 2, FALSE) -> -14000000 | K32: =K90*-Assumptions!$D$72/4/VLOOKUP(Assumptions!$D$7, Lists!$B$7:$C$10, 2, FALSE) -> -16000000 | L32: =L90*-Assumptions!$D$72/4/VLOOKUP(Assumptions!$D$7, Lists!$B$7:$C$10, 2, FALSE) -> -18000000 | M32: =SUM(I32:L32) -> -60000000 | N32: =N90*-Assumptions!$D$72/4/VLOOKUP(Assumptions!$D$7, Lists!$B$7:$C$10, 2, FALSE) -> -20000000 | O32: =O90*-Assumptions!$D$72/4/VLOOKUP(Assumptions!$D$7, Lists!$B$7:$C$10, 2, FALSE) -> -22000000 | P32: =P90*-Assumptions!$D$72/4/VLOOKUP(Assumptions!$D$7, Lists!$B$7:$C$10, 2, FALSE) -> -24000000 | Q32: =Q90*-Assumptions!$D$72/4/VLOOKUP(Assumptions!$D$7, Lists!$B$7:$C$10, 2, FALSE) -> -26000000 | R32: =SUM(N32:Q32) -> -92000000 | S32: =S90*-Assumptions!$D$72/4/VLOOKUP(Assumptions!$D$7, Lists!$B$7:$C$10, 2, FALSE) -> -28000000 | T32: =T90*-Assumptions!$D$72/4/VLOOKUP(Assumptions!$D$7, Lists!$B$7:$C$10, 2, FALSE) -> -30000000 | U32: =U90*-Assumptions!$D$72/4/VLOOKUP(Assumptions!$D$7, Lists!$B$7:$C$10, 2, FALSE) -> -32000000 | V32: =V90*-Assumptions!$D$72/4/VLOOKUP(Assumptions!$D$7, Lists!$B$7:$C$10, 2, FALSE) -> -34000000 | W32: =SUM(S32:V32) -> -124000000 | X32: =X90*-Assumptions!$D$72/4/VLOOKUP(Assumptions!$D$7, Lists!$B$7:$C$10, 2, FALSE) -> -36000000 | Y32: =Y90*-Assumptions!$D$72/4/VLOOKUP(Assumptions!$D$7, Lists!$B$7:$C$10, 2, FALSE) -> -37000000 | Z32: =Z90*-Assumptions!$D$72/4/VLOOKUP(Assumptions!$D$7, Lists!$B$7:$C$10, 2, FALSE) -> -39000000 | AA32: =AA90*-Assumptions!$D$72/4/VLOOKUP(Assumptions!$D$7, Lists!$B$7:$C$10, 2, FALSE) -> -41000000 | AB32: =SUM(X32:AA32) -> -153000000 | AC32: =AC90*-Assumptions!$D$72/4/VLOOKUP(Assumptions!$D$7, Lists!$B$7:$C$10, 2, FALSE) -> -41000000 | AD32: =AD90*-Assumptions!$D$72/4/VLOOKUP(Assumptions!$D$7, Lists!$B$7:$C$10, 2, FALSE) -> -40000000 | AE32: =AE90*-Assumptions!$D$72/4/VLOOKUP(Assumptions!$D$7, Lists!$B$7:$C$10, 2, FALSE) -> -40000000 | AF32: =AF90*-Assumptions!$D$72/4/VLOOKUP(Assumptions!$D$7, Lists!$B$7:$C$10, 2, FALSE) -> -40000000 | AG32: =SUM(AC32:AF32) -> -161000000 | AH32: =AH90*-Assumptions!$D$72/4/VLOOKUP(Assumptions!$D$7, Lists!$B$7:$C$10, 2, FALSE) -> -39000000 | AI32: =AI90*-Assumptions!$D$72/4/VLOOKUP(Assumptions!$D$7, Lists!$B$7:$C$10, 2, FALSE) -> -39000000 | AJ32: =AJ90*-Assumptions!$D$72/4/VLOOKUP(Assumptions!$D$7, Lists!$B$7:$C$10, 2, FALSE) -> -39000000 | AK32: =AK90*-Assumptions!$D$72/4/VLOOKUP(Assumptions!$D$7, Lists!$B$7:$C$10, 2, FALSE) -> -39000000 | AL32: =SUM(AH32:AK32) -> -156000000
B33: Employee compensation | D33: =SUM(D29:D32) -> -7750000 | E33: =SUM(E29:E32) -> -13500000 | F33: =SUM(F29:F32) -> -19250000 | G33: =SUM(G29:G32) -> -26125000 | H33: =SUM(D33:G33) -> -66625000 | I33: =SUM(I29:I32) -> -32000000 | J33: =SUM(J29:J32) -> -37750000 | K33: =SUM(K29:K32) -> -43125000 | L33: =SUM(L29:L32) -> -48500000 | M33: =SUM(I33:L33) -> -161375000 | N33: =SUM(N29:N32) -> -54250000 | O33: =SUM(O29:O32) -> -59625000 | P33: =SUM(P29:P32) -> -65500000 | Q33: =SUM(Q29:Q32) -> -70875000 | R33: =SUM(N33:Q33) -> -250250000 | S33: =SUM(S29:S32) -> -75875000 | T33: =SUM(T29:T32) -> -81250000 | U33: =SUM(U29:U32) -> -86625000 | V33: =SUM(V29:V32) -> -92000000 | W33: =SUM(S33:V33) -> -335750000 | X33: =SUM(X29:X32) -> -97000000 | Y33: =SUM(Y29:Y32) -> -100875000 | Z33: =SUM(Z29:Z32) -> -105875000 | AA33: =SUM(AA29:AA32) -> -111250000 | AB33: =SUM(X33:AA33) -> -415000000 | AC33: =SUM(AC29:AC32) -> -110875000 | AD33: =SUM(AD29:AD32) -> -108500000 | AE33: =SUM(AE29:AE32) -> -108125000 | AF33: =SUM(AF29:AF32) -> -108125000 | AG33: =SUM(AC33:AF33) -> -435625000 | AH33: =SUM(AH29:AH32) -> -106250000 | AI33: =SUM(AI29:AI32) -> -105875000 | AJ33: =SUM(AJ29:AJ32) -> -105875000 | AK33: =SUM(AK29:AK32) -> -105000000 | AL33: =SUM(AH33:AK33) -> -423000000
C34: Depreciation of workspace equipment | D34: =SUM(D87:D90)*-Assumptions!$D$80/28/VLOOKUP(Assumptions!$D$7, Lists!$B$7:$C$10, 2, FALSE) -> -75000 | E34: =SUM(E87:E90)*-Assumptions!$D$80/28/VLOOKUP(Assumptions!$D$7, Lists!$B$7:$C$10, 2, FALSE) -> -133928.57 | F34: =SUM(F87:F90)*-Assumptions!$D$80/28/VLOOKUP(Assumptions!$D$7, Lists!$B$7:$C$10, 2, FALSE) -> -192857.14 | G34: =SUM(G87:G90)*-Assumptions!$D$80/28/VLOOKUP(Assumptions!$D$7, Lists!$B$7:$C$10, 2, FALSE) -> -257142.86 | H34: =SUM(D34:G34) -> -658928.57 | I34: =SUM(I87:I90)*-Assumptions!$D$80/28/VLOOKUP(Assumptions!$D$7, Lists!$B$7:$C$10, 2, FALSE) -> -316071.43 | J34: =SUM(J87:J90)*-Assumptions!$D$80/28/VLOOKUP(Assumptions!$D$7, Lists!$B$7:$C$10, 2, FALSE) -> -375000 | K34: =SUM(K87:K90)*-Assumptions!$D$80/28/VLOOKUP(Assumptions!$D$7, Lists!$B$7:$C$10, 2, FALSE) -> -428571.43 | L34: =SUM(L87:L90)*-Assumptions!$D$80/28/VLOOKUP(Assumptions!$D$7, Lists!$B$7:$C$10, 2, FALSE) -> -482142.86 | M34: =SUM(I34:L34) -> -1601785.7 | N34: =SUM(N87:N90)*-Assumptions!$D$80/28/VLOOKUP(Assumptions!$D$7, Lists!$B$7:$C$10, 2, FALSE) -> -541071.43 | O34: =SUM(O87:O90)*-Assumptions!$D$80/28/VLOOKUP(Assumptions!$D$7, Lists!$B$7:$C$10, 2, FALSE) -> -594642.86 | P34: =SUM(P87:P90)*-Assumptions!$D$80/28/VLOOKUP(Assumptions!$D$7, Lists!$B$7:$C$10, 2, FALSE) -> -653571.43 | Q34: =SUM(Q87:Q90)*-Assumptions!$D$80/28/VLOOKUP(Assumptions!$D$7, Lists!$B$7:$C$10, 2, FALSE) -> -707142.86 | R34: =SUM(N34:Q34) -> -2496428.6 | S34: =SUM(S87:S90)*-Assumptions!$D$80/28/VLOOKUP(Assumptions!$D$7, Lists!$B$7:$C$10, 2, FALSE) -> -755357.14 | T34: =SUM(T87:T90)*-Assumptions!$D$80/28/VLOOKUP(Assumptions!$D$7, Lists!$B$7:$C$10, 2, FALSE) -> -808928.57 | U34: =SUM(U87:U90)*-Assumptions!$D$80/28/VLOOKUP(Assumptions!$D$7, Lists!$B$7:$C$10, 2, FALSE) -> -862500 | V34: =SUM(V87:V90)*-Assumptions!$D$80/28/VLOOKUP(Assumptions!$D$7, Lists!$B$7:$C$10, 2, FALSE) -> -916071.43 | W34: =SUM(S34:V34) -> -3342857.1 | X34: =SUM(X87:X90)*-Assumptions!$D$80/28/VLOOKUP(Assumptions!$D$7, Lists!$B$7:$C$10, 2, FALSE) -> -964285.71 | Y34: =SUM(Y87:Y90)*-Assumptions!$D$80/28/VLOOKUP(Assumptions!$D$7, Lists!$B$7:$C$10, 2, FALSE) -> -1007142.9 | Z34: =SUM(Z87:Z90)*-Assumptions!$D$80/28/VLOOKUP(Assumptions!$D$7, Lists!$B$7:$C$10, 2, FALSE) -> -1055357.1 | AA34: =SUM(AA87:AA90)*-Assumptions!$D$80/28/VLOOKUP(Assumptions!$D$7, Lists!$B$7:$C$10, 2, FALSE) -> -1108928.6 | AB34: =SUM(X34:AA34) -> -4135714.3 | AC34: =SUM(AC87:AC90)*-Assumptions!$D$80/28/VLOOKUP(Assumptions!$D$7, Lists!$B$7:$C$10, 2, FALSE) -> -1103571.4 | AD34: =SUM(AD87:AD90)*-Assumptions!$D$80/28/VLOOKUP(Assumptions!$D$7, Lists!$B$7:$C$10, 2, FALSE) -> -1082142.9 | AE34: =SUM(AE87:AE90)*-Assumptions!$D$80/28/VLOOKUP(Assumptions!$D$7, Lists!$B$7:$C$10, 2, FALSE) -> -1076785.7 | AF34: =SUM(AF87:AF90)*-Assumptions!$D$80/28/VLOOKUP(Assumptions!$D$7, Lists!$B$7:$C$10, 2, FALSE) -> -1076785.7 | AG34: =SUM(AC34:AF34) -> -4339285.7 | AH34: =SUM(AH87:AH90)*-Assumptions!$D$80/28/VLOOKUP(Assumptions!$D$7, Lists!$B$7:$C$10, 2, FALSE) -> -1060714.3 | AI34: =SUM(AI87:AI90)*-Assumptions!$D$80/28/VLOOKUP(Assumptions!$D$7, Lists!$B$7:$C$10, 2, FALSE) -> -1055357.1 | AJ34: =SUM(AJ87:AJ90)*-Assumptions!$D$80/28/VLOOKUP(Assumptions!$D$7, Lists!$B$7:$C$10, 2, FALSE) -> -1055357.1 | AK34: =SUM(AK87:AK90)*-Assumptions!$D$80/28/VLOOKUP(Assumptions!$D$7, Lists!$B$7:$C$10, 2, FALSE) -> -1044642.9 | AL34: =SUM(AH34:AK34) -> -4216071.4
C35: Depreciation of branch inventory | D35: =D86*-Assumptions!$D$79/28/VLOOKUP(Assumptions!$D$7, Lists!$B$7:$C$10, 2, FALSE) -> -714285.71 | E35: =E86*-Assumptions!$D$79/28/VLOOKUP(Assumptions!$D$7, Lists!$B$7:$C$10, 2, FALSE) -> -1071428.6 | F35: =F86*-Assumptions!$D$79/28/VLOOKUP(Assumptions!$D$7, Lists!$B$7:$C$10, 2, FALSE) -> -1428571.4 | G35: =G86*-Assumptions!$D$79/28/VLOOKUP(Assumptions!$D$7, Lists!$B$7:$C$10, 2, FALSE) -> -1785714.3 | H35: =SUM(D35:G35) -> -5000000 | I35: =I86*-Assumptions!$D$79/28/VLOOKUP(Assumptions!$D$7, Lists!$B$7:$C$10, 2, FALSE) -> -2142857.1 | J35: =J86*-Assumptions!$D$79/28/VLOOKUP(Assumptions!$D$7, Lists!$B$7:$C$10, 2, FALSE) -> -2500000 | K35: =K86*-Assumptions!$D$79/28/VLOOKUP(Assumptions!$D$7, Lists!$B$7:$C$10, 2, FALSE) -> -2857142.9 | L35: =L86*-Assumptions!$D$79/28/VLOOKUP(Assumptions!$D$7, Lists!$B$7:$C$10, 2, FALSE) -> -3214285.7 | M35: =SUM(I35:L35) -> -10714286 | N35: =N86*-Assumptions!$D$79/28/VLOOKUP(Assumptions!$D$7, Lists!$B$7:$C$10, 2, FALSE) -> -3571428.6 | O35: =O86*-Assumptions!$D$79/28/VLOOKUP(Assumptions!$D$7, Lists!$B$7:$C$10, 2, FALSE) -> -3928571.4 | P35: =P86*-Assumptions!$D$79/28/VLOOKUP(Assumptions!$D$7, Lists!$B$7:$C$10, 2, FALSE) -> -4285714.3 | Q35: =Q86*-Assumptions!$D$79/28/VLOOKUP(Assumptions!$D$7, Lists!$B$7:$C$10, 2, FALSE) -> -4642857.1 | R35: =SUM(N35:Q35) -> -16428571 | S35: =S86*-Assumptions!$D$79/28/VLOOKUP(Assumptions!$D$7, Lists!$B$7:$C$10, 2, FALSE) -> -5000000 | T35: =T86*-Assumptions!$D$79/28/VLOOKUP(Assumptions!$D$7, Lists!$B$7:$C$10, 2, FALSE) -> -5357142.9 | U35: =U86*-Assumptions!$D$79/28/VLOOKUP(Assumptions!$D$7, Lists!$B$7:$C$10, 2, FALSE) -> -5714285.7 | V35: =V86*-Assumptions!$D$79/28/VLOOKUP(Assumptions!$D$7, Lists!$B$7:$C$10, 2, FALSE) -> -6071428.6 | W35: =SUM(S35:V35) -> -22142857 | X35: =X86*-Assumptions!$D$79/28/VLOOKUP(Assumptions!$D$7, Lists!$B$7:$C$10, 2, FALSE) -> -6428571.4 | Y35: =Y86*-Assumptions!$D$79/28/VLOOKUP(Assumptions!$D$7, Lists!$B$7:$C$10, 2, FALSE) -> -6785714.3 | Z35: =Z86*-Assumptions!$D$79/28/VLOOKUP(Assumptions!$D$7, Lists!$B$7:$C$10, 2, FALSE) -> -7142857.1 | AA35: =AA86*-Assumptions!$D$79/28/VLOOKUP(Assumptions!$D$7, Lists!$B$7:$C$10, 2, FALSE) -> -7500000 | AB35: =SUM(X35:AA35) -> -27857143 | AC35: =AC86*-Assumptions!$D$79/28/VLOOKUP(Assumptions!$D$7, Lists!$B$7:$C$10, 2, FALSE) -> -7500000 | AD35: =AD86*-Assumptions!$D$79/28/VLOOKUP(Assumptions!$D$7, Lists!$B$7:$C$10, 2, FALSE) -> -7142857.1 | AE35: =AE86*-Assumptions!$D$79/28/VLOOKUP(Assumptions!$D$7, Lists!$B$7:$C$10, 2, FALSE) -> -7142857.1 | AF35: =AF86*-Assumptions!$D$79/28/VLOOKUP(Assumptions!$D$7, Lists!$B$7:$C$10, 2, FALSE) -> -7142857.1 | AG35: =SUM(AC35:AF35) -> -28928571 | AH35: =AH86*-Assumptions!$D$79/28/VLOOKUP(Assumptions!$D$7, Lists!$B$7:$C$10, 2, FALSE) -> -7142857.1 | AI35: =AI86*-Assumptions!$D$79/28/VLOOKUP(Assumptions!$D$7, Lists!$B$7:$C$10, 2, FALSE) -> -7142857.1 | AJ35: =AJ86*-Assumptions!$D$79/28/VLOOKUP(Assumptions!$D$7, Lists!$B$7:$C$10, 2, FALSE) -> -7142857.1 | AK35: =AK86*-Assumptions!$D$79/28/VLOOKUP(Assumptions!$D$7, Lists!$B$7:$C$10, 2, FALSE) -> -7142857.1 | AL35: =SUM(AH35:AK35) -> -28571429
C36: Depreciation of server and infrastructure equipment | D36: =-Assumptions!$D$81/28/VLOOKUP(Assumptions!$D$7, Lists!$B$7:$C$10, 2, FALSE) -> -8928571.4 | E36: =-Assumptions!$D$81/28/VLOOKUP(Assumptions!$D$7, Lists!$B$7:$C$10, 2, FALSE) -> -8928571.4 | F36: =-Assumptions!$D$81/28/VLOOKUP(Assumptions!$D$7, Lists!$B$7:$C$10, 2, FALSE) -> -8928571.4 | G36: =-Assumptions!$D$81/28/VLOOKUP(Assumptions!$D$7, Lists!$B$7:$C$10, 2, FALSE) -> -8928571.4 | H36: =SUM(D36:G36) -> -35714286 | I36: =-Assumptions!$D$81/28/VLOOKUP(Assumptions!$D$7, Lists!$B$7:$C$10, 2, FALSE) -> -8928571.4 | J36: =-Assumptions!$D$81/28/VLOOKUP(Assumptions!$D$7, Lists!$B$7:$C$10, 2, FALSE) -> -8928571.4 | K36: =-Assumptions!$D$81/28/VLOOKUP(Assumptions!$D$7, Lists!$B$7:$C$10, 2, FALSE) -> -8928571.4 | L36: =-Assumptions!$D$81/28/VLOOKUP(Assumptions!$D$7, Lists!$B$7:$C$10, 2, FALSE) -> -8928571.4 | M36: =SUM(I36:L36) -> -35714286 | N36: =-Assumptions!$D$81/28/VLOOKUP(Assumptions!$D$7, Lists!$B$7:$C$10, 2, FALSE) -> -8928571.4 | O36: =-Assumptions!$D$81/28/VLOOKUP(Assumptions!$D$7, Lists!$B$7:$C$10, 2, FALSE) -> -8928571.4 | P36: =-Assumptions!$D$81/28/VLOOKUP(Assumptions!$D$7, Lists!$B$7:$C$10, 2, FALSE) -> -8928571.4 | Q36: =-Assumptions!$D$81/28/VLOOKUP(Assumptions!$D$7, Lists!$B$7:$C$10, 2, FALSE) -> -8928571.4 | R36: =SUM(N36:Q36) -> -35714286 | S36: =-Assumptions!$D$81/28/VLOOKUP(Assumptions!$D$7, Lists!$B$7:$C$10, 2, FALSE) -> -8928571.4 | T36: =-Assumptions!$D$81/28/VLOOKUP(Assumptions!$D$7, Lists!$B$7:$C$10, 2, FALSE) -> -8928571.4 | U36: =-Assumptions!$D$81/28/VLOOKUP(Assumptions!$D$7, Lists!$B$7:$C$10, 2, FALSE) -> -8928571.4 | V36: =-Assumptions!$D$81/28/VLOOKUP(Assumptions!$D$7, Lists!$B$7:$C$10, 2, FALSE) -> -8928571.4 | W36: =SUM(S36:V36) -> -35714286 | X36: =-Assumptions!$D$81/28/VLOOKUP(Assumptions!$D$7, Lists!$B$7:$C$10, 2, FALSE) -> -8928571.4 | Y36: =-Assumptions!$D$81/28/VLOOKUP(Assumptions!$D$7, Lists!$B$7:$C$10, 2, FALSE) -> -8928571.4 | Z36: =-Assumptions!$D$81/28/VLOOKUP(Assumptions!$D$7, Lists!$B$7:$C$10, 2, FALSE) -> -8928571.4 | AA36: =-Assumptions!$D$81/28/VLOOKUP(Assumptions!$D$7, Lists!$B$7:$C$10, 2, FALSE) -> -8928571.4 | AB36: =SUM(X36:AA36) -> -35714286 | AC36: =-Assumptions!$D$81/28/VLOOKUP(Assumptions!$D$7, Lists!$B$7:$C$10, 2, FALSE) -> -8928571.4 | AD36: =-Assumptions!$D$81/28/VLOOKUP(Assumptions!$D$7, Lists!$B$7:$C$10, 2, FALSE) -> -8928571.4 | AE36: =-Assumptions!$D$81/28/VLOOKUP(Assumptions!$D$7, Lists!$B$7:$C$10, 2, FALSE) -> -8928571.4 | AF36: =-Assumptions!$D$81/28/VLOOKUP(Assumptions!$D$7, Lists!$B$7:$C$10, 2, FALSE) -> -8928571.4 | AG36: =SUM(AC36:AF36) -> -35714286 | AH36: =-Assumptions!$D$81/28/VLOOKUP(Assumptions!$D$7, Lists!$B$7:$C$10, 2, FALSE) -> -8928571.4 | AI36: =-Assumptions!$D$81/28/VLOOKUP(Assumptions!$D$7, Lists!$B$7:$C$10, 2, FALSE) -> -8928571.4 | AJ36: =-Assumptions!$D$81/28/VLOOKUP(Assumptions!$D$7, Lists!$B$7:$C$10, 2, FALSE) -> -8928571.4 | AK36: =-Assumptions!$D$81/28/VLOOKUP(Assumptions!$D$7, Lists!$B$7:$C$10, 2, FALSE) -> -8928571.4 | AL36: =SUM(AH36:AK36) -> -35714286
B37: Depreciation | D37: =SUM(D34:D36) -> -9717857.1 | E37: =SUM(E34:E36) -> -10133929 | F37: =SUM(F34:F36) -> -10550000 | G37: =SUM(G34:G36) -> -10971429 | H37: =SUM(D37:G37) -> -41373214 | I37: =SUM(I34:I36) -> -11387500 | J37: =SUM(J34:J36) -> -11803571 | K37: =SUM(K34:K36) -> -12214286 | L37: =SUM(L34:L36) -> -12625000 | M37: =SUM(I37:L37) -> -48030357 | N37: =SUM(N34:N36) -> -13041071 | O37: =SUM(O34:O36) -> -13451786 | P37: =SUM(P34:P36) -> -13867857 | Q37: =SUM(Q34:Q36) -> -14278571 | R37: =SUM(N37:Q37) -> -54639286 | S37: =SUM(S34:S36) -> -14683929 | T37: =SUM(T34:T36) -> -15094643 | U37: =SUM(U34:U36) -> -15505357 | V37: =SUM(V34:V36) -> -15916071 | W37: =SUM(S37:V37) -> -61200000 | X37: =SUM(X34:X36) -> -16321429 | Y37: =SUM(Y34:Y36) -> -16721429 | Z37: =SUM(Z34:Z36) -> -17126786 | AA37: =SUM(AA34:AA36) -> -17537500 | AB37: =SUM(X37:AA37) -> -67707143 | AC37: =SUM(AC34:AC36) -> -17532143 | AD37: =SUM(AD34:AD36) -> -17153571 | AE37: =SUM(AE34:AE36) -> -17148214 | AF37: =SUM(AF34:AF36) -> -17148214 | AG37: =SUM(AC37:AF37) -> -68982143 | AH37: =SUM(AH34:AH36) -> -17132143 | AI37: =SUM(AI34:AI36) -> -17126786 | AJ37: =SUM(AJ34:AJ36) -> -17126786 | AK37: =SUM(AK34:AK36) -> -17116071 | AL37: =SUM(AH37:AK37) -> -68501786
C38: Premises cost (rent and maintenance) | D38: =D86*-Assumptions!$D$78/4/VLOOKUP(Assumptions!$D$7, Lists!$B$7:$C$10, 2, FALSE) -> -2500000 | E38: =E86*-Assumptions!$D$78/4/VLOOKUP(Assumptions!$D$7, Lists!$B$7:$C$10, 2, FALSE) -> -3750000 | F38: =F86*-Assumptions!$D$78/4/VLOOKUP(Assumptions!$D$7, Lists!$B$7:$C$10, 2, FALSE) -> -5000000 | G38: =G86*-Assumptions!$D$78/4/VLOOKUP(Assumptions!$D$7, Lists!$B$7:$C$10, 2, FALSE) -> -6250000 | H38: =SUM(D38:G38) -> -17500000 | I38: =I86*-Assumptions!$D$78/4/VLOOKUP(Assumptions!$D$7, Lists!$B$7:$C$10, 2, FALSE) -> -7500000 | J38: =J86*-Assumptions!$D$78/4/VLOOKUP(Assumptions!$D$7, Lists!$B$7:$C$10, 2, FALSE) -> -8750000 | K38: =K86*-Assumptions!$D$78/4/VLOOKUP(Assumptions!$D$7, Lists!$B$7:$C$10, 2, FALSE) -> -10000000 | L38: =L86*-Assumptions!$D$78/4/VLOOKUP(Assumptions!$D$7, Lists!$B$7:$C$10, 2, FALSE) -> -11250000 | M38: =SUM(I38:L38) -> -37500000 | N38: =N86*-Assumptions!$D$78/4/VLOOKUP(Assumptions!$D$7, Lists!$B$7:$C$10, 2, FALSE) -> -12500000 | O38: =O86*-Assumptions!$D$78/4/VLOOKUP(Assumptions!$D$7, Lists!$B$7:$C$10, 2, FALSE) -> -13750000 | P38: =P86*-Assumptions!$D$78/4/VLOOKUP(Assumptions!$D$7, Lists!$B$7:$C$10, 2, FALSE) -> -15000000 | Q38: =Q86*-Assumptions!$D$78/4/VLOOKUP(Assumptions!$D$7, Lists!$B$7:$C$10, 2, FALSE) -> -16250000 | R38: =SUM(N38:Q38) -> -57500000 | S38: =S86*-Assumptions!$D$78/4/VLOOKUP(Assumptions!$D$7, Lists!$B$7:$C$10, 2, FALSE) -> -17500000 | T38: =T86*-Assumptions!$D$78/4/VLOOKUP(Assumptions!$D$7, Lists!$B$7:$C$10, 2, FALSE) -> -18750000 | U38: =U86*-Assumptions!$D$78/4/VLOOKUP(Assumptions!$D$7, Lists!$B$7:$C$10, 2, FALSE) -> -20000000 | V38: =V86*-Assumptions!$D$78/4/VLOOKUP(Assumptions!$D$7, Lists!$B$7:$C$10, 2, FALSE) -> -21250000 | W38: =SUM(S38:V38) -> -77500000 | X38: =X86*-Assumptions!$D$78/4/VLOOKUP(Assumptions!$D$7, Lists!$B$7:$C$10, 2, FALSE) -> -22500000 | Y38: =Y86*-Assumptions!$D$78/4/VLOOKUP(Assumptions!$D$7, Lists!$B$7:$C$10, 2, FALSE) -> -23750000 | Z38: =Z86*-Assumptions!$D$78/4/VLOOKUP(Assumptions!$D$7, Lists!$B$7:$C$10, 2, FALSE) -> -25000000 | AA38: =AA86*-Assumptions!$D$78/4/VLOOKUP(Assumptions!$D$7, Lists!$B$7:$C$10, 2, FALSE) -> -26250000 | AB38: =SUM(X38:AA38) -> -97500000 | AC38: =AC86*-Assumptions!$D$78/4/VLOOKUP(Assumptions!$D$7, Lists!$B$7:$C$10, 2, FALSE) -> -26250000 | AD38: =AD86*-Assumptions!$D$78/4/VLOOKUP(Assumptions!$D$7, Lists!$B$7:$C$10, 2, FALSE) -> -25000000 | AE38: =AE86*-Assumptions!$D$78/4/VLOOKUP(Assumptions!$D$7, Lists!$B$7:$C$10, 2, FALSE) -> -25000000 | AF38: =AF86*-Assumptions!$D$78/4/VLOOKUP(Assumptions!$D$7, Lists!$B$7:$C$10, 2, FALSE) -> -25000000 | AG38: =SUM(AC38:AF38) -> -101250000 | AH38: =AH86*-Assumptions!$D$78/4/VLOOKUP(Assumptions!$D$7, Lists!$B$7:$C$10, 2, FALSE) -> -25000000 | AI38: =AI86*-Assumptions!$D$78/4/VLOOKUP(Assumptions!$D$7, Lists!$B$7:$C$10, 2, FALSE) -> -25000000 | AJ38: =AJ86*-Assumptions!$D$78/4/VLOOKUP(Assumptions!$D$7, Lists!$B$7:$C$10, 2, FALSE) -> -25000000 | AK38: =AK86*-Assumptions!$D$78/4/VLOOKUP(Assumptions!$D$7, Lists!$B$7:$C$10, 2, FALSE) -> -25000000 | AL38: =SUM(AH38:AK38) -> -100000000
C39: Office supplies | D39: =D86*-Assumptions!$D$83/4/VLOOKUP(Assumptions!$D$7, Lists!$B$7:$C$10, 2, FALSE) -> -250000 | E39: =E86*-Assumptions!$D$83/4/VLOOKUP(Assumptions!$D$7, Lists!$B$7:$C$10, 2, FALSE) -> -375000 | F39: =F86*-Assumptions!$D$83/4/VLOOKUP(Assumptions!$D$7, Lists!$B$7:$C$10, 2, FALSE) -> -500000 | G39: =G86*-Assumptions!$D$83/4/VLOOKUP(Assumptions!$D$7, Lists!$B$7:$C$10, 2, FALSE) -> -625000 | H39: =SUM(D39:G39) -> -1750000 | I39: =I86*-Assumptions!$D$83/4/VLOOKUP(Assumptions!$D$7, Lists!$B$7:$C$10, 2, FALSE) -> -750000 | J39: =J86*-Assumptions!$D$83/4/VLOOKUP(Assumptions!$D$7, Lists!$B$7:$C$10, 2, FALSE) -> -875000 | K39: =K86*-Assumptions!$D$83/4/VLOOKUP(Assumptions!$D$7, Lists!$B$7:$C$10, 2, FALSE) -> -1000000 | L39: =L86*-Assumptions!$D$83/4/VLOOKUP(Assumptions!$D$7, Lists!$B$7:$C$10, 2, FALSE) -> -1125000 | M39: =SUM(I39:L39) -> -3750000 | N39: =N86*-Assumptions!$D$83/4/VLOOKUP(Assumptions!$D$7, Lists!$B$7:$C$10, 2, FALSE) -> -1250000 | O39: =O86*-Assumptions!$D$83/4/VLOOKUP(Assumptions!$D$7, Lists!$B$7:$C$10, 2, FALSE) -> -1375000 | P39: =P86*-Assumptions!$D$83/4/VLOOKUP(Assumptions!$D$7, Lists!$B$7:$C$10, 2, FALSE) -> -1500000 | Q39: =Q86*-Assumptions!$D$83/4/VLOOKUP(Assumptions!$D$7, Lists!$B$7:$C$10, 2, FALSE) -> -1625000 | R39: =SUM(N39:Q39) -> -5750000 | S39: =S86*-Assumptions!$D$83/4/VLOOKUP(Assumptions!$D$7, Lists!$B$7:$C$10, 2, FALSE) -> -1750000 | T39: =T86*-Assumptions!$D$83/4/VLOOKUP(Assumptions!$D$7, Lists!$B$7:$C$10, 2, FALSE) -> -1875000 | U39: =U86*-Assumptions!$D$83/4/VLOOKUP(Assumptions!$D$7, Lists!$B$7:$C$10, 2, FALSE) -> -2000000 | V39: =V86*-Assumptions!$D$83/4/VLOOKUP(Assumptions!$D$7, Lists!$B$7:$C$10, 2, FALSE) -> -2125000 | W39: =SUM(S39:V39) -> -7750000 | X39: =X86*-Assumptions!$D$83/4/VLOOKUP(Assumptions!$D$7, Lists!$B$7:$C$10, 2, FALSE) -> -2250000 | Y39: =Y86*-Assumptions!$D$83/4/VLOOKUP(Assumptions!$D$7, Lists!$B$7:$C$10, 2, FALSE) -> -2375000 | Z39: =Z86*-Assumptions!$D$83/4/VLOOKUP(Assumptions!$D$7, Lists!$B$7:$C$10, 2, FALSE) -> -2500000 | AA39: =AA86*-Assumptions!$D$83/4/VLOOKUP(Assumptions!$D$7, Lists!$B$7:$C$10, 2, FALSE) -> -2625000 | AB39: =SUM(X39:AA39) -> -9750000 | AC39: =AC86*-Assumptions!$D$83/4/VLOOKUP(Assumptions!$D$7, Lists!$B$7:$C$10, 2, FALSE) -> -2625000 | AD39: =AD86*-Assumptions!$D$83/4/VLOOKUP(Assumptions!$D$7, Lists!$B$7:$C$10, 2, FALSE) -> -2500000 | AE39: =AE86*-Assumptions!$D$83/4/VLOOKUP(Assumptions!$D$7, Lists!$B$7:$C$10, 2, FALSE) -> -2500000 | AF39: =AF86*-Assumptions!$D$83/4/VLOOKUP(Assumptions!$D$7, Lists!$B$7:$C$10, 2, FALSE) -> -2500000 | AG39: =SUM(AC39:AF39) -> -10125000 | AH39: =AH86*-Assumptions!$D$83/4/VLOOKUP(Assumptions!$D$7, Lists!$B$7:$C$10, 2, FALSE) -> -2500000 | AI39: =AI86*-Assumptions!$D$83/4/VLOOKUP(Assumptions!$D$7, Lists!$B$7:$C$10, 2, FALSE) -> -2500000 | AJ39: =AJ86*-Assumptions!$D$83/4/VLOOKUP(Assumptions!$D$7, Lists!$B$7:$C$10, 2, FALSE) -> -2500000 | AK39: =AK86*-Assumptions!$D$83/4/VLOOKUP(Assumptions!$D$7, Lists!$B$7:$C$10, 2, FALSE) -> -2500000 | AL39: =SUM(AH39:AK39) -> -10000000
C40: Marketing and advertising | D40: =SUM(D68:D71)*(1-Assumptions!$D$88)*-Assumptions!D86/VLOOKUP(Assumptions!$D$7, Lists!$B$7:$C$10, 2, FALSE) -> -103950000 | E40: =(-IF((SUM(E68:E71)-SUM(D68:D71)-SUM(E68:E71)*(Assumptions!$D$87+Assumptions!$D$88)-Assumptions!$D$59*Assumptions!$D$60)*Assumptions!$D$86>0,(SUM(E68:E71)-SUM(D68:D71)-SUM(E68:E71)*(Assumptions!$D$87+Assumptions!$D$88)-Assumptions!$D$59*Assumptions!$D$60)*Assumptions!$D$86,0))/VLOOKUP(Assumptions!$D$7, Lists!$B$7:$C$10, 2, FALSE) -> -82970000 | F40: =(-IF((SUM(F68:F71)-SUM(E68:E71)-SUM(F68:F71)*(Assumptions!$D$87+Assumptions!$D$88)-Assumptions!$D$59*Assumptions!$D$60)*Assumptions!$D$86>0,(SUM(F68:F71)-SUM(E68:E71)-SUM(F68:F71)*(Assumptions!$D$87+Assumptions!$D$88)-Assumptions!$D$59*Assumptions!$D$60)*Assumptions!$D$86,0))/VLOOKUP(Assumptions!$D$7, Lists!$B$7:$C$10, 2, FALSE) -> -67955000 | G40: =(-IF((SUM(G68:G71)-SUM(F68:F71)-SUM(G68:G71)*(Assumptions!$D$87+Assumptions!$D$88)-Assumptions!$D$59*Assumptions!$D$60)*Assumptions!$D$86>0,(SUM(G68:G71)-SUM(F68:F71)-SUM(G68:G71)*(Assumptions!$D$87+Assumptions!$D$88)-Assumptions!$D$59*Assumptions!$D$60)*Assumptions!$D$86,0))/VLOOKUP(Assumptions!$D$7, Lists!$B$7:$C$10, 2, FALSE) -> -52940000 | H40: =SUM(D40:G40) -> -307815000 | I40: =(-IF((SUM(I68:I71)-SUM(H68:H71)-SUM(I68:I71)*(Assumptions!$D$87+Assumptions!$D$88)-Assumptions!$D$59*Assumptions!$D$60)*Assumptions!$D$86>0,(SUM(I68:I71)-SUM(H68:H71)-SUM(I68:I71)*(Assumptions!$D$87+Assumptions!$D$88)-Assumptions!$D$59*Assumptions!$D$60)*Assumptions!$D$86,0))/VLOOKUP(Assumptions!$D$7, Lists!$B$7:$C$10, 2, FALSE) -> -37925000 | J40: =(-IF((SUM(J68:J71)-SUM(I68:I71)-SUM(J68:J71)*(Assumptions!$D$87+Assumptions!$D$88)-Assumptions!$D$59*Assumptions!$D$60)*Assumptions!$D$86>0,(SUM(J68:J71)-SUM(I68:I71)-SUM(J68:J71)*(Assumptions!$D$87+Assumptions!$D$88)-Assumptions!$D$59*Assumptions!$D$60)*Assumptions!$D$86,0))/VLOOKUP(Assumptions!$D$7, Lists!$B$7:$C$10, 2, FALSE) -> -22910000 | K40: =(-IF((SUM(K68:K71)-SUM(J68:J71)-SUM(K68:K71)*(Assumptions!$D$87+Assumptions!$D$88)-Assumptions!$D$59*Assumptions!$D$60)*Assumptions!$D$86>0,(SUM(K68:K71)-SUM(J68:J71)-SUM(K68:K71)*(Assumptions!$D$87+Assumptions!$D$88)-Assumptions!$D$59*Assumptions!$D$60)*Assumptions!$D$86,0))/VLOOKUP(Assumptions!$D$7, Lists!$B$7:$C$10, 2, FALSE) -> -7895000 | L40: =(-IF((SUM(L68:L71)-SUM(K68:K71)-SUM(L68:L71)*(Assumptions!$D$87+Assumptions!$D$88)-Assumptions!$D$59*Assumptions!$D$60)*Assumptions!$D$86>0,(SUM(L68:L71)-SUM(K68:K71)-SUM(L68:L71)*(Assumptions!$D$87+Assumptions!$D$88)-Assumptions!$D$59*Assumptions!$D$60)*Assumptions!$D$86,0))/VLOOKUP(Assumptions!$D$7, Lists!$B$7:$C$10, 2, FALSE) -> 0 | M40: =SUM(I40:L40) -> -68730000 | N40: =(-IF((SUM(N68:N71)-SUM(M68:M71)-SUM(N68:N71)*(Assumptions!$D$87+Assumptions!$D$88)-Assumptions!$D$59*Assumptions!$D$60)*Assumptions!$D$86>0,(SUM(N68:N71)-SUM(M68:M71)-SUM(N68:N71)*(Assumptions!$D$87+Assumptions!$D$88)-Assumptions!$D$59*Assumptions!$D$60)*Assumptions!$D$86,0))/VLOOKUP(Assumptions!$D$7, Lists!$B$7:$C$10, 2, FALSE) -> 0 | O40: =(-IF((SUM(O68:O71)-SUM(N68:N71)-SUM(O68:O71)*(Assumptions!$D$87+Assumptions!$D$88)-Assumptions!$D$59*Assumptions!$D$60)*Assumptions!$D$86>0,(SUM(O68:O71)-SUM(N68:N71)-SUM(O68:O71)*(Assumptions!$D$87+Assumptions!$D$88)-Assumptions!$D$59*Assumptions!$D$60)*Assumptions!$D$86,0))/VLOOKUP(Assumptions!$D$7, Lists!$B$7:$C$10, 2, FALSE) -> 0 | P40: =(-IF((SUM(P68:P71)-SUM(O68:O71)-SUM(P68:P71)*(Assumptions!$D$87+Assumptions!$D$88)-Assumptions!$D$59*Assumptions!$D$60)*Assumptions!$D$86>0,(SUM(P68:P71)-SUM(O68:O71)-SUM(P68:P71)*(Assumptions!$D$87+Assumptions!$D$88)-Assumptions!$D$59*Assumptions!$D$60)*Assumptions!$D$86,0))/VLOOKUP(Assumptions!$D$7, Lists!$B$7:$C$10, 2, FALSE) -> 0 | Q40: =(-IF((SUM(Q68:Q71)-SUM(P68:P71)-SUM(Q68:Q71)*(Assumptions!$D$87+Assumptions!$D$88)-Assumptions!$D$59*Assumptions!$D$60)*Assumptions!$D$86>0,(SUM(Q68:Q71)-SUM(P68:P71)-SUM(Q68:Q71)*(Assumptions!$D$87+Assumptions!$D$88)-Assumptions!$D$59*Assumptions!$D$60)*Assumptions!$D$86,0))/VLOOKUP(Assumptions!$D$7, Lists!$B$7:$C$10, 2, FALSE) -> 0 | R40: =SUM(N40:Q40) -> 0 | S40: =(-IF((SUM(S68:S71)-SUM(R68:R71)-SUM(S68:S71)*(Assumptions!$D$87+Assumptions!$D$88)-Assumptions!$D$59*Assumptions!$D$60)*Assumptions!$D$86>0,(SUM(S68:S71)-SUM(R68:R71)-SUM(S68:S71)*(Assumptions!$D$87+Assumptions!$D$88)-Assumptions!$D$59*Assumptions!$D$60)*Assumptions!$D$86,0))/VLOOKUP(Assumptions!$D$7, Lists!$B$7:$C$10, 2, FALSE) -> 0 | T40: =(-IF((SUM(T68:T71)-SUM(S68:S71)-SUM(T68:T71)*(Assumptions!$D$87+Assumptions!$D$88)-Assumptions!$D$59*Assumptions!$D$60)*Assumptions!$D$86>0,(SUM(T68:T71)-SUM(S68:S71)-SUM(T68:T71)*(Assumptions!$D$87+Assumptions!$D$88)-Assumptions!$D$59*Assumptions!$D$60)*Assumptions!$D$86,0))/VLOOKUP(Assumptions!$D$7, Lists!$B$7:$C$10, 2, FALSE) -> 0 | U40: =(-IF((SUM(U68:U71)-SUM(T68:T71)-SUM(U68:U71)*(Assumptions!$D$87+Assumptions!$D$88)-Assumptions!$D$59*Assumptions!$D$60)*Assumptions!$D$86>0,(SUM(U68:U71)-SUM(T68:T71)-SUM(U68:U71)*(Assumptions!$D$87+Assumptions!$D$88)-Assumptions!$D$59*Assumptions!$D$60)*Assumptions!$D$86,0))/VLOOKUP(Assumptions!$D$7, Lists!$B$7:$C$10, 2, FALSE) -> 0 | V40: =(-IF((SUM(V68:V71)-SUM(U68:U71)-SUM(V68:V71)*(Assumptions!$D$87+Assumptions!$D$88)-Assumptions!$D$59*Assumptions!$D$60)*Assumptions!$D$86>0,(SUM(V68:V71)-SUM(U68:U71)-SUM(V68:V71)*(Assumptions!$D$87+Assumptions!$D$88)-Assumptions!$D$59*Assumptions!$D$60)*Assumptions!$D$86,0))/VLOOKUP(Assumptions!$D$7, Lists!$B$7:$C$10, 2, FALSE) -> 0 | W40: =SUM(S40:V40) -> 0 | X40: =(-IF((SUM(X68:X71)-SUM(W68:W71)-SUM(X68:X71)*(Assumptions!$D$87+Assumptions!$D$88)-Assumptions!$D$59*Assumptions!$D$60)*Assumptions!$D$86>0,(SUM(X68:X71)-SUM(W68:W71)-SUM(X68:X71)*(Assumptions!$D$87+Assumptions!$D$88)-Assumptions!$D$59*Assumptions!$D$60)*Assumptions!$D$86,0))/VLOOKUP(Assumptions!$D$7, Lists!$B$7:$C$10, 2, FALSE) -> 0 | Y40: =(-IF((SUM(Y68:Y71)-SUM(X68:X71)-SUM(Y68:Y71)*(Assumptions!$D$87+Assumptions!$D$88)-Assumptions!$D$59*Assumptions!$D$60)*Assumptions!$D$86>0,(SUM(Y68:Y71)-SUM(X68:X71)-SUM(Y68:Y71)*(Assumptions!$D$87+Assumptions!$D$88)-Assumptions!$D$59*Assumptions!$D$60)*Assumptions!$D$86,0))/VLOOKUP(Assumptions!$D$7, Lists!$B$7:$C$10, 2, FALSE) -> 0 | Z40: =(-IF((SUM(Z68:Z71)-SUM(Y68:Y71)-SUM(Z68:Z71)*(Assumptions!$D$87+Assumptions!$D$88)-Assumptions!$D$59*Assumptions!$D$60)*Assumptions!$D$86>0,(SUM(Z68:Z71)-SUM(Y68:Y71)-SUM(Z68:Z71)*(Assumptions!$D$87+Assumptions!$D$88)-Assumptions!$D$59*Assumptions!$D$60)*Assumptions!$D$86,0))/VLOOKUP(Assumptions!$D$7, Lists!$B$7:$C$10, 2, FALSE) -> 0 | AA40: =(-IF((SUM(AA68:AA71)-SUM(Z68:Z71)-SUM(AA68:AA71)*(Assumptions!$D$87+Assumptions!$D$88)-Assumptions!$D$59*Assumptions!$D$60)*Assumptions!$D$86>0,(SUM(AA68:AA71)-SUM(Z68:Z71)-SUM(AA68:AA71)*(Assumptions!$D$87+Assumptions!$D$88)-Assumptions!$D$59*Assumptions!$D$60)*Assumptions!$D$86,0))/VLOOKUP(Assumptions!$D$7, Lists!$B$7:$C$10, 2, FALSE) -> 0 | AB40: =SUM(X40:AA40) -> 0 | AC40: =-IF((SUM(AC68:AC71)-SUM(AB68:AB71)-SUM(AC68:AC71)*(Assumptions!$D$87+Assumptions!$D$88)-Assumptions!$D$59*Assumptions!$D$60)*Assumptions!$D$86>0,(SUM(AC68:AC71)-SUM(AB68:AB71)-SUM(AC68:AC71)*(Assumptions!$D$87+Assumptions!$D$88)-Assumptions!$D$59*Assumptions!$D$60)*Assumptions!$D$86,0) -> 0 | AD40: =-IF((SUM(AD68:AD71)-SUM(AC68:AC71)-SUM(AD68:AD71)*(Assumptions!$D$87+Assumptions!$D$88)-Assumptions!$D$59*Assumptions!$D$60)*Assumptions!$D$86>0,(SUM(AD68:AD71)-SUM(AC68:AC71)-SUM(AD68:AD71)*(Assumptions!$D$87+Assumptions!$D$88)-Assumptions!$D$59*Assumptions!$D$60)*Assumptions!$D$86,0) -> 0 | AE40: =-IF((SUM(AE68:AE71)-SUM(AD68:AD71)-SUM(AE68:AE71)*(Assumptions!$D$87+Assumptions!$D$88)-Assumptions!$D$59*Assumptions!$D$60)*Assumptions!$D$86>0,(SUM(AE68:AE71)-SUM(AD68:AD71)-SUM(AE68:AE71)*(Assumptions!$D$87+Assumptions!$D$88)-Assumptions!$D$59*Assumptions!$D$60)*Assumptions!$D$86,0) -> 0 | AF40: =-IF((SUM(AF68:AF71)-SUM(AE68:AE71)-SUM(AF68:AF71)*(Assumptions!$D$87+Assumptions!$D$88)-Assumptions!$D$59*Assumptions!$D$60)*Assumptions!$D$86>0,(SUM(AF68:AF71)-SUM(AE68:AE71)-SUM(AF68:AF71)*(Assumptions!$D$87+Assumptions!$D$88)-Assumptions!$D$59*Assumptions!$D$60)*Assumptions!$D$86,0) -> 0 | AG40: =SUM(AC40:AF40) -> 0 | AH40: =(-IF((SUM(AH68:AH71)-SUM(AG68:AG71)-SUM(AH68:AH71)*(Assumptions!$D$87+Assumptions!$D$88)-Assumptions!$D$59*Assumptions!$D$60)*Assumptions!$D$86>0,(SUM(AH68:AH71)-SUM(AG68:AG71)-SUM(AH68:AH71)*(Assumptions!$D$87+Assumptions!$D$88)-Assumptions!$D$59*Assumptions!$D$60)*Assumptions!$D$86,0))/VLOOKUP(Assumptions!$D$7, Lists!$B$7:$C$10, 2, FALSE) -> 0 | AI40: =(-IF((SUM(AI68:AI71)-SUM(AH68:AH71)-SUM(AI68:AI71)*(Assumptions!$D$87+Assumptions!$D$88)-Assumptions!$D$59*Assumptions!$D$60)*Assumptions!$D$86>0,(SUM(AI68:AI71)-SUM(AH68:AH71)-SUM(AI68:AI71)*(Assumptions!$D$87+Assumptions!$D$88)-Assumptions!$D$59*Assumptions!$D$60)*Assumptions!$D$86,0))/VLOOKUP(Assumptions!$D$7, Lists!$B$7:$C$10, 2, FALSE) -> 0 | AJ40: =(-IF((SUM(AJ68:AJ71)-SUM(AI68:AI71)-SUM(AJ68:AJ71)*(Assumptions!$D$87+Assumptions!$D$88)-Assumptions!$D$59*Assumptions!$D$60)*Assumptions!$D$86>0,(SUM(AJ68:AJ71)-SUM(AI68:AI71)-SUM(AJ68:AJ71)*(Assumptions!$D$87+Assumptions!$D$88)-Assumptions!$D$59*Assumptions!$D$60)*Assumptions!$D$86,0))/VLOOKUP(Assumptions!$D$7, Lists!$B$7:$C$10, 2, FALSE) -> 0 | AK40: =(-IF((SUM(AK68:AK71)-SUM(AJ68:AJ71)-SUM(AK68:AK71)*(Assumptions!$D$87+Assumptions!$D$88)-Assumptions!$D$59*Assumptions!$D$60)*Assumptions!$D$86>0,(SUM(AK68:AK71)-SUM(AJ68:AJ71)-SUM(AK68:AK71)*(Assumptions!$D$87+Assumptions!$D$88)-Assumptions!$D$59*Assumptions!$D$60)*Assumptions!$D$86,0))/VLOOKUP(Assumptions!$D$7, Lists!$B$7:$C$10, 2, FALSE) -> 0 | AL40: =SUM(AH40:AK40) -> 0
C41: Client acqusition agent commissions | D41: =SUM(D68:D71)*Assumptions!$D$88*-Assumptions!$D$89/VLOOKUP(Assumptions!$D$7, Lists!$B$7:$C$10, 2, FALSE) -> -4620000 | E41: =((SUM(E68:E70)-SUM(D68:D70))*-Assumptions!$D$89)/VLOOKUP(Assumptions!$D$7, Lists!$B$7:$C$10, 2, FALSE) -> -6200000 | F41: =((SUM(F68:F70)-SUM(E68:E70))*-Assumptions!$D$89)/VLOOKUP(Assumptions!$D$7, Lists!$B$7:$C$10, 2, FALSE) -> -6200000 | G41: =((SUM(G68:G70)-SUM(F68:F70))*-Assumptions!$D$89)/VLOOKUP(Assumptions!$D$7, Lists!$B$7:$C$10, 2, FALSE) -> -6200000 | H41: =SUM(D41:G41) -> -23220000 | I41: =((SUM(I68:I70)-SUM(H68:H70))*-Assumptions!$D$89)/VLOOKUP(Assumptions!$D$7, Lists!$B$7:$C$10, 2, FALSE) -> -6200000 | J41: =((SUM(J68:J70)-SUM(I68:I70))*-Assumptions!$D$89)/VLOOKUP(Assumptions!$D$7, Lists!$B$7:$C$10, 2, FALSE) -> -6200000 | K41: =((SUM(K68:K70)-SUM(J68:J70))*-Assumptions!$D$89)/VLOOKUP(Assumptions!$D$7, Lists!$B$7:$C$10, 2, FALSE) -> -6200000 | L41: =((SUM(L68:L70)-SUM(K68:K70))*-Assumptions!$D$89)/VLOOKUP(Assumptions!$D$7, Lists!$B$7:$C$10, 2, FALSE) -> -6200000 | M41: =SUM(I41:L41) -> -24800000 | N41: =((SUM(N68:N70)-SUM(M68:M70))*-Assumptions!$D$89)/VLOOKUP(Assumptions!$D$7, Lists!$B$7:$C$10, 2, FALSE) -> -6200000 | O41: =((SUM(O68:O70)-SUM(N68:N70))*-Assumptions!$D$89)/VLOOKUP(Assumptions!$D$7, Lists!$B$7:$C$10, 2, FALSE) -> -6200000 | P41: =((SUM(P68:P70)-SUM(O68:O70))*-Assumptions!$D$89)/VLOOKUP(Assumptions!$D$7, Lists!$B$7:$C$10, 2, FALSE) -> -6200000 | Q41: =((SUM(Q68:Q70)-SUM(P68:P70))*-Assumptions!$D$89)/VLOOKUP(Assumptions!$D$7, Lists!$B$7:$C$10, 2, FALSE) -> -6200000 | R41: =SUM(N41:Q41) -> -24800000 | S41: =((SUM(S68:S70)-SUM(R68:R70))*-Assumptions!$D$89)/VLOOKUP(Assumptions!$D$7, Lists!$B$7:$C$10, 2, FALSE) -> -6200000 | T41: =((SUM(T68:T70)-SUM(S68:S70))*-Assumptions!$D$89)/VLOOKUP(Assumptions!$D$7, Lists!$B$7:$C$10, 2, FALSE) -> -6200000 | U41: =((SUM(U68:U70)-SUM(T68:T70))*-Assumptions!$D$89)/VLOOKUP(Assumptions!$D$7, Lists!$B$7:$C$10, 2, FALSE) -> -6200000 | V41: =((SUM(V68:V70)-SUM(U68:U70))*-Assumptions!$D$89)/VLOOKUP(Assumptions!$D$7, Lists!$B$7:$C$10, 2, FALSE) -> -6200000 | W41: =SUM(S41:V41) -> -24800000 | X41: =((SUM(X68:X70)-SUM(W68:W70))*-Assumptions!$D$89)/VLOOKUP(Assumptions!$D$7, Lists!$B$7:$C$10, 2, FALSE) -> -6200000 | Y41: =((SUM(Y68:Y70)-SUM(X68:X70))*-Assumptions!$D$89)/VLOOKUP(Assumptions!$D$7, Lists!$B$7:$C$10, 2, FALSE) -> -6200000 | Z41: =((SUM(Z68:Z70)-SUM(Y68:Y70))*-Assumptions!$D$89)/VLOOKUP(Assumptions!$D$7, Lists!$B$7:$C$10, 2, FALSE) -> -6200000 | AA41: =((SUM(AA68:AA70)-SUM(Z68:Z70))*-Assumptions!$D$89)/VLOOKUP(Assumptions!$D$7, Lists!$B$7:$C$10, 2, FALSE) -> -6200000 | AB41: =SUM(X41:AA41) -> -24800000 | AC41: =((SUM(AC68:AC70)-SUM(AB68:AB70))*-Assumptions!$D$89)/VLOOKUP(Assumptions!$D$7, Lists!$B$7:$C$10, 2, FALSE) -> 0 | AD41: =((SUM(AD68:AD70)-SUM(AC68:AC70))*-Assumptions!$D$89)/VLOOKUP(Assumptions!$D$7, Lists!$B$7:$C$10, 2, FALSE) -> 0 | AE41: =((SUM(AE68:AE70)-SUM(AD68:AD70))*-Assumptions!$D$89)/VLOOKUP(Assumptions!$D$7, Lists!$B$7:$C$10, 2, FALSE) -> 0 | AF41: =((SUM(AF68:AF70)-SUM(AE68:AE70))*-Assumptions!$D$89)/VLOOKUP(Assumptions!$D$7, Lists!$B$7:$C$10, 2, FALSE) -> 0 | AG41: =SUM(AC41:AF41) -> 0 | AH41: =((SUM(AH68:AH70)-SUM(AG68:AG70))*-Assumptions!$D$89)/VLOOKUP(Assumptions!$D$7, Lists!$B$7:$C$10, 2, FALSE) -> 0 | AI41: =((SUM(AI68:AI70)-SUM(AH68:AH70))*-Assumptions!$D$89)/VLOOKUP(Assumptions!$D$7, Lists!$B$7:$C$10, 2, FALSE) -> 0 | AJ41: =((SUM(AJ68:AJ70)-SUM(AI68:AI70))*-Assumptions!$D$89)/VLOOKUP(Assumptions!$D$7, Lists!$B$7:$C$10, 2, FALSE) -> 0 | AK41: =((SUM(AK68:AK70)-SUM(AJ68:AJ70))*-Assumptions!$D$89)/VLOOKUP(Assumptions!$D$7, Lists!$B$7:$C$10, 2, FALSE) -> 0 | AL41: =SUM(AH41:AK41) -> 0
C42: Client service agent commissions | D42: =D85*-Assumptions!$D$77/VLOOKUP(Assumptions!$D$7, Lists!$B$7:$C$10, 2, FALSE) -> -1147781.2 | E42: =E85*-Assumptions!$D$77/VLOOKUP(Assumptions!$D$7, Lists!$B$7:$C$10, 2, FALSE) -> -2281125 | F42: =F85*-Assumptions!$D$77/VLOOKUP(Assumptions!$D$7, Lists!$B$7:$C$10, 2, FALSE) -> -3400031.2 | G42: =G85*-Assumptions!$D$77/VLOOKUP(Assumptions!$D$7, Lists!$B$7:$C$10, 2, FALSE) -> -4504500 | H42: =SUM(D42:G42) -> -11333438 | I42: =I85*-Assumptions!$D$77/VLOOKUP(Assumptions!$D$7, Lists!$B$7:$C$10, 2, FALSE) -> -5594531.2 | J42: =J85*-Assumptions!$D$77/VLOOKUP(Assumptions!$D$7, Lists!$B$7:$C$10, 2, FALSE) -> -6670125 | K42: =K85*-Assumptions!$D$77/VLOOKUP(Assumptions!$D$7, Lists!$B$7:$C$10, 2, FALSE) -> -7731281.3 | L42: =L85*-Assumptions!$D$77/VLOOKUP(Assumptions!$D$7, Lists!$B$7:$C$10, 2, FALSE) -> -8778000 | M42: =SUM(I42:L42) -> -28773938 | N42: =N85*-Assumptions!$D$77/VLOOKUP(Assumptions!$D$7, Lists!$B$7:$C$10, 2, FALSE) -> -9810281.2 | O42: =O85*-Assumptions!$D$77/VLOOKUP(Assumptions!$D$7, Lists!$B$7:$C$10, 2, FALSE) -> -10828125 | P42: =P85*-Assumptions!$D$77/VLOOKUP(Assumptions!$D$7, Lists!$B$7:$C$10, 2, FALSE) -> -11831531 | Q42: =Q85*-Assumptions!$D$77/VLOOKUP(Assumptions!$D$7, Lists!$B$7:$C$10, 2, FALSE) -> -12820500 | R42: =SUM(N42:Q42) -> -45290438 | S42: =S85*-Assumptions!$D$77/VLOOKUP(Assumptions!$D$7, Lists!$B$7:$C$10, 2, FALSE) -> -13795031 | T42: =T85*-Assumptions!$D$77/VLOOKUP(Assumptions!$D$7, Lists!$B$7:$C$10, 2, FALSE) -> -14755125 | U42: =U85*-Assumptions!$D$77/VLOOKUP(Assumptions!$D$7, Lists!$B$7:$C$10, 2, FALSE) -> -15700781 | V42: =V85*-Assumptions!$D$77/VLOOKUP(Assumptions!$D$7, Lists!$B$7:$C$10, 2, FALSE) -> -16632000 | W42: =SUM(S42:V42) -> -60882938 | X42: =X85*-Assumptions!$D$77/VLOOKUP(Assumptions!$D$7, Lists!$B$7:$C$10, 2, FALSE) -> -17548781 | Y42: =Y85*-Assumptions!$D$77/VLOOKUP(Assumptions!$D$7, Lists!$B$7:$C$10, 2, FALSE) -> -18451125 | Z42: =Z85*-Assumptions!$D$77/VLOOKUP(Assumptions!$D$7, Lists!$B$7:$C$10, 2, FALSE) -> -19339031 | AA42: =AA85*-Assumptions!$D$77/VLOOKUP(Assumptions!$D$7, Lists!$B$7:$C$10, 2, FALSE) -> -20212500 | AB42: =SUM(X42:AA42) -> -75551438 | AC42: =AC85*-Assumptions!$D$77/VLOOKUP(Assumptions!$D$7, Lists!$B$7:$C$10, 2, FALSE) -> -20068125 | AD42: =AD85*-Assumptions!$D$77/VLOOKUP(Assumptions!$D$7, Lists!$B$7:$C$10, 2, FALSE) -> -19923750 | AE42: =AE85*-Assumptions!$D$77/VLOOKUP(Assumptions!$D$7, Lists!$B$7:$C$10, 2, FALSE) -> -19779375 | AF42: =AF85*-Assumptions!$D$77/VLOOKUP(Assumptions!$D$7, Lists!$B$7:$C$10, 2, FALSE) -> -19635000 | AG42: =SUM(AC42:AF42) -> -79406250 | AH42: =AH85*-Assumptions!$D$77/VLOOKUP(Assumptions!$D$7, Lists!$B$7:$C$10, 2, FALSE) -> -19490625 | AI42: =AI85*-Assumptions!$D$77/VLOOKUP(Assumptions!$D$7, Lists!$B$7:$C$10, 2, FALSE) -> -19346250 | AJ42: =AJ85*-Assumptions!$D$77/VLOOKUP(Assumptions!$D$7, Lists!$B$7:$C$10, 2, FALSE) -> -19201875 | AK42: =AK85*-Assumptions!$D$77/VLOOKUP(Assumptions!$D$7, Lists!$B$7:$C$10, 2, FALSE) -> -19057500 | AL42: =SUM(AH42:AK42) -> -77096250
C43: IT expenses | D43: =-Assumptions!$D$82/4/VLOOKUP(Assumptions!$D$7, Lists!$B$7:$C$10, 2, FALSE) -> -12500000 | E43: =-Assumptions!$D$82/4/VLOOKUP(Assumptions!$D$7, Lists!$B$7:$C$10, 2, FALSE) -> -12500000 | F43: =-Assumptions!$D$82/4/VLOOKUP(Assumptions!$D$7, Lists!$B$7:$C$10, 2, FALSE) -> -12500000 | G43: =-Assumptions!$D$82/4/VLOOKUP(Assumptions!$D$7, Lists!$B$7:$C$10, 2, FALSE) -> -12500000 | H43: =SUM(D43:G43) -> -50000000 | I43: =-Assumptions!$D$82/4/VLOOKUP(Assumptions!$D$7, Lists!$B$7:$C$10, 2, FALSE) -> -12500000 | J43: =-Assumptions!$D$82/4/VLOOKUP(Assumptions!$D$7, Lists!$B$7:$C$10, 2, FALSE) -> -12500000 | K43: =-Assumptions!$D$82/4/VLOOKUP(Assumptions!$D$7, Lists!$B$7:$C$10, 2, FALSE) -> -12500000 | L43: =-Assumptions!$D$82/4/VLOOKUP(Assumptions!$D$7, Lists!$B$7:$C$10, 2, FALSE) -> -12500000 | M43: =SUM(I43:L43) -> -50000000 | N43: =-Assumptions!$D$82/4/VLOOKUP(Assumptions!$D$7, Lists!$B$7:$C$10, 2, FALSE) -> -12500000 | O43: =-Assumptions!$D$82/4/VLOOKUP(Assumptions!$D$7, Lists!$B$7:$C$10, 2, FALSE) -> -12500000 | P43: =-Assumptions!$D$82/4/VLOOKUP(Assumptions!$D$7, Lists!$B$7:$C$10, 2, FALSE) -> -12500000 | Q43: =-Assumptions!$D$82/4/VLOOKUP(Assumptions!$D$7, Lists!$B$7:$C$10, 2, FALSE) -> -12500000 | R43: =SUM(N43:Q43) -> -50000000 | S43: =-Assumptions!$D$82/4/VLOOKUP(Assumptions!$D$7, Lists!$B$7:$C$10, 2, FALSE) -> -12500000 | T43: =-Assumptions!$D$82/4/VLOOKUP(Assumptions!$D$7, Lists!$B$7:$C$10, 2, FALSE) -> -12500000 | U43: =-Assumptions!$D$82/4/VLOOKUP(Assumptions!$D$7, Lists!$B$7:$C$10, 2, FALSE) -> -12500000 | V43: =-Assumptions!$D$82/4/VLOOKUP(Assumptions!$D$7, Lists!$B$7:$C$10, 2, FALSE) -> -12500000 | W43: =SUM(S43:V43) -> -50000000 | X43: =-Assumptions!$D$82/4/VLOOKUP(Assumptions!$D$7, Lists!$B$7:$C$10, 2, FALSE) -> -12500000 | Y43: =-Assumptions!$D$82/4/VLOOKUP(Assumptions!$D$7, Lists!$B$7:$C$10, 2, FALSE) -> -12500000 | Z43: =-Assumptions!$D$82/4/VLOOKUP(Assumptions!$D$7, Lists!$B$7:$C$10, 2, FALSE) -> -12500000 | AA43: =-Assumptions!$D$82/4/VLOOKUP(Assumptions!$D$7, Lists!$B$7:$C$10, 2, FALSE) -> -12500000 | AB43: =SUM(X43:AA43) -> -50000000 | AC43: =-Assumptions!$D$82/4/VLOOKUP(Assumptions!$D$7, Lists!$B$7:$C$10, 2, FALSE) -> -12500000 | AD43: =-Assumptions!$D$82/4/VLOOKUP(Assumptions!$D$7, Lists!$B$7:$C$10, 2, FALSE) -> -12500000 | AE43: =-Assumptions!$D$82/4/VLOOKUP(Assumptions!$D$7, Lists!$B$7:$C$10, 2, FALSE) -> -12500000 | AF43: =-Assumptions!$D$82/4/VLOOKUP(Assumptions!$D$7, Lists!$B$7:$C$10, 2, FALSE) -> -12500000 | AG43: =SUM(AC43:AF43) -> -50000000 | AH43: =-Assumptions!$D$82/4/VLOOKUP(Assumptions!$D$7, Lists!$B$7:$C$10, 2, FALSE) -> -12500000 | AI43: =-Assumptions!$D$82/4/VLOOKUP(Assumptions!$D$7, Lists!$B$7:$C$10, 2, FALSE) -> -12500000 | AJ43: =-Assumptions!$D$82/4/VLOOKUP(Assumptions!$D$7, Lists!$B$7:$C$10, 2, FALSE) -> -12500000 | AK43: =-Assumptions!$D$82/4/VLOOKUP(Assumptions!$D$7, Lists!$B$7:$C$10, 2, FALSE) -> -12500000 | AL43: =SUM(AH43:AK43) -> -50000000
B44: Other operating expenses | D44: =SUM(D38:D43) -> -1.2496778e+08 | E44: =SUM(E38:E43) -> -108076125 | F44: =SUM(F38:F43) -> -95555031 | G44: =SUM(G38:G43) -> -83019500 | H44: =SUM(D44:G44) -> -4.1161844e+08 | I44: =SUM(I38:I43) -> -70469531 | J44: =SUM(J38:J43) -> -57905125 | K44: =SUM(K38:K43) -> -45326281 | L44: =SUM(L38:L43) -> -39853000 | M44: =SUM(I44:L44) -> -2.1355394e+08 | N44: =SUM(N38:N43) -> -42260281 | O44: =SUM(O38:O43) -> -44653125 | P44: =SUM(P38:P43) -> -47031531 | Q44: =SUM(Q38:Q43) -> -49395500 | R44: =SUM(N44:Q44) -> -1.8334044e+08 | S44: =SUM(S38:S43) -> -51745031 | T44: =SUM(T38:T43) -> -54080125 | U44: =SUM(U38:U43) -> -56400781 | V44: =SUM(V38:V43) -> -58707000 | W44: =SUM(S44:V44) -> -2.2093294e+08 | X44: =SUM(X38:X43) -> -60998781 | Y44: =SUM(Y38:Y43) -> -63276125 | Z44: =SUM(Z38:Z43) -> -65539031 | AA44: =SUM(AA38:AA43) -> -67787500 | AB44: =SUM(X44:AA44) -> -2.5760144e+08 | AC44: =SUM(AC38:AC43) -> -61443125 | AD44: =SUM(AD38:AD43) -> -59923750 | AE44: =SUM(AE38:AE43) -> -59779375 | AF44: =SUM(AF38:AF43) -> -59635000 | AG44: =SUM(AC44:AF44) -> -240781250 | AH44: =SUM(AH38:AH43) -> -59490625 | AI44: =SUM(AI38:AI43) -> -59346250 | AJ44: =SUM(AJ38:AJ43) -> -59201875 | AK44: =SUM(AK38:AK43) -> -59057500 | AL44: =SUM(AH44:AK44) -> -237096250
A45: EARNINGS BEFORE TAX | D45: =D28+D33+D37+D44 -> -84440721 | E45: =E28+E33+E37+E44 -> -37794354 | F45: =F28+F33+F37+F44 -> 4019848.4 | G45: =G28+G33+G37+G44 -> 44256528 | H45: =SUM(D45:G45) -> -73958699 | I45: =I28+I33+I37+I44 -> 85051398 | J45: =J28+J33+J37+J44 -> 1.255241e+08 | K45: =K28+K33+K37+K44 -> 1.6593e+08 | L45: =L28+L33+L37+L44 -> 1.9876873e+08 | M45: =SUM(I45:L45) -> 5.7527423e+08 | N45: =N28+N33+N37+N44 -> 2.2288494e+08 | O45: =O28+O33+O37+O44 -> 2.4693434e+08 | P45: =P28+P33+P37+P44 -> 2.7003122e+08 | Q45: =Q28+Q33+Q37+Q44 -> 2.9318628e+08 | R45: =SUM(N45:Q45) -> 1.0330368e+09 | S45: =S28+S33+S37+S44 -> 3.1627454e+08 | T45: =T28+T33+T37+T44 -> 3.3853528e+08 | U45: =U28+U33+U37+U44 -> 3.6034885e+08 | V45: =V28+V33+V37+V44 -> 3.8171526e+08 | W45: =SUM(S45:V45) -> 1.3968739e+09 | X45: =X28+X33+X37+X44 -> 4.0301486e+08 | Y45: =Y28+Y33+Y37+Y44 -> 4.2499765e+08 | Z45: =Z28+Z33+Z37+Z44 -> 4.4540291e+08 | AA45: =AA28+AA33+AA37+AA44 -> 4.6498066e+08 | AB45: =SUM(X45:AA45) -> 1.7383961e+09 | AC45: =AC28+AC33+AC37+AC44 -> 4.4487745e+08 | AD45: =AD28+AD33+AD37+AD44 -> 4.4453437e+08 | AE45: =AE28+AE33+AE37+AE44 -> 4.4044307e+08 | AF45: =AF28+AF33+AF37+AF44 -> 4.3597141e+08 | AG45: =SUM(AC45:AF45) -> 1.7658263e+09 | AH45: =AH28+AH33+AH37+AH44 -> 4.3339083e+08 | AI45: =AI28+AI33+AI37+AI44 -> 4.2929953e+08 | AJ45: =AJ28+AJ33+AJ37+AJ44 -> 4.2482787e+08 | AK45: =AK28+AK33+AK37+AK44 -> 4.2124193e+08 | AL45: =SUM(AH45:AK45) -> 1.7087602e+09
C46: Corporate tax | H46: =SUM(D46:G46) -> 0 | M46: =SUM(I46:L46) -> 0 | R46: =SUM(N46:Q46) -> 0 | W46: =SUM(S46:V46) -> 0 | AB46: =SUM(X46:AA46) -> 0 | AG46: =SUM(AC46:AF46) -> 0 | AL46: =SUM(AH46:AK46) -> 0
B47: Corporate tax | H47: =IF(H45>0,H45*-Assumptions!$D$62,0) -> 0 | M47: =M45*-Assumptions!$D$62 -> -57527423 | R47: =R45*-Assumptions!$D$62 -> -1.0330368e+08 | W47: =W45*-Assumptions!$D$62 -> -1.3968739e+08 | AB47: =AB45*-Assumptions!$D$62 -> -1.7383961e+08 | AG47: =AG45*-Assumptions!$D$62 -> -1.7658263e+08 | AL47: =AL45*-Assumptions!$D$62 -> -1.7087602e+08
A48: NET INCOME | H48: =H45+H47 -> -73958699 | M48: =M45+M47 -> 5.1774681e+08 | R48: =R45+R47 -> 9.297331e+08 | W48: =W45+W47 -> 1.2571865e+09 | AB48: =AB45+AB47 -> 1.5645565e+09 | AG48: =AG45+AG47 -> 1.5892437e+09 | AL48: =AL45+AL47 -> 1.5378841e+09
A49: ACCUMULATED GAINS FROM BUSINESS UNIT | H49: =H48 -> -73958699 | M49: =H49+M48 -> 4.4378811e+08 | R49: =M49+R48 -> 1.3735212e+09 | W49: =R49+W48 -> 2.6307078e+09 | AB49: =W49+AB48 -> 4.1952642e+09 | AG49: =AB49+AG48 -> 5.7845079e+09 | AL49: =AG49+AL48 -> 7.322392e+09
A51: CASH FLOW STATEMENT | D51: Q1 Y1 | E51: Q2 Y1 | F51: Q3 Y1 | G51: Q4 Y1 | H51: Y1 | I51: Q1 Y2 | J51: Q2 Y2 | K51: Q3 Y2 | L51: Q4 Y2 | M51: Y2 | N51: Q1 Y3 | O51: Q2 Y3 | P51: Q3 Y3 | Q51: Q4 Y3 | R51: Y3 | S51: Q1 Y4 | T51: Q2 Y4 | U51: Q3 Y4 | V51: Q4 Y4 | W51: Y4 | X51: Q1 Y5 | Y51: Q2 Y5 | Z51: Q3 Y5 | AA51: Q4 Y5 | AB51: Y5 | AC51: Q1 Y6 | AD51: Q2 Y6 | AE51: Q3 Y6 | AF51: Q4 Y6 | AG51: Y6 | AH51: Q1 Y7 | AI51: Q2 Y7 | AJ51: Q3 Y7 | AK51: Q4 Y7 | AL51: Y7
B52: NET INTEREST INCOME | D52: =D12 -> 15916148 | E52: =E12 -> 31632094 | F52: =F12 -> 47147836 | G52: =G12 -> 62463375 | H52: =SUM(D52:G52) -> 1.5715945e+08 | I52: =I12 -> 77578711 | J52: =J12 -> 92493844 | K52: =K12 -> 1.0720877e+08 | L52: =L12 -> 121723500 | M52: =SUM(I52:L52) -> 3.9900483e+08 | N52: =N12 -> 1.3603802e+08 | O52: =O12 -> 1.5015234e+08 | P52: =P12 -> 1.6406646e+08 | Q52: =Q12 -> 1.7778038e+08 | R52: =SUM(N52:Q52) -> 6.280372e+08 | S52: =S12 -> 1.9129409e+08 | T52: =T12 -> 2.0460759e+08 | U52: =U12 -> 2.177209e+08 | V52: =V12 -> 230634000 | W52: =SUM(S52:V52) -> 8.4425658e+08 | X52: =X12 -> 2.433469e+08 | Y52: =Y12 -> 2.5585959e+08 | Z52: =Z12 -> 2.6817209e+08 | AA52: =AA12 -> 280284375 | AB52: =SUM(X52:AA52) -> 1.047663e+09 | AC52: =AC12 -> 2.7828234e+08 | AD52: =AD12 -> 2.7628031e+08 | AE52: =AE12 -> 2.7427828e+08 | AF52: =AF12 -> 272276250 | AG52: =SUM(AC52:AF52) -> 1.1011172e+09 | AH52: =AH12 -> 2.7027422e+08 | AI52: =AI12 -> 2.6827219e+08 | AJ52: =AJ12 -> 2.6627016e+08 | AK52: =AK12 -> 264268125 | AL52: =SUM(AH52:AK52) -> 1.0690847e+09
B53: NET FEE INCOME | D53: =D18 -> 33827995 | E53: =E18 -> 42183012 | F53: =F18 -> 50427583 | G53: =G18 -> 58561706 | H53: =SUM(D53:G53) -> 1.850003e+08 | I53: =I18 -> 66585383 | J53: =J18 -> 74498612 | K53: =K18 -> 82301395 | L53: =L18 -> 89993731 | M53: =SUM(I53:L53) -> 3.1337912e+08 | N53: =N18 -> 97575620 | O53: =O18 -> 1.0504706e+08 | P53: =P18 -> 1.1240806e+08 | Q53: =Q18 -> 1.1965861e+08 | R53: =SUM(N53:Q53) -> 4.3468935e+08 | S53: =S18 -> 1.2679871e+08 | T53: =T18 -> 1.3382836e+08 | U53: =U18 -> 1.4074757e+08 | V53: =V18 -> 1.4755633e+08 | W53: =SUM(S53:V53) -> 5.4893097e+08 | X53: =X18 -> 1.5425465e+08 | Y53: =Y18 -> 1.6084251e+08 | Z53: =Z18 -> 1.6731993e+08 | AA53: =AA18 -> 1.7368691e+08 | AB53: =SUM(X53:AA53) -> 6.56104e+08 | AC53: =AC18 -> 1.5037053e+08 | AD53: =AD18 -> 1.4926606e+08 | AE53: =AE18 -> 1.4816159e+08 | AF53: =AF18 -> 147057125 | AG53: =SUM(AC53:AF53) -> 5.9485531e+08 | AH53: =AH18 -> 1.4595266e+08 | AI53: =AI18 -> 1.4484819e+08 | AJ53: =AJ18 -> 1.4374372e+08 | AK53: =AK18 -> 142639250 | AL53: =SUM(AH53:AK53) -> 5.7718381e+08
B54: NON-FINANCIAL INCOME | D54: =D23 -> 1988906.2 | E54: =E23 -> 7655625 | F54: =F23 -> 13250156 | G54: =G23 -> 18772500 | H54: =SUM(D54:G54) -> 41667188 | I54: =I23 -> 24222656 | J54: =J23 -> 29600625 | K54: =K23 -> 34906406 | L54: =L23 -> 40140000 | M54: =SUM(I54:L54) -> 1.2886969e+08 | N54: =N23 -> 45301406 | O54: =O23 -> 50390625 | P54: =P23 -> 55407656 | Q54: =Q23 -> 60352500 | R54: =SUM(N54:Q54) -> 2.1145219e+08 | S54: =S23 -> 65225156 | T54: =T23 -> 70025625 | U54: =U23 -> 74753906 | V54: =V23 -> 79410000 | W54: =SUM(S54:V54) -> 2.8941469e+08 | X54: =X23 -> 83993906 | Y54: =Y23 -> 88505625 | Z54: =Z23 -> 92945156 | AA54: =AA23 -> 97312500 | AB54: =SUM(X54:AA54) -> 3.6275719e+08 | AC54: =AC23 -> 96590625 | AD54: =AD23 -> 95868750 | AE54: =AE23 -> 95146875 | AF54: =AF23 -> 94425000 | AG54: =SUM(AC54:AF54) -> 382031250 | AH54: =AH23 -> 93703125 | AI54: =AI23 -> 92981250 | AJ54: =AJ23 -> 92259375 | AK54: =AK23 -> 91537500 | AL54: =SUM(AH54:AK54) -> 370481250
B55: WRITE-DOWN OF NON-PERFORMING LOANS | D55: =D27 -> -6261867.2 | E55: =E27 -> -12444969 | F55: =F27 -> -18549305 | G55: =G27 -> -24574875 | H55: =SUM(D55:G55) -> -61831016 | I55: =I27 -> -30521680 | J55: =J27 -> -36389719 | K55: =K27 -> -42178992 | L55: =L27 -> -47889500 | M55: =SUM(I55:L55) -> -1.5697989e+08 | N55: =N27 -> -53521242 | O55: =O27 -> -59074219 | P55: =P27 -> -64548430 | Q55: =Q27 -> -69943875 | R55: =SUM(N55:Q55) -> -2.4708777e+08 | S55: =S27 -> -75260555 | T55: =T27 -> -80498469 | U55: =U27 -> -85657617 | V55: =V27 -> -90738000 | W55: =SUM(S55:V55) -> -3.3215464e+08 | X55: =X27 -> -95739617 | Y55: =Y27 -> -1.0066247e+08 | Z55: =Z27 -> -1.0550655e+08 | AA55: =AA27 -> -110271875 | AB55: =SUM(X55:AA55) -> -4.1218052e+08 | AC55: =AC27 -> -1.0948422e+08 | AD55: =AD27 -> -1.0869656e+08 | AE55: =AE27 -> -1.0790891e+08 | AF55: =AF27 -> -107121250 | AG55: =SUM(AC55:AF55) -> -4.3321094e+08 | AH55: =AH27 -> -1.0633359e+08 | AI55: =AI27 -> -1.0554594e+08 | AJ55: =AJ27 -> -1.0475828e+08 | AK55: =AK27 -> -103970625 | AL55: =SUM(AH55:AK55) -> -4.2060844e+08
B56: EMPLOYEE COMPENSATION | D56: =D33 -> -7750000 | E56: =E33 -> -13500000 | F56: =F33 -> -19250000 | G56: =G33 -> -26125000 | H56: =SUM(D56:G56) -> -66625000 | I56: =I33 -> -32000000 | J56: =J33 -> -37750000 | K56: =K33 -> -43125000 | L56: =L33 -> -48500000 | M56: =SUM(I56:L56) -> -161375000 | N56: =N33 -> -54250000 | O56: =O33 -> -59625000 | P56: =P33 -> -65500000 | Q56: =Q33 -> -70875000 | R56: =SUM(N56:Q56) -> -250250000 | S56: =S33 -> -75875000 | T56: =T33 -> -81250000 | U56: =U33 -> -86625000 | V56: =V33 -> -92000000 | W56: =SUM(S56:V56) -> -335750000 | X56: =X33 -> -97000000 | Y56: =Y33 -> -100875000 | Z56: =Z33 -> -105875000 | AA56: =AA33 -> -111250000 | AB56: =SUM(X56:AA56) -> -415000000 | AC56: =AC33 -> -110875000 | AD56: =AD33 -> -108500000 | AE56: =AE33 -> -108125000 | AF56: =AF33 -> -108125000 | AG56: =SUM(AC56:AF56) -> -435625000 | AH56: =AH33 -> -106250000 | AI56: =AI33 -> -105875000 | AJ56: =AJ33 -> -105875000 | AK56: =AK33 -> -105000000 | AL56: =SUM(AH56:AK56) -> -423000000
B57: OPERATING EXPENSES | D57: =D44 -> -1.2496778e+08 | E57: =E44 -> -108076125 | F57: =F44 -> -95555031 | G57: =G44 -> -83019500 | H57: =SUM(D57:G57) -> -4.1161844e+08 | I57: =I44 -> -70469531 | J57: =J44 -> -57905125 | K57: =K44 -> -45326281 | L57: =L44 -> -39853000 | M57: =SUM(I57:L57) -> -2.1355394e+08 | N57: =N44 -> -42260281 | O57: =O44 -> -44653125 | P57: =P44 -> -47031531 | Q57: =Q44 -> -49395500 | R57: =SUM(N57:Q57) -> -1.8334044e+08 | S57: =S44 -> -51745031 | T57: =T44 -> -54080125 | U57: =U44 -> -56400781 | V57: =V44 -> -58707000 | W57: =SUM(S57:V57) -> -2.2093294e+08 | X57: =X44 -> -60998781 | Y57: =Y44 -> -63276125 | Z57: =Z44 -> -65539031 | AA57: =AA44 -> -67787500 | AB57: =SUM(X57:AA57) -> -2.5760144e+08 | AC57: =AC44 -> -61443125 | AD57: =AD44 -> -59923750 | AE57: =AE44 -> -59779375 | AF57: =AF44 -> -59635000 | AG57: =SUM(AC57:AF57) -> -240781250 | AH57: =AH44 -> -59490625 | AI57: =AI44 -> -59346250 | AJ57: =AJ44 -> -59201875 | AK57: =AK44 -> -59057500 | AL57: =SUM(AH57:AK57) -> -237096250
B58: CAPITAL EXPENDITURES | D58: =(SUM(D87:D90)*-Assumptions!$D$80+D86*-Assumptions!$D$79+-Assumptions!$D$81)/VLOOKUP(Assumptions!$D$7, Lists!$B$7:$C$10, 2, FALSE) -> -272100000 | E58: =((SUM(E87:E90)-SUM(D87:D90))*-Assumptions!$D$80+(E86-D86)*-Assumptions!$D$79)/VLOOKUP(Assumptions!$D$7, Lists!$B$7:$C$10, 2, FALSE) -> -11650000 | F58: =((SUM(F87:F90)-SUM(E87:E90))*-Assumptions!$D$80+(F86-E86)*-Assumptions!$D$79)/VLOOKUP(Assumptions!$D$7, Lists!$B$7:$C$10, 2, FALSE) -> -11650000 | G58: =((SUM(G87:G90)-SUM(F87:F90))*-Assumptions!$D$80+(G86-F86)*-Assumptions!$D$79)/VLOOKUP(Assumptions!$D$7, Lists!$B$7:$C$10, 2, FALSE) -> -11800000 | H58: =SUM(D58:G58) -> -307200000 | I58: =((SUM(I87:I90)-SUM(G87:G90))*-Assumptions!$D$80+(I86-G86)*-Assumptions!$D$79)/VLOOKUP(Assumptions!$D$7, Lists!$B$7:$C$10, 2, FALSE) -> -11650000 | J58: =((SUM(J87:J90)-SUM(I87:I90))*-Assumptions!$D$80+(J86-I86)*-Assumptions!$D$79)/VLOOKUP(Assumptions!$D$7, Lists!$B$7:$C$10, 2, FALSE) -> -11650000 | K58: =((SUM(K87:K90)-SUM(J87:J90))*-Assumptions!$D$80+(K86-J86)*-Assumptions!$D$79)/VLOOKUP(Assumptions!$D$7, Lists!$B$7:$C$10, 2, FALSE) -> -11500000 | L58: =((SUM(L87:L90)-SUM(K87:K90))*-Assumptions!$D$80+(L86-K86)*-Assumptions!$D$79)/VLOOKUP(Assumptions!$D$7, Lists!$B$7:$C$10, 2, FALSE) -> -11500000 | M58: =SUM(I58:L58) -> -46300000 | N58: =((SUM(N87:N90)-SUM(L87:L90))*-Assumptions!$D$80+(N86-L86)*-Assumptions!$D$79)/VLOOKUP(Assumptions!$D$7, Lists!$B$7:$C$10, 2, FALSE) -> -11650000 | O58: =((SUM(O87:O90)-SUM(N87:N90))*-Assumptions!$D$80+(O86-N86)*-Assumptions!$D$79)/VLOOKUP(Assumptions!$D$7, Lists!$B$7:$C$10, 2, FALSE) -> -11500000 | P58: =((SUM(P87:P90)-SUM(O87:O90))*-Assumptions!$D$80+(P86-O86)*-Assumptions!$D$79)/VLOOKUP(Assumptions!$D$7, Lists!$B$7:$C$10, 2, FALSE) -> -11650000 | Q58: =((SUM(Q87:Q90)-SUM(P87:P90))*-Assumptions!$D$80+(Q86-P86)*-Assumptions!$D$79)/VLOOKUP(Assumptions!$D$7, Lists!$B$7:$C$10, 2, FALSE) -> -11500000 | R58: =SUM(N58:Q58) -> -46300000 | S58: =((SUM(S87:S90)-SUM(Q87:Q90))*-Assumptions!$D$80+(S86-Q86)*-Assumptions!$D$79)/VLOOKUP(Assumptions!$D$7, Lists!$B$7:$C$10, 2, FALSE) -> -11350000 | T58: =((SUM(T87:T90)-SUM(S87:S90))*-Assumptions!$D$80+(T86-S86)*-Assumptions!$D$79)/VLOOKUP(Assumptions!$D$7, Lists!$B$7:$C$10, 2, FALSE) -> -11500000 | U58: =((SUM(U87:U90)-SUM(T87:T90))*-Assumptions!$D$80+(U86-T86)*-Assumptions!$D$79)/VLOOKUP(Assumptions!$D$7, Lists!$B$7:$C$10, 2, FALSE) -> -11500000 | V58: =((SUM(V87:V90)-SUM(U87:U90))*-Assumptions!$D$80+(V86-U86)*-Assumptions!$D$79)/VLOOKUP(Assumptions!$D$7, Lists!$B$7:$C$10, 2, FALSE) -> -11500000 | W58: =SUM(S58:V58) -> -45850000 | X58: =((SUM(X87:X90)-SUM(V87:V90))*-Assumptions!$D$80+(X86-V86)*-Assumptions!$D$79)/VLOOKUP(Assumptions!$D$7, Lists!$B$7:$C$10, 2, FALSE) -> -11350000 | Y58: =((SUM(Y87:Y90)-SUM(X87:X90))*-Assumptions!$D$80+(Y86-X86)*-Assumptions!$D$79)/VLOOKUP(Assumptions!$D$7, Lists!$B$7:$C$10, 2, FALSE) -> -11200000 | Z58: =((SUM(Z87:Z90)-SUM(Y87:Y90))*-Assumptions!$D$80+(Z86-Y86)*-Assumptions!$D$79)/VLOOKUP(Assumptions!$D$7, Lists!$B$7:$C$10, 2, FALSE) -> -11350000 | AA58: =((SUM(AA87:AA90)-SUM(Z87:Z90))*-Assumptions!$D$80+(AA86-Z86)*-Assumptions!$D$79)/VLOOKUP(Assumptions!$D$7, Lists!$B$7:$C$10, 2, FALSE) -> -11500000 | AB58: =SUM(X58:AA58) -> -45400000 | AC58: =((SUM(AC87:AC90)-SUM(AA87:AA90))*-Assumptions!$D$80+(AC86-AA86)*-Assumptions!$D$79)/VLOOKUP(Assumptions!$D$7, Lists!$B$7:$C$10, 2, FALSE) -> 150000 | AD58: =((SUM(AD87:AD90)-SUM(AC87:AC90))*-Assumptions!$D$80+(AD86-AC86)*-Assumptions!$D$79)/VLOOKUP(Assumptions!$D$7, Lists!$B$7:$C$10, 2, FALSE) -> 10600000 | AE58: =((SUM(AE87:AE90)-SUM(AD87:AD90))*-Assumptions!$D$80+(AE86-AD86)*-Assumptions!$D$79)/VLOOKUP(Assumptions!$D$7, Lists!$B$7:$C$10, 2, FALSE) -> 150000 | AF58: =((SUM(AF87:AF90)-SUM(AE87:AE90))*-Assumptions!$D$80+(AF86-AE86)*-Assumptions!$D$79)/VLOOKUP(Assumptions!$D$7, Lists!$B$7:$C$10, 2, FALSE) -> 0 | AG58: =SUM(AC58:AF58) -> 10900000 | AH58: =((SUM(AH87:AH90)-SUM(AF87:AF90))*-Assumptions!$D$80+(AH86-AF86)*-Assumptions!$D$79)/VLOOKUP(Assumptions!$D$7, Lists!$B$7:$C$10, 2, FALSE) -> 450000 | AI58: =((SUM(AI87:AI90)-SUM(AH87:AH90))*-Assumptions!$D$80+(AI86-AH86)*-Assumptions!$D$79)/VLOOKUP(Assumptions!$D$7, Lists!$B$7:$C$10, 2, FALSE) -> 150000 | AJ58: =((SUM(AJ87:AJ90)-SUM(AI87:AI90))*-Assumptions!$D$80+(AJ86-AI86)*-Assumptions!$D$79)/VLOOKUP(Assumptions!$D$7, Lists!$B$7:$C$10, 2, FALSE) -> 0 | AK58: =((SUM(AK87:AK90)-SUM(AJ87:AJ90))*-Assumptions!$D$80+(AK86-AJ86)*-Assumptions!$D$79)/VLOOKUP(Assumptions!$D$7, Lists!$B$7:$C$10, 2, FALSE) -> 300000 | AL58: =SUM(AH58:AK58) -> 900000
B59: CORPORATE TAX | H59: =SUM(D59:G59) -> 0 | I59: =-H47 -> 0 | M59: =SUM(I59:L59) -> 0 | N59: =-M47 -> 57527423 | R59: =SUM(N59:Q59) -> 57527423 | S59: =-R47 -> 1.0330368e+08 | W59: =SUM(S59:V59) -> 1.0330368e+08 | X59: =-W47 -> 1.3968739e+08 | AB59: =SUM(X59:AA59) -> 1.3968739e+08 | AC59: =-AB47 -> 1.7383961e+08 | AG59: =SUM(AC59:AF59) -> 1.7383961e+08 | AH59: =-AG47 -> 1.7658263e+08 | AL59: =SUM(AH59:AK59) -> 1.7658263e+08
A60: FREE CASH FLOW | D60: =SUM(D52:D59) -> -3.593466e+08 | E60: =SUM(E52:E59) -> -64200362 | F60: =SUM(F52:F59) -> -34178761 | G60: =SUM(G52:G59) -> -5721793.8 | H60: =SUM(D60:G60) -> -4.6344752e+08 | I60: =SUM(I52:I59) -> 23745539 | J60: =SUM(J52:J59) -> 52898238 | K60: =SUM(K52:K59) -> 82286302 | L60: =SUM(L52:L59) -> 1.0411473e+08 | M60: =SUM(I60:L60) -> 2.6304481e+08 | N60: =SUM(N52:N59) -> 1.7476095e+08 | O60: =SUM(O52:O59) -> 1.3073769e+08 | P60: =SUM(P52:P59) -> 1.4315221e+08 | Q60: =SUM(Q52:Q59) -> 1.5607711e+08 | R60: =SUM(N60:Q60) -> 6.0472796e+08 | S60: =SUM(S52:S59) -> 2.7239104e+08 | T60: =SUM(T52:T59) -> 1.8113299e+08 | U60: =SUM(U52:U59) -> 1.9303898e+08 | V60: =SUM(V52:V59) -> 2.0465533e+08 | W60: =SUM(S60:V60) -> 8.5121834e+08 | X60: =SUM(X52:X59) -> 3.5619445e+08 | Y60: =SUM(Y52:Y59) -> 2.2919414e+08 | Z60: =SUM(Z52:Z59) -> 2.4016659e+08 | AA60: =SUM(AA52:AA59) -> 2.5047441e+08 | AB60: =SUM(X60:AA60) -> 1.0760296e+09 | AC60: =SUM(AC52:AC59) -> 4.1743076e+08 | AD60: =SUM(AD52:AD59) -> 2.5489481e+08 | AE60: =SUM(AE52:AE59) -> 2.4192347e+08 | AF60: =SUM(AF52:AF59) -> 238877125 | AG60: =SUM(AC60:AF60) -> 1.1531262e+09 | AH60: =SUM(AH52:AH59) -> 4.1488841e+08 | AI60: =SUM(AI52:AI59) -> 2.3548444e+08 | AJ60: =SUM(AJ52:AJ59) -> 2.3243809e+08 | AK60: =SUM(AK52:AK59) -> 230716750 | AL60: =SUM(AH60:AK60) -> 1.1135277e+09
A61: ACCUMULATED CASH FLOW | D61: =D60 -> -3.593466e+08 | E61: =D61+E60 -> -4.2354696e+08 | F61: =E61+F60 -> -4.5772572e+08 | G61: =F61+G60 -> -4.6344752e+08 | H61: =G61 -> -4.6344752e+08 | I61: =G61+I60 -> -4.3970198e+08 | J61: =I61+J60 -> -3.8680374e+08 | K61: =J61+K60 -> -3.0451744e+08 | L61: =K61+L60 -> -2.0040271e+08 | M61: =L61 -> -2.0040271e+08 | N61: =L61+N60 -> -25641756 | O61: =N61+O60 -> 1.0509593e+08 | P61: =O61+P60 -> 2.4824815e+08 | Q61: =P61+Q60 -> 4.0432525e+08 | R61: =Q61 -> 4.0432525e+08 | S61: =Q61+S60 -> 6.7671629e+08 | T61: =S61+T60 -> 8.5784928e+08 | U61: =T61+U60 -> 1.0508883e+09 | V61: =U61+V60 -> 1.2555436e+09 | W61: =V61 -> 1.2555436e+09 | X61: =V61+X60 -> 1.611738e+09 | Y61: =X61+Y60 -> 1.8409322e+09 | Z61: =Y61+Z60 -> 2.0810988e+09 | AA61: =Z61+AA60 -> 2.3315732e+09 | AB61: =AA61 -> 2.3315732e+09 | AC61: =AA61+AC60 -> 2.7490039e+09 | AD61: =AC61+AD60 -> 3.0038987e+09 | AE61: =AD61+AE60 -> 3.2458222e+09 | AF61: =AE61+AF60 -> 3.4846993e+09 | AG61: =AF61 -> 3.4846993e+09 | AH61: =AF61+AH60 -> 3.8995877e+09 | AI61: =AH61+AI60 -> 4.1350722e+09 | AJ61: =AI61+AJ60 -> 4.3675103e+09 | AK61: =AJ61+AK60 -> 4.598227e+09 | AL61: =AK61 -> 4.598227e+09
A63: OTHER INFORMATION | D63: Q1 Y1 | E63: Q2 Y1 | F63: Q3 Y1 | G63: Q4 Y1 | H63: Y1 | I63: Q1 Y2 | J63: Q2 Y2 | K63: Q3 Y2 | L63: Q4 Y2 | M63: Y2 | N63: Q1 Y3 | O63: Q2 Y3 | P63: Q3 Y3 | Q63: Q4 Y3 | R63: Y3 | S63: Q1 Y4 | T63: Q2 Y4 | U63: Q3 Y4 | V63: Q4 Y4 | W63: Y4 | X63: Q1 Y5 | Y63: Q2 Y5 | Z63: Q3 Y5 | AA63: Q4 Y5 | AB63: Y5 | AC63: Q1 Y6 | AD63: Q2 Y6 | AE63: Q3 Y6 | AF63: Q4 Y6 | AG63: Y6 | AH63: Q1 Y7 | AI63: Q2 Y7 | AJ63: Q3 Y7 | AK63: Q4 Y7 | AL63: Y7
C64: Share of medium sector | D64: =IFERROR(D72/(_xlfn.XLOOKUP(Assumptions!$D$5, 'Baseline Headcount Estimates'!$B$13:$B$180, 'Baseline Headcount Estimates'!$R$13:$R$180, "")*1000), "N/A") -> 0.0034927718 | E64: =IFERROR(E72/(_xlfn.XLOOKUP(Assumptions!$D$5, 'Baseline Headcount Estimates'!$B$13:$B$180, 'Baseline Headcount Estimates'!$R$13:$R$180, "")*1000), "N/A") -> 0.0069416095 | F64: =IFERROR(F72/(_xlfn.XLOOKUP(Assumptions!$D$5, 'Baseline Headcount Estimates'!$B$13:$B$180, 'Baseline Headcount Estimates'!$R$13:$R$180, "")*1000), "N/A") -> 0.010346513 | G64: =IFERROR(G72/(_xlfn.XLOOKUP(Assumptions!$D$5, 'Baseline Headcount Estimates'!$B$13:$B$180, 'Baseline Headcount Estimates'!$R$13:$R$180, "")*1000), "N/A") -> 0.013707482 | H64: =G64 -> 0.013707482 | I64: =IFERROR(I72/(_xlfn.XLOOKUP(Assumptions!$D$5, 'Baseline Headcount Estimates'!$B$13:$B$180, 'Baseline Headcount Estimates'!$R$13:$R$180, "")*1000), "N/A") -> 0.017024517 | J64: =IFERROR(J72/(_xlfn.XLOOKUP(Assumptions!$D$5, 'Baseline Headcount Estimates'!$B$13:$B$180, 'Baseline Headcount Estimates'!$R$13:$R$180, "")*1000), "N/A") -> 0.020297618 | K64: =IFERROR(K72/(_xlfn.XLOOKUP(Assumptions!$D$5, 'Baseline Headcount Estimates'!$B$13:$B$180, 'Baseline Headcount Estimates'!$R$13:$R$180, "")*1000), "N/A") -> 0.023526784 | L64: =IFERROR(L72/(_xlfn.XLOOKUP(Assumptions!$D$5, 'Baseline Headcount Estimates'!$B$13:$B$180, 'Baseline Headcount Estimates'!$R$13:$R$180, "")*1000), "N/A") -> 0.026712016 | M64: =L64 -> 0.026712016 | N64: =IFERROR(N72/(_xlfn.XLOOKUP(Assumptions!$D$5, 'Baseline Headcount Estimates'!$B$13:$B$180, 'Baseline Headcount Estimates'!$R$13:$R$180, "")*1000), "N/A") -> 0.029853314 | O64: =IFERROR(O72/(_xlfn.XLOOKUP(Assumptions!$D$5, 'Baseline Headcount Estimates'!$B$13:$B$180, 'Baseline Headcount Estimates'!$R$13:$R$180, "")*1000), "N/A") -> 0.032950678 | P64: =IFERROR(P72/(_xlfn.XLOOKUP(Assumptions!$D$5, 'Baseline Headcount Estimates'!$B$13:$B$180, 'Baseline Headcount Estimates'!$R$13:$R$180, "")*1000), "N/A") -> 0.036004107 | Q64: =IFERROR(Q72/(_xlfn.XLOOKUP(Assumptions!$D$5, 'Baseline Headcount Estimates'!$B$13:$B$180, 'Baseline Headcount Estimates'!$R$13:$R$180, "")*1000), "N/A") -> 0.039013603 | R64: =Q64 -> 0.039013603 | S64: =IFERROR(S72/(_xlfn.XLOOKUP(Assumptions!$D$5, 'Baseline Headcount Estimates'!$B$13:$B$180, 'Baseline Headcount Estimates'!$R$13:$R$180, "")*1000), "N/A") -> 0.041979164 | T64: =IFERROR(T72/(_xlfn.XLOOKUP(Assumptions!$D$5, 'Baseline Headcount Estimates'!$B$13:$B$180, 'Baseline Headcount Estimates'!$R$13:$R$180, "")*1000), "N/A") -> 0.04490079 | U64: =IFERROR(U72/(_xlfn.XLOOKUP(Assumptions!$D$5, 'Baseline Headcount Estimates'!$B$13:$B$180, 'Baseline Headcount Estimates'!$R$13:$R$180, "")*1000), "N/A") -> 0.047778483 | V64: =IFERROR(V72/(_xlfn.XLOOKUP(Assumptions!$D$5, 'Baseline Headcount Estimates'!$B$13:$B$180, 'Baseline Headcount Estimates'!$R$13:$R$180, "")*1000), "N/A") -> 0.050612241 | W64: =V64 -> 0.050612241 | X64: =IFERROR(X72/(_xlfn.XLOOKUP(Assumptions!$D$5, 'Baseline Headcount Estimates'!$B$13:$B$180, 'Baseline Headcount Estimates'!$R$13:$R$180, "")*1000), "N/A") -> 0.053402065 | Y64: =IFERROR(Y72/(_xlfn.XLOOKUP(Assumptions!$D$5, 'Baseline Headcount Estimates'!$B$13:$B$180, 'Baseline Headcount Estimates'!$R$13:$R$180, "")*1000), "N/A") -> 0.056147955 | Z64: =IFERROR(Z72/(_xlfn.XLOOKUP(Assumptions!$D$5, 'Baseline Headcount Estimates'!$B$13:$B$180, 'Baseline Headcount Estimates'!$R$13:$R$180, "")*1000), "N/A") -> 0.058849911 | AA64: =IFERROR(AA72/(_xlfn.XLOOKUP(Assumptions!$D$5, 'Baseline Headcount Estimates'!$B$13:$B$180, 'Baseline Headcount Estimates'!$R$13:$R$180, "")*1000), "N/A") -> 0.061507932 | AB64: =AA64 -> 0.061507932 | AC64: =IFERROR(AC72/(_xlfn.XLOOKUP(Assumptions!$D$5, 'Baseline Headcount Estimates'!$B$13:$B$180, 'Baseline Headcount Estimates'!$R$13:$R$180, "")*1000), "N/A") -> 0.06106859 | AD64: =IFERROR(AD72/(_xlfn.XLOOKUP(Assumptions!$D$5, 'Baseline Headcount Estimates'!$B$13:$B$180, 'Baseline Headcount Estimates'!$R$13:$R$180, "")*1000), "N/A") -> 0.060629247 | AE64: =IFERROR(AE72/(_xlfn.XLOOKUP(Assumptions!$D$5, 'Baseline Headcount Estimates'!$B$13:$B$180, 'Baseline Headcount Estimates'!$R$13:$R$180, "")*1000), "N/A") -> 0.060189905 | AF64: =IFERROR(AF72/(_xlfn.XLOOKUP(Assumptions!$D$5, 'Baseline Headcount Estimates'!$B$13:$B$180, 'Baseline Headcount Estimates'!$R$13:$R$180, "")*1000), "N/A") -> 0.059750562 | AG64: =AF64 -> 0.059750562 | AH64: =IFERROR(AH72/(_xlfn.XLOOKUP(Assumptions!$D$5, 'Baseline Headcount Estimates'!$B$13:$B$180, 'Baseline Headcount Estimates'!$R$13:$R$180, "")*1000), "N/A") -> 0.05931122 | AI64: =IFERROR(AI72/(_xlfn.XLOOKUP(Assumptions!$D$5, 'Baseline Headcount Estimates'!$B$13:$B$180, 'Baseline Headcount Estimates'!$R$13:$R$180, "")*1000), "N/A") -> 0.058871878 | AJ64: =IFERROR(AJ72/(_xlfn.XLOOKUP(Assumptions!$D$5, 'Baseline Headcount Estimates'!$B$13:$B$180, 'Baseline Headcount Estimates'!$R$13:$R$180, "")*1000), "N/A") -> 0.058432535 | AK64: =IFERROR(AK72/(_xlfn.XLOOKUP(Assumptions!$D$5, 'Baseline Headcount Estimates'!$B$13:$B$180, 'Baseline Headcount Estimates'!$R$13:$R$180, "")*1000), "N/A") -> 0.057993193 | AL64: =AK64 -> 0.057993193
C65: Share of small sector | D65: =IFERROR(D73/(_xlfn.XLOOKUP(Assumptions!$D$5, 'Baseline Headcount Estimates'!$B$13:$B$180, 'Baseline Headcount Estimates'!$Q$13:$Q$180, "")*1000), "N/A") -> 0.0059714715 | E65: =IFERROR(E73/(_xlfn.XLOOKUP(Assumptions!$D$5, 'Baseline Headcount Estimates'!$B$13:$B$180, 'Baseline Headcount Estimates'!$Q$13:$Q$180, "")*1000), "N/A") -> 0.01186783 | F65: =IFERROR(F73/(_xlfn.XLOOKUP(Assumptions!$D$5, 'Baseline Headcount Estimates'!$B$13:$B$180, 'Baseline Headcount Estimates'!$Q$13:$Q$180, "")*1000), "N/A") -> 0.017689076 | G65: =IFERROR(G73/(_xlfn.XLOOKUP(Assumptions!$D$5, 'Baseline Headcount Estimates'!$B$13:$B$180, 'Baseline Headcount Estimates'!$Q$13:$Q$180, "")*1000), "N/A") -> 0.023435209 | H65: =G65 -> 0.023435209 | I65: =IFERROR(I73/(_xlfn.XLOOKUP(Assumptions!$D$5, 'Baseline Headcount Estimates'!$B$13:$B$180, 'Baseline Headcount Estimates'!$Q$13:$Q$180, "")*1000), "N/A") -> 0.029106229 | J65: =IFERROR(J73/(_xlfn.XLOOKUP(Assumptions!$D$5, 'Baseline Headcount Estimates'!$B$13:$B$180, 'Baseline Headcount Estimates'!$Q$13:$Q$180, "")*1000), "N/A") -> 0.034702136 | K65: =IFERROR(K73/(_xlfn.XLOOKUP(Assumptions!$D$5, 'Baseline Headcount Estimates'!$B$13:$B$180, 'Baseline Headcount Estimates'!$Q$13:$Q$180, "")*1000), "N/A") -> 0.040222931 | L65: =IFERROR(L73/(_xlfn.XLOOKUP(Assumptions!$D$5, 'Baseline Headcount Estimates'!$B$13:$B$180, 'Baseline Headcount Estimates'!$Q$13:$Q$180, "")*1000), "N/A") -> 0.045668612 | M65: =L65 -> 0.045668612 | N65: =IFERROR(N73/(_xlfn.XLOOKUP(Assumptions!$D$5, 'Baseline Headcount Estimates'!$B$13:$B$180, 'Baseline Headcount Estimates'!$Q$13:$Q$180, "")*1000), "N/A") -> 0.051039181 | O65: =IFERROR(O73/(_xlfn.XLOOKUP(Assumptions!$D$5, 'Baseline Headcount Estimates'!$B$13:$B$180, 'Baseline Headcount Estimates'!$Q$13:$Q$180, "")*1000), "N/A") -> 0.056334637 | P65: =IFERROR(P73/(_xlfn.XLOOKUP(Assumptions!$D$5, 'Baseline Headcount Estimates'!$B$13:$B$180, 'Baseline Headcount Estimates'!$Q$13:$Q$180, "")*1000), "N/A") -> 0.06155498 | Q65: =IFERROR(Q73/(_xlfn.XLOOKUP(Assumptions!$D$5, 'Baseline Headcount Estimates'!$B$13:$B$180, 'Baseline Headcount Estimates'!$Q$13:$Q$180, "")*1000), "N/A") -> 0.06670021 | R65: =Q65 -> 0.06670021 | S65: =IFERROR(S73/(_xlfn.XLOOKUP(Assumptions!$D$5, 'Baseline Headcount Estimates'!$B$13:$B$180, 'Baseline Headcount Estimates'!$Q$13:$Q$180, "")*1000), "N/A") -> 0.071770327 | T65: =IFERROR(T73/(_xlfn.XLOOKUP(Assumptions!$D$5, 'Baseline Headcount Estimates'!$B$13:$B$180, 'Baseline Headcount Estimates'!$Q$13:$Q$180, "")*1000), "N/A") -> 0.076765332 | U65: =IFERROR(U73/(_xlfn.XLOOKUP(Assumptions!$D$5, 'Baseline Headcount Estimates'!$B$13:$B$180, 'Baseline Headcount Estimates'!$Q$13:$Q$180, "")*1000), "N/A") -> 0.081685224 | V65: =IFERROR(V73/(_xlfn.XLOOKUP(Assumptions!$D$5, 'Baseline Headcount Estimates'!$B$13:$B$180, 'Baseline Headcount Estimates'!$Q$13:$Q$180, "")*1000), "N/A") -> 0.086530002 | W65: =V65 -> 0.086530002 | X65: =IFERROR(X73/(_xlfn.XLOOKUP(Assumptions!$D$5, 'Baseline Headcount Estimates'!$B$13:$B$180, 'Baseline Headcount Estimates'!$Q$13:$Q$180, "")*1000), "N/A") -> 0.091299668 | Y65: =IFERROR(Y73/(_xlfn.XLOOKUP(Assumptions!$D$5, 'Baseline Headcount Estimates'!$B$13:$B$180, 'Baseline Headcount Estimates'!$Q$13:$Q$180, "")*1000), "N/A") -> 0.095994221 | Z65: =IFERROR(Z73/(_xlfn.XLOOKUP(Assumptions!$D$5, 'Baseline Headcount Estimates'!$B$13:$B$180, 'Baseline Headcount Estimates'!$Q$13:$Q$180, "")*1000), "N/A") -> 0.10061366 | AA65: =IFERROR(AA73/(_xlfn.XLOOKUP(Assumptions!$D$5, 'Baseline Headcount Estimates'!$B$13:$B$180, 'Baseline Headcount Estimates'!$Q$13:$Q$180, "")*1000), "N/A") -> 0.10515799 | AB65: =AA65 -> 0.10515799 | AC65: =IFERROR(AC73/(_xlfn.XLOOKUP(Assumptions!$D$5, 'Baseline Headcount Estimates'!$B$13:$B$180, 'Baseline Headcount Estimates'!$Q$13:$Q$180, "")*1000), "N/A") -> 0.10440686 | AD65: =IFERROR(AD73/(_xlfn.XLOOKUP(Assumptions!$D$5, 'Baseline Headcount Estimates'!$B$13:$B$180, 'Baseline Headcount Estimates'!$Q$13:$Q$180, "")*1000), "N/A") -> 0.10365573 | AE65: =IFERROR(AE73/(_xlfn.XLOOKUP(Assumptions!$D$5, 'Baseline Headcount Estimates'!$B$13:$B$180, 'Baseline Headcount Estimates'!$Q$13:$Q$180, "")*1000), "N/A") -> 0.1029046 | AF65: =IFERROR(AF73/(_xlfn.XLOOKUP(Assumptions!$D$5, 'Baseline Headcount Estimates'!$B$13:$B$180, 'Baseline Headcount Estimates'!$Q$13:$Q$180, "")*1000), "N/A") -> 0.10215347 | AG65: =AF65 -> 0.10215347 | AH65: =IFERROR(AH73/(_xlfn.XLOOKUP(Assumptions!$D$5, 'Baseline Headcount Estimates'!$B$13:$B$180, 'Baseline Headcount Estimates'!$Q$13:$Q$180, "")*1000), "N/A") -> 0.10140235 | AI65: =IFERROR(AI73/(_xlfn.XLOOKUP(Assumptions!$D$5, 'Baseline Headcount Estimates'!$B$13:$B$180, 'Baseline Headcount Estimates'!$Q$13:$Q$180, "")*1000), "N/A") -> 0.10065122 | AJ65: =IFERROR(AJ73/(_xlfn.XLOOKUP(Assumptions!$D$5, 'Baseline Headcount Estimates'!$B$13:$B$180, 'Baseline Headcount Estimates'!$Q$13:$Q$180, "")*1000), "N/A") -> 0.099900089 | AK65: =IFERROR(AK73/(_xlfn.XLOOKUP(Assumptions!$D$5, 'Baseline Headcount Estimates'!$B$13:$B$180, 'Baseline Headcount Estimates'!$Q$13:$Q$180, "")*1000), "N/A") -> 0.099148961 | AL65: =AK65 -> 0.099148961
C66: Share of very small sector | D66: =IFERROR(D74/(_xlfn.XLOOKUP(Assumptions!$D$5, 'Baseline Headcount Estimates'!$B$13:$B$180, 'Baseline Headcount Estimates'!$P$13:$P$180, "")*1000), "N/A") -> 0.009818102 | E66: =IFERROR(E74/(_xlfn.XLOOKUP(Assumptions!$D$5, 'Baseline Headcount Estimates'!$B$13:$B$180, 'Baseline Headcount Estimates'!$P$13:$P$180, "")*1000), "N/A") -> 0.019512706 | F66: =IFERROR(F74/(_xlfn.XLOOKUP(Assumptions!$D$5, 'Baseline Headcount Estimates'!$B$13:$B$180, 'Baseline Headcount Estimates'!$P$13:$P$180, "")*1000), "N/A") -> 0.029083812 | G66: =IFERROR(G74/(_xlfn.XLOOKUP(Assumptions!$D$5, 'Baseline Headcount Estimates'!$B$13:$B$180, 'Baseline Headcount Estimates'!$P$13:$P$180, "")*1000), "N/A") -> 0.038531419 | H66: =G66 -> 0.038531419 | I66: =IFERROR(I74/(_xlfn.XLOOKUP(Assumptions!$D$5, 'Baseline Headcount Estimates'!$B$13:$B$180, 'Baseline Headcount Estimates'!$P$13:$P$180, "")*1000), "N/A") -> 0.047855529 | J66: =IFERROR(J74/(_xlfn.XLOOKUP(Assumptions!$D$5, 'Baseline Headcount Estimates'!$B$13:$B$180, 'Baseline Headcount Estimates'!$P$13:$P$180, "")*1000), "N/A") -> 0.05705614 | K66: =IFERROR(K74/(_xlfn.XLOOKUP(Assumptions!$D$5, 'Baseline Headcount Estimates'!$B$13:$B$180, 'Baseline Headcount Estimates'!$P$13:$P$180, "")*1000), "N/A") -> 0.066133253 | L66: =IFERROR(L74/(_xlfn.XLOOKUP(Assumptions!$D$5, 'Baseline Headcount Estimates'!$B$13:$B$180, 'Baseline Headcount Estimates'!$P$13:$P$180, "")*1000), "N/A") -> 0.075086868 | M66: =L66 -> 0.075086868 | N66: =IFERROR(N74/(_xlfn.XLOOKUP(Assumptions!$D$5, 'Baseline Headcount Estimates'!$B$13:$B$180, 'Baseline Headcount Estimates'!$P$13:$P$180, "")*1000), "N/A") -> 0.083916985 | O66: =IFERROR(O74/(_xlfn.XLOOKUP(Assumptions!$D$5, 'Baseline Headcount Estimates'!$B$13:$B$180, 'Baseline Headcount Estimates'!$P$13:$P$180, "")*1000), "N/A") -> 0.092623604 | P66: =IFERROR(P74/(_xlfn.XLOOKUP(Assumptions!$D$5, 'Baseline Headcount Estimates'!$B$13:$B$180, 'Baseline Headcount Estimates'!$P$13:$P$180, "")*1000), "N/A") -> 0.10120672 | Q66: =IFERROR(Q74/(_xlfn.XLOOKUP(Assumptions!$D$5, 'Baseline Headcount Estimates'!$B$13:$B$180, 'Baseline Headcount Estimates'!$P$13:$P$180, "")*1000), "N/A") -> 0.10966635 | R66: =Q66 -> 0.10966635 | S66: =IFERROR(S74/(_xlfn.XLOOKUP(Assumptions!$D$5, 'Baseline Headcount Estimates'!$B$13:$B$180, 'Baseline Headcount Estimates'!$P$13:$P$180, "")*1000), "N/A") -> 0.11800247 | T66: =IFERROR(T74/(_xlfn.XLOOKUP(Assumptions!$D$5, 'Baseline Headcount Estimates'!$B$13:$B$180, 'Baseline Headcount Estimates'!$P$13:$P$180, "")*1000), "N/A") -> 0.1262151 | U66: =IFERROR(U74/(_xlfn.XLOOKUP(Assumptions!$D$5, 'Baseline Headcount Estimates'!$B$13:$B$180, 'Baseline Headcount Estimates'!$P$13:$P$180, "")*1000), "N/A") -> 0.13430423 | V66: =IFERROR(V74/(_xlfn.XLOOKUP(Assumptions!$D$5, 'Baseline Headcount Estimates'!$B$13:$B$180, 'Baseline Headcount Estimates'!$P$13:$P$180, "")*1000), "N/A") -> 0.14226986 | W66: =V66 -> 0.14226986 | X66: =IFERROR(X74/(_xlfn.XLOOKUP(Assumptions!$D$5, 'Baseline Headcount Estimates'!$B$13:$B$180, 'Baseline Headcount Estimates'!$P$13:$P$180, "")*1000), "N/A") -> 0.15011199 | Y66: =IFERROR(Y74/(_xlfn.XLOOKUP(Assumptions!$D$5, 'Baseline Headcount Estimates'!$B$13:$B$180, 'Baseline Headcount Estimates'!$P$13:$P$180, "")*1000), "N/A") -> 0.15783062 | Z66: =IFERROR(Z74/(_xlfn.XLOOKUP(Assumptions!$D$5, 'Baseline Headcount Estimates'!$B$13:$B$180, 'Baseline Headcount Estimates'!$P$13:$P$180, "")*1000), "N/A") -> 0.16542576 | AA66: =IFERROR(AA74/(_xlfn.XLOOKUP(Assumptions!$D$5, 'Baseline Headcount Estimates'!$B$13:$B$180, 'Baseline Headcount Estimates'!$P$13:$P$180, "")*1000), "N/A") -> 0.17289739 | AB66: =AA66 -> 0.17289739 | AC66: =IFERROR(AC74/(_xlfn.XLOOKUP(Assumptions!$D$5, 'Baseline Headcount Estimates'!$B$13:$B$180, 'Baseline Headcount Estimates'!$P$13:$P$180, "")*1000), "N/A") -> 0.17166241 | AD66: =IFERROR(AD74/(_xlfn.XLOOKUP(Assumptions!$D$5, 'Baseline Headcount Estimates'!$B$13:$B$180, 'Baseline Headcount Estimates'!$P$13:$P$180, "")*1000), "N/A") -> 0.17042743 | AE66: =IFERROR(AE74/(_xlfn.XLOOKUP(Assumptions!$D$5, 'Baseline Headcount Estimates'!$B$13:$B$180, 'Baseline Headcount Estimates'!$P$13:$P$180, "")*1000), "N/A") -> 0.16919245 | AF66: =IFERROR(AF74/(_xlfn.XLOOKUP(Assumptions!$D$5, 'Baseline Headcount Estimates'!$B$13:$B$180, 'Baseline Headcount Estimates'!$P$13:$P$180, "")*1000), "N/A") -> 0.16795747 | AG66: =AF66 -> 0.16795747 | AH66: =IFERROR(AH74/(_xlfn.XLOOKUP(Assumptions!$D$5, 'Baseline Headcount Estimates'!$B$13:$B$180, 'Baseline Headcount Estimates'!$P$13:$P$180, "")*1000), "N/A") -> 0.16672249 | AI66: =IFERROR(AI74/(_xlfn.XLOOKUP(Assumptions!$D$5, 'Baseline Headcount Estimates'!$B$13:$B$180, 'Baseline Headcount Estimates'!$P$13:$P$180, "")*1000), "N/A") -> 0.16548751 | AJ66: =IFERROR(AJ74/(_xlfn.XLOOKUP(Assumptions!$D$5, 'Baseline Headcount Estimates'!$B$13:$B$180, 'Baseline Headcount Estimates'!$P$13:$P$180, "")*1000), "N/A") -> 0.16425252 | AK66: =IFERROR(AK74/(_xlfn.XLOOKUP(Assumptions!$D$5, 'Baseline Headcount Estimates'!$B$13:$B$180, 'Baseline Headcount Estimates'!$P$13:$P$180, "")*1000), "N/A") -> 0.16301754 | AL66: =AK66 -> 0.16301754
C67: Share of micro and self employed sector | D67: =IFERROR(D75/(_xlfn.XLOOKUP(Assumptions!$D$5, 'Baseline Headcount Estimates'!$B$13:$B$180, 'Baseline Headcount Estimates'!$O$13:$O$180, "")*1000), "N/A") -> 0.0094418131 | E67: =IFERROR(E75/(_xlfn.XLOOKUP(Assumptions!$D$5, 'Baseline Headcount Estimates'!$B$13:$B$180, 'Baseline Headcount Estimates'!$O$13:$O$180, "")*1000), "N/A") -> 0.018764861 | F67: =IFERROR(F75/(_xlfn.XLOOKUP(Assumptions!$D$5, 'Baseline Headcount Estimates'!$B$13:$B$180, 'Baseline Headcount Estimates'!$O$13:$O$180, "")*1000), "N/A") -> 0.027969144 | G67: =IFERROR(G75/(_xlfn.XLOOKUP(Assumptions!$D$5, 'Baseline Headcount Estimates'!$B$13:$B$180, 'Baseline Headcount Estimates'!$O$13:$O$180, "")*1000), "N/A") -> 0.037054663 | H67: =G67 -> 0.037054663 | I67: =IFERROR(I75/(_xlfn.XLOOKUP(Assumptions!$D$5, 'Baseline Headcount Estimates'!$B$13:$B$180, 'Baseline Headcount Estimates'!$O$13:$O$180, "")*1000), "N/A") -> 0.046021416 | J67: =IFERROR(J75/(_xlfn.XLOOKUP(Assumptions!$D$5, 'Baseline Headcount Estimates'!$B$13:$B$180, 'Baseline Headcount Estimates'!$O$13:$O$180, "")*1000), "N/A") -> 0.054869404 | K67: =IFERROR(K75/(_xlfn.XLOOKUP(Assumptions!$D$5, 'Baseline Headcount Estimates'!$B$13:$B$180, 'Baseline Headcount Estimates'!$O$13:$O$180, "")*1000), "N/A") -> 0.063598628 | L67: =IFERROR(L75/(_xlfn.XLOOKUP(Assumptions!$D$5, 'Baseline Headcount Estimates'!$B$13:$B$180, 'Baseline Headcount Estimates'!$O$13:$O$180, "")*1000), "N/A") -> 0.072209086 | M67: =L67 -> 0.072209086 | N67: =IFERROR(N75/(_xlfn.XLOOKUP(Assumptions!$D$5, 'Baseline Headcount Estimates'!$B$13:$B$180, 'Baseline Headcount Estimates'!$O$13:$O$180, "")*1000), "N/A") -> 0.08070078 | O67: =IFERROR(O75/(_xlfn.XLOOKUP(Assumptions!$D$5, 'Baseline Headcount Estimates'!$B$13:$B$180, 'Baseline Headcount Estimates'!$O$13:$O$180, "")*1000), "N/A") -> 0.089073708 | P67: =IFERROR(P75/(_xlfn.XLOOKUP(Assumptions!$D$5, 'Baseline Headcount Estimates'!$B$13:$B$180, 'Baseline Headcount Estimates'!$O$13:$O$180, "")*1000), "N/A") -> 0.097327872 | Q67: =IFERROR(Q75/(_xlfn.XLOOKUP(Assumptions!$D$5, 'Baseline Headcount Estimates'!$B$13:$B$180, 'Baseline Headcount Estimates'!$O$13:$O$180, "")*1000), "N/A") -> 0.10546327 | R67: =Q67 -> 0.10546327 | S67: =IFERROR(S75/(_xlfn.XLOOKUP(Assumptions!$D$5, 'Baseline Headcount Estimates'!$B$13:$B$180, 'Baseline Headcount Estimates'!$O$13:$O$180, "")*1000), "N/A") -> 0.1134799 | T67: =IFERROR(T75/(_xlfn.XLOOKUP(Assumptions!$D$5, 'Baseline Headcount Estimates'!$B$13:$B$180, 'Baseline Headcount Estimates'!$O$13:$O$180, "")*1000), "N/A") -> 0.12137777 | U67: =IFERROR(U75/(_xlfn.XLOOKUP(Assumptions!$D$5, 'Baseline Headcount Estimates'!$B$13:$B$180, 'Baseline Headcount Estimates'!$O$13:$O$180, "")*1000), "N/A") -> 0.12915688 | V67: =IFERROR(V75/(_xlfn.XLOOKUP(Assumptions!$D$5, 'Baseline Headcount Estimates'!$B$13:$B$180, 'Baseline Headcount Estimates'!$O$13:$O$180, "")*1000), "N/A") -> 0.13681722 | W67: =V67 -> 0.13681722 | X67: =IFERROR(X75/(_xlfn.XLOOKUP(Assumptions!$D$5, 'Baseline Headcount Estimates'!$B$13:$B$180, 'Baseline Headcount Estimates'!$O$13:$O$180, "")*1000), "N/A") -> 0.14435879 | Y67: =IFERROR(Y75/(_xlfn.XLOOKUP(Assumptions!$D$5, 'Baseline Headcount Estimates'!$B$13:$B$180, 'Baseline Headcount Estimates'!$O$13:$O$180, "")*1000), "N/A") -> 0.1517816 | Z67: =IFERROR(Z75/(_xlfn.XLOOKUP(Assumptions!$D$5, 'Baseline Headcount Estimates'!$B$13:$B$180, 'Baseline Headcount Estimates'!$O$13:$O$180, "")*1000), "N/A") -> 0.15908564 | AA67: =IFERROR(AA75/(_xlfn.XLOOKUP(Assumptions!$D$5, 'Baseline Headcount Estimates'!$B$13:$B$180, 'Baseline Headcount Estimates'!$O$13:$O$180, "")*1000), "N/A") -> 0.16627092 | AB67: =AA67 -> 0.16627092 | AC67: =IFERROR(AC75/(_xlfn.XLOOKUP(Assumptions!$D$5, 'Baseline Headcount Estimates'!$B$13:$B$180, 'Baseline Headcount Estimates'!$O$13:$O$180, "")*1000), "N/A") -> 0.16508327 | AD67: =IFERROR(AD75/(_xlfn.XLOOKUP(Assumptions!$D$5, 'Baseline Headcount Estimates'!$B$13:$B$180, 'Baseline Headcount Estimates'!$O$13:$O$180, "")*1000), "N/A") -> 0.16389562 | AE67: =IFERROR(AE75/(_xlfn.XLOOKUP(Assumptions!$D$5, 'Baseline Headcount Estimates'!$B$13:$B$180, 'Baseline Headcount Estimates'!$O$13:$O$180, "")*1000), "N/A") -> 0.16270797 | AF67: =IFERROR(AF75/(_xlfn.XLOOKUP(Assumptions!$D$5, 'Baseline Headcount Estimates'!$B$13:$B$180, 'Baseline Headcount Estimates'!$O$13:$O$180, "")*1000), "N/A") -> 0.16152032 | AG67: =AF67 -> 0.16152032 | AH67: =IFERROR(AH75/(_xlfn.XLOOKUP(Assumptions!$D$5, 'Baseline Headcount Estimates'!$B$13:$B$180, 'Baseline Headcount Estimates'!$O$13:$O$180, "")*1000), "N/A") -> 0.16033267 | AI67: =IFERROR(AI75/(_xlfn.XLOOKUP(Assumptions!$D$5, 'Baseline Headcount Estimates'!$B$13:$B$180, 'Baseline Headcount Estimates'!$O$13:$O$180, "")*1000), "N/A") -> 0.15914503 | AJ67: =IFERROR(AJ75/(_xlfn.XLOOKUP(Assumptions!$D$5, 'Baseline Headcount Estimates'!$B$13:$B$180, 'Baseline Headcount Estimates'!$O$13:$O$180, "")*1000), "N/A") -> 0.15795738 | AK67: =IFERROR(AK75/(_xlfn.XLOOKUP(Assumptions!$D$5, 'Baseline Headcount Estimates'!$B$13:$B$180, 'Baseline Headcount Estimates'!$O$13:$O$180, "")*1000), "N/A") -> 0.15676973 | AL67: =AK67 -> 0.15676973
C68: Medium market captured (cummulative) | D68: =Assumptions!$D$12*(1/(Assumptions!$D$16*4)) -> 10 | E68: =D68+Assumptions!$D$12*(1/(Assumptions!$D$16*4)) -> 20 | F68: =E68+Assumptions!$D$12*(1/(Assumptions!$D$16*4)) -> 30 | G68: =F68+Assumptions!$D$12*(1/(Assumptions!$D$16*4)) -> 40 | H68: =G68 -> 40 | I68: =IF($H$68<Assumptions!$D$12,(H68+Assumptions!$D$12*(1/(Assumptions!$D$16*4))),$H$68) -> 50 | J68: =IF($H$68<Assumptions!$D$12,(I68+Assumptions!$D$12*(1/(Assumptions!$D$16*4))),$H$68) -> 60 | K68: =IF($H$68<Assumptions!$D$12,(J68+Assumptions!$D$12*(1/(Assumptions!$D$16*4))),$H$68) -> 70 | L68: =IF($H$68<Assumptions!$D$12,(K68+Assumptions!$D$12*(1/(Assumptions!$D$16*4))),$H$68) -> 80 | M68: =L68 -> 80 | N68: =IF($M$68<Assumptions!$D$12,(M68+Assumptions!$D$12*(1/(Assumptions!$D$16*4))),$M$68) -> 90 | O68: =IF($M$68<Assumptions!$D$12,(N68+Assumptions!$D$12*(1/(Assumptions!$D$16*4))),$M$68) -> 100 | P68: =IF($M$68<Assumptions!$D$12,(O68+Assumptions!$D$12*(1/(Assumptions!$D$16*4))),$M$68) -> 110 | Q68: =IF($M$68<Assumptions!$D$12,(P68+Assumptions!$D$12*(1/(Assumptions!$D$16*4))),$M$68) -> 120 | R68: =Q68 -> 120 | S68: =IF($R$68<Assumptions!$D$12,(R68+Assumptions!$D$12*(1/(Assumptions!$D$16*4))),$R$68) -> 130 | T68: =IF($R$68<Assumptions!$D$12,(S68+Assumptions!$D$12*(1/(Assumptions!$D$16*4))),$R$68) -> 140 | U68: =IF($R$68<Assumptions!$D$12,(T68+Assumptions!$D$12*(1/(Assumptions!$D$16*4))),$R$68) -> 150 | V68: =IF($R$68<Assumptions!$D$12,(U68+Assumptions!$D$12*(1/(Assumptions!$D$16*4))),$R$68) -> 160 | W68: =V68 -> 160 | X68: =IF($W$68<Assumptions!$D$12,(W68+Assumptions!$D$12*(1/(Assumptions!$D$16*4))),$W$68) -> 170 | Y68: =IF($W$68<Assumptions!$D$12,(X68+Assumptions!$D$12*(1/(Assumptions!$D$16*4))),$W$68) -> 180 | Z68: =IF($W$68<Assumptions!$D$12,(Y68+Assumptions!$D$12*(1/(Assumptions!$D$16*4))),$W$68) -> 190 | AA68: =IF($W$68<Assumptions!$D$12,(Z68+Assumptions!$D$12*(1/(Assumptions!$D$16*4))),$W$68) -> 200 | AB68: =AA68 -> 200 | AC68: =IF($AB$68<Assumptions!$D$12,(AB68+Assumptions!$D$12*(1/(Assumptions!$D$16*4))),$AB$68) -> 200 | AD68: =IF($AB$68<Assumptions!$D$12,(AC68+Assumptions!$D$12*(1/(Assumptions!$D$16*4))),$AB$68) -> 200 | AE68: =IF($AB$68<Assumptions!$D$12,(AD68+Assumptions!$D$12*(1/(Assumptions!$D$16*4))),$AB$68) -> 200 | AF68: =IF($AB$68<Assumptions!$D$12,(AE68+Assumptions!$D$12*(1/(Assumptions!$D$16*4))),$AB$68) -> 200 | AG68: =AF68 -> 200 | AH68: =IF($AB$68<Assumptions!$D$12,(AG68+Assumptions!$D$12*(1/(Assumptions!$D$16*4))),$AB$68) -> 200 | AI68: =IF($AB$68<Assumptions!$D$12,(AH68+Assumptions!$D$12*(1/(Assumptions!$D$16*4))),$AB$68) -> 200 | AJ68: =IF($AB$68<Assumptions!$D$12,(AI68+Assumptions!$D$12*(1/(Assumptions!$D$16*4))),$AB$68) -> 200 | AK68: =IF($AB$68<Assumptions!$D$12,(AJ68+Assumptions!$D$12*(1/(Assumptions!$D$16*4))),$AB$68) -> 200 | AL68: =AK68 -> 200
C69: Small market captured (cummulative) | D69: =Assumptions!$D$13*(1/(Assumptions!$D$16*4)) -> 50 | E69: =D69+Assumptions!$D$13*(1/(Assumptions!$D$16*4)) -> 100 | F69: =E69+Assumptions!$D$13*(1/(Assumptions!$D$16*4)) -> 150 | G69: =F69+Assumptions!$D$13*(1/(Assumptions!$D$16*4)) -> 200 | H69: =G69 -> 200 | I69: =IF($H$69<Assumptions!$D$13,(H69+Assumptions!$D$13*(1/(Assumptions!$D$16*4))),$H$69) -> 250 | J69: =IF($H$69<Assumptions!$D$13,(I69+Assumptions!$D$13*(1/(Assumptions!$D$16*4))),$H$69) -> 300 | K69: =IF($H$69<Assumptions!$D$13,(J69+Assumptions!$D$13*(1/(Assumptions!$D$16*4))),$H$69) -> 350 | L69: =IF($H$69<Assumptions!$D$13,(K69+Assumptions!$D$13*(1/(Assumptions!$D$16*4))),$H$69) -> 400 | M69: =L69 -> 400 | N69: =IF($M$69<Assumptions!$D$13,(M69+Assumptions!$D$13*(1/(Assumptions!$D$16*4))),$M$69) -> 450 | O69: =IF($M$69<Assumptions!$D$13,(N69+Assumptions!$D$13*(1/(Assumptions!$D$16*4))),$M$69) -> 500 | P69: =IF($M$69<Assumptions!$D$13,(O69+Assumptions!$D$13*(1/(Assumptions!$D$16*4))),$M$69) -> 550 | Q69: =IF($M$69<Assumptions!$D$13,(P69+Assumptions!$D$13*(1/(Assumptions!$D$16*4))),$M$69) -> 600 | R69: =Q69 -> 600 | S69: =IF($R$69<Assumptions!$D$13,(R69+Assumptions!$D$13*(1/(Assumptions!$D$16*4))),$R$69) -> 650 | T69: =IF($R$69<Assumptions!$D$13,(S69+Assumptions!$D$13*(1/(Assumptions!$D$16*4))),$R$69) -> 700 | U69: =IF($R$69<Assumptions!$D$13,(T69+Assumptions!$D$13*(1/(Assumptions!$D$16*4))),$R$69) -> 750 | V69: =IF($R$69<Assumptions!$D$13,(U69+Assumptions!$D$13*(1/(Assumptions!$D$16*4))),$R$69) -> 800 | W69: =V69 -> 800 | X69: =IF($W$69<Assumptions!$D$13,(W69+Assumptions!$D$13*(1/(Assumptions!$D$16*4))),$W$69) -> 850 | Y69: =IF($W$69<Assumptions!$D$13,(X69+Assumptions!$D$13*(1/(Assumptions!$D$16*4))),$W$69) -> 900 | Z69: =IF($W$69<Assumptions!$D$13,(Y69+Assumptions!$D$13*(1/(Assumptions!$D$16*4))),$W$69) -> 950 | AA69: =IF($W$69<Assumptions!$D$13,(Z69+Assumptions!$D$13*(1/(Assumptions!$D$16*4))),$W$69) -> 1000 | AB69: =AA69 -> 1000 | AC69: =IF($AB$69<Assumptions!$D$13,(AB69+Assumptions!$D$13*(1/(Assumptions!$D$16*4))),$AB$69) -> 1000 | AD69: =IF($AB$69<Assumptions!$D$13,(AC69+Assumptions!$D$13*(1/(Assumptions!$D$16*4))),$AB$69) -> 1000 | AE69: =IF($AB$69<Assumptions!$D$13,(AD69+Assumptions!$D$13*(1/(Assumptions!$D$16*4))),$AB$69) -> 1000 | AF69: =IF($AB$69<Assumptions!$D$13,(AE69+Assumptions!$D$13*(1/(Assumptions!$D$16*4))),$AB$69) -> 1000 | AG69: =AF69 -> 1000 | AH69: =IF($AB$69<Assumptions!$D$13,(AG69+Assumptions!$D$13*(1/(Assumptions!$D$16*4))),$AB$69) -> 1000 | AI69: =IF($AB$69<Assumptions!$D$13,(AH69+Assumptions!$D$13*(1/(Assumptions!$D$16*4))),$AB$69) -> 1000 | AJ69: =IF($AB$69<Assumptions!$D$13,(AI69+Assumptions!$D$13*(1/(Assumptions!$D$16*4))),$AB$69) -> 1000 | AK69: =IF($AB$69<Assumptions!$D$13,(AJ69+Assumptions!$D$13*(1/(Assumptions!$D$16*4))),$AB$69) -> 1000 | AL69: =AK69 -> 1000
C70: Very small market captured (cummulative) | D70: =Assumptions!$D$14*(1/(Assumptions!$D$16*4)) -> 250 | E70: =D70+Assumptions!$D$14*(1/(Assumptions!$D$16*4)) -> 500 | F70: =E70+Assumptions!$D$14*(1/(Assumptions!$D$16*4)) -> 750 | G70: =F70+Assumptions!$D$14*(1/(Assumptions!$D$16*4)) -> 1000 | H70: =G70 -> 1000 | I70: =IF($H$70<Assumptions!$D$14,(H70+Assumptions!$D$14*(1/(Assumptions!$D$16*4))),$H$70) -> 1250 | J70: =IF($H$70<Assumptions!$D$14,(I70+Assumptions!$D$14*(1/(Assumptions!$D$16*4))),$H$70) -> 1500 | K70: =IF($H$70<Assumptions!$D$14,(J70+Assumptions!$D$14*(1/(Assumptions!$D$16*4))),$H$70) -> 1750 | L70: =IF($H$70<Assumptions!$D$14,(K70+Assumptions!$D$14*(1/(Assumptions!$D$16*4))),$H$70) -> 2000 | M70: =L70 -> 2000 | N70: =IF($M$70<Assumptions!$D$14,(M70+Assumptions!$D$14*(1/(Assumptions!$D$16*4))),$M$70) -> 2250 | O70: =IF($M$70<Assumptions!$D$14,(N70+Assumptions!$D$14*(1/(Assumptions!$D$16*4))),$M$70) -> 2500 | P70: =IF($M$70<Assumptions!$D$14,(O70+Assumptions!$D$14*(1/(Assumptions!$D$16*4))),$M$70) -> 2750 | Q70: =IF($M$70<Assumptions!$D$14,(P70+Assumptions!$D$14*(1/(Assumptions!$D$16*4))),$M$70) -> 3000 | R70: =Q70 -> 3000 | S70: =IF($R$70<Assumptions!$D$14,(R70+Assumptions!$D$14*(1/(Assumptions!$D$16*4))),$R$70) -> 3250 | T70: =IF($R$70<Assumptions!$D$14,(S70+Assumptions!$D$14*(1/(Assumptions!$D$16*4))),$R$70) -> 3500 | U70: =IF($R$70<Assumptions!$D$14,(T70+Assumptions!$D$14*(1/(Assumptions!$D$16*4))),$R$70) -> 3750 | V70: =IF($R$70<Assumptions!$D$14,(U70+Assumptions!$D$14*(1/(Assumptions!$D$16*4))),$R$70) -> 4000 | W70: =V70 -> 4000 | X70: =IF($W$70<Assumptions!$D$14,(W70+Assumptions!$D$14*(1/(Assumptions!$D$16*4))),$W$70) -> 4250 | Y70: =IF($W$70<Assumptions!$D$14,(X70+Assumptions!$D$14*(1/(Assumptions!$D$16*4))),$W$70) -> 4500 | Z70: =IF($W$70<Assumptions!$D$14,(Y70+Assumptions!$D$14*(1/(Assumptions!$D$16*4))),$W$70) -> 4750 | AA70: =IF($W$70<Assumptions!$D$14,(Z70+Assumptions!$D$14*(1/(Assumptions!$D$16*4))),$W$70) -> 5000 | AB70: =AA70 -> 5000 | AC70: =IF($AB$70<Assumptions!$D$14,(AB70+Assumptions!$D$14*(1/(Assumptions!$D$16*4))),$AB$70) -> 5000 | AD70: =IF($AB$70<Assumptions!$D$14,(AC70+Assumptions!$D$14*(1/(Assumptions!$D$16*4))),$AB$70) -> 5000 | AE70: =IF($AB$70<Assumptions!$D$14,(AD70+Assumptions!$D$14*(1/(Assumptions!$D$16*4))),$AB$70) -> 5000 | AF70: =IF($AB$70<Assumptions!$D$14,(AE70+Assumptions!$D$14*(1/(Assumptions!$D$16*4))),$AB$70) -> 5000 | AG70: =AF70 -> 5000 | AH70: =IF($AB$70<Assumptions!$D$14,(AG70+Assumptions!$D$14*(1/(Assumptions!$D$16*4))),$AB$70) -> 5000 | AI70: =IF($AB$70<Assumptions!$D$14,(AH70+Assumptions!$D$14*(1/(Assumptions!$D$16*4))),$AB$70) -> 5000 | AJ70: =IF($AB$70<Assumptions!$D$14,(AI70+Assumptions!$D$14*(1/(Assumptions!$D$16*4))),$AB$70) -> 5000 | AK70: =IF($AB$70<Assumptions!$D$14,(AJ70+Assumptions!$D$14*(1/(Assumptions!$D$16*4))),$AB$70) -> 5000 | AL70: =AK70 -> 5000
C71: Micro and self-employed market captured (cummulative) | D71: =Assumptions!$D$15*(1/(Assumptions!$D$16*4)) -> 2000 | E71: =D71+Assumptions!$D$15*(1/(Assumptions!$D$16*4)) -> 4000 | F71: =E71+Assumptions!$D$15*(1/(Assumptions!$D$16*4)) -> 6000 | G71: =F71+Assumptions!$D$15*(1/(Assumptions!$D$16*4)) -> 8000 | H71: =G71 -> 8000 | I71: =IF($H$71<Assumptions!$D$15,(H71+Assumptions!$D$15*(1/(Assumptions!$D$16*4))),$H$71) -> 10000 | J71: =IF($H$71<Assumptions!$D$15,(I71+Assumptions!$D$15*(1/(Assumptions!$D$16*4))),$H$71) -> 12000 | K71: =IF($H$71<Assumptions!$D$15,(J71+Assumptions!$D$15*(1/(Assumptions!$D$16*4))),$H$71) -> 14000 | L71: =IF($H$71<Assumptions!$D$15,(K71+Assumptions!$D$15*(1/(Assumptions!$D$16*4))),$H$71) -> 16000 | M71: =L71 -> 16000 | N71: =IF($M$71<Assumptions!$D$15,(M71+Assumptions!$D$15*(1/(Assumptions!$D$16*4))),$M$71) -> 18000 | O71: =IF($M$71<Assumptions!$D$15,(N71+Assumptions!$D$15*(1/(Assumptions!$D$16*4))),$M$71) -> 20000 | P71: =IF($M$71<Assumptions!$D$15,(O71+Assumptions!$D$15*(1/(Assumptions!$D$16*4))),$M$71) -> 22000 | Q71: =IF($M$71<Assumptions!$D$15,(P71+Assumptions!$D$15*(1/(Assumptions!$D$16*4))),$M$71) -> 24000 | R71: =Q71 -> 24000 | S71: =IF($R$71<Assumptions!$D$15,(R71+Assumptions!$D$15*(1/(Assumptions!$D$16*4))),$R$71) -> 26000 | T71: =IF($R$71<Assumptions!$D$15,(S71+Assumptions!$D$15*(1/(Assumptions!$D$16*4))),$R$71) -> 28000 | U71: =IF($R$71<Assumptions!$D$15,(T71+Assumptions!$D$15*(1/(Assumptions!$D$16*4))),$R$71) -> 30000 | V71: =IF($R$71<Assumptions!$D$15,(U71+Assumptions!$D$15*(1/(Assumptions!$D$16*4))),$R$71) -> 32000 | W71: =V71 -> 32000 | X71: =IF($W$71<Assumptions!$D$15,(W71+Assumptions!$D$15*(1/(Assumptions!$D$16*4))),$W$71) -> 34000 | Y71: =IF($W$71<Assumptions!$D$15,(X71+Assumptions!$D$15*(1/(Assumptions!$D$16*4))),$W$71) -> 36000 | Z71: =IF($W$71<Assumptions!$D$15,(Y71+Assumptions!$D$15*(1/(Assumptions!$D$16*4))),$W$71) -> 38000 | AA71: =IF($W$71<Assumptions!$D$15,(Z71+Assumptions!$D$15*(1/(Assumptions!$D$16*4))),$W$71) -> 40000 | AB71: =AA71 -> 40000 | AC71: =IF($AB$71<Assumptions!$D$15,(AB71+Assumptions!$D$15*(1/(Assumptions!$D$16*4))),$AB$71) -> 40000 | AD71: =IF($AB$71<Assumptions!$D$15,(AC71+Assumptions!$D$15*(1/(Assumptions!$D$16*4))),$AB$71) -> 40000 | AE71: =IF($AB$71<Assumptions!$D$15,(AD71+Assumptions!$D$15*(1/(Assumptions!$D$16*4))),$AB$71) -> 40000 | AF71: =IF($AB$71<Assumptions!$D$15,(AE71+Assumptions!$D$15*(1/(Assumptions!$D$16*4))),$AB$71) -> 40000 | AG71: =AF71 -> 40000 | AH71: =IF($AB$71<Assumptions!$D$15,(AG71+Assumptions!$D$15*(1/(Assumptions!$D$16*4))),$AB$71) -> 40000 | AI71: =IF($AB$71<Assumptions!$D$15,(AH71+Assumptions!$D$15*(1/(Assumptions!$D$16*4))),$AB$71) -> 40000 | AJ71: =IF($AB$71<Assumptions!$D$15,(AI71+Assumptions!$D$15*(1/(Assumptions!$D$16*4))),$AB$71) -> 40000 | AK71: =IF($AB$71<Assumptions!$D$15,(AJ71+Assumptions!$D$15*(1/(Assumptions!$D$16*4))),$AB$71) -> 40000 | AL71: =AK71 -> 40000
C72: Number of active medium clients | D72: =D68*(1-(Assumptions!$D$85/4)) -> 9.9375 | E72: =E68*(1-2*(Assumptions!$D$85/4)) -> 19.75 | F72: =F68*(1-3*(Assumptions!$D$85/4)) -> 29.4375 | G72: =G68*(1-4*(Assumptions!$D$85/4)) -> 39 | H72: =G72 -> 39 | I72: =I68*(1-5*(Assumptions!$D$85/4)) -> 48.4375 | J72: =J68*(1-6*(Assumptions!$D$85/4)) -> 57.75 | K72: =K68*(1-7*(Assumptions!$D$85/4)) -> 66.9375 | L72: =L68*(1-8*(Assumptions!$D$85/4)) -> 76 | M72: =L72 -> 76 | N72: =N68*(1-9*(Assumptions!$D$85/4)) -> 84.9375 | O72: =O68*(1-10*(Assumptions!$D$85/4)) -> 93.75 | P72: =P68*(1-11*(Assumptions!$D$85/4)) -> 102.4375 | Q72: =Q68*(1-12*(Assumptions!$D$85/4)) -> 111 | R72: =Q72 -> 111 | S72: =S68*(1-13*(Assumptions!$D$85/4)) -> 119.4375 | T72: =T68*(1-14*(Assumptions!$D$85/4)) -> 127.75 | U72: =U68*(1-15*(Assumptions!$D$85/4)) -> 135.9375 | V72: =V68*(1-16*(Assumptions!$D$85/4)) -> 144 | W72: =V72 -> 144 | X72: =X68*(1-17*(Assumptions!$D$85/4)) -> 151.9375 | Y72: =Y68*(1-18*(Assumptions!$D$85/4)) -> 159.75 | Z72: =Z68*(1-19*(Assumptions!$D$85/4)) -> 167.4375 | AA72: =AA68*(1-20*(Assumptions!$D$85/4)) -> 175 | AB72: =AA72 -> 175 | AC72: =AC68*(1-21*(Assumptions!$D$85/4)) -> 173.75 | AD72: =AD68*(1-22*(Assumptions!$D$85/4)) -> 172.5 | AE72: =AE68*(1-23*(Assumptions!$D$85/4)) -> 171.25 | AF72: =AF68*(1-24*(Assumptions!$D$85/4)) -> 170 | AG72: =AF72 -> 170 | AH72: =AH68*(1-25*(Assumptions!$D$85/4)) -> 168.75 | AI72: =AI68*(1-26*(Assumptions!$D$85/4)) -> 167.5 | AJ72: =AJ68*(1-27*(Assumptions!$D$85/4)) -> 166.25 | AK72: =AK68*(1-28*(Assumptions!$D$85/4)) -> 165 | AL72: =AK72 -> 165
C73: Number of active small clients | D73: =D69*(1-(Assumptions!$D$85/4)) -> 49.6875 | E73: =E69*(1-2*(Assumptions!$D$85/4)) -> 98.75 | F73: =F69*(1-3*(Assumptions!$D$85/4)) -> 147.1875 | G73: =G69*(1-4*(Assumptions!$D$85/4)) -> 195 | H73: =G73 -> 195 | I73: =I69*(1-5*(Assumptions!$D$85/4)) -> 242.1875 | J73: =J69*(1-6*(Assumptions!$D$85/4)) -> 288.75 | K73: =K69*(1-7*(Assumptions!$D$85/4)) -> 334.6875 | L73: =L69*(1-8*(Assumptions!$D$85/4)) -> 380 | M73: =L73 -> 380 | N73: =N69*(1-9*(Assumptions!$D$85/4)) -> 424.6875 | O73: =O69*(1-10*(Assumptions!$D$85/4)) -> 468.75 | P73: =P69*(1-11*(Assumptions!$D$85/4)) -> 512.1875 | Q73: =Q69*(1-12*(Assumptions!$D$85/4)) -> 555 | R73: =Q73 -> 555 | S73: =S69*(1-13*(Assumptions!$D$85/4)) -> 597.1875 | T73: =T69*(1-14*(Assumptions!$D$85/4)) -> 638.75 | U73: =U69*(1-15*(Assumptions!$D$85/4)) -> 679.6875 | V73: =V69*(1-16*(Assumptions!$D$85/4)) -> 720 | W73: =V73 -> 720 | X73: =X69*(1-17*(Assumptions!$D$85/4)) -> 759.6875 | Y73: =Y69*(1-18*(Assumptions!$D$85/4)) -> 798.75 | Z73: =Z69*(1-19*(Assumptions!$D$85/4)) -> 837.1875 | AA73: =AA69*(1-20*(Assumptions!$D$85/4)) -> 875 | AB73: =AA73 -> 875 | AC73: =AC69*(1-21*(Assumptions!$D$85/4)) -> 868.75 | AD73: =AD69*(1-22*(Assumptions!$D$85/4)) -> 862.5 | AE73: =AE69*(1-23*(Assumptions!$D$85/4)) -> 856.25 | AF73: =AF69*(1-24*(Assumptions!$D$85/4)) -> 850 | AG73: =AF73 -> 850 | AH73: =AH69*(1-25*(Assumptions!$D$85/4)) -> 843.75 | AI73: =AI69*(1-26*(Assumptions!$D$85/4)) -> 837.5 | AJ73: =AJ69*(1-27*(Assumptions!$D$85/4)) -> 831.25 | AK73: =AK69*(1-28*(Assumptions!$D$85/4)) -> 825 | AL73: =AK73 -> 825
C74: Number of active very small clients | D74: =D70*(1-(Assumptions!$D$85/4)) -> 248.4375 | E74: =E70*(1-2*(Assumptions!$D$85/4)) -> 493.75 | F74: =F70*(1-3*(Assumptions!$D$85/4)) -> 735.9375 | G74: =G70*(1-4*(Assumptions!$D$85/4)) -> 975 | H74: =G74 -> 975 | I74: =I70*(1-5*(Assumptions!$D$85/4)) -> 1210.9375 | J74: =J70*(1-6*(Assumptions!$D$85/4)) -> 1443.75 | K74: =K70*(1-7*(Assumptions!$D$85/4)) -> 1673.4375 | L74: =L70*(1-8*(Assumptions!$D$85/4)) -> 1900 | M74: =L74 -> 1900 | N74: =N70*(1-9*(Assumptions!$D$85/4)) -> 2123.4375 | O74: =O70*(1-10*(Assumptions!$D$85/4)) -> 2343.75 | P74: =P70*(1-11*(Assumptions!$D$85/4)) -> 2560.9375 | Q74: =Q70*(1-12*(Assumptions!$D$85/4)) -> 2775 | R74: =Q74 -> 2775 | S74: =S70*(1-13*(Assumptions!$D$85/4)) -> 2985.9375 | T74: =T70*(1-14*(Assumptions!$D$85/4)) -> 3193.75 | U74: =U70*(1-15*(Assumptions!$D$85/4)) -> 3398.4375 | V74: =V70*(1-16*(Assumptions!$D$85/4)) -> 3600 | W74: =V74 -> 3600 | X74: =X70*(1-17*(Assumptions!$D$85/4)) -> 3798.4375 | Y74: =Y70*(1-18*(Assumptions!$D$85/4)) -> 3993.75 | Z74: =Z70*(1-19*(Assumptions!$D$85/4)) -> 4185.9375 | AA74: =AA70*(1-20*(Assumptions!$D$85/4)) -> 4375 | AB74: =AA74 -> 4375 | AC74: =AC70*(1-21*(Assumptions!$D$85/4)) -> 4343.75 | AD74: =AD70*(1-22*(Assumptions!$D$85/4)) -> 4312.5 | AE74: =AE70*(1-23*(Assumptions!$D$85/4)) -> 4281.25 | AF74: =AF70*(1-24*(Assumptions!$D$85/4)) -> 4250 | AG74: =AF74 -> 4250 | AH74: =AH70*(1-25*(Assumptions!$D$85/4)) -> 4218.75 | AI74: =AI70*(1-26*(Assumptions!$D$85/4)) -> 4187.5 | AJ74: =AJ70*(1-27*(Assumptions!$D$85/4)) -> 4156.25 | AK74: =AK70*(1-28*(Assumptions!$D$85/4)) -> 4125 | AL74: =AK74 -> 4125
C75: Number of active micro and self-employed clients | D75: =D71*(1-(Assumptions!$D$85/4)) -> 1987.5 | E75: =E71*(1-2*(Assumptions!$D$85/4)) -> 3950 | F75: =F71*(1-3*(Assumptions!$D$85/4)) -> 5887.5 | G75: =G71*(1-4*(Assumptions!$D$85/4)) -> 7800 | H75: =G75 -> 7800 | I75: =I71*(1-5*(Assumptions!$D$85/4)) -> 9687.5 | J75: =J71*(1-6*(Assumptions!$D$85/4)) -> 11550 | K75: =K71*(1-7*(Assumptions!$D$85/4)) -> 13387.5 | L75: =L71*(1-8*(Assumptions!$D$85/4)) -> 15200 | M75: =L75 -> 15200 | N75: =N71*(1-9*(Assumptions!$D$85/4)) -> 16987.5 | O75: =O71*(1-10*(Assumptions!$D$85/4)) -> 18750 | P75: =P71*(1-11*(Assumptions!$D$85/4)) -> 20487.5 | Q75: =Q71*(1-12*(Assumptions!$D$85/4)) -> 22200 | R75: =Q75 -> 22200 | S75: =S71*(1-13*(Assumptions!$D$85/4)) -> 23887.5 | T75: =T71*(1-14*(Assumptions!$D$85/4)) -> 25550 | U75: =U71*(1-15*(Assumptions!$D$85/4)) -> 27187.5 | V75: =V71*(1-16*(Assumptions!$D$85/4)) -> 28800 | W75: =V75 -> 28800 | X75: =X71*(1-17*(Assumptions!$D$85/4)) -> 30387.5 | Y75: =Y71*(1-18*(Assumptions!$D$85/4)) -> 31950 | Z75: =Z71*(1-19*(Assumptions!$D$85/4)) -> 33487.5 | AA75: =AA71*(1-20*(Assumptions!$D$85/4)) -> 35000 | AB75: =AA75 -> 35000 | AC75: =AC71*(1-21*(Assumptions!$D$85/4)) -> 34750 | AD75: =AD71*(1-22*(Assumptions!$D$85/4)) -> 34500 | AE75: =AE71*(1-23*(Assumptions!$D$85/4)) -> 34250 | AF75: =AF71*(1-24*(Assumptions!$D$85/4)) -> 34000 | AG75: =AF75 -> 34000 | AH75: =AH71*(1-25*(Assumptions!$D$85/4)) -> 33750 | AI75: =AI71*(1-26*(Assumptions!$D$85/4)) -> 33500 | AJ75: =AJ71*(1-27*(Assumptions!$D$85/4)) -> 33250 | AK75: =AK71*(1-28*(Assumptions!$D$85/4)) -> 33000 | AL75: =AK75 -> 33000
C76: Business loans volume (cummulative) | D76: =(D72*Assumptions!$D$37*Assumptions!$D$41+D73*Assumptions!$D$38*Assumptions!$D$42+D74*Assumptions!$D$39*Assumptions!$D$43+D75*Assumptions!$D$40*Assumptions!$D$44)/VLOOKUP(Assumptions!$D$7, Lists!$B$7:$C$10, 2, FALSE) -> 1242187500 | E76: =(E72*Assumptions!$D$37*Assumptions!$D$41+E73*Assumptions!$D$38*Assumptions!$D$42+E74*Assumptions!$D$39*Assumptions!$D$43+E75*Assumptions!$D$40*Assumptions!$D$44)/VLOOKUP(Assumptions!$D$7, Lists!$B$7:$C$10, 2, FALSE) -> 2468750000 | F76: =(F72*Assumptions!$D$37*Assumptions!$D$41+F73*Assumptions!$D$38*Assumptions!$D$42+F74*Assumptions!$D$39*Assumptions!$D$43+F75*Assumptions!$D$40*Assumptions!$D$44)/VLOOKUP(Assumptions!$D$7, Lists!$B$7:$C$10, 2, FALSE) -> 3679687500 | G76: =(G72*Assumptions!$D$37*Assumptions!$D$41+G73*Assumptions!$D$38*Assumptions!$D$42+G74*Assumptions!$D$39*Assumptions!$D$43+G75*Assumptions!$D$40*Assumptions!$D$44)/VLOOKUP(Assumptions!$D$7, Lists!$B$7:$C$10, 2, FALSE) -> 4875000000 | H76: =G76 -> 4875000000 | I76: =(I72*Assumptions!$D$37*Assumptions!$D$41+I73*Assumptions!$D$38*Assumptions!$D$42+I74*Assumptions!$D$39*Assumptions!$D$43+I75*Assumptions!$D$40*Assumptions!$D$44)/VLOOKUP(Assumptions!$D$7, Lists!$B$7:$C$10, 2, FALSE) -> 6054687500 | J76: =(J72*Assumptions!$D$37*Assumptions!$D$41+J73*Assumptions!$D$38*Assumptions!$D$42+J74*Assumptions!$D$39*Assumptions!$D$43+J75*Assumptions!$D$40*Assumptions!$D$44)/VLOOKUP(Assumptions!$D$7, Lists!$B$7:$C$10, 2, FALSE) -> 7218750000 | K76: =(K72*Assumptions!$D$37*Assumptions!$D$41+K73*Assumptions!$D$38*Assumptions!$D$42+K74*Assumptions!$D$39*Assumptions!$D$43+K75*Assumptions!$D$40*Assumptions!$D$44)/VLOOKUP(Assumptions!$D$7, Lists!$B$7:$C$10, 2, FALSE) -> 8367187500 | L76: =(L72*Assumptions!$D$37*Assumptions!$D$41+L73*Assumptions!$D$38*Assumptions!$D$42+L74*Assumptions!$D$39*Assumptions!$D$43+L75*Assumptions!$D$40*Assumptions!$D$44)/VLOOKUP(Assumptions!$D$7, Lists!$B$7:$C$10, 2, FALSE) -> 9500000000 | M76: =L76 -> 9500000000 | N76: =(N72*Assumptions!$D$37*Assumptions!$D$41+N73*Assumptions!$D$38*Assumptions!$D$42+N74*Assumptions!$D$39*Assumptions!$D$43+N75*Assumptions!$D$40*Assumptions!$D$44)/VLOOKUP(Assumptions!$D$7, Lists!$B$7:$C$10, 2, FALSE) -> 10617187500 | O76: =(O72*Assumptions!$D$37*Assumptions!$D$41+O73*Assumptions!$D$38*Assumptions!$D$42+O74*Assumptions!$D$39*Assumptions!$D$43+O75*Assumptions!$D$40*Assumptions!$D$44)/VLOOKUP(Assumptions!$D$7, Lists!$B$7:$C$10, 2, FALSE) -> 11718750000 | P76: =(P72*Assumptions!$D$37*Assumptions!$D$41+P73*Assumptions!$D$38*Assumptions!$D$42+P74*Assumptions!$D$39*Assumptions!$D$43+P75*Assumptions!$D$40*Assumptions!$D$44)/VLOOKUP(Assumptions!$D$7, Lists!$B$7:$C$10, 2, FALSE) -> 12804687500 | Q76: =(Q72*Assumptions!$D$37*Assumptions!$D$41+Q73*Assumptions!$D$38*Assumptions!$D$42+Q74*Assumptions!$D$39*Assumptions!$D$43+Q75*Assumptions!$D$40*Assumptions!$D$44)/VLOOKUP(Assumptions!$D$7, Lists!$B$7:$C$10, 2, FALSE) -> 13875000000 | R76: =Q76 -> 13875000000 | S76: =(S72*Assumptions!$D$37*Assumptions!$D$41+S73*Assumptions!$D$38*Assumptions!$D$42+S74*Assumptions!$D$39*Assumptions!$D$43+S75*Assumptions!$D$40*Assumptions!$D$44)/VLOOKUP(Assumptions!$D$7, Lists!$B$7:$C$10, 2, FALSE) -> 14929687500 | T76: =(T72*Assumptions!$D$37*Assumptions!$D$41+T73*Assumptions!$D$38*Assumptions!$D$42+T74*Assumptions!$D$39*Assumptions!$D$43+T75*Assumptions!$D$40*Assumptions!$D$44)/VLOOKUP(Assumptions!$D$7, Lists!$B$7:$C$10, 2, FALSE) -> 15968750000 | U76: =(U72*Assumptions!$D$37*Assumptions!$D$41+U73*Assumptions!$D$38*Assumptions!$D$42+U74*Assumptions!$D$39*Assumptions!$D$43+U75*Assumptions!$D$40*Assumptions!$D$44)/VLOOKUP(Assumptions!$D$7, Lists!$B$7:$C$10, 2, FALSE) -> 16992187500 | V76: =(V72*Assumptions!$D$37*Assumptions!$D$41+V73*Assumptions!$D$38*Assumptions!$D$42+V74*Assumptions!$D$39*Assumptions!$D$43+V75*Assumptions!$D$40*Assumptions!$D$44)/VLOOKUP(Assumptions!$D$7, Lists!$B$7:$C$10, 2, FALSE) -> 18000000000 | W76: =V76 -> 18000000000 | X76: =(X72*Assumptions!$D$37*Assumptions!$D$41+X73*Assumptions!$D$38*Assumptions!$D$42+X74*Assumptions!$D$39*Assumptions!$D$43+X75*Assumptions!$D$40*Assumptions!$D$44)/VLOOKUP(Assumptions!$D$7, Lists!$B$7:$C$10, 2, FALSE) -> 18992187500 | Y76: =(Y72*Assumptions!$D$37*Assumptions!$D$41+Y73*Assumptions!$D$38*Assumptions!$D$42+Y74*Assumptions!$D$39*Assumptions!$D$43+Y75*Assumptions!$D$40*Assumptions!$D$44)/VLOOKUP(Assumptions!$D$7, Lists!$B$7:$C$10, 2, FALSE) -> 19968750000 | Z76: =(Z72*Assumptions!$D$37*Assumptions!$D$41+Z73*Assumptions!$D$38*Assumptions!$D$42+Z74*Assumptions!$D$39*Assumptions!$D$43+Z75*Assumptions!$D$40*Assumptions!$D$44)/VLOOKUP(Assumptions!$D$7, Lists!$B$7:$C$10, 2, FALSE) -> 20929687500 | AA76: =(AA72*Assumptions!$D$37*Assumptions!$D$41+AA73*Assumptions!$D$38*Assumptions!$D$42+AA74*Assumptions!$D$39*Assumptions!$D$43+AA75*Assumptions!$D$40*Assumptions!$D$44)/VLOOKUP(Assumptions!$D$7, Lists!$B$7:$C$10, 2, FALSE) -> 21875000000 | AB76: =AA76 -> 21875000000 | AC76: =(AC72*Assumptions!$D$37*Assumptions!$D$41+AC73*Assumptions!$D$38*Assumptions!$D$42+AC74*Assumptions!$D$39*Assumptions!$D$43+AC75*Assumptions!$D$40*Assumptions!$D$44)/VLOOKUP(Assumptions!$D$7, Lists!$B$7:$C$10, 2, FALSE) -> 21718750000 | AD76: =(AD72*Assumptions!$D$37*Assumptions!$D$41+AD73*Assumptions!$D$38*Assumptions!$D$42+AD74*Assumptions!$D$39*Assumptions!$D$43+AD75*Assumptions!$D$40*Assumptions!$D$44)/VLOOKUP(Assumptions!$D$7, Lists!$B$7:$C$10, 2, FALSE) -> 21562500000 | AE76: =(AE72*Assumptions!$D$37*Assumptions!$D$41+AE73*Assumptions!$D$38*Assumptions!$D$42+AE74*Assumptions!$D$39*Assumptions!$D$43+AE75*Assumptions!$D$40*Assumptions!$D$44)/VLOOKUP(Assumptions!$D$7, Lists!$B$7:$C$10, 2, FALSE) -> 21406250000 | AF76: =(AF72*Assumptions!$D$37*Assumptions!$D$41+AF73*Assumptions!$D$38*Assumptions!$D$42+AF74*Assumptions!$D$39*Assumptions!$D$43+AF75*Assumptions!$D$40*Assumptions!$D$44)/VLOOKUP(Assumptions!$D$7, Lists!$B$7:$C$10, 2, FALSE) -> 21250000000 | AG76: =AF76 -> 21250000000 | AH76: =(AH72*Assumptions!$D$37*Assumptions!$D$41+AH73*Assumptions!$D$38*Assumptions!$D$42+AH74*Assumptions!$D$39*Assumptions!$D$43+AH75*Assumptions!$D$40*Assumptions!$D$44)/VLOOKUP(Assumptions!$D$7, Lists!$B$7:$C$10, 2, FALSE) -> 21093750000 | AI76: =(AI72*Assumptions!$D$37*Assumptions!$D$41+AI73*Assumptions!$D$38*Assumptions!$D$42+AI74*Assumptions!$D$39*Assumptions!$D$43+AI75*Assumptions!$D$40*Assumptions!$D$44)/VLOOKUP(Assumptions!$D$7, Lists!$B$7:$C$10, 2, FALSE) -> 20937500000 | AJ76: =(AJ72*Assumptions!$D$37*Assumptions!$D$41+AJ73*Assumptions!$D$38*Assumptions!$D$42+AJ74*Assumptions!$D$39*Assumptions!$D$43+AJ75*Assumptions!$D$40*Assumptions!$D$44)/VLOOKUP(Assumptions!$D$7, Lists!$B$7:$C$10, 2, FALSE) -> 20781250000 | AK76: =(AK72*Assumptions!$D$37*Assumptions!$D$41+AK73*Assumptions!$D$38*Assumptions!$D$42+AK74*Assumptions!$D$39*Assumptions!$D$43+AK75*Assumptions!$D$40*Assumptions!$D$44)/VLOOKUP(Assumptions!$D$7, Lists!$B$7:$C$10, 2, FALSE) -> 20625000000 | AL76: =AK76 -> 20625000000
C77: Mortgages volume (cummulative) | D77: =SUM(D72:D75)*Assumptions!$D$45*Assumptions!$D$46/VLOOKUP(Assumptions!$D$7, Lists!$B$7:$C$10, 2, FALSE) -> 1147781250 | E77: =SUM(E72:E75)*Assumptions!$D$45*Assumptions!$D$46/VLOOKUP(Assumptions!$D$7, Lists!$B$7:$C$10, 2, FALSE) -> 2281125000 | F77: =SUM(F72:F75)*Assumptions!$D$45*Assumptions!$D$46/VLOOKUP(Assumptions!$D$7, Lists!$B$7:$C$10, 2, FALSE) -> 3400031250 | G77: =SUM(G72:G75)*Assumptions!$D$45*Assumptions!$D$46/VLOOKUP(Assumptions!$D$7, Lists!$B$7:$C$10, 2, FALSE) -> 4504500000 | H77: =G77 -> 4504500000 | I77: =SUM(I72:I75)*Assumptions!$D$45*Assumptions!$D$46/VLOOKUP(Assumptions!$D$7, Lists!$B$7:$C$10, 2, FALSE) -> 5594531250 | J77: =SUM(J72:J75)*Assumptions!$D$45*Assumptions!$D$46/VLOOKUP(Assumptions!$D$7, Lists!$B$7:$C$10, 2, FALSE) -> 6670125000 | K77: =SUM(K72:K75)*Assumptions!$D$45*Assumptions!$D$46/VLOOKUP(Assumptions!$D$7, Lists!$B$7:$C$10, 2, FALSE) -> 7731281250 | L77: =SUM(L72:L75)*Assumptions!$D$45*Assumptions!$D$46/VLOOKUP(Assumptions!$D$7, Lists!$B$7:$C$10, 2, FALSE) -> 8778000000 | M77: =L77 -> 8778000000 | N77: =SUM(N72:N75)*Assumptions!$D$45*Assumptions!$D$46/VLOOKUP(Assumptions!$D$7, Lists!$B$7:$C$10, 2, FALSE) -> 9810281250 | O77: =SUM(O72:O75)*Assumptions!$D$45*Assumptions!$D$46/VLOOKUP(Assumptions!$D$7, Lists!$B$7:$C$10, 2, FALSE) -> 10828125000 | P77: =SUM(P72:P75)*Assumptions!$D$45*Assumptions!$D$46/VLOOKUP(Assumptions!$D$7, Lists!$B$7:$C$10, 2, FALSE) -> 11831531250 | Q77: =SUM(Q72:Q75)*Assumptions!$D$45*Assumptions!$D$46/VLOOKUP(Assumptions!$D$7, Lists!$B$7:$C$10, 2, FALSE) -> 12820500000 | R77: =Q77 -> 12820500000 | S77: =SUM(S72:S75)*Assumptions!$D$45*Assumptions!$D$46/VLOOKUP(Assumptions!$D$7, Lists!$B$7:$C$10, 2, FALSE) -> 13795031250 | T77: =SUM(T72:T75)*Assumptions!$D$45*Assumptions!$D$46/VLOOKUP(Assumptions!$D$7, Lists!$B$7:$C$10, 2, FALSE) -> 14755125000 | U77: =SUM(U72:U75)*Assumptions!$D$45*Assumptions!$D$46/VLOOKUP(Assumptions!$D$7, Lists!$B$7:$C$10, 2, FALSE) -> 15700781250 | V77: =SUM(V72:V75)*Assumptions!$D$45*Assumptions!$D$46/VLOOKUP(Assumptions!$D$7, Lists!$B$7:$C$10, 2, FALSE) -> 16632000000 | W77: =V77 -> 16632000000 | X77: =SUM(X72:X75)*Assumptions!$D$45*Assumptions!$D$46/VLOOKUP(Assumptions!$D$7, Lists!$B$7:$C$10, 2, FALSE) -> 17548781250 | Y77: =SUM(Y72:Y75)*Assumptions!$D$45*Assumptions!$D$46/VLOOKUP(Assumptions!$D$7, Lists!$B$7:$C$10, 2, FALSE) -> 18451125000 | Z77: =SUM(Z72:Z75)*Assumptions!$D$45*Assumptions!$D$46/VLOOKUP(Assumptions!$D$7, Lists!$B$7:$C$10, 2, FALSE) -> 19339031250 | AA77: =SUM(AA72:AA75)*Assumptions!$D$45*Assumptions!$D$46/VLOOKUP(Assumptions!$D$7, Lists!$B$7:$C$10, 2, FALSE) -> 20212500000 | AB77: =AA77 -> 20212500000 | AC77: =SUM(AC72:AC75)*Assumptions!$D$45*Assumptions!$D$46/VLOOKUP(Assumptions!$D$7, Lists!$B$7:$C$10, 2, FALSE) -> 20068125000 | AD77: =SUM(AD72:AD75)*Assumptions!$D$45*Assumptions!$D$46/VLOOKUP(Assumptions!$D$7, Lists!$B$7:$C$10, 2, FALSE) -> 19923750000 | AE77: =SUM(AE72:AE75)*Assumptions!$D$45*Assumptions!$D$46/VLOOKUP(Assumptions!$D$7, Lists!$B$7:$C$10, 2, FALSE) -> 19779375000 | AF77: =SUM(AF72:AF75)*Assumptions!$D$45*Assumptions!$D$46/VLOOKUP(Assumptions!$D$7, Lists!$B$7:$C$10, 2, FALSE) -> 19635000000 | AG77: =AF77 -> 19635000000 | AH77: =SUM(AH72:AH75)*Assumptions!$D$45*Assumptions!$D$46/VLOOKUP(Assumptions!$D$7, Lists!$B$7:$C$10, 2, FALSE) -> 19490625000 | AI77: =SUM(AI72:AI75)*Assumptions!$D$45*Assumptions!$D$46/VLOOKUP(Assumptions!$D$7, Lists!$B$7:$C$10, 2, FALSE) -> 19346250000 | AJ77: =SUM(AJ72:AJ75)*Assumptions!$D$45*Assumptions!$D$46/VLOOKUP(Assumptions!$D$7, Lists!$B$7:$C$10, 2, FALSE) -> 19201875000 | AK77: =SUM(AK72:AK75)*Assumptions!$D$45*Assumptions!$D$46/VLOOKUP(Assumptions!$D$7, Lists!$B$7:$C$10, 2, FALSE) -> 19057500000 | AL77: =AK77 -> 19057500000
C78: Auto loans and leasing volume (cummulative) | D78: =SUM(D72:D75)*Assumptions!$D$47*Assumptions!$D$48/VLOOKUP(Assumptions!$D$7, Lists!$B$7:$C$10, 2, FALSE) -> 114778125 | E78: =SUM(E72:E75)*Assumptions!$D$47*Assumptions!$D$48/VLOOKUP(Assumptions!$D$7, Lists!$B$7:$C$10, 2, FALSE) -> 228112500 | F78: =SUM(F72:F75)*Assumptions!$D$47*Assumptions!$D$48/VLOOKUP(Assumptions!$D$7, Lists!$B$7:$C$10, 2, FALSE) -> 340003125 | G78: =SUM(G72:G75)*Assumptions!$D$47*Assumptions!$D$48/VLOOKUP(Assumptions!$D$7, Lists!$B$7:$C$10, 2, FALSE) -> 450450000 | H78: =G78 -> 450450000 | I78: =SUM(I72:I75)*Assumptions!$D$47*Assumptions!$D$48/VLOOKUP(Assumptions!$D$7, Lists!$B$7:$C$10, 2, FALSE) -> 559453125 | J78: =SUM(J72:J75)*Assumptions!$D$47*Assumptions!$D$48/VLOOKUP(Assumptions!$D$7, Lists!$B$7:$C$10, 2, FALSE) -> 667012500 | K78: =SUM(K72:K75)*Assumptions!$D$47*Assumptions!$D$48/VLOOKUP(Assumptions!$D$7, Lists!$B$7:$C$10, 2, FALSE) -> 773128125 | L78: =SUM(L72:L75)*Assumptions!$D$47*Assumptions!$D$48/VLOOKUP(Assumptions!$D$7, Lists!$B$7:$C$10, 2, FALSE) -> 877800000 | M78: =L78 -> 877800000 | N78: =SUM(N72:N75)*Assumptions!$D$47*Assumptions!$D$48/VLOOKUP(Assumptions!$D$7, Lists!$B$7:$C$10, 2, FALSE) -> 981028125 | O78: =SUM(O72:O75)*Assumptions!$D$47*Assumptions!$D$48/VLOOKUP(Assumptions!$D$7, Lists!$B$7:$C$10, 2, FALSE) -> 1082812500 | P78: =SUM(P72:P75)*Assumptions!$D$47*Assumptions!$D$48/VLOOKUP(Assumptions!$D$7, Lists!$B$7:$C$10, 2, FALSE) -> 1183153125 | Q78: =SUM(Q72:Q75)*Assumptions!$D$47*Assumptions!$D$48/VLOOKUP(Assumptions!$D$7, Lists!$B$7:$C$10, 2, FALSE) -> 1282050000 | R78: =Q78 -> 1282050000 | S78: =SUM(S72:S75)*Assumptions!$D$47*Assumptions!$D$48/VLOOKUP(Assumptions!$D$7, Lists!$B$7:$C$10, 2, FALSE) -> 1379503125 | T78: =SUM(T72:T75)*Assumptions!$D$47*Assumptions!$D$48/VLOOKUP(Assumptions!$D$7, Lists!$B$7:$C$10, 2, FALSE) -> 1475512500 | U78: =SUM(U72:U75)*Assumptions!$D$47*Assumptions!$D$48/VLOOKUP(Assumptions!$D$7, Lists!$B$7:$C$10, 2, FALSE) -> 1570078125 | V78: =SUM(V72:V75)*Assumptions!$D$47*Assumptions!$D$48/VLOOKUP(Assumptions!$D$7, Lists!$B$7:$C$10, 2, FALSE) -> 1663200000 | W78: =V78 -> 1663200000 | X78: =SUM(X72:X75)*Assumptions!$D$47*Assumptions!$D$48/VLOOKUP(Assumptions!$D$7, Lists!$B$7:$C$10, 2, FALSE) -> 1754878125 | Y78: =SUM(Y72:Y75)*Assumptions!$D$47*Assumptions!$D$48/VLOOKUP(Assumptions!$D$7, Lists!$B$7:$C$10, 2, FALSE) -> 1845112500 | Z78: =SUM(Z72:Z75)*Assumptions!$D$47*Assumptions!$D$48/VLOOKUP(Assumptions!$D$7, Lists!$B$7:$C$10, 2, FALSE) -> 1933903125 | AA78: =SUM(AA72:AA75)*Assumptions!$D$47*Assumptions!$D$48/VLOOKUP(Assumptions!$D$7, Lists!$B$7:$C$10, 2, FALSE) -> 2021250000 | AB78: =AA78 -> 2021250000 | AC78: =SUM(AC72:AC75)*Assumptions!$D$47*Assumptions!$D$48/VLOOKUP(Assumptions!$D$7, Lists!$B$7:$C$10, 2, FALSE) -> 2006812500 | AD78: =SUM(AD72:AD75)*Assumptions!$D$47*Assumptions!$D$48/VLOOKUP(Assumptions!$D$7, Lists!$B$7:$C$10, 2, FALSE) -> 1992375000 | AE78: =SUM(AE72:AE75)*Assumptions!$D$47*Assumptions!$D$48/VLOOKUP(Assumptions!$D$7, Lists!$B$7:$C$10, 2, FALSE) -> 1977937500 | AF78: =SUM(AF72:AF75)*Assumptions!$D$47*Assumptions!$D$48/VLOOKUP(Assumptions!$D$7, Lists!$B$7:$C$10, 2, FALSE) -> 1963500000 | AG78: =AF78 -> 1963500000 | AH78: =SUM(AH72:AH75)*Assumptions!$D$47*Assumptions!$D$48/VLOOKUP(Assumptions!$D$7, Lists!$B$7:$C$10, 2, FALSE) -> 1949062500 | AI78: =SUM(AI72:AI75)*Assumptions!$D$47*Assumptions!$D$48/VLOOKUP(Assumptions!$D$7, Lists!$B$7:$C$10, 2, FALSE) -> 1934625000 | AJ78: =SUM(AJ72:AJ75)*Assumptions!$D$47*Assumptions!$D$48/VLOOKUP(Assumptions!$D$7, Lists!$B$7:$C$10, 2, FALSE) -> 1920187500 | AK78: =SUM(AK72:AK75)*Assumptions!$D$47*Assumptions!$D$48/VLOOKUP(Assumptions!$D$7, Lists!$B$7:$C$10, 2, FALSE) -> 1905750000 | AL78: =AK78 -> 1905750000
